Workbook
Name Ccy: MAIN!$C$6
Name circ: MAIN!$C$9
Name CoName: MAIN!$C$4
Name g: Presentation!$R$17
Name IQ_CH: 110000
Name IQ_CQ: 5000
Name IQ_CY: 10000
Name IQ_DAILY: 500000
Name IQ_FH: 100000
Name IQ_FQ: 500
Name IQ_FY: 1000
Name IQ_LTM: 2000
Name IQ_MONTH: 15000
Name IQ_NTM: 6000
Name IQ_WEEK: 50000
Name IQ_YTD: 3000
Name OpCase: [1]DCF!$E$98
Name ScenarioREV: Assumptions!$D$4
Name TTS: #REF!
Name Units: MAIN!$C$7

Sheet MAIN
A1: =CoName -> Adobe Inc.
A2: Model Details
B4: Company name | C4: Adobe Inc. | E4: Current Stock Price | F4: 328.46 | I4: Perpetuity | J4: Terminal Mult
B5: Latest BS date | C5: 247.43 | E5: Diluted s/o | F5: 418.6 | H5: Implied | I5: ='DCF Model'!M16 -> 261.41348 | J5: ='DCF Model'!R16 -> 459.01675
B6: Currency | C6: USD | E6: Mkt Cap | F6: =F5*F4 -> 137493.36 | H6: Difference | I6: =I5/$F$4-1 -> -0.20412386 | J6: =J5/$F$4-1 -> 0.39748142
B7: Units | C7: m | E7: Cash | F7: =4982+958 -> 5940
B8: Analyst name | C8: Alan Chen | E8: Debt | F8: =6200 -> 6200
B9: Circular switch | C9: 0 | E9: EV | F9: =F6-F7+F8 -> 137753.36

Sheet Assumptions
A1: =CoName -> Adobe Inc. | C1: Hist. | D1: Hist. | E1: Hist. | F1: Proj. | G1: Proj. | H1: Proj. | I1: Proj. | J1: Proj. | K1: Proj. | L1: Proj. | M1: Proj.
A2: * | B2: Income Statement | C2: 44926 | D2: 45291 | E2: 45657 | F2: 46022 | G2: 46387 | H2: 46752 | I2: 47118 | J2: 47483 | K2: 47848 | L2: 48213 | M2: 48579
B4: Operating Case | D4: 1
D5: Variance
B6: Street Case | D6: 0 | F6: =Revenue!N11 -> 0.098189723 | G6: =Revenue!O11 -> 0.098834735 | H6: =Revenue!P11 -> 0.099456567 | I6: =Revenue!Q11 -> 0.10005577 | J6: =Revenue!R11 -> 0.1006329 | K6: =Revenue!S11 -> 0.10118852 | L6: =Revenue!T11 -> 0.1017232 | M6: =Revenue!U11 -> 0.10223749
B7: Optimistic Case | D7: 0.025 | F7: =F6+$D$7 -> 0.12318972 | G7: =G6+$D$7 -> 0.12383474 | H7: =H6+$D$7 -> 0.12445657 | I7: =I6+$D$7 -> 0.12505577 | J7: =J6+$D$7 -> 0.1256329 | K7: =K6+$D$7 -> 0.12618852 | L7: =L6+$D$7 -> 0.1267232 | M7: =M6+$D$7 -> 0.12723749
B8: Pessimistic Case | D8: -0.025 | F8: =F6+$D$8 -> 0.073189723 | G8: =G6+$D$8 -> 0.073834735 | H8: =H6+$D$8 -> 0.074456567 | I8: =I6+$D$8 -> 0.07505577 | J8: =J6+$D$8 -> 0.0756329 | K8: =K6+$D$8 -> 0.07618852 | L8: =L6+$D$8 -> 0.076723196 | M8: =M6+$D$8 -> 0.077237493
B10: Revenue Growth | C10: =Revenue!C11 -> 0.1143038 | D10: =Revenue!D11 -> 0.10240827 | E10: =Revenue!I11 -> 0.10799114 | F10: =CHOOSE(ScenarioREV,F6,F7,F8) -> 0.098189723 | G10: =CHOOSE(ScenarioREV,G6,G7,G8) -> 0.098834735 | H10: =CHOOSE(ScenarioREV,H6,H7,H8) -> 0.099456567 | I10: =CHOOSE(ScenarioREV,I6,I7,I8) -> 0.10005577 | J10: =CHOOSE(ScenarioREV,J6,J7,J8) -> 0.1006329 | K10: =CHOOSE(ScenarioREV,K6,K7,K8) -> 0.10118852 | L10: =CHOOSE(ScenarioREV,L6,L7,L8) -> 0.1017232 | M10: =CHOOSE(ScenarioREV,M6,M7,M8) -> 0.10223749
B11: COGS % of sales | C11: =IncState!C17/IncState!C16 -> 0.12296944 | D11: =IncState!D17/IncState!D16 -> 0.12128394 | E11: =IncState!E17/IncState!E16 -> 0.10964892 | F11: =E11 -> 0.10964892 | G11: =F11 -> 0.10964892 | H11: =G11 -> 0.10964892 | I11: =H11 -> 0.10964892 | J11: =I11 -> 0.10964892 | K11: =J11 -> 0.10964892 | L11: =K11 -> 0.10964892 | M11: =L11 -> 0.10964892
B12: R&D % of sales | C12: =IncState!C18/IncState!C16 -> 0.16965807 | D12: =IncState!D18/IncState!D16 -> 0.12226287 | E12: =IncState!E18/IncState!E16 -> 0.18339921 | F12: =E12 -> 0.18339921 | G12: =F12 -> 0.18339921 | H12: =G12 -> 0.18339921 | I12: =H12 -> 0.18339921 | J12: =I12 -> 0.18339921 | K12: =J12 -> 0.18339921 | L12: =K12 -> 0.18339921 | M12: =L12 -> 0.18339921
B13: SG&A % of sales | C13: =IncState!C19/IncState!C16 -> 0.36101329 | D13: =IncState!D19/IncState!D16 -> 0.41382864 | E13: =IncState!E19/IncState!E16 -> 0.39348989 | F13: =E13 -> 0.39348989 | G13: =F13 -> 0.39348989 | H13: =G13 -> 0.39348989 | I13: =H13 -> 0.39348989 | J13: =I13 -> 0.39348989 | K13: =J13 -> 0.39348989 | L13: =K13 -> 0.39348989 | M13: =L13 -> 0.39348989
B14: Amortization $ Amt | C14: =IncState!C23 -> 169 | D14: =IncState!D23 -> 168 | E14: =IncState!E23 -> 169 | F14: =E14 -> 169 | G14: =F14 -> 169 | H14: =G14 -> 169 | I14: =H14 -> 169 | J14: =I14 -> 169 | K14: =J14 -> 169 | L14: =K14 -> 169 | M14: =L14 -> 169
B15: Non recurring income / (expense) | C15: =IncState!C26 -> -19 | D15: =IncState!D26 -> 16 | E15: =IncState!E26 -> 48 | F15: 0 | G15: 0 | H15: 0 | I15: 0 | J15: 0 | K15: 0 | L15: 0 | M15: 0
B16: Other Income / (expense) | C16: =IncState!C27 -> 41 | D16: =IncState!D27 -> 246 | E16: =IncState!E27 -> 311 | F16: 0 | G16: 0 | H16: 0 | I16: 0 | J16: 0 | K16: 0 | L16: 0 | M16: 0
B17: Effective tax rate | C17: =IncState!C34/IncState!C32 -> 0.20838881 | D17: =IncState!D34/IncState!D32 -> 0.2016473 | E17: =IncState!E34/IncState!E32 -> 0.19780695 | F17: 0.19 | G17: =F17 -> 0.19 | H17: =G17 -> 0.19 | I17: =H17 -> 0.19 | J17: =I17 -> 0.19 | K17: =J17 -> 0.19 | L17: =K17 -> 0.19 | M17: =L17 -> 0.19
B18: Basic WASO | C18: =IncState!C38 -> 470 | D18: =IncState!D38 -> 457 | E18: =IncState!E38 -> 447 | F18: =E18 -> 447 | G18: =F18 -> 447 | H18: =G18 -> 447 | I18: =H18 -> 447 | J18: =I18 -> 447 | K18: =J18 -> 447 | L18: =K18 -> 447 | M18: =L18 -> 447
B19: Diluted WASO | C19: =IncState!C39 -> 471 | D19: =IncState!D39 -> 459 | E19: =IncState!E39 -> 450 | F19: =E19 -> 450 | G19: =F19 -> 450 | H19: =G19 -> 450 | I19: =H19 -> 450 | J19: =I19 -> 450 | K19: =J19 -> 450 | L19: =K19 -> 450 | M19: =L19 -> 450
A21: * | B21: Debt | C21: 44926 | D21: 45291 | E21: 45657 | F21: 46022 | G21: 46387 | H21: 46752 | I21: 47118 | J21: 47483 | K21: =K2 -> 47848 | L21: =L2 -> 48213 | M21: =M2 -> 48579
B23: Interest rate on Revolver | E23: =E24 -> 0.036 | F23: =E23 -> 0.036 | G23: =F23 -> 0.036 | H23: =G23 -> 0.036 | I23: =H23 -> 0.036 | J23: =I23 -> 0.036 | K23: =J23 -> 0.036 | L23: =K23 -> 0.036 | M23: =L23 -> 0.036
B24: Interest rate on long-term debt | E24: 0.036 | F24: =E24 -> 0.036 | G24: =F24 -> 0.036 | H24: =G24 -> 0.036 | I24: =H24 -> 0.036 | J24: =I24 -> 0.036 | K24: =J24 -> 0.036 | L24: =K24 -> 0.036 | M24: =L24 -> 0.036
B25: Interest rate on cash | E25: =341/BalSheet!E15 -> 0.050067907 | F25: =E25 -> 0.050067907 | G25: =F25 -> 0.050067907 | H25: =G25 -> 0.050067907 | I25: =H25 -> 0.050067907 | J25: =I25 -> 0.050067907 | K25: =J25 -> 0.050067907 | L25: =K25 -> 0.050067907 | M25: =L25 -> 0.050067907
B27: Issuance of long-term debt | F27: 0 | G27: 0 | H27: 0 | I27: 0 | J27: 0 | K27: 0 | L27: 0 | M27: 0
B28: Repayment of long-term debt | F28: -1499 | G28: 0 | H28: 0 | I28: 0 | J28: 0 | K28: 0 | L28: 0 | M28: 0
A30: * | B30: Calcs | C30: 44926 | D30: 45291 | E30: 45657 | F30: 46022 | G30: 46387 | H30: 46752 | I30: 47118 | J30: 47483 | K30: 2030 | L30: =K30+1 -> 2031 | M30: =L30+1 -> 2032
B32: CapEx % of Sales | C32: =442/IncState!C16 -> 0.025105078 | D32: =360/IncState!D16 -> 0.018548096 | E32: =291/IncState!E16 -> 0.013531737 | F32: =E32 -> 0.013531737 | G32: =F32 -> 0.013531737 | H32: =G32 -> 0.013531737 | I32: =H32 -> 0.013531737 | J32: =I32 -> 0.013531737 | K32: =J32 -> 0.013531737 | L32: =K32 -> 0.013531737 | M32: =L32 -> 0.013531737
B33: Depreciation % of beginning PP&E | D33: =IncState!D22/BalSheet!C20 -> 0.30410367 | E33: =IncState!E22/BalSheet!D20 -> 0.2881072 | F33: =E33 -> 0.2881072 | G33: =F33 -> 0.2881072 | H33: =G33 -> 0.2881072 | I33: =H33 -> 0.2881072 | J33: =I33 -> 0.2881072 | K33: =J33 -> 0.2881072 | L33: =K33 -> 0.2881072 | M33: =L33 -> 0.2881072
B34: Share issuance / (repurchases) | F34: -2500 | G34: =F34 -> -2500 | H34: =G34 -> -2500 | I34: -900 | J34: 0 | K34: 0 | L34: 0 | M34: 0
A36: * | B36: Shareholder information | C36: 44926 | D36: 45291 | E36: 45657 | F36: 46022 | G36: 46387 | H36: 46752 | I36: 47118 | J36: 47483 | K36: 2030 | L36: =K36+1 -> 2031 | M36: =L36+1 -> 2032
B38: Basic WASO | C38: =C18 -> 470 | D38: =D18 -> 457 | E38: =E18 -> 447 | F38: =F18 -> 447 | G38: =G18 -> 447 | H38: =H18 -> 447 | I38: =I18 -> 447 | J38: =J18 -> 447 | ... M38: =M18 -> 447
B39: Diluted WASO | C39: =C19 -> 471 | D39: =D19 -> 459 | E39: =E19 -> 450 | F39: =F19 -> 450 | G39: =G19 -> 450 | H39: =H19 -> 450 | I39: =I19 -> 450 | J39: =J19 -> 450 | ... M39: =M19 -> 450
A41: * | B41: Balance Sheet - Assets | C41: 44926 | D41: 45291 | E41: 45657 | F41: 46022 | G41: 46387 | H41: 46752 | I41: 47118 | J41: 47483 | K41: 2030 | L41: =K41+1 -> 2031 | M41: =L41+1 -> 2032
B43: Operating Cash % of sales | C43: =BalSheet!C14/IncState!C16 -> 0.05 | D43: =BalSheet!D14/IncState!D16 -> 0.05 | E43: =BalSheet!E14/IncState!E16 -> 0.05 | F43: =E43 -> 0.05 | G43: =F43 -> 0.05 | H43: =G43 -> 0.05 | I43: =H43 -> 0.05 | J43: =I43 -> 0.05 | K43: =J43 -> 0.05 | L43: =K43 -> 0.05 | M43: =L43 -> 0.05
B44: Accounts receivable % of sales | C44: =BalSheet!C16/IncState!C16 -> 0.11728956 | D44: =BalSheet!D16/IncState!D16 -> 0.11458602 | E44: =BalSheet!E16/IncState!E16 -> 0.096349686 | F44: =E44 -> 0.096349686 | G44: =F44 -> 0.096349686 | H44: =G44 -> 0.096349686 | I44: =H44 -> 0.096349686 | J44: =I44 -> 0.096349686 | K44: =J44 -> 0.096349686 | L44: =K44 -> 0.096349686 | M44: =L44 -> 0.096349686
B45: Other current assets % of sales | C45: =BalSheet!C17/IncState!C16 -> 0.047427014 | D45: =BalSheet!D17/IncState!D16 -> 0.052449894 | E45: =BalSheet!E17/IncState!E16 -> 0.059242037 | F45: =E45 -> 0.059242037 | G45: =F45 -> 0.059242037 | H45: =G45 -> 0.059242037 | I45: =H45 -> 0.059242037 | J45: =I45 -> 0.059242037 | K45: =J45 -> 0.059242037 | L45: =K45 -> 0.059242037 | M45: =L45 -> 0.059242037
B47: Investments in unconsolidated entities | C47: 0 | D47: 0 | E47: 0 | F47: =E47 -> 0 | G47: =F47 -> 0 | H47: =G47 -> 0 | I47: =H47 -> 0 | J47: =I47 -> 0 | K47: =J47 -> 0 | L47: =K47 -> 0 | M47: =L47 -> 0
B48: Other long-term assets % of sales | C48: =BalSheet!C22/IncState!C16 -> 0.091900488 | D48: =BalSheet!D22/IncState!D16 -> 0.12437529 | E48: =BalSheet!E22/IncState!E16 -> 0.14931411 | F48: =E48 -> 0.14931411 | G48: =F48 -> 0.14931411 | H48: =G48 -> 0.14931411 | I48: =H48 -> 0.14931411 | J48: =I48 -> 0.14931411 | K48: =J48 -> 0.14931411 | L48: =K48 -> 0.14931411 | M48: =L48 -> 0.14931411
A50: * | B50: Balance Sheet - Liabilities | C50: 44926 | D50: 45291 | E50: 45657 | F50: 46022 | G50: 46387 | H50: 46752 | I50: 47118 | J50: 47483 | K50: 2030 | L50: =K50+1 -> 2031 | M50: =L50+1 -> 2032
B52: Accounts payable % of COGS | C52: =BalSheet!C28/IncState!C17 -> 1.0364896 | D52: =BalSheet!D28/IncState!D17 -> 0.99447749 | E52: =BalSheet!E28/IncState!E17 -> 1.1942324 | F52: =E52 -> 1.1942324 | G52: =F52 -> 1.1942324 | H52: =G52 -> 1.1942324 | I52: =H52 -> 1.1942324 | J52: =I52 -> 1.1942324 | K52: =J52 -> 1.1942324 | L52: =K52 -> 1.1942324 | M52: =L52 -> 1.1942324
B53: Other current liabilities % of sales | C53: =BalSheet!C29/IncState!C16 -> 0.30580484 | D53: =BalSheet!D29/IncState!D16 -> 0.30449791 | E53: =BalSheet!E29/IncState!E16 -> 0.28858405 | F53: =E53 -> 0.28858405 | G53: =F53 -> 0.28858405 | H53: =G53 -> 0.28858405 | I53: =H53 -> 0.28858405 | J53: =I53 -> 0.28858405 | K53: =J53 -> 0.28858405 | L53: =K53 -> 0.28858405 | M53: =L53 -> 0.28858405
B54: Other long-term liabilities % of sales | C54: =BalSheet!C33/IncState!C16 -> 0.077075997 | D54: =BalSheet!D33/IncState!D16 -> 0.070894946 | E54: =BalSheet!E33/IncState!E16 -> 0.0685887 | F54: =E54 -> 0.0685887 | G54: =F54 -> 0.0685887 | H54: =G54 -> 0.0685887 | I54: =H54 -> 0.0685887 | J54: =I54 -> 0.0685887 | K54: =J54 -> 0.0685887 | L54: =K54 -> 0.0685887 | M54: =L54 -> 0.0685887

Sheet Revenue
A1: =CoName -> Adobe Inc.
A2: Revenues | C2: 2022 | D2: 2023 | E2: Q124 | F2: Q224 | G2: Q324 | H2: Q424 | I2: 2024 | J2: Q125 | K2: Q225 | L2: Q325 | M2: Q425 | N2: 2025 | O2: =N2+1 -> 2026 | P2: =O2+1 -> 2027 | Q2: =P2+1 -> 2028 | R2: =Q2+1 -> 2029 | S2: =R2+1 -> 2030 | T2: =S2+1 -> 2031 | U2: =T2+1 -> 2032
A3: * | B3: Digital Media | C3: 12842 | D3: 14216 | E3: 3725 | F3: 3828 | G3: 3921 | H3: =I3-SUM(E3:G3) -> 4390 | I3: 15864 | J3: 4159 | K3: 4280 | L3: 4397 | M3: =H3*(1+M8) -> 4829 | N3: =SUM(J3:M3) -> 17665 | O3: =N3*(1+O8) -> 19670.463 | P3: =O3*(1+P8) -> 21903.601 | Q3: =P3*(1+Q8) -> 24390.262 | R3: =Q3*(1+R8) -> 27159.227 | S3: =R3*(1+S8) -> 30242.546 | T3: =S3*(1+T8) -> 33675.906 | U3: =T3*(1+U8) -> 37499.047
B4: Digital Experience | C4: 4422 | D4: 4893 | E4: 1164 | F4: 1204 | G4: 1231 | H4: =I4-SUM(E4:G4) -> 1767 | I4: 5366 | J4: 1297 | K4: 1334 | L4: 1368 | M4: =H4*(1+M9) -> 1678.65 | N4: =SUM(J4:M4) -> 5677.65 | O4: =N4*(1+O9) -> 6007.4002 | P4: =O4*(1+P9) -> 6356.3019 | Q4: =P4*(1+Q9) -> 6725.4673 | R4: =Q4*(1+R9) -> 7116.0733 | S4: =R4*(1+S9) -> 7529.3651 | T4: =S4*(1+T9) -> 7966.6605 | U4: =T4*(1+U9) -> 8429.3533
B5: Publishing and Advertising | C5: 342 | D5: 300 | E5: 27 | F5: 28 | G5: 28 | H5: =I5-SUM(E5:G5) -> 192 | I5: 275 | J5: 27 | K5: 27 | L5: 26 | M5: =H5*(1+M10) -> 193.92 | N5: =SUM(J5:M5) -> 273.92 | O5: =N5*(1+O10) -> 272.84424 | P5: =O5*(1+P10) -> 271.77271 | Q5: =P5*(1+Q10) -> 270.70538 | R5: =Q5*(1+R10) -> 269.64225 | S5: =R5*(1+S10) -> 268.58329 | T5: =S5*(1+T10) -> 267.52849 | U5: =T5*(1+U10) -> 266.47783
B6: TOTAL REVENUES | C6: =SUM(C3:C5) -> 17606 | D6: =SUM(D3:D5) -> 19409 | E6: =SUM(E3:E5) -> 4916 | F6: =SUM(F3:F5) -> 5060 | G6: =SUM(G3:G5) -> 5180 | H6: =SUM(H3:H5) -> 6349 | I6: =SUM(I3:I5) -> 21505 | J6: =SUM(J3:J5) -> 5483 | ... U6: =SUM(U3:U5) -> 46194.878
B8: Digital Media y/y | C8: =C3/11048-1 -> 0.16238233 | D8: =D3/C3-1 -> 0.10699268 | I8: =I3/D3-1 -> 0.11592572 | J8: =J3/E3-1 -> 0.11651007 | K8: =K3/F3-1 -> 0.11807732 | L8: =L3/G3-1 -> 0.1213976 | M8: 0.1 | N8: =N3/I3-1 -> 0.11352748 | O8: =N8 -> 0.11352748 | P8: =O8 -> 0.11352748 | Q8: =P8 -> 0.11352748 | R8: =Q8 -> 0.11352748 | S8: =R8 -> 0.11352748 | T8: =S8 -> 0.11352748 | U8: =T8 -> 0.11352748
B9: Digital Experience y/y | C9: =C4/3379-1 -> 0.3086712 | D9: =D4/C4-1 -> 0.10651289 | I9: =I4/D4-1 -> 0.09666871 | J9: =J4/E4-1 -> 0.11426117 | K9: =K4/F4-1 -> 0.10797342 | L9: =L4/G4-1 -> 0.11129163 | M9: -0.05 | N9: =N4/I4-1 -> 0.058078643 | O9: =N9 -> 0.058078643 | P9: =O9 -> 0.058078643 | Q9: =P9 -> 0.058078643 | R9: =Q9 -> 0.058078643 | S9: =R9 -> 0.058078643 | T9: =S9 -> 0.058078643 | U9: =T9 -> 0.058078643
B10: Publishing and Advertising y/y | C10: =C5/146-1 -> 1.3424658 | D10: =D5/C5-1 -> -0.12280702 | I10: =I5/D5-1 -> -0.083333333 | J10: =J5/E5-1 -> 0 | K10: =K5/F5-1 -> -0.035714286 | L10: =L5/G5-1 -> -0.071428571 | M10: 0.01 | N10: =N5/I5-1 -> -0.0039272727 | O10: =N10 -> -0.0039272727 | P10: =O10 -> -0.0039272727 | Q10: =P10 -> -0.0039272727 | R10: =Q10 -> -0.0039272727 | S10: =R10 -> -0.0039272727 | T10: =S10 -> -0.0039272727 | U10: =T10 -> -0.0039272727
B11: TOTAL REVENUE y/y | C11: =C6/15800-1 -> 0.1143038 | D11: =D6/C6-1 -> 0.10240827 | I11: =I6/D6-1 -> 0.10799114 | J11: =J6/E6-1 -> 0.11533767 | K11: =K6/F6-1 -> 0.11482213 | L11: =L6/G6-1 -> 0.11795367 | M11: =AVERAGE(J11:L11) -> 0.11603783 | N11: =N6/I6-1 -> 0.098189723 | O11: =O6/N6-1 -> 0.098834735 | P11: =P6/O6-1 -> 0.099456567 | Q11: =Q6/P6-1 -> 0.10005577 | R11: =R6/Q6-1 -> 0.1006329 | S11: =S6/R6-1 -> 0.10118852 | T11: =T6/S6-1 -> 0.1017232 | U11: =U6/T6-1 -> 0.10223749

Sheet Calcs
A1: =CoName -> Adobe Inc. | C1: Hist. | D1: Hist. | E1: Hist. | F1: Proj. | G1: Proj. | H1: Proj. | I1: Proj. | J1: Proj. | K1: Proj. | L1: Proj. | M1: Proj.
A2: Net PP&E | C2: 2022 | D2: =C2+1 -> 2023 | E2: =D2+1 -> 2024 | F2: =E2+1 -> 2025 | G2: =F2+1 -> 2026 | H2: =G2+1 -> 2027 | I2: =H2+1 -> 2028 | J2: =I2+1 -> 2029 | K2: =J2+1 -> 2030 | ... M2: =L2+1 -> 2032
B3: Capital expenditure % of sales | F3: =Assumptions!F32 -> 0.013531737 | G3: =Assumptions!G32 -> 0.013531737 | H3: =Assumptions!H32 -> 0.013531737 | I3: =Assumptions!I32 -> 0.013531737 | J3: =Assumptions!J32 -> 0.013531737 | K3: =Assumptions!K32 -> 0.013531737 | L3: =Assumptions!L32 -> 0.013531737 | M3: =Assumptions!M32 -> 0.013531737
B4: Depreciation % of PP&E | F4: =Assumptions!F33 -> 0.2881072 | G4: =F4 -> 0.2881072 | H4: =G4 -> 0.2881072 | I4: =H4 -> 0.2881072 | J4: =I4 -> 0.2881072 | K4: =J4 -> 0.2881072 | L4: =K4 -> 0.2881072 | M4: =L4 -> 0.2881072
B6: Beginning PP&E | F6: =E9 -> 2217 | G6: =F9 -> 1897.8395 | H6: =G9 -> 1702.2164 | I6: =H9 -> 1597.8788 | J6: =I9 -> 1562.2313 | K6: =J9 -> 1579.5943 | L6: =K9 -> 1639.2558 | M6: =L9 -> 1734.0907
B7: Capex | F7: =F3*IncState!F16 -> 319.57321 | G7: =G3*IncState!G16 -> 351.15814 | H7: =H3*IncState!H16 -> 386.08313 | I7: =I3*IncState!I16 -> 424.71297 | J7: =J3*IncState!J16 -> 467.45307 | K7: =K3*IncState!K16 -> 514.75395 | L7: =L3*IncState!L16 -> 567.11637 | M7: =M3*IncState!M16 -> 625.09693
B8: Depreciation | F8: =F4*F6 -> 638.73367 | G8: =G4*G6 -> 546.78124 | H8: =H4*H6 -> 490.42082 | I8: =I4*I6 -> 460.36038 | J8: =J4*J6 -> 450.0901 | K8: =K4*K6 -> 455.0925 | L8: =L4*L6 -> 472.28139 | M8: =M4*M6 -> 499.60403
B9: Ending PP&E | E9: =BalSheet!E20 -> 2217 | F9: =F6+F7-F8 -> 1897.8395 | G9: =G6+G7-G8 -> 1702.2164 | H9: =H6+H7-H8 -> 1597.8788 | I9: =I6+I7-I8 -> 1562.2313 | J9: =J6+J7-J8 -> 1579.5943 | K9: =K6+K7-K8 -> 1639.2558 | L9: =L6+L7-L8 -> 1734.0907 | M9: =M6+M7-M8 -> 1859.5836
A10: Equity | C10: =C2 -> 2022 | D10: =D2 -> 2023 | E10: =E2 -> 2024 | F10: =F2 -> 2025 | G10: =G2 -> 2026 | H10: =H2 -> 2027 | I10: =I2 -> 2028 | J10: =J2 -> 2029 | ... M10: =M2 -> 2032
B11: Share issuance/(repurchases) | F11: =Assumptions!F34 -> -2500 | G11: =Assumptions!G34 -> -2500 | H11: =Assumptions!H34 -> -2500 | I11: =Assumptions!I34 -> -900 | J11: =Assumptions!J34 -> 0 | K11: =Assumptions!K34 -> 0 | L11: =Assumptions!L34 -> 0 | M11: =Assumptions!M34 -> 0
B13: Beginning balance | F13: =E16 -> 14105 | G13: =F16 -> 17601.347 | H13: =G16 -> 21690.34 | I13: =H16 -> 26434.653 | J13: =I16 -> 33503.801 | K13: =J16 -> 42274.907 | L13: =K16 -> 51933.548 | M13: =L16 -> 62574.698
B14: Net income | F14: =IncState!F35 -> 5996.3465 | G14: =IncState!G35 -> 6588.9938 | H14: =IncState!H35 -> 7244.3125 | I14: =IncState!I35 -> 7969.1478 | J14: =IncState!J35 -> 8771.1063 | K14: =IncState!K35 -> 9658.6415 | L14: =IncState!L35 -> 10641.149 | M14: =IncState!M35 -> 11729.074
B15: Share issuance / (repurchase) | F15: =F11 -> -2500 | G15: =G11 -> -2500 | H15: =H11 -> -2500 | I15: =I11 -> -900 | J15: =J11 -> 0 | K15: =K11 -> 0 | L15: =L11 -> 0 | M15: =M11 -> 0
B16: Ending balance | E16: =BalSheet!E36 -> 14105 | F16: =SUM(F13:F15) -> 17601.347 | G16: =SUM(G13:G15) -> 21690.34 | H16: =SUM(H13:H15) -> 26434.653 | I16: =SUM(I13:I15) -> 33503.801 | J16: =SUM(J13:J15) -> 42274.907 | K16: =SUM(K13:K15) -> 51933.548 | L16: =SUM(L13:L15) -> 62574.698 | M16: =SUM(M13:M15) -> 74303.772
A17: OWC | C17: =C10 -> 2022 | D17: =D10 -> 2023 | E17: =E10 -> 2024 | F17: =F10 -> 2025 | G17: =G10 -> 2026 | H17: =H10 -> 2027 | I17: =I10 -> 2028 | J17: =J10 -> 2029 | ... M17: =M10 -> 2032
B18: Operating Cash | E18: =BalSheet!E14 -> 1075.25 | F18: =BalSheet!F14 -> 1180.8285 | G18: =BalSheet!G14 -> 1297.5354 | H18: =BalSheet!H14 -> 1426.5838 | I18: =BalSheet!I14 -> 1569.3217 | J18: =BalSheet!J14 -> 1727.2471 | K18: =BalSheet!K14 -> 1902.0247 | L18: =BalSheet!L14 -> 2095.5047 | M18: =BalSheet!M14 -> 2309.7439
B19: =BalSheet!B16 -> Accounts receivable | E19: =BalSheet!E16 -> 2072 | F19: =BalSheet!F16 -> 2275.4491 | G19: =BalSheet!G16 -> 2500.3425 | H19: =BalSheet!H16 -> 2749.018 | I19: =BalSheet!I16 -> 3024.0731 | J19: =BalSheet!J16 -> 3328.3944 | K19: =BalSheet!K16 -> 3665.1897 | L19: =BalSheet!L16 -> 4038.0245 | M19: =BalSheet!M16 -> 4450.862
B20: Other current assets | E20: =BalSheet!E17 -> 1274 | F20: =BalSheet!F17 -> 1399.0937 | G20: =BalSheet!G17 -> 1537.3728 | H20: =BalSheet!H17 -> 1690.2746 | I20: =BalSheet!I17 -> 1859.3963 | J20: =BalSheet!J17 -> 2046.5128 | K20: =BalSheet!K17 -> 2253.5963 | L20: =BalSheet!L17 -> 2482.8394 | M20: =BalSheet!M17 -> 2736.6786
B21: Accounts payables | E21: =BalSheet!E28 -> 2816 | F21: =BalSheet!F28 -> 3092.5023 | G21: =BalSheet!G28 -> 3398.1489 | H21: =BalSheet!H28 -> 3736.1171 | I21: =BalSheet!I28 -> 4109.9372 | J21: =BalSheet!J28 -> 4523.5321 | K21: =BalSheet!K28 -> 4981.2616 | L21: =BalSheet!L28 -> 5487.9715 | M21: =BalSheet!M28 -> 6049.0479
B22: Other current liabilities | E22: =BalSheet!E29 -> 6206 | F22: =BalSheet!F29 -> 6815.3654 | G22: =BalSheet!G29 -> 7488.9603 | H22: =BalSheet!H29 -> 8233.7865 | I22: =BalSheet!I29 -> 9057.6244 | J22: =BalSheet!J29 -> 9969.1194 | K22: =BalSheet!K29 -> 10977.88 | L22: =BalSheet!L29 -> 12094.585 | M22: =BalSheet!M29 -> 13331.105
A23: * | B23: OWC | E23: =SUM(E18:E20)-SUM(E21:E22) -> -4600.75 | F23: =SUM(F18:F20)-SUM(F21:F22) -> -5052.4964 | G23: =SUM(G18:G20)-SUM(G21:G22) -> -5551.8585 | H23: =SUM(H18:H20)-SUM(H21:H22) -> -6104.0273 | I23: =SUM(I18:I20)-SUM(I21:I22) -> -6714.7705 | J23: =SUM(J18:J20)-SUM(J21:J22) -> -7390.4973 | K23: =SUM(K18:K20)-SUM(K21:K22) -> -8138.3308 | L23: =SUM(L18:L20)-SUM(L21:L22) -> -8966.1878 | M23: =SUM(M18:M20)-SUM(M21:M22) -> -9882.8683
B24: Change in OWC | F24: =E23-F23 -> 451.74637 | G24: =F23-G23 -> 499.36214 | H24: =G23-H23 -> 552.16879 | I24: =H23-I23 -> 610.74315 | J24: =I23-J23 -> 675.72683 | K24: =J23-K23 -> 747.83348 | L24: =K23-L23 -> 827.85701 | M24: =L23-M23 -> 916.68056

Sheet Debt
A1: =CoName -> Adobe Inc. | C1: Hist. | D1: Hist. | E1: Hist. | F1: Proj. | G1: Proj. | H1: Proj. | I1: Proj. | J1: Proj. | K1: Proj. | L1: Proj. | M1: Proj.
A2: Assumptions | C2: 44926 | D2: 45291 | E2: 45657 | F2: 46022 | G2: 46387 | H2: 46752 | I2: 47118 | J2: 47483 | K2: =2030 -> 2030 | L2: =K2+1 -> 2031 | M2: =L2+1 -> 2032
B4: Interest rate on revolver | F4: =Assumptions!F23 -> 0.036 | G4: =Assumptions!G23 -> 0.036 | H4: =Assumptions!H23 -> 0.036 | I4: =Assumptions!I23 -> 0.036 | J4: =Assumptions!J23 -> 0.036 | K4: =Assumptions!K23 -> 0.036 | L4: =Assumptions!L23 -> 0.036 | M4: =Assumptions!M23 -> 0.036
B5: Interest rate on long-term debt | F5: =Assumptions!F24 -> 0.036 | G5: =Assumptions!G24 -> 0.036 | H5: =Assumptions!H24 -> 0.036 | I5: =Assumptions!I24 -> 0.036 | J5: =Assumptions!J24 -> 0.036 | K5: =Assumptions!K24 -> 0.036 | L5: =Assumptions!L24 -> 0.036 | M5: =Assumptions!M24 -> 0.036
B6: Interest rate on cash | F6: =Assumptions!F25 -> 0.050067907 | G6: =Assumptions!G25 -> 0.050067907 | H6: =Assumptions!H25 -> 0.050067907 | I6: =Assumptions!I25 -> 0.050067907 | J6: =Assumptions!J25 -> 0.050067907 | K6: =Assumptions!K25 -> 0.050067907 | L6: =Assumptions!L25 -> 0.050067907 | M6: =Assumptions!M25 -> 0.050067907
B8: Issuance of long-term debt | F8: =Assumptions!F27 -> 0 | G8: =Assumptions!G27 -> 0 | H8: =Assumptions!H27 -> 0 | I8: =Assumptions!I27 -> 0 | J8: =Assumptions!J27 -> 0 | K8: =Assumptions!K27 -> 0 | L8: =Assumptions!L27 -> 0 | M8: =Assumptions!M27 -> 0
B9: Repayment of long-term debt | F9: =Assumptions!F28 -> -1499 | G9: =Assumptions!G28 -> 0 | H9: =Assumptions!H28 -> 0 | I9: =Assumptions!I28 -> 0 | J9: =Assumptions!J28 -> 0 | K9: =Assumptions!K28 -> 0 | L9: =Assumptions!L28 -> 0 | M9: =Assumptions!M28 -> 0
A11: Revolver | C11: =C2 -> 44926 | D11: =D2 -> 45291 | E11: =E2 -> 45657 | F11: =F2 -> 46022 | G11: =G2 -> 46387 | H11: =H2 -> 46752 | I11: =I2 -> 47118 | J11: =J2 -> 47483 | ... M11: =M2 -> 2032
B12: Balance | F12: NO REVOLVER
B13: Interest rate
B14: Interest expense
A16: Long term debt | C16: =C11 -> 44926 | D16: =D11 -> 45291 | E16: =E11 -> 45657 | F16: =F11 -> 46022 | G16: =G11 -> 46387 | H16: =H11 -> 46752 | I16: =I11 -> 47118 | J16: =J11 -> 47483 | ... M16: =M11 -> 2032
B17: Beginning balance | F17: =E20 -> 5628 | G17: =F20 -> 4129 | H17: =G20 -> 4129 | I17: =H20 -> 4129 | J17: =I20 -> 4129 | K17: =J20 -> 4129 | L17: =K20 -> 4129 | M17: =L20 -> 4129
B18: Issuance | F18: =F8 -> 0 | G18: =G8 -> 0 | H18: =H8 -> 0 | I18: =I8 -> 0 | J18: =J8 -> 0 | K18: =K8 -> 0 | L18: =L8 -> 0 | M18: =M8 -> 0
B19: Repayment | F19: =F9 -> -1499 | G19: =G9 -> 0 | H19: =H9 -> 0 | I19: =I9 -> 0 | J19: =J9 -> 0 | K19: =K9 -> 0 | L19: =L9 -> 0 | M19: =M9 -> 0
B20: Ending balance | E20: =BalSheet!E27+BalSheet!E32 -> 5628 | F20: =SUM(F17:F19) -> 4129 | G20: =SUM(G17:G19) -> 4129 | H20: =SUM(H17:H19) -> 4129 | I20: =SUM(I17:I19) -> 4129 | J20: =SUM(J17:J19) -> 4129 | K20: =SUM(K17:K19) -> 4129 | L20: =SUM(L17:L19) -> 4129 | M20: =SUM(M17:M19) -> 4129
B21: Interest rate | F21: =F5 -> 0.036 | G21: =G5 -> 0.036 | H21: =H5 -> 0.036 | I21: =I5 -> 0.036 | J21: =J5 -> 0.036 | K21: =K5 -> 0.036 | L21: =L5 -> 0.036 | M21: =M5 -> 0.036
B22: Interest expense | F22: =F20*F21 -> 148.644 | G22: =G20*G21 -> 148.644 | H22: =H20*H21 -> 148.644 | I22: =I20*I21 -> 148.644 | J22: =J20*J21 -> 148.644 | K22: =K20*K21 -> 148.644 | L22: =L20*L21 -> 148.644 | M22: =M20*M21 -> 148.644
A24: Debt summary | C24: =C16 -> 44926 | D24: =D16 -> 45291 | E24: =E16 -> 45657 | F24: =F16 -> 46022 | G24: =G16 -> 46387 | H24: =H16 -> 46752 | I24: =I16 -> 47118 | J24: =J16 -> 47483 | ... M24: =M16 -> 2032
B25: Revolver | F25: =F12 -> NO REVOLVER
B26: Total long term debt | F26: =F20 -> 4129 | G26: =G20 -> 4129 | H26: =H20 -> 4129 | I26: =I20 -> 4129 | J26: =J20 -> 4129 | K26: =K20 -> 4129 | L26: =L20 -> 4129 | M26: =M20 -> 4129
B27: Total debt | F27: =F22 -> 148.644 | G27: =G22 -> 148.644 | H27: =H22 -> 148.644 | I27: =I22 -> 148.644 | J27: =J22 -> 148.644 | K27: =K22 -> 148.644 | L27: =L22 -> 148.644 | M27: =M22 -> 148.644
B28: Total interest expense
A30: Interest income | C30: =C11 -> 44926 | D30: =D11 -> 45291 | E30: =E11 -> 45657 | F30: =F11 -> 46022 | G30: =G11 -> 46387 | H30: =H11 -> 46752 | I30: =I11 -> 47118 | J30: =J11 -> 47483 | ... M30: =M11 -> 2032
B31: Excess Cash | F31: =BalSheet!F15 -> 9577.546 | G31: =BalSheet!G15 -> 14342.101 | H31: =BalSheet!H15 -> 19703.57 | I31: =BalSheet!I15 -> 27357.657 | J31: =BalSheet!J15 -> 36701.155 | K31: =BalSheet!K15 -> 46934.789 | L31: =BalSheet!L15 -> 58165.585 | M31: =BalSheet!M15 -> 70508.956
B32: Interest rate | F32: =F6 -> 0.050067907 | G32: =G6 -> 0.050067907 | H32: =H6 -> 0.050067907 | I32: =I6 -> 0.050067907 | J32: =J6 -> 0.050067907 | K32: =K6 -> 0.050067907 | L32: =L6 -> 0.050067907 | M32: =M6 -> 0.050067907
B33: Interest income | F33: =F31*F32 -> 479.52768 | G33: =G31*G32 -> 718.07898 | H33: =H31*H32 -> 986.51652 | I33: =I31*I32 -> 1369.7406 | J33: =J31*J32 -> 1837.55 | K33: =K31*K32 -> 2349.9267 | L33: =L31*L32 -> 2912.2291 | M33: =M31*M32 -> 3530.2359

Sheet IncState
A1: =CoName -> Adobe Inc. | C1: Hist. | D1: Hist. | E1: Hist. | F1: Proj. | G1: Proj. | H1: Proj. | I1: Proj. | J1: Proj. | K1: Proj. | L1: Proj. | M1: Proj.
A2: Assumptions | C2: 44926 | D2: 45291 | E2: 45657 | F2: 46022 | G2: 46387 | H2: 46752 | I2: 47118 | J2: 47483 | K2: 2030 | L2: 2031 | M2: 2032
B4: Revenue growth | F4: =Assumptions!F10 -> 0.098189723 | G4: =Assumptions!G10 -> 0.098834735 | H4: =Assumptions!H10 -> 0.099456567 | I4: =Assumptions!I10 -> 0.10005577 | J4: =Assumptions!J10 -> 0.1006329 | K4: =Assumptions!K10 -> 0.10118852 | L4: =Assumptions!L10 -> 0.1017232 | M4: =Assumptions!M10 -> 0.10223749
B5: Cost of goods sold as % of sales | F5: =Assumptions!F11 -> 0.10964892 | G5: =Assumptions!G11 -> 0.10964892 | H5: =Assumptions!H11 -> 0.10964892 | I5: =Assumptions!I11 -> 0.10964892 | J5: =Assumptions!J11 -> 0.10964892 | K5: =Assumptions!K11 -> 0.10964892 | L5: =Assumptions!L11 -> 0.10964892 | M5: =Assumptions!M11 -> 0.10964892
B6: R&D % of sales | F6: =Assumptions!F12 -> 0.18339921 | G6: =Assumptions!G12 -> 0.18339921 | H6: =Assumptions!H12 -> 0.18339921 | I6: =Assumptions!I12 -> 0.18339921 | J6: =Assumptions!J12 -> 0.18339921 | K6: =Assumptions!K12 -> 0.18339921 | L6: =Assumptions!L12 -> 0.18339921 | M6: =Assumptions!M12 -> 0.18339921
B7: SG&A % of sales | F7: =Assumptions!F13 -> 0.39348989 | G7: =Assumptions!G13 -> 0.39348989 | H7: =Assumptions!H13 -> 0.39348989 | I7: =Assumptions!I13 -> 0.39348989 | J7: =Assumptions!J13 -> 0.39348989 | K7: =Assumptions!K13 -> 0.39348989 | L7: =Assumptions!L13 -> 0.39348989 | M7: =Assumptions!M13 -> 0.39348989
B8: Amortization amount | C8: =C23 -> 169 | D8: =D23 -> 168 | E8: =E23 -> 169 | F8: =Assumptions!F14 -> 169 | G8: =Assumptions!G14 -> 169 | H8: =Assumptions!H14 -> 169 | I8: =Assumptions!I14 -> 169 | J8: =Assumptions!J14 -> 169 | K8: =Assumptions!K14 -> 169 | L8: =Assumptions!L14 -> 169 | M8: =Assumptions!M14 -> 169
B9: Non recurring items, amount | F9: =Assumptions!F15 -> 0 | G9: =Assumptions!G15 -> 0 | H9: =Assumptions!H15 -> 0 | I9: =Assumptions!I15 -> 0 | J9: =Assumptions!J15 -> 0 | K9: =Assumptions!K15 -> 0 | L9: =Assumptions!L15 -> 0 | M9: =Assumptions!M15 -> 0
B10: Other income (expense), amt | F10: =Assumptions!F16 -> 0 | G10: =Assumptions!G16 -> 0 | H10: =Assumptions!H16 -> 0 | I10: =Assumptions!I16 -> 0 | J10: =Assumptions!J16 -> 0 | K10: =Assumptions!K16 -> 0 | L10: =Assumptions!L16 -> 0 | M10: =Assumptions!M16 -> 0
B11: Effective tax rate | F11: =Assumptions!F17 -> 0.19 | G11: =Assumptions!G17 -> 0.19 | H11: =Assumptions!H17 -> 0.19 | I11: =Assumptions!I17 -> 0.19 | J11: =Assumptions!J17 -> 0.19 | K11: =Assumptions!K17 -> 0.19 | L11: =Assumptions!L17 -> 0.19 | M11: =Assumptions!M17 -> 0.19
B12: Basic WASO | F12: =Assumptions!F18 -> 447 | G12: =Assumptions!G18 -> 447 | H12: =Assumptions!H18 -> 447 | I12: =Assumptions!I18 -> 447 | J12: =Assumptions!J18 -> 447 | K12: =Assumptions!K18 -> 447 | L12: =Assumptions!L18 -> 447 | M12: =Assumptions!M18 -> 447
B13: Diluted WASO | F13: =Assumptions!F19 -> 450 | G13: =Assumptions!G19 -> 450 | H13: =Assumptions!H19 -> 450 | I13: =Assumptions!I19 -> 450 | J13: =Assumptions!J19 -> 450 | K13: =Assumptions!K19 -> 450 | L13: =Assumptions!L19 -> 450 | M13: =Assumptions!M19 -> 450
A15: Income statement | C15: =C37 -> 44926 | D15: =D37 -> 45291 | E15: =E37 -> 45657 | F15: =F37 -> 46022 | G15: =G37 -> 46022 | H15: =H37 -> 46022 | I15: =I37 -> 46022 | J15: =J37 -> 46022 | ... M15: =M37 -> 46022
B16: Revenue | C16: 17606 | D16: 19409 | E16: 21505 | F16: =E16*(1+F4) -> 23616.57 | G16: =F16*(1+G4) -> 25950.707 | H16: =G16*(1+H4) -> 28531.676 | I16: =H16*(1+I4) -> 31386.435 | J16: =I16*(1+J4) -> 34544.942 | K16: =J16*(1+K4) -> 38040.494 | L16: =K16*(1+L4) -> 41910.095 | M16: =L16*(1+M4) -> 46194.878
B17: COGS | C17: 2165 | D17: 2354 | E17: 2358 | F17: =F16*F5 -> 2589.5314 | G17: =G16*G5 -> 2845.467 | H17: =H16*H5 -> 3128.4674 | I17: =I16*I5 -> 3441.4886 | J17: =J16*J5 -> 3787.8156 | K17: =K16*K5 -> 4171.099 | L17: =L16*L5 -> 4595.3966 | M17: =M16*M5 -> 5065.2184
B18: R&D | C18: 2987 | D18: 2373 | E18: 3944 | F18: =F16*F6 -> 4331.2603 | G18: =G16*G6 -> 4759.3392 | H18: =H16*H6 -> 5232.6868 | I18: =I16*I6 -> 5756.2473 | J18: =J16*J6 -> 6335.5151 | K18: =K16*K6 -> 6976.5965 | L18: =L16*L6 -> 7686.2782 | M18: =M16*M6 -> 8472.1041
B19: SG&A | C19: =9343-C18 -> 6356 | D19: =10405-D18 -> 8032 | E19: =12406-E18 -> 8462 | F19: =F7*F16 -> 9292.8814 | G19: =G7*G16 -> 10211.341 | H19: =H7*H16 -> 11226.926 | I19: =I7*I16 -> 12350.245 | J19: =J7*J16 -> 13593.085 | K19: =K7*K16 -> 14968.55 | L19: =L7*L16 -> 16491.198 | M19: =M7*M16 -> 18177.217
A20: * | B20: EBIT | C20: =C16-SUM(C17:C19) -> 6098 | D20: =D16-SUM(D17:D19) -> 6650 | E20: =E16-SUM(E17:E19) -> 6741 | F20: =F16-SUM(F17:F19) -> 7402.8969 | G20: =G16-SUM(G17:G19) -> 8134.5603 | H20: =H16-SUM(H17:H19) -> 8943.5957 | I20: =I16-SUM(I17:I19) -> 9838.4541 | J20: =J16-SUM(J17:J19) -> 10828.526 | ... M20: =M16-SUM(M17:M19) -> 14480.338
B22: Depreciation | C22: =856-C23 -> 687 | D22: =872-D23 -> 704 | E22: =857-E23 -> 688 | F22: =Calcs!F8 -> 638.73367 | G22: =Calcs!G8 -> 546.78124 | H22: =Calcs!H8 -> 490.42082 | I22: =Calcs!I8 -> 460.36038 | J22: =Calcs!J8 -> 450.0901 | K22: =Calcs!K8 -> 455.0925 | L22: =Calcs!L8 -> 472.28139 | M22: =Calcs!M8 -> 499.60403
B23: Amortization | C23: 169 | D23: 168 | E23: 169 | F23: =F8 -> 169 | G23: =G8 -> 169 | H23: =H8 -> 169 | I23: =I8 -> 169 | J23: =J8 -> 169 | K23: =K8 -> 169 | L23: =L8 -> 169 | M23: =M8 -> 169
A24: * | B24: EBITDA | C24: =C20+SUM(C22:C23) -> 6954 | D24: =D20+SUM(D22:D23) -> 7522 | E24: =E20+SUM(E22:E23) -> 7598 | F24: =F20+SUM(F22:F23) -> 8210.6306 | G24: =G20+SUM(G22:G23) -> 8850.3415 | H24: =H20+SUM(H22:H23) -> 9603.0165 | I24: =I20+SUM(I22:I23) -> 10467.814 | J24: =J20+SUM(J22:J23) -> 11447.616 | ... M24: =M20+SUM(M22:M23) -> 15148.942
B26: Non-recurring items | C26: -19 | D26: 16 | E26: 48 | F26: =F9 -> 0 | G26: =G9 -> 0 | H26: =H9 -> 0 | I26: =I9 -> 0 | J26: =J9 -> 0 | K26: =K9 -> 0 | L26: =L9 -> 0 | M26: =M9 -> 0
B27: Other income (expense) | C27: 41 | D27: 246 | E27: 311 | F27: =F10 -> 0 | G27: =G10 -> 0 | H27: =H10 -> 0 | I27: =I10 -> 0 | J27: =J10 -> 0 | K27: =K10 -> 0 | L27: =L10 -> 0 | M27: =M10 -> 0
B29: Interest income | F29: =IF(circ=1,Debt!F33,0) -> 0 | G29: =IF(circ=1,Debt!G33,0) -> 0 | H29: =IF(circ=1,Debt!H33,0) -> 0 | I29: =IF(circ=1,Debt!I33,0) -> 0 | J29: =IF(circ=1,Debt!J33,0) -> 0 | K29: =IF(circ=1,Debt!K33,0) -> 0 | L29: =IF(circ=1,Debt!L33,0) -> 0 | M29: =IF(circ=1,Debt!M33,0) -> 0
B30: Interest expense | C30: -112 | D30: -113 | E30: -169 | F30: =IF(circ=1,Debt!F22,0) -> 0 | G30: =IF(circ=1,Debt!G22,0) -> 0 | H30: =IF(circ=1,Debt!H22,0) -> 0 | I30: =IF(circ=1,Debt!I22,0) -> 0 | J30: =IF(circ=1,Debt!J22,0) -> 0 | K30: =IF(circ=1,Debt!K22,0) -> 0 | L30: =IF(circ=1,Debt!L22,0) -> 0 | M30: =IF(circ=1,Debt!M22,0) -> 0
A32: * | B32: Pretax Income | C32: =C20+SUM(C26:C27,C29:C30) -> 6008 | D32: =D20+SUM(D26:D27,D29:D30) -> 6799 | E32: =E20+SUM(E26:E27,E29:E30) -> 6931 | F32: =F20+SUM(F26:F27,F29:F30) -> 7402.8969 | G32: =G20+SUM(G26:G27,G29:G30) -> 8134.5603 | H32: =H20+SUM(H26:H27,H29:H30) -> 8943.5957 | I32: =I20+SUM(I26:I27,I29:I30) -> 9838.4541 | J32: =J20+SUM(J26:J27,J29:J30) -> 10828.526 | ... M32: =M20+SUM(M26:M27,M29:M30) -> 14480.338
B34: Tax expense | C34: 1252 | D34: 1371 | E34: 1371 | F34: =F32*F11 -> 1406.5504 | G34: =G32*G11 -> 1545.5665 | H34: =H32*H11 -> 1699.2832 | I34: =I32*I11 -> 1869.3063 | J34: =J32*J11 -> 2057.42 | K34: =K32*K11 -> 2265.6073 | L34: =L32*L11 -> 2496.0721 | M34: =M32*M11 -> 2751.2642
A35: * | B35: Net income | C35: =C32-C34 -> 4756 | D35: =D32-D34 -> 5428 | E35: =E32-E34 -> 5560 | F35: =F32-F34 -> 5996.3465 | G35: =G32-G34 -> 6588.9938 | H35: =H32-H34 -> 7244.3125 | I35: =I32-I34 -> 7969.1478 | J35: =J32-J34 -> 8771.1063 | ... M35: =M32-M34 -> 11729.074
A37: Shareholder information | C37: 44926 | D37: 45291 | E37: 45657 | F37: 46022 | G37: 46022 | H37: 46022 | I37: 46022 | J37: 46022 | K37: 46022 | L37: 46022 | M37: 46022
B38: Basic WASO | C38: 470 | D38: 457 | E38: 447 | F38: =F12 -> 447 | G38: =G12 -> 447 | H38: =H12 -> 447 | I38: =I12 -> 447 | J38: =J12 -> 447 | K38: =K12 -> 447 | L38: =L12 -> 447 | M38: =M12 -> 447
B39: Diluted WASO | C39: 471 | D39: 459 | E39: 450 | F39: =F13 -> 450 | G39: =G13 -> 450 | H39: =H13 -> 450 | I39: =I13 -> 450 | J39: =J13 -> 450 | K39: =K13 -> 450 | L39: =L13 -> 450 | M39: =M13 -> 450
B40: Basic earnings per share | C40: =C35/C38 -> 10.119149 | D40: =D35/D38 -> 11.877462 | E40: =E35/E38 -> 12.438479 | F40: =F35/F38 -> 13.414645 | G40: =G35/G38 -> 14.740478 | H40: =H35/H38 -> 16.206516 | I40: =I35/I38 -> 17.828071 | J40: =J35/J38 -> 19.622162 | ... M40: =M35/M38 -> 26.239539
A41: * | B41: Diluted earnings per share | C41: =C35/C39 -> 10.097665 | D41: =D35/D39 -> 11.825708 | E41: =E35/E39 -> 12.355556 | F41: =F35/F39 -> 13.325214 | G41: =G35/G39 -> 14.642209 | H41: =H35/H39 -> 16.098472 | I41: =I35/I39 -> 17.709217 | J41: =J35/J39 -> 19.491347 | ... M41: =M35/M39 -> 26.064609

Sheet BalSheet
A1: =CoName -> Adobe Inc. | C1: Hist. | D1: Hist. | E1: Hist. | F1: Proj. | G1: Proj. | H1: Proj. | I1: Proj. | J1: Proj. | K1: Proj. | L1: Proj. | M1: Proj.
A2: Assumptions | C2: 44926 | D2: 45291 | E2: 45657 | F2: 46022 | G2: 46387 | H2: 46752 | I2: 47118 | J2: 47483 | K2: =2030 -> 2030 | L2: =K2+1 -> 2031 | M2: =L2+1 -> 2032
B4: Operating Cash % of sales | F4: =Assumptions!F43 -> 0.05 | G4: =F4 -> 0.05 | H4: =G4 -> 0.05 | I4: =H4 -> 0.05 | J4: =I4 -> 0.05 | K4: =J4 -> 0.05 | L4: =K4 -> 0.05 | M4: =L4 -> 0.05
B5: Accounts receivable % of sales | F5: =Assumptions!F44 -> 0.096349686 | G5: =Assumptions!G44 -> 0.096349686 | H5: =Assumptions!H44 -> 0.096349686 | I5: =Assumptions!I44 -> 0.096349686 | J5: =Assumptions!J44 -> 0.096349686 | K5: =Assumptions!K44 -> 0.096349686 | L5: =Assumptions!L44 -> 0.096349686 | M5: =Assumptions!M44 -> 0.096349686
B6: Other current assets % of sales | F6: =Assumptions!F45 -> 0.059242037 | G6: =Assumptions!G45 -> 0.059242037 | H6: =Assumptions!H45 -> 0.059242037 | I6: =Assumptions!I45 -> 0.059242037 | J6: =Assumptions!J45 -> 0.059242037 | K6: =Assumptions!K45 -> 0.059242037 | L6: =Assumptions!L45 -> 0.059242037 | M6: =Assumptions!M45 -> 0.059242037
B7: Other long-term assets % of sales | F7: =Assumptions!F48 -> 0.14931411 | G7: =Assumptions!G48 -> 0.14931411 | H7: =Assumptions!H48 -> 0.14931411 | I7: =Assumptions!I48 -> 0.14931411 | J7: =Assumptions!J48 -> 0.14931411 | K7: =Assumptions!K48 -> 0.14931411 | L7: =Assumptions!L48 -> 0.14931411 | M7: =Assumptions!M48 -> 0.14931411
B9: Accounts payable/Accural % of COGS | F9: =Assumptions!F52 -> 1.1942324 | G9: =Assumptions!G52 -> 1.1942324 | H9: =Assumptions!H52 -> 1.1942324 | I9: =Assumptions!I52 -> 1.1942324 | J9: =Assumptions!J52 -> 1.1942324 | K9: =Assumptions!K52 -> 1.1942324 | L9: =Assumptions!L52 -> 1.1942324 | M9: =Assumptions!M52 -> 1.1942324
B10: Other current liabilities % of sales | F10: =Assumptions!F53 -> 0.28858405 | G10: =Assumptions!G53 -> 0.28858405 | H10: =Assumptions!H53 -> 0.28858405 | I10: =Assumptions!I53 -> 0.28858405 | J10: =Assumptions!J53 -> 0.28858405 | K10: =Assumptions!K53 -> 0.28858405 | L10: =Assumptions!L53 -> 0.28858405 | M10: =Assumptions!M53 -> 0.28858405
B11: Other long-term liabilities % of sales | F11: =Assumptions!F54 -> 0.0685887 | G11: =Assumptions!G54 -> 0.0685887 | H11: =Assumptions!H54 -> 0.0685887 | I11: =Assumptions!I54 -> 0.0685887 | J11: =Assumptions!J54 -> 0.0685887 | K11: =Assumptions!K54 -> 0.0685887 | L11: =Assumptions!L54 -> 0.0685887 | M11: =Assumptions!M54 -> 0.0685887
A13: Balance sheet | C13: =C2 -> 44926 | D13: =D2 -> 45291 | E13: =E2 -> 45657 | F13: =F2 -> 46022 | G13: =G2 -> 46387 | H13: =H2 -> 46752 | I13: =I2 -> 47118 | J13: =J2 -> 47483 | ... M13: =M2 -> 2032
B14: Operating Cash | C14: =5%*IncState!C16 -> 880.3 | D14: =5%*IncState!D16 -> 970.45 | E14: =5%*IncState!E16 -> 1075.25 | F14: =F4*IncState!F16 -> 1180.8285 | G14: =G4*IncState!G16 -> 1297.5354 | H14: =H4*IncState!H16 -> 1426.5838 | I14: =I4*IncState!I16 -> 1569.3217 | J14: =J4*IncState!J16 -> 1727.2471 | K14: =K4*IncState!K16 -> 1902.0247 | L14: =L4*IncState!L16 -> 2095.5047 | M14: =M4*IncState!M16 -> 2309.7439
B15: Excess cash | C15: =4236+1860-C14 -> 5215.7 | D15: =7141+701-D14 -> 6871.55 | E15: =7613+273-E14 -> 6810.75 | F15: =MAX(CashFlow!F22,0) -> 9577.546 | G15: =MAX(CashFlow!G22,0) -> 14342.101 | H15: =MAX(CashFlow!H22,0) -> 19703.57 | I15: =MAX(CashFlow!I22,0) -> 27357.657 | J15: =MAX(CashFlow!J22,0) -> 36701.155 | K15: =MAX(CashFlow!K22,0) -> 46934.789 | L15: =MAX(CashFlow!L22,0) -> 58165.585 | M15: =MAX(CashFlow!M22,0) -> 70508.956
B16: Accounts receivable | C16: 2065 | D16: 2224 | E16: 2072 | F16: =F5*IncState!F16 -> 2275.4491 | G16: =G5*IncState!G16 -> 2500.3425 | H16: =H5*IncState!H16 -> 2749.018 | I16: =I5*IncState!I16 -> 3024.0731 | J16: =J5*IncState!J16 -> 3328.3944 | K16: =K5*IncState!K16 -> 3665.1897 | L16: =L5*IncState!L16 -> 4038.0245 | M16: =M5*IncState!M16 -> 4450.862
B17: Other current assets | C17: 835 | D17: 1018 | E17: 1274 | F17: =F6*IncState!F16 -> 1399.0937 | G17: =G6*IncState!G16 -> 1537.3728 | H17: =H6*IncState!H16 -> 1690.2746 | I17: =I6*IncState!I16 -> 1859.3963 | J17: =J6*IncState!J16 -> 2046.5128 | K17: =K6*IncState!K16 -> 2253.5963 | L17: =L6*IncState!L16 -> 2482.8394 | M17: =M6*IncState!M16 -> 2736.6786
B18: Total current assets | C18: =SUM(C14:C17) -> 8996 | D18: =SUM(D14:D17) -> 11084 | E18: =SUM(E14:E17) -> 11232 | F18: =SUM(F14:F17) -> 14432.917 | G18: =SUM(G14:G17) -> 19677.351 | H18: =SUM(H14:H17) -> 25569.447 | I18: =SUM(I14:I17) -> 33810.448 | J18: =SUM(J14:J17) -> 43803.309 | ... M18: =SUM(M14:M17) -> 80006.24
B20: Property, plant & equipment, net | C20: =1908+407 -> 2315 | D20: =2030+358 -> 2388 | E20: =1936+281 -> 2217 | F20: =Calcs!F9 -> 1897.8395 | G20: =Calcs!G9 -> 1702.2164 | H20: =Calcs!H9 -> 1597.8788 | I20: =Calcs!I9 -> 1562.2313 | J20: =Calcs!J9 -> 1579.5943 | K20: =Calcs!K9 -> 1639.2558 | L20: =Calcs!L9 -> 1734.0907 | M20: =Calcs!M9 -> 1859.5836
B21: Intangible assets | C21: =12787+1449 -> 14236 | D21: =12805+1088 -> 13893 | E21: =12788+782 -> 13570 | F21: =E21-IncState!F8 -> 13401 | G21: =F21-IncState!G8 -> 13232 | H21: =G21-IncState!H8 -> 13063 | I21: =H21-IncState!I8 -> 12894 | J21: =I21-IncState!J8 -> 12725 | K21: =J21-IncState!K8 -> 12556 | L21: =K21-IncState!L8 -> 12387 | M21: =L21-IncState!M8 -> 12218
B22: Other assets | C22: =777+841 -> 1618 | D22: =1191+1223 -> 2414 | E22: =1554+1657 -> 3211 | F22: =F7*IncState!F16 -> 3526.2872 | G22: =G7*IncState!G16 -> 3874.8069 | H22: =H7*IncState!H16 -> 4260.1819 | I22: =I7*IncState!I16 -> 4686.4376 | J22: =J7*IncState!J16 -> 5158.0474 | K22: =K7*IncState!K16 -> 5679.9826 | L22: =L7*IncState!L16 -> 6257.7686 | M22: =M7*IncState!M16 -> 6897.5472
B23: Total non-current assets | C23: =SUM(C20:C22) -> 18169 | D23: =SUM(D20:D22) -> 18695 | E23: =SUM(E20:E22) -> 18998 | F23: =SUM(F20:F22) -> 18825.127 | G23: =SUM(G20:G22) -> 18809.023 | H23: =SUM(H20:H22) -> 18921.061 | I23: =SUM(I20:I22) -> 19142.669 | J23: =SUM(J20:J22) -> 19462.642 | ... M23: =SUM(M20:M22) -> 20975.131
A25: * | B25: TOTAL ASSETS | C25: =SUM(C23,C18) -> 27165 | D25: =SUM(D23,D18) -> 29779 | E25: =SUM(E23,E18) -> 30230 | F25: =SUM(F23,F18) -> 33258.044 | G25: =SUM(G23,G18) -> 38486.375 | H25: =SUM(H23,H18) -> 44490.507 | I25: =SUM(I23,I18) -> 52953.117 | J25: =SUM(J23,J18) -> 63265.951 | ... M25: =SUM(M23,M18) -> 100981.37
B27: Revolver/Short term debt | C27: 500 | D27: 0 | E27: 1499 | F27: =MIN(CashFlow!F22,0) -> 0 | G27: =MIN(CashFlow!G22,0) -> 0 | H27: =MIN(CashFlow!H22,0) -> 0 | I27: =MIN(CashFlow!I22,0) -> 0 | J27: =MIN(CashFlow!J22,0) -> 0 | K27: =MIN(CashFlow!K22,0) -> 0 | L27: =MIN(CashFlow!L22,0) -> 0 | M27: =MIN(CashFlow!M22,0) -> 0
B28: Accounts payable/Accurals | C28: =379+1790+75 -> 2244 | D28: =314+1942+85 -> 2341 | E28: =361+119+2336 -> 2816 | F28: =F9*IncState!F17 -> 3092.5023 | G28: =G9*IncState!G17 -> 3398.1489 | H28: =H9*IncState!H17 -> 3736.1171 | I28: =I9*IncState!I17 -> 4109.9372 | J28: =J9*IncState!J17 -> 4523.5321 | K28: =K9*IncState!K17 -> 4981.2616 | L28: =L9*IncState!L17 -> 5487.9715 | M28: =M9*IncState!M17 -> 6049.0479
B29: Other current liabilities | C29: =5297+87 -> 5384 | D29: =73+5837 -> 5910 | E29: =75+6131 -> 6206 | F29: =F10*(IncState!F16) -> 6815.3654 | G29: =G10*(IncState!G16) -> 7488.9603 | H29: =H10*(IncState!H16) -> 8233.7865 | I29: =I10*(IncState!I16) -> 9057.6244 | J29: =J10*(IncState!J16) -> 9969.1194 | K29: =K10*(IncState!K16) -> 10977.88 | L29: =L10*(IncState!L16) -> 12094.585 | M29: =M10*(IncState!M16) -> 13331.105
B30: Total current liabilities | C30: =SUM(C27:C29) -> 8128 | D30: =SUM(D27:D29) -> 8251 | E30: =SUM(E27:E29) -> 10521 | F30: =SUM(F27:F29) -> 9907.8677 | G30: =SUM(G27:G29) -> 10887.109 | H30: =SUM(H27:H29) -> 11969.904 | I30: =SUM(I27:I29) -> 13167.562 | J30: =SUM(J27:J29) -> 14492.652 | ... M30: =SUM(M27:M29) -> 19380.153
B32: Long-term debt, including current maturities | C32: 3629 | D32: 3634 | E32: 4129 | F32: =Debt!F20 -> 4129 | G32: =Debt!G20 -> 4129 | H32: =Debt!H20 -> 4129 | I32: =Debt!I20 -> 4129 | J32: =Debt!J20 -> 4129 | K32: =Debt!K20 -> 4129 | L32: =Debt!L20 -> 4129 | M32: =Debt!M20 -> 4129
B33: Other long-term liabilities | C33: =117+530+417+293 -> 1357 | D33: =113+514+373+376 -> 1376 | E33: =128+548+353+446 -> 1475 | F33: =F11*IncState!F16 -> 1619.8298 | G33: =G11*IncState!G16 -> 1779.9253 | H33: =H11*IncState!H16 -> 1956.9506 | I33: =I11*IncState!I16 -> 2152.7548 | J33: =J11*IncState!J16 -> 2369.3927 | K33: =K11*IncState!K16 -> 2609.148 | L33: =L11*IncState!L16 -> 2874.5589 | M33: =M11*IncState!M16 -> 3168.4466
B34: Total non-current liabilities | C34: =SUM(C32:C33) -> 4986 | D34: =SUM(D32:D33) -> 5010 | E34: =SUM(E32:E33) -> 5604 | F34: =SUM(F32:F33) -> 5748.8298 | G34: =SUM(G32:G33) -> 5908.9253 | H34: =SUM(H32:H33) -> 6085.9506 | I34: =SUM(I32:I33) -> 6281.7548 | J34: =SUM(J32:J33) -> 6498.3927 | ... M34: =SUM(M32:M33) -> 7297.4466
B36: Equity | C36: 14051 | D36: 16518 | E36: 14105 | F36: =Calcs!F16 -> 17601.347 | G36: =Calcs!G16 -> 21690.34 | H36: =Calcs!H16 -> 26434.653 | I36: =Calcs!I16 -> 33503.801 | J36: =Calcs!J16 -> 42274.907 | K36: =Calcs!K16 -> 51933.548 | L36: =Calcs!L16 -> 62574.698 | M36: =Calcs!M16 -> 74303.772
A37: * | B37: TOTAL LIABILITIES & EQUITY | C37: =SUM(C36,C34,C30) -> 27165 | D37: =SUM(D36,D34,D30) -> 29779 | E37: =SUM(E36,E34,E30) -> 30230 | F37: =SUM(F36,F34,F30) -> 33258.044 | G37: =SUM(G36,G34,G30) -> 38486.375 | H37: =SUM(H36,H34,H30) -> 44490.507 | I37: =SUM(I36,I34,I30) -> 52953.117 | J37: =SUM(J36,J34,J30) -> 63265.951 | ... M37: =SUM(M36,M34,M30) -> 100981.37
A39: * | B39: Balance check | C39: =C37-C25 -> 0 | D39: =D37-D25 -> 0 | E39: =E37-E25 -> 0 | F39: =F37-F25 -> 0 | G39: =G37-G25 -> 0 | H39: =H37-H25 -> 0 | I39: =I37-I25 -> 0 | J39: =J37-J25 -> 0 | ... M39: =M37-M25 -> 0

Sheet CashFlow
A1: =CoName -> Adobe Inc. | C1: Hist. | D1: Hist. | E1: Hist. | F1: Proj. | G1: Proj. | H1: Proj. | I1: Proj. | J1: Proj. | K1: Proj. | L1: Proj. | M1: Proj.
A2: Cash flow statement | C2: 2022 | D2: =C2+1 -> 2023 | E2: =D2+1 -> 2024 | F2: =E2+1 -> 2025 | G2: =F2+1 -> 2026 | H2: =G2+1 -> 2027 | I2: =H2+1 -> 2028 | J2: =I2+1 -> 2029 | K2: =J2+1 -> 2030 | ... M2: =L2+1 -> 2032
B3: Net Income | F3: =IncState!F35 -> 5996.3465 | G3: =IncState!G35 -> 6588.9938 | H3: =IncState!H35 -> 7244.3125 | I3: =IncState!I35 -> 7969.1478 | J3: =IncState!J35 -> 8771.1063 | K3: =IncState!K35 -> 9658.6415 | L3: =IncState!L35 -> 10641.149 | M3: =IncState!M35 -> 11729.074
B4: Depreciation | F4: =Calcs!F8 -> 638.73367 | G4: =Calcs!G8 -> 546.78124 | H4: =Calcs!H8 -> 490.42082 | I4: =Calcs!I8 -> 460.36038 | J4: =Calcs!J8 -> 450.0901 | K4: =Calcs!K8 -> 455.0925 | L4: =Calcs!L8 -> 472.28139 | M4: =Calcs!M8 -> 499.60403
B5: Amortization | F5: =IncState!F23 -> 169 | G5: =IncState!G23 -> 169 | H5: =IncState!H23 -> 169 | I5: =IncState!I23 -> 169 | J5: =IncState!J23 -> 169 | K5: =IncState!K23 -> 169 | L5: =IncState!L23 -> 169 | M5: =IncState!M23 -> 169
B6: (inc) / dec in OWC | F6: =Calcs!F24 -> 451.74637 | G6: =Calcs!G24 -> 499.36214 | H6: =Calcs!H24 -> 552.16879 | I6: =Calcs!I24 -> 610.74315 | J6: =Calcs!J24 -> 675.72683 | K6: =Calcs!K24 -> 747.83348 | L6: =Calcs!L24 -> 827.85701 | M6: =Calcs!M24 -> 916.68056
B7: (inc) /dec in LT assets | F7: =BalSheet!E22-BalSheet!F22 -> -315.2872 | G7: =BalSheet!F22-BalSheet!G22 -> -348.51966 | H7: =BalSheet!G22-BalSheet!H22 -> -385.37499 | I7: =BalSheet!H22-BalSheet!I22 -> -426.25578 | J7: =BalSheet!I22-BalSheet!J22 -> -471.60981 | K7: =BalSheet!J22-BalSheet!K22 -> -521.93519 | L7: =BalSheet!K22-BalSheet!L22 -> -577.78598 | M7: =BalSheet!L22-BalSheet!M22 -> -639.77857
B8: inc / (dec) in Liabilities | F8: =BalSheet!F33-BalSheet!E33 -> 144.82984 | G8: =BalSheet!G33-BalSheet!F33 -> 160.09545 | H8: =BalSheet!H33-BalSheet!G33 -> 177.02526 | I8: =BalSheet!I33-BalSheet!H33 -> 195.80419 | J8: =BalSheet!J33-BalSheet!I33 -> 216.63795 | K8: =BalSheet!K33-BalSheet!J33 -> 239.75534 | L8: =BalSheet!L33-BalSheet!K33 -> 265.41088 | M8: =BalSheet!M33-BalSheet!L33 -> 293.8877
B9: Cash Flow From Operations | F9: =SUM(F3:F8) -> 7085.3692 | G9: =SUM(G3:G8) -> 7615.713 | H9: =SUM(H3:H8) -> 8247.5524 | I9: =SUM(I3:I8) -> 8978.7998 | J9: =SUM(J3:J8) -> 9810.9513 | K9: =SUM(K3:K8) -> 10748.388 | L9: =SUM(L3:L8) -> 11797.913 | M9: =SUM(M3:M8) -> 12968.468
B11: Capex | F11: =Calcs!F7 -> 319.57321 | G11: =Calcs!G7 -> 351.15814 | H11: =Calcs!H7 -> 386.08313 | I11: =Calcs!I7 -> 424.71297 | J11: =Calcs!J7 -> 467.45307 | K11: =Calcs!K7 -> 514.75395 | L11: =Calcs!L7 -> 567.11637 | M11: =Calcs!M7 -> 625.09693
B12: Cash Flow From Investing | F12: =-F11 -> -319.57321 | G12: =-G11 -> -351.15814 | H12: =-H11 -> -386.08313 | I12: =-I11 -> -424.71297 | J12: =-J11 -> -467.45307 | K12: =-K11 -> -514.75395 | L12: =-L11 -> -567.11637 | M12: =-M11 -> -625.09693
B14: Share Issuance / (repayments) | F14: =Calcs!F11 -> -2500 | G14: =Calcs!G11 -> -2500 | H14: =Calcs!H11 -> -2500 | I14: =Calcs!I11 -> -900 | J14: =Calcs!J11 -> 0 | K14: =Calcs!K11 -> 0 | L14: =Calcs!L11 -> 0 | M14: =Calcs!M11 -> 0
B15: Debt issuance / (repayments) | F15: =SUM(Debt!F8:F9) -> -1499 | G15: =SUM(Debt!G8:G9) -> 0 | H15: =SUM(Debt!H8:H9) -> 0 | I15: =SUM(Debt!I8:I9) -> 0 | J15: =SUM(Debt!J8:J9) -> 0 | K15: =SUM(Debt!K8:K9) -> 0 | L15: =SUM(Debt!L8:L9) -> 0 | M15: =SUM(Debt!M8:M9) -> 0
B16: Cash Flow From Financing | F16: =SUM(F14:F15) -> -3999 | G16: =SUM(G14:G15) -> -2500 | H16: =SUM(H14:H15) -> -2500 | I16: =SUM(I14:I15) -> -900 | J16: =SUM(J14:J15) -> 0 | K16: =SUM(K14:K15) -> 0 | L16: =SUM(L14:L15) -> 0 | M16: =SUM(M14:M15) -> 0
B18: Net changes in cash | F18: =SUM(F16,F12,F9) -> 2766.796 | G18: =SUM(G16,G12,G9) -> 4764.5549 | H18: =SUM(H16,H12,H9) -> 5361.4693 | I18: =SUM(I16,I12,I9) -> 7654.0868 | J18: =SUM(J16,J12,J9) -> 9343.4983 | K18: =SUM(K16,K12,K9) -> 10233.634 | L18: =SUM(L16,L12,L9) -> 11230.796 | M18: =SUM(M16,M12,M9) -> 12343.371
B20: Beginning Cash | F20: =BalSheet!E15 -> 6810.75 | G20: =BalSheet!F15 -> 9577.546 | H20: =BalSheet!G15 -> 14342.101 | I20: =BalSheet!H15 -> 19703.57 | J20: =BalSheet!I15 -> 27357.657 | K20: =BalSheet!J15 -> 36701.155 | L20: =BalSheet!K15 -> 46934.789 | M20: =BalSheet!L15 -> 58165.585
B21: Changes | F21: =F18 -> 2766.796 | G21: =G18 -> 4764.5549 | H21: =H18 -> 5361.4693 | I21: =I18 -> 7654.0868 | J21: =J18 -> 9343.4983 | K21: =K18 -> 10233.634 | L21: =L18 -> 11230.796 | M21: =M18 -> 12343.371
B22: Ending Cash | F22: =SUM(F20:F21) -> 9577.546 | G22: =SUM(G20:G21) -> 14342.101 | H22: =SUM(H20:H21) -> 19703.57 | I22: =SUM(I20:I21) -> 27357.657 | J22: =SUM(J20:J21) -> 36701.155 | K22: =SUM(K20:K21) -> 46934.789 | L22: =SUM(L20:L21) -> 58165.585 | M22: =SUM(M20:M21) -> 70508.956

Sheet Free Cash Flow
A1: =CoName -> Adobe Inc. | C1: Hist. | D1: Hist. | E1: Hist. | F1: Proj. | G1: Proj. | H1: Proj. | I1: Proj. | J1: Proj. | K1: Proj. | L1: Proj. | M1: Proj.
A2: Free Cash Flows | C2: 2022 | D2: =C2+1 -> 2023 | E2: =D2+1 -> 2024 | F2: =E2+1 -> 2025 | G2: =F2+1 -> 2026 | H2: =G2+1 -> 2027 | I2: =H2+1 -> 2028 | J2: =I2+1 -> 2029 | K2: =J2+1 -> 2030 | ... M2: =L2+1 -> 2032
A3: * | B3: Sales | F3: =IncState!F16 -> 23616.57 | G3: =IncState!G16 -> 25950.707 | H3: =IncState!H16 -> 28531.676 | I3: =IncState!I16 -> 31386.435 | J3: =IncState!J16 -> 34544.942 | K3: =IncState!K16 -> 38040.494 | L3: =IncState!L16 -> 41910.095 | M3: =IncState!M16 -> 46194.878
B4: EBIT | F4: =IncState!F20 -> 7402.8969 | G4: =IncState!G20 -> 8134.5603 | H4: =IncState!H20 -> 8943.5957 | I4: =IncState!I20 -> 9838.4541 | J4: =IncState!J20 -> 10828.526 | K4: =IncState!K20 -> 11924.249 | L4: =IncState!L20 -> 13137.221 | M4: =IncState!M20 -> 14480.338
B5: Effective Tax Rate | F5: =IncState!F11 -> 0.19 | G5: =IncState!G11 -> 0.19 | H5: =IncState!H11 -> 0.19 | I5: =IncState!I11 -> 0.19 | J5: =IncState!J11 -> 0.19 | K5: =IncState!K11 -> 0.19 | L5: =IncState!L11 -> 0.19 | M5: =IncState!M11 -> 0.19
A7: * | B7: NOPAT | F7: =F4*(1-F5) -> 5996.3465 | G7: =G4*(1-G5) -> 6588.9938 | H7: =H4*(1-H5) -> 7244.3125 | I7: =I4*(1-I5) -> 7969.1478 | J7: =J4*(1-J5) -> 8771.1063 | K7: =K4*(1-K5) -> 9658.6415 | L7: =L4*(1-L5) -> 10641.149 | M7: =M4*(1-M5) -> 11729.074
B8: Depreciation | F8: =CashFlow!F4 -> 638.73367 | G8: =CashFlow!G4 -> 546.78124 | H8: =CashFlow!H4 -> 490.42082 | I8: =CashFlow!I4 -> 460.36038 | J8: =CashFlow!J4 -> 450.0901 | K8: =CashFlow!K4 -> 455.0925 | L8: =CashFlow!L4 -> 472.28139 | M8: =CashFlow!M4 -> 499.60403
B9: Amortization | F9: =CashFlow!F5 -> 169 | G9: =CashFlow!G5 -> 169 | H9: =CashFlow!H5 -> 169 | I9: =CashFlow!I5 -> 169 | J9: =CashFlow!J5 -> 169 | K9: =CashFlow!K5 -> 169 | L9: =CashFlow!L5 -> 169 | M9: =CashFlow!M5 -> 169
B10: (inc) / dec in OWC | F10: =CashFlow!F6 -> 451.74637 | G10: =CashFlow!G6 -> 499.36214 | H10: =CashFlow!H6 -> 552.16879 | I10: =CashFlow!I6 -> 610.74315 | J10: =CashFlow!J6 -> 675.72683 | K10: =CashFlow!K6 -> 747.83348 | L10: =CashFlow!L6 -> 827.85701 | M10: =CashFlow!M6 -> 916.68056
B11: (inc) / dec in other long-term assets | F11: =CashFlow!F7 -> -315.2872 | G11: =CashFlow!G7 -> -348.51966 | H11: =CashFlow!H7 -> -385.37499 | I11: =CashFlow!I7 -> -426.25578 | J11: =CashFlow!J7 -> -471.60981 | K11: =CashFlow!K7 -> -521.93519 | L11: =CashFlow!L7 -> -577.78598 | M11: =CashFlow!M7 -> -639.77857
B12: inc / (dec) other long-term liabilities | F12: =CashFlow!F8 -> 144.82984 | G12: =CashFlow!G8 -> 160.09545 | H12: =CashFlow!H8 -> 177.02526 | I12: =CashFlow!I8 -> 195.80419 | J12: =CashFlow!J8 -> 216.63795 | K12: =CashFlow!K8 -> 239.75534 | L12: =CashFlow!L8 -> 265.41088 | M12: =CashFlow!M8 -> 293.8877
B13: (Capex) | F13: =CashFlow!F12 -> -319.57321 | G13: =CashFlow!G12 -> -351.15814 | H13: =CashFlow!H12 -> -386.08313 | I13: =CashFlow!I12 -> -424.71297 | J13: =CashFlow!J12 -> -467.45307 | K13: =CashFlow!K12 -> -514.75395 | L13: =CashFlow!L12 -> -567.11637 | M13: =CashFlow!M12 -> -625.09693
A15: * | B15: Free Cash Flow | F15: =SUM(F7:F13) -> 6765.796 | G15: =SUM(G7:G13) -> 7264.5549 | H15: =SUM(H7:H13) -> 7861.4693 | I15: =SUM(I7:I13) -> 8554.0868 | J15: =SUM(J7:J13) -> 9343.4983 | K15: =SUM(K7:K13) -> 10233.634 | L15: =SUM(L7:L13) -> 11230.796 | M15: =SUM(M7:M13) -> 12343.371

Sheet WACC
A1: =CoName -> Adobe Inc.
A3: * | B3: WACC | G3: Comp | H3: Levered beta | I3: Gross debt | J3: Market cap | K3: Debt/Mcap | L3: MTR | M3: Unlevered beta
B4: Tax Rate | E4: 0.185 | G4: CRM | H4: 1.24 | I4: 8436 | J4: =238.94*952 -> 227470.88 | K4: =I4/J4 -> 0.037086066 | L4: =E4 -> 0.185 | M4: =H4/((1+K4*(1-L4))) -> 1.2036204
B5: Risk free rate | E5: 0.0409 | G5: INTU | H5: 1.26 | I5: 5973 | J5: =646.95*278.8 -> 180369.66 | K5: =I5/J5 -> 0.033115325 | L5: =L4 -> 0.185 | M5: =H5/((1+K5*(1-L5))) -> 1.2268875
B6: Market risk Premium | E6: 0.05 | G6: ADSK | H6: 1.48 | I6: 2481 | J6: =213*295.84 -> 63013.92 | K6: =I6/J6 -> 0.039372253 | L6: =L5 -> 0.185 | M6: =H6/((1+K6*(1-L6))) -> 1.4339857
B7: Beta | E7: 1 | G7: MSFT | H7: 1.06 | I7: =7832+35376 -> 43208 | J7: =7400*496.77 -> 3676098 | K7: =I7/J7 -> 0.011753767 | L7: =L6 -> 0.185 | M7: =H7/((1+K7*(1-L7))) -> 1.0499423
B8: Cost of Equity | E8: =E5+E6*E7 -> 0.0909
B9: % Equity | E9: =1-E10 -> 0.95490691 | G9: Industry beta (average) | M9: =AVERAGE(M4:M7) -> 1.228609
B10: % Debt | E10: =MAIN!F8/MAIN!F6 -> 0.045093088
B11: Cost of debt | E11: =Debt!F5 -> 0.036 | G11: Re-levered beta | M11: =M9*(1+E10*(1-E4)) -> 1.2737614
B12: Post tax cost of debt | E12: =E11*(1-E4) -> 0.02934
A13: * | B13: WACC | E13: =WACC!E8*WACC!E9+WACC!E12*WACC!E10 -> 0.08812407
B14: Long Term growth rate | E14: 0.025

Sheet DCF Model
A1: =CoName -> Adobe Inc. | D1: Proj. | E1: Proj. | F1: Proj. | G1: Proj. | H1: Proj. | I1: Proj. | J1: Proj. | K1: Proj.
A2: Discount Model Year count | D2: 0.5 | E2: =D2+1 -> 1.5 | F2: =E2+1 -> 2.5 | G2: =F2+1 -> 3.5 | H2: =G2+1 -> 4.5 | I2: =H2+1 -> 5.5 | J2: =I2+1 -> 6.5 | K2: =J2+1 -> 7.5
B3: Discount Rate | D3: =1/(1+$O$3)^D2 -> 0.95865158 | E3: =1/(1+$O$3)^E2 -> 0.88101312 | F3: =1/(1+$O$3)^F2 -> 0.80966237 | G3: =1/(1+$O$3)^G2 -> 0.74409012 | H3: =1/(1+$O$3)^H2 -> 0.68382838 | I3: =1/(1+$O$3)^I2 -> 0.62844707 | J3: =1/(1+$O$3)^J2 -> 0.57755093 | K3: =1/(1+$O$3)^K2 -> 0.53077673 | L3: WACC | O3: =WACC!E13 -> 0.08812407
B4: PV FCF | D4: =D3*'Free Cash Flow'!F15 -> 6486.041 | E4: =E3*'Free Cash Flow'!G15 -> 6400.1681 | F4: =F3*'Free Cash Flow'!H15 -> 6365.1359 | G4: =G3*'Free Cash Flow'!I15 -> 6365.0115 | H4: =H3*'Free Cash Flow'!J15 -> 6389.3493 | I4: =I3*'Free Cash Flow'!K15 -> 6431.2971 | J4: =J3*'Free Cash Flow'!L15 -> 6486.3569 | K4: =K3*'Free Cash Flow'!M15 -> 6551.5739 | L4: Long Term growth rate | O4: 0.025
K5: =((K4*(1+O4)))/(O3-O4) -> 106383.56
A6: Value Calculation | E6: Multiples Calculation
B7: Total PV of FCFs | C7: =SUM(D4:K4) -> 51474.934 | E7: Total PV of FCFs | G7: =C7 -> 51474.934 | M7: LTGR | R7: Terminal Mult
B8: PV of TV | C8: =K5*K3 -> 56465.918 | E8: Multiple TV | G8: =G10*K3*IncState!M24 -> 140712.35 | K8: =C18 -> 257.24045 | L8: =M8-E23 -> 0.0225 | M8: 0.025 | N8: =M8+E23 -> 0.0275 | P8: =G18 -> 458.49806 | Q8: =R8-1 -> 16.5 | R8: 17.5 | S8: =R8+1 -> 18.5
B9: EV | C9: =SUM(C7:C8) -> 107940.85 | E9: EV | G9: =SUM(G7:G8) -> 192187.29 | K9: =K10+$E$22 -> 0.09812407 | L9: 215.86316 | M9: 219.45845 | N9: 223.30828 | P9: =K9 -> 0.09812407 | Q9: 413.86908 | R9: 431.80392 | S9: 449.73876
E10: Implied EBITDA multiple | G10: 17.5 | K10: =K11+$E$22 -> 0.09312407 | L10: 232.39462 | M10: 236.79965 | N10: 241.5403 | P10: =K10 -> 0.09312407 | Q10: 426.34324 | R10: 444.90257 | S10: 463.46189
K11: 0.08812407 | L11: 251.78515 | M11: 257.24045 | N11: 263.14567 | P11: 0.08812407 | Q11: 439.28949 | R11: 458.49806 | S11: 477.70662
B12: Cash & Cash Equiv | C12: =MAIN!F7 -> 5940 | E12: Cash & Cash Equiv | G12: =C12 -> 5940 | K12: =K11-$E$22 -> 0.08312407 | L12: 274.78203 | M12: 281.62238 | N12: 289.07761 | P12: =K12 -> 0.08312407 | Q12: 452.72836 | R12: 472.61203 | S12: 492.4957
B13: Debt & Claims | C13: =MAIN!F8 -> 6200 | E13: Debt & Claims | G13: =C13 -> 6200 | K13: =K12-$E$22 -> 0.07812407 | L13: 302.40551 | M13: 311.10829 | N13: 320.67062 | P13: =K13 -> 0.07812407 | Q13: 466.68137 | R13: 487.26716 | S13: 507.85295
B14: NCI | C14: 0 | E14: NCI | G14: =C14 -> 0
B15: Equity Value | C15: =C9+C12-C13 -> 107680.85 | E15: Equity Value | G15: =G9+G12-G13 -> 191927.29 | M15: Average | R15: Average
M16: =AVERAGE(L9:N13) -> 261.41348 | R16: =AVERAGE(Q9:S13) -> 459.01675
B17: Diluted S/O | C17: =MAIN!F5 -> 418.6 | E17: Diluted S/O | G17: =C17 -> 418.6
A18: * | B18: Implied Share Price | C18: =C15/C17 -> 257.24045 | E18: Implied Share Price | G18: =G15/G17 -> 458.49806
A20: Sensitivity analysis
C22: Discount rate variance | E22: 0.005 | J22: Discount rate variance | L22: 0.005
C23: Implied growth rate variance | E23: 0.0025 | J23: TV multiple variance | L23: 1
A25: DCF tables

Sheet COMPS
A1: =CoName -> Adobe Inc.
A2: * | C2: Company Symbol | D2: Price 10/14/25 | E2: Enterprise Value | F2: LTM EV/EBITDA | G2: EV/EBITDA 2026E | H2: LTM EV/EBIT | I2: EV/EBIT 2026E | J2: LTM P/E Ratio | K2: P/E Ratio 2026E | L2: LTM EV/Sales | M2: EV/Sales 2026E | N2: Delta % Average
A8: * | B8: Average
A10: * | B10: Current price
B11: Delta -> Average

Sheet Presentation
A1: =CoName -> Adobe Inc.
A2: Presentation slide
A3: Football field + SOTP Comps analysis
A21: DCF Analysis (Sensitivity tables)
A41: Projection ranges
