Workbook
Name Ccy: MAIN!$C$6
Name circ: MAIN!$C$9
Name CoName: MAIN!$C$4
Name g: Presentation!$R$17
Name IQ_CH: 110000
Name IQ_CQ: 5000
Name IQ_CY: 10000
Name IQ_DAILY: 500000
Name IQ_FH: 100000
Name IQ_FQ: 500
Name IQ_FY: 1000
Name IQ_LTM: 2000
Name IQ_MONTH: 15000
Name IQ_NTM: 6000
Name IQ_WEEK: 50000
Name IQ_YTD: 3000
Name OpCase: [1]DCF!$E$98
Name ScenarioREV: Assumptions!$D$4
Name TTS: #REF!
Name Units: MAIN!$C$7

Sheet MAIN
A1: =CoName -> Berkshire Hathaway Non-Insurance
A2: Model Details
B3: PLEASE REFER TO MY OTHER BERKSHIRE MODEL TO COMBINE THE POTENTIAL EV NUMBERS
B4: Company name | C4: Berkshire Hathaway Non-Insurance | E4: Total Cash & Equivalents | F4: 100486
B5: Latest BS date | C5: 247.43 | E5: Total Debt | F5: =127020 -> 127020
B6: Currency | C6: USD | E6: Total Mkt Cap | F6: =726000*F7 -> 1043784.7
B7: Units | C7: m | E7: Class A outstanding | F7: =IncState!E36 -> 1.43772
B8: Analyst name | C8: Alan Chen | E8: Class A price | F8: 726000
B9: Circular switch | C9: 0 | E9: Class B outstanding | F9: =IncState!E37 -> 2156.5803
E10: Class B Price | F10: 478.73
B11: Scenario | C11: Perpetuity | D11: Terminal Multiple
B12: Case 1 | C12: 104771.76 | D12: 246650.22 | F12: SHARE PRICE CLASS A | J12: SHARE PRICE CLASS B
B13: Case 2 | C13: 145099.4 | D13: 276233.93 | F13: Case 1 | G13: =(C17+$F$4-$F$5)/$F$7 -> 821785.66 | H13: =(D17+$F$4-$F$5)/$F$7 -> 718155.9 | J13: =F13 -> Case 1 | K13: =G13/1500 -> 547.8571 | L13: =H13/1500 -> 478.7706
B14: Case 3 | C14: 71066.042 | D14: 219642.62 | F14: Case 2 | G14: =(C18+$F$4-$F$5)/$F$7 -> 985567.87 | H14: =(D18+$F$4-$F$5)/$F$7 -> 807924.41 | J14: =F14 -> Case 2 | K14: =G14/1500 -> 657.04525 | L14: =H14/1500 -> 538.61627
F15: Case 3 | G15: =(C19+$F$4-$F$5)/$F$7 -> 678018.26 | H15: =(D19+$F$4-$F$5)/$F$7 -> 636117.51 | J15: =F15 -> Case 3 | K15: =G15/1500 -> 452.01217 | L15: =H15/1500 -> 424.07834
B16: COMBINED EV | C16: Perpetuity | D16: Terminal Multiple | F16: DIFFERENCE | J16: DIFFERENCE
B17: Case 1 | C17: 1208031.7 | D17: 1059041.1 | F17: =F13 -> Case 1 | G17: =G13/$F$8-1 -> 0.13193617 | H17: =H13/$F$8-1 -> -0.010804543 | J17: =J13 -> Case 1 | K17: =K13/$F$10-1 -> 0.14439685 | L17: =L13/$F$10-1 -> 8.4810023e-05
B18: Case 2 | C18: 1443504.6 | D18: 1188103.1 | F18: =F14 -> Case 2 | G18: =G14/$F$8-1 -> 0.3575315 | H18: =H14/$F$8-1 -> 0.11284354 | J18: =J14 -> Case 2 | K18: =K14/$F$10-1 -> 0.37247561 | L18: =L14/$F$10-1 -> 0.12509405
B19: Case 3 | C19: 1001334.4 | D19: 941092.86 | F19: =F15 -> Case 3 | G19: =G15/$F$8-1 -> -0.066090552 | H19: =H15/$F$8-1 -> -0.12380508 | J19: =J15 -> Case 3 | K19: =K15/$F$10-1 -> -0.055809803 | L19: =L15/$F$10-1 -> -0.11415967
G21: Weighted Average | K21: Weighted Average
G22: =AVERAGE(G13:H15) -> 774594.93 | K22: =AVERAGE(K13:L15) -> 516.39662
G23: =G22/F8-1 -> 0.066935171 | K23: =K22/F10-1 -> 0.078680306

Sheet Assumptions
A1: =CoName -> Berkshire Hathaway Non-Insurance | C1: Hist. | D1: Hist. | E1: Hist. | F1: Proj. | G1: Proj. | H1: Proj. | I1: Proj. | J1: Proj.
A2: * | B2: Income Statement | C2: 44926 | D2: 45291 | E2: 45657 | F2: 46022 | G2: 46387 | H2: 46752 | I2: 47118 | J2: 47483
B4: Operating Case | D4: 3
D5: Variance
B6: Street Case | D6: 0 | F6: 0.05 | G6: 0.05 | H6: 0.05 | I6: 0.05 | J6: 0.05
B7: Optimistic Case | D7: 0.025 | F7: =F6+$D$7 -> 0.075 | G7: =G6+$D$7 -> 0.075 | H7: =H6+$D$7 -> 0.075 | I7: =I6+$D$7 -> 0.075 | J7: =J6+$D$7 -> 0.075
B8: Pessimistic Case | D8: -0.025 | F8: =F6+$D$8 -> 0.025 | G8: =G6+$D$8 -> 0.025 | H8: =H6+$D$8 -> 0.025 | I8: =I6+$D$8 -> 0.025 | J8: =J6+$D$8 -> 0.025
B10: Revenue Growth | C10: =52149/48229-1 -> 0.081278899 | D10: =IncState!D15/IncState!C15-1 -> -0.045983624 | E10: =IncState!E15/IncState!D15-1 -> 0.00078390384 | F10: =CHOOSE(ScenarioREV,F6,F7,F8) -> 0.025 | G10: =CHOOSE(ScenarioREV,G6,G7,G8) -> 0.025 | H10: =CHOOSE(ScenarioREV,H6,H7,H8) -> 0.025 | I10: =CHOOSE(ScenarioREV,I6,I7,I8) -> 0.025 | J10: =CHOOSE(ScenarioREV,J6,J7,J8) -> 0.025
B11: COGS % of sales | C11: =IncState!C16/IncState!C15 -> 0.63621546 | D11: =IncState!D16/IncState!D15 -> 0.70074973 | E11: =IncState!E16/IncState!E15 -> 0.66175939 | F11: =E11 -> 0.66175939 | G11: =F11 -> 0.66175939 | H11: =G11 -> 0.66175939 | I11: =H11 -> 0.66175939 | J11: =I11 -> 0.66175939
B12: SG&A % of sales | C12: =IncState!C17/IncState!C15 -> 0.095572302 | D12: =IncState!D17/IncState!D15 -> 0.080721996 | E12: =IncState!E17/IncState!E15 -> 0.087226351 | F12: =E12 -> 0.087226351 | G12: =F12 -> 0.087226351 | H12: =G12 -> 0.087226351 | I12: =H12 -> 0.087226351 | J12: =I12 -> 0.087226351
B13: Amortization $ Amt | C13: 0 | D13: 0 | E13: 0 | F13: =E13 -> 0 | G13: =F13 -> 0 | H13: =G13 -> 0 | I13: =H13 -> 0 | J13: =I13 -> 0
B14: Non recurring income / (expense) | C14: 0 | D14: 0 | E14: 0 | F14: 0 | G14: 0 | H14: 0 | I14: 0 | J14: 0
B15: Other Income / (expense) | C15: 0 | D15: 0 | E15: 0 | F15: 0 | G15: 0 | H15: 0 | I15: 0 | J15: 0
B16: Effective tax rate | C16: =IncState!C32/IncState!C30 -> 0.3596956 | D16: =IncState!D32/IncState!D30 -> 0.45265252 | E16: =IncState!E32/IncState!E30 -> 0.3651559 | F16: =E16 -> 0.3651559 | G16: =F16 -> 0.3651559 | H16: =G16 -> 0.3651559 | I16: =H16 -> 0.3651559 | J16: =I16 -> 0.3651559
B17: Basic WASO | C17: =IncState!C36 -> 1.468876 | D17: =IncState!D36 -> 1.44888 | E17: =IncState!E36 -> 1.43772 | F17: =E17 -> 1.43772 | G17: =F17 -> 1.43772 | H17: =G17 -> 1.43772 | I17: =H17 -> 1.43772 | J17: =I17 -> 1.43772
B18: Diluted WASO | C18: =IncState!C37 -> 2203.3136 | D18: =IncState!D37 -> 2173.3197 | E18: =IncState!E37 -> 2156.5803 | F18: =E18 -> 2156.5803 | G18: =F18 -> 2156.5803 | H18: =G18 -> 2156.5803 | I18: =H18 -> 2156.5803 | J18: =I18 -> 2156.5803
A20: * | B20: Debt | C20: 44926 | D20: 45291 | E20: 45657 | F20: 46022 | G20: 46387 | H20: 46752 | I20: 47118 | J20: 47483
B22: Interest rate on Revolver | F22: =E22 -> 0 | G22: =F22 -> 0 | H22: =G22 -> 0 | I22: =H22 -> 0 | J22: =I22 -> 0
B23: Interest rate on long-term debt | F23: =E23 -> 0 | G23: =F23 -> 0 | H23: =G23 -> 0 | I23: =H23 -> 0 | J23: =I23 -> 0
B24: Interest rate on cash | F24: =E24 -> 0 | G24: =F24 -> 0 | H24: =G24 -> 0 | I24: =H24 -> 0 | J24: =I24 -> 0
B26: Issuance of long-term debt | F26: 0 | G26: 0 | H26: 0 | I26: 0 | J26: 0
B27: Repayment of long-term debt | F27: 0 | G27: 0 | H27: 0 | I27: 0 | J27: 0
A29: * | B29: Calcs | C29: 44926 | D29: 45291 | E29: 45657 | F29: 46022 | G29: 46387 | H29: 46752 | I29: 47118 | J29: 47483
B31: CapEx % of Sales | C31: =(18976-99)/IncState!C15 -> 0.36198201 | D31: =(19409-68)/IncState!D15 -> 0.388756 | E31: =(15464-82)/IncState!E15 -> 0.30893754 | F31: =E31 -> 0.30893754 | G31: =F31 -> 0.30893754 | H31: =G31 -> 0.30893754 | I31: =H31 -> 0.30893754 | J31: =I31 -> 0.30893754
B32: Depreciation % of beginning PP&E | D32: =IncState!D20/BalSheet!C20 -> 0.075404947 | E32: =IncState!E20/BalSheet!D20 -> 0.073438892 | F32: =E32 -> 0.073438892 | G32: =F32 -> 0.073438892 | H32: =G32 -> 0.073438892 | I32: =H32 -> 0.073438892 | J32: =I32 -> 0.073438892
B33: Share issuance / (repurchases) | C33: 0 | D33: 0 | E33: 0 | F33: 0 | G33: 0 | H33: 0 | I33: 0 | J33: 0
A35: * | B35: Shareholder information | C35: 44926 | D35: 45291 | E35: 45657 | F35: 46022 | G35: 46387 | H35: 46752 | I35: 47118 | J35: 47483
B37: Dividend payout ratio | F37: =E37 -> 0 | G37: =F37 -> 0 | H37: =G37 -> 0 | I37: =H37 -> 0 | J37: =I37 -> 0
B38: Basic WASO | C38: =C17 -> 1.468876 | D38: =D17 -> 1.44888 | E38: =E17 -> 1.43772 | F38: =F17 -> 1.43772 | G38: =G17 -> 1.43772 | H38: =H17 -> 1.43772 | I38: =I17 -> 1.43772 | J38: =J17 -> 1.43772
B39: Diluted WASO | C39: =C18 -> 2203.3136 | D39: =D18 -> 2173.3197 | E39: =E18 -> 2156.5803 | F39: =F18 -> 2156.5803 | G39: =G18 -> 2156.5803 | H39: =H18 -> 2156.5803 | I39: =I18 -> 2156.5803 | J39: =J18 -> 2156.5803
A41: * | B41: Balance Sheet - Assets | C41: 44926 | D41: 45291 | E41: 45657 | F41: 46022 | G41: 46387 | H41: 46752 | I41: 47118 | J41: 47483
B43: Operating Cash % of sales | C43: =BalSheet!C14/IncState!C15 -> 0.015 | D43: =BalSheet!D14/IncState!D15 -> 0.015 | E43: =BalSheet!E14/IncState!E15 -> 0.015 | F43: =E43 -> 0.015 | G43: =F43 -> 0.015 | H43: =G43 -> 0.015 | I43: =H43 -> 0.015 | J43: =I43 -> 0.015
B44: Accounts receivable % of sales | C44: =BalSheet!C16/IncState!C15 -> 0.091948072 | D44: =BalSheet!D16/IncState!D15 -> 0.10048039 | E44: =BalSheet!E16/IncState!E15 -> 0.090439847 | F44: =E44 -> 0.090439847 | G44: =F44 -> 0.090439847 | H44: =G44 -> 0.090439847 | I44: =H44 -> 0.090439847 | J44: =I44 -> 0.090439847
B45: Other current assets % of sales | C45: =BalSheet!C17/IncState!C15 -> 0.097068017 | D45: =BalSheet!D17/IncState!D15 -> 0.11185705 | E45: =BalSheet!E17/IncState!E15 -> 0.10743121 | F45: =E45 -> 0.10743121 | G45: =F45 -> 0.10743121 | H45: =G45 -> 0.10743121 | I45: =H45 -> 0.10743121 | J45: =I45 -> 0.10743121
B46: Other long-term assets % of sales | C46: =BalSheet!C22/IncState!C15 -> 0.42551152 | D46: =BalSheet!D22/IncState!D15 -> 0.39888645 | E46: =BalSheet!E22/IncState!E15 -> 0.4179755 | F46: =E46 -> 0.4179755 | G46: =F46 -> 0.4179755 | H46: =G46 -> 0.4179755 | I46: =H46 -> 0.4179755 | J46: =I46 -> 0.4179755
A48: * | B48: Balance Sheet - Liabilities | C48: 44926 | D48: 45291 | E48: 45657 | F48: 46022 | G48: 46387 | H48: 46752 | I48: 47118 | J48: 47483
B50: Accounts payable % of COGS | C50: =BalSheet!C28/IncState!C16 -> 0.50078365 | D50: =BalSheet!D28/IncState!D16 -> 0.52502653 | E50: =BalSheet!E28/IncState!E16 -> 0.55315791 | F50: =E50 -> 0.55315791 | G50: =F50 -> 0.55315791 | H50: =G50 -> 0.55315791 | I50: =H50 -> 0.55315791 | J50: =I50 -> 0.55315791
B51: Other current liabilities % of sales | C51: =BalSheet!C29/IncState!C15 -> 0.14130664 | D51: =BalSheet!D29/IncState!D15 -> 0.13704247 | E51: =BalSheet!E29/IncState!E15 -> 0.14125326 | F51: =E51 -> 0.14125326 | G51: =F51 -> 0.14125326 | H51: =G51 -> 0.14125326 | I51: =H51 -> 0.14125326 | J51: =I51 -> 0.14125326
B52: Other long-term liabilities % of sales | C52: =BalSheet!C33/IncState!C15 -> 1.4613128 | D52: =BalSheet!D33/IncState!D15 -> 1.6040482 | E52: =BalSheet!E33/IncState!E15 -> 1.604278 | F52: =E52 -> 1.604278 | G52: =F52 -> 1.604278 | H52: =G52 -> 1.604278 | I52: =H52 -> 1.604278 | J52: =I52 -> 1.604278

Sheet Revenue

Sheet Calcs
A1: =CoName -> Berkshire Hathaway Non-Insurance | C1: Hist. | D1: Hist. | E1: Hist. | F1: Proj. | G1: Proj. | H1: Proj. | I1: Proj. | J1: Proj.
A2: Net PP&E | C2: 2022 | D2: =C2+1 -> 2023 | E2: =D2+1 -> 2024 | F2: =E2+1 -> 2025 | G2: =F2+1 -> 2026 | H2: =G2+1 -> 2027 | I2: =H2+1 -> 2028 | J2: =I2+1 -> 2029
B3: Capital expenditure % of sales | F3: =Assumptions!F31 -> 0.30893754 | G3: =Assumptions!G31 -> 0.30893754 | H3: =Assumptions!H31 -> 0.30893754 | I3: =Assumptions!I31 -> 0.30893754 | J3: =Assumptions!J31 -> 0.30893754
B4: Depreciation % of PP&E | F4: =Assumptions!F32 -> 0.073438892 | G4: =F4 -> 0.073438892 | H4: =G4 -> 0.073438892 | I4: =H4 -> 0.073438892 | J4: =I4 -> 0.073438892
B6: Beginning PP&E | F6: =E9 -> 175030 | G6: =F9 -> 177942.54 | H6: =G9 -> 181035.35 | I6: =H9 -> 184305.05 | J6: =I9 -> 187748.74
B7: Capex | F7: =F3*IncState!F15 -> 15766.55 | G7: =G3*IncState!G15 -> 16160.714 | H7: =H3*IncState!H15 -> 16564.732 | I7: =I3*IncState!I15 -> 16978.85 | J7: =J3*IncState!J15 -> 17403.321
B8: Depreciation | F8: =F6*F4 -> 12854.009 | G8: =G6*G4 -> 13067.903 | H8: =H6*H4 -> 13295.036 | I8: =I6*I4 -> 13535.159 | J8: =J6*J4 -> 13788.059
B9: Ending PP&E | E9: =BalSheet!E20 -> 175030 | F9: =F6+F7-F8 -> 177942.54 | G9: =G6+G7-G8 -> 181035.35 | H9: =H6+H7-H8 -> 184305.05 | I9: =I6+I7-I8 -> 187748.74 | J9: =J6+J7-J8 -> 191364
A10: Equity | C10: =C2 -> 2022 | D10: =D2 -> 2023 | E10: =E2 -> 2024 | F10: =F2 -> 2025 | G10: =G2 -> 2026 | H10: =H2 -> 2027 | I10: =I2 -> 2028 | J10: =J2 -> 2029
B11: Share issuance/(repurchases) | F11: =Assumptions!F33 -> 0 | G11: =Assumptions!G33 -> 0 | H11: =Assumptions!H33 -> 0 | I11: =Assumptions!I33 -> 0 | J11: =Assumptions!J33 -> 0
B13: Beginning balance | F13: =E16 -> 130973 | G13: =F16 -> 137096.36 | H13: =G16 -> 143423.03 | I13: =H16 -> 149958.1 | J13: =I16 -> 156706.78
B14: Net income | F14: =IncState!F33 -> 6123.357 | G14: =IncState!G33 -> 6326.673 | H14: =IncState!H33 -> 6535.0719 | I14: =IncState!I33 -> 6748.6807 | J14: =IncState!J33 -> 6967.6298
B15: Share issuance / (repurchase) | F15: =F11 -> 0 | G15: =G11 -> 0 | H15: =H11 -> 0 | I15: =I11 -> 0 | J15: =J11 -> 0
B16: Ending balance | E16: =BalSheet!E36 -> 130973 | F16: =SUM(F13:F15) -> 137096.36 | G16: =SUM(G13:G15) -> 143423.03 | H16: =SUM(H13:H15) -> 149958.1 | I16: =SUM(I13:I15) -> 156706.78 | J16: =SUM(J13:J15) -> 163674.41
A17: OWC | C17: =C10 -> 2022 | D17: =D10 -> 2023 | E17: =E10 -> 2024 | F17: =F10 -> 2025 | G17: =G10 -> 2026 | H17: =H10 -> 2027 | I17: =I10 -> 2028 | J17: =J10 -> 2029
B18: Operating Cash | E18: =BalSheet!E14 -> 746.85 | F18: =BalSheet!F14 -> 765.52125 | G18: =BalSheet!G14 -> 784.65928 | H18: =BalSheet!H14 -> 804.27576 | I18: =BalSheet!I14 -> 824.38266 | J18: =BalSheet!J14 -> 844.99222
B19: =BalSheet!B16 -> Accounts receivable | E19: =BalSheet!E16 -> 4503 | F19: =BalSheet!F16 -> 4615.575 | G19: =BalSheet!G16 -> 4730.9644 | H19: =BalSheet!H16 -> 4849.2385 | I19: =BalSheet!I16 -> 4970.4694 | J19: =BalSheet!J16 -> 5094.7312
B20: Other current assets | E20: =BalSheet!E17 -> 5349 | F20: =BalSheet!F17 -> 5482.725 | G20: =BalSheet!G17 -> 5619.7931 | H20: =BalSheet!H17 -> 5760.288 | I20: =BalSheet!I17 -> 5904.2952 | J20: =BalSheet!J17 -> 6051.9025
B21: Accounts payables | E21: =BalSheet!E28 -> 18226 | F21: =BalSheet!F28 -> 18681.65 | G21: =BalSheet!G28 -> 19148.691 | H21: =BalSheet!H28 -> 19627.409 | I21: =BalSheet!I28 -> 20118.094 | J21: =BalSheet!J28 -> 20621.046
B22: Other current liabilities | E22: =BalSheet!E29 -> 7033 | F22: =BalSheet!F29 -> 7208.825 | G22: =BalSheet!G29 -> 7389.0456 | H22: =BalSheet!H29 -> 7573.7718 | I22: =BalSheet!I29 -> 7763.1161 | J22: =BalSheet!J29 -> 7957.194
A23: * | B23: OWC | E23: =SUM(E18:E20)-SUM(E21:E22) -> -14660.15 | F23: =SUM(F18:F20)-SUM(F21:F22) -> -15026.654 | G23: =SUM(G18:G20)-SUM(G21:G22) -> -15402.32 | H23: =SUM(H18:H20)-SUM(H21:H22) -> -15787.378 | I23: =SUM(I18:I20)-SUM(I21:I22) -> -16182.063 | J23: =SUM(J18:J20)-SUM(J21:J22) -> -16586.614
B24: Change in OWC | F24: =E23-F23 -> 366.50375 | G24: =F23-G23 -> 375.66634 | H24: =G23-H23 -> 385.058 | I24: =H23-I23 -> 394.68445 | J24: =I23-J23 -> 404.55156

Sheet Debt
A1: =CoName -> Berkshire Hathaway Non-Insurance | C1: Hist. | D1: Hist. | E1: Hist. | F1: Proj. | G1: Proj. | H1: Proj. | I1: Proj. | J1: Proj.
A2: Assumptions | C2: 44926 | D2: 45291 | E2: 45657 | F2: 46022 | G2: 46387 | H2: 46752 | I2: 47118 | J2: 47483
B4: Interest rate on revolver | F4: =Assumptions!F22 -> 0 | G4: =Assumptions!G22 -> 0 | H4: =Assumptions!H22 -> 0 | I4: =Assumptions!I22 -> 0 | J4: =Assumptions!J22 -> 0
B5: Interest rate on long-term debt | F5: =Assumptions!F23 -> 0 | G5: =Assumptions!G23 -> 0 | H5: =Assumptions!H23 -> 0 | I5: =Assumptions!I23 -> 0 | J5: =Assumptions!J23 -> 0
B6: Interest rate on cash | F6: =Assumptions!F24 -> 0 | G6: =Assumptions!G24 -> 0 | H6: =Assumptions!H24 -> 0 | I6: =Assumptions!I24 -> 0 | J6: =Assumptions!J24 -> 0
B8: Issuance of long-term debt | F8: =Assumptions!F26 -> 0 | G8: =Assumptions!G26 -> 0 | H8: =Assumptions!H26 -> 0 | I8: =Assumptions!I26 -> 0 | J8: =Assumptions!J26 -> 0
B9: Repayment of long-term debt | F9: =Assumptions!F27 -> 0 | G9: =Assumptions!G27 -> 0 | H9: =Assumptions!H27 -> 0 | I9: =Assumptions!I27 -> 0 | J9: =Assumptions!J27 -> 0
A11: Revolver | C11: =C2 -> 44926 | D11: =D2 -> 45291 | E11: =E2 -> 45657 | F11: =F2 -> 46022 | G11: =G2 -> 46387 | H11: =H2 -> 46752 | I11: =I2 -> 47118 | J11: =J2 -> 47483
B12: Balance
B13: Interest rate
B14: Interest expense
A16: Long term debt | C16: =C11 -> 44926 | D16: =D11 -> 45291 | E16: =E11 -> 45657 | F16: =F11 -> 46022 | G16: =G11 -> 46387 | H16: =H11 -> 46752 | I16: =I11 -> 47118 | J16: =J11 -> 47483
B17: Beginning balance
B18: Issuance
B19: Repayment
B20: Ending balance
B21: Interest rate
B22: Interest expense
A24: Debt summary | C24: =C16 -> 44926 | D24: =D16 -> 45291 | E24: =E16 -> 45657 | F24: =F16 -> 46022 | G24: =G16 -> 46387 | H24: =H16 -> 46752 | I24: =I16 -> 47118 | J24: =J16 -> 47483
B25: Revolver
B26: Total long term debt
B27: Total debt
B28: Total interest expense
A30: Interest income | C30: =C11 -> 44926 | D30: =D11 -> 45291 | E30: =E11 -> 45657 | F30: =F11 -> 46022 | G30: =G11 -> 46387 | H30: =H11 -> 46752 | I30: =I11 -> 47118 | J30: =J11 -> 47483
B31: Excess Cash
B32: Interest rate
B33: Interest income

Sheet IncState
A1: =CoName -> Berkshire Hathaway Non-Insurance | C1: Hist. | D1: Hist. | E1: Hist. | F1: Proj. | G1: Proj. | H1: Proj. | I1: Proj. | J1: Proj.
A2: Assumptions | C2: 44926 | D2: 45291 | E2: 45657 | F2: 46022 | G2: 46387 | H2: 46752 | I2: 47118 | J2: 47483
B4: Revenue growth | F4: =Assumptions!F10 -> 0.025 | G4: =Assumptions!G10 -> 0.025 | H4: =Assumptions!H10 -> 0.025 | I4: =Assumptions!I10 -> 0.025 | J4: =Assumptions!J10 -> 0.025
B5: Cost of goods sold as % of sales | F5: =Assumptions!F11 -> 0.66175939 | G5: =Assumptions!G11 -> 0.66175939 | H5: =Assumptions!H11 -> 0.66175939 | I5: =Assumptions!I11 -> 0.66175939 | J5: =Assumptions!J11 -> 0.66175939
B6: SG&A % of sales | F6: =Assumptions!F12 -> 0.087226351 | G6: =Assumptions!G12 -> 0.087226351 | H6: =Assumptions!H12 -> 0.087226351 | I6: =Assumptions!I12 -> 0.087226351 | J6: =Assumptions!J12 -> 0.087226351
B7: Amortization amount | F7: =Assumptions!F13 -> 0 | G7: =Assumptions!G13 -> 0 | H7: =Assumptions!H13 -> 0 | I7: =Assumptions!I13 -> 0 | J7: =Assumptions!J13 -> 0
B8: Non recurring items, amount | F8: =Assumptions!F14 -> 0 | G8: =Assumptions!G14 -> 0 | H8: =Assumptions!H14 -> 0 | I8: =Assumptions!I14 -> 0 | J8: =Assumptions!J14 -> 0
B9: Other income (expense), amt | F9: =Assumptions!F15 -> 0 | G9: =Assumptions!G15 -> 0 | H9: =Assumptions!H15 -> 0 | I9: =Assumptions!I15 -> 0 | J9: =Assumptions!J15 -> 0
B10: Effective tax rate | F10: =Assumptions!F16 -> 0.3651559 | G10: =Assumptions!G16 -> 0.3651559 | H10: =Assumptions!H16 -> 0.3651559 | I10: =Assumptions!I16 -> 0.3651559 | J10: =Assumptions!J16 -> 0.3651559
B11: Basic WASO | F11: =Assumptions!F17 -> 1.43772 | G11: =Assumptions!G17 -> 1.43772 | H11: =Assumptions!H17 -> 1.43772 | I11: =Assumptions!I17 -> 1.43772 | J11: =Assumptions!J17 -> 1.43772
B12: Diluted WASO | F12: =Assumptions!F18 -> 2156.5803 | G12: =Assumptions!G18 -> 2156.5803 | H12: =Assumptions!H18 -> 2156.5803 | I12: =Assumptions!I18 -> 2156.5803 | J12: =Assumptions!J18 -> 2156.5803
A14: Income statement | C14: =C35 -> 44926 | D14: =D35 -> 45291 | E14: =E35 -> 45657 | F14: =F35 -> 46022 | G14: =G35 -> 46022 | H14: =H35 -> 46022 | I14: =I35 -> 46022 | J14: =J35 -> 46022
B15: Revenue | C15: 52149 | D15: 49751 | E15: 49790 | F15: =E15*(1+F4) -> 51034.75 | G15: =F15*(1+G4) -> 52310.619 | H15: =G15*(1+H4) -> 53618.384 | I15: =H15*(1+I4) -> 54958.844 | J15: =I15*(1+J4) -> 56332.815
B16: COGS | C16: =41327-4984-3165 -> 33178 | D16: =42211-4016-3332 -> 34863 | E16: =40898-4343-3606 -> 32949 | F16: =F15*F5 -> 33772.725 | G16: =G15*G5 -> 34617.043 | H16: =H15*H5 -> 35482.469 | I16: =I15*I5 -> 36369.531 | J16: =J15*J5 -> 37278.769
B17: SG&A | C17: 4984 | D17: 4016 | E17: 4343 | F17: =F15*F6 -> 4451.575 | G17: =G15*G6 -> 4562.8644 | H17: =H15*H6 -> 4676.936 | I17: =I15*I6 -> 4793.8594 | J17: =J15*J6 -> 4913.7059
A18: * | B18: EBIT | C18: =C15-SUM(C16:C17) -> 13987 | D18: =D15-SUM(D16:D17) -> 10872 | E18: =E15-SUM(E16:E17) -> 12498 | F18: =F15-SUM(F16:F17) -> 12810.45 | G18: =G15-SUM(G16:G17) -> 13130.711 | H18: =H15-SUM(H16:H17) -> 13458.979 | I18: =I15-SUM(I16:I17) -> 13795.454 | J18: =J15-SUM(J16:J17) -> 14140.34
B20: Depreciation | C20: =10899-260 -> 10639 | D20: =12486-401 -> 12085 | E20: =12855-411 -> 12444 | F20: =Calcs!F8 -> 12854.009 | G20: =Calcs!G8 -> 13067.903 | H20: =Calcs!H8 -> 13295.036 | I20: =Calcs!I8 -> 13535.159 | J20: =Calcs!J8 -> 13788.059
B21: Amortization | C21: 0 | D21: 0 | E21: 0 | F21: =F7 -> 0 | G21: =G7 -> 0 | H21: =H7 -> 0 | I21: =I7 -> 0 | J21: =J7 -> 0
A22: * | B22: EBITDA | C22: =C18+C20 -> 24626 | D22: =D18+D20 -> 22957 | E22: =E18+E20 -> 24942 | F22: =F18+F20 -> 25664.459 | G22: =G18+G20 -> 26198.614 | H22: =H18+H20 -> 26754.015 | I22: =I18+I20 -> 27330.612 | J22: =J18+J20 -> 27928.399
B24: Non-recurring items | C24: 0 | D24: 0 | E24: 0 | F24: =F8 -> 0 | G24: =G8 -> 0 | H24: =H8 -> 0 | I24: =I8 -> 0 | J24: =J8 -> 0
B25: Other income (expense) | C25: 0 | D25: 0 | E25: 0 | F25: =F9 -> 0 | G25: =G9 -> 0 | H25: =H9 -> 0 | I25: =I9 -> 0 | J25: =J9 -> 0
B27: Interest income | C27: 0 | D27: 0 | E27: 0 | F27: 0 | G27: 0 | H27: 0 | I27: 0 | J27: 0
B28: Interest expense | C28: 3606 | D28: 3332 | E28: 3165 | F28: =E28 -> 3165 | G28: =F28 -> 3165 | H28: =G28 -> 3165 | I28: =H28 -> 3165 | J28: =I28 -> 3165
A30: * | B30: Pretax Income | C30: =C18-C28 -> 10381 | D30: =D18-D28 -> 7540 | E30: =E18-E28 -> 9333 | F30: =F18-F28 -> 9645.45 | G30: =G18-G28 -> 9965.7113 | H30: =H18-H28 -> 10293.979 | I30: =I18-I28 -> 10630.454 | J30: =J18-J28 -> 10975.34
B32: Tax expense | C32: =1763-1629+2403+66+1131 -> 3734 | D32: =1527-2022+2487+169+117+1135 -> 3413 | E32: =1617-1871+2598+152+912 -> 3408 | F32: =F30*F10 -> 3522.093 | G32: =G30*G10 -> 3639.0382 | H32: =H30*H10 -> 3758.9072 | I32: =I30*I10 -> 3881.7728 | J32: =J30*J10 -> 4007.7101
A33: * | B33: Net income | C33: =C30-C32 -> 6647 | D33: =D30-D32 -> 4127 | E33: =E30-E32 -> 5925 | F33: =F30-F32 -> 6123.357 | G33: =G30-G32 -> 6326.673 | H33: =H30-H32 -> 6535.0719 | I33: =I30-I32 -> 6748.6807 | J33: =J30-J32 -> 6967.6298
A35: Shareholder information | C35: 44926 | D35: 45291 | E35: 45657 | F35: 46022 | G35: 46022 | H35: 46022 | I35: 46022 | J35: 46022
B36: Class A WASO | C36: 1.468876 | D36: 1.44888 | E36: 1.43772 | F36: 1.43772 | G36: 1.43772 | H36: 1.43772 | I36: 1.43772 | J36: 1.43772
B37: Class B WASO | C37: 2203.3136 | D37: 2173.3197 | E37: 2156.5803 | F37: 2156.5803 | G37: 2156.5803 | H37: 2156.5803 | I37: 2156.5803 | J37: 2156.5803
B38: Class A EPS | C38: =C33/C36 -> 4525.2288 | D38: =D33/D36 -> 2848.407 | E38: =E33/E36 -> 4121.1084 | F38: =F33/F36 -> 4259.0748 | G38: =G33/G36 -> 4400.4904 | H38: =H33/H36 -> 4545.4413 | I38: =I33/I36 -> 4694.016 | J38: =J33/J36 -> 4846.3051
A39: * | B39: Class B EPS | C39: =C33/C37 -> 3.0168197 | D39: =D33/D37 -> 1.8989383 | E39: =E33/E37 -> 2.7474052 | F39: =F33/F37 -> 2.8393828 | G39: =G33/G37 -> 2.9336598 | H39: =H33/H37 -> 3.0302938 | I39: =I33/I37 -> 3.1293436 | J39: =J33/J37 -> 3.2308696

Sheet BalSheet
A1: =CoName -> Berkshire Hathaway Non-Insurance | C1: Hist. | D1: Hist. | E1: Hist. | F1: Proj. | G1: Proj. | H1: Proj. | I1: Proj. | J1: Proj.
A2: Assumptions | C2: 44926 | D2: 45291 | E2: 45657 | F2: 46022 | G2: 46387 | H2: 46752 | I2: 47118 | J2: 47483
B4: Operating Cash % of sales | F4: =Assumptions!F43 -> 0.015 | G4: =F4 -> 0.015 | H4: =G4 -> 0.015 | I4: =H4 -> 0.015 | J4: =I4 -> 0.015
B5: Accounts receivable % of sales | F5: =Assumptions!F44 -> 0.090439847 | G5: =Assumptions!G44 -> 0.090439847 | H5: =Assumptions!H44 -> 0.090439847 | I5: =Assumptions!I44 -> 0.090439847 | J5: =Assumptions!J44 -> 0.090439847
B6: Other current assets % of sales | F6: =Assumptions!F45 -> 0.10743121 | G6: =Assumptions!G45 -> 0.10743121 | H6: =Assumptions!H45 -> 0.10743121 | I6: =Assumptions!I45 -> 0.10743121 | J6: =Assumptions!J45 -> 0.10743121
B7: Other long-term assets % of sales | F7: =Assumptions!F46 -> 0.4179755 | G7: =Assumptions!G46 -> 0.4179755 | H7: =Assumptions!H46 -> 0.4179755 | I7: =Assumptions!I46 -> 0.4179755 | J7: =Assumptions!J46 -> 0.4179755
B9: Accounts payable/Accural % of COGS | F9: =Assumptions!F50 -> 0.55315791 | G9: =Assumptions!G50 -> 0.55315791 | H9: =Assumptions!H50 -> 0.55315791 | I9: =Assumptions!I50 -> 0.55315791 | J9: =Assumptions!J50 -> 0.55315791
B10: Other current liabilities % of sales | F10: =Assumptions!F51 -> 0.14125326 | G10: =Assumptions!G51 -> 0.14125326 | H10: =Assumptions!H51 -> 0.14125326 | I10: =Assumptions!I51 -> 0.14125326 | J10: =Assumptions!J51 -> 0.14125326
B11: Other long-term liabilities % of sales | F11: =Assumptions!F52 -> 1.604278 | G11: =Assumptions!G52 -> 1.604278 | H11: =Assumptions!H52 -> 1.604278 | I11: =Assumptions!I52 -> 1.604278 | J11: =Assumptions!J52 -> 1.604278
A13: Balance sheet | C13: =C2 -> 44926 | D13: =D2 -> 45291 | E13: =E2 -> 45657 | F13: =F2 -> 46022 | G13: =G2 -> 46387 | H13: =H2 -> 46752 | I13: =I2 -> 47118 | J13: =J2 -> 47483
B14: Operating Cash | C14: =1.5%*IncState!C15 -> 782.235 | D14: =1.5%*IncState!D15 -> 746.265 | E14: =1.5%*IncState!E15 -> 746.85 | F14: =F4*IncState!F15 -> 765.52125 | G14: =G4*IncState!G15 -> 784.65928 | H14: =H4*IncState!H15 -> 804.27576 | I14: =I4*IncState!I15 -> 824.38266 | J14: =J4*IncState!J15 -> 844.99222
B15: Excess cash | C15: =3551-C14 -> 2768.765 | D15: =3754-D14 -> 3007.735 | E15: =3396-E14 -> 2649.15 | F15: =MAX(CashFlow!F22,0) -> 7703.1201 | G15: =MAX(CashFlow!G22,0) -> 12826.215 | H15: =MAX(CashFlow!H22,0) -> 18028.054 | I15: =MAX(CashFlow!I22,0) -> 23317.919 | J15: =MAX(CashFlow!J22,0) -> 28704.784
B16: Accounts receivable | C16: 4795 | D16: 4999 | E16: 4503 | F16: =F5*IncState!F15 -> 4615.575 | G16: =G5*IncState!G15 -> 4730.9644 | H16: =H5*IncState!H15 -> 4849.2385 | I16: =I5*IncState!I15 -> 4970.4694 | J16: =J5*IncState!J15 -> 5094.7312
B17: Other current assets | C17: 5062 | D17: 5565 | E17: 5349 | F17: =F6*IncState!F15 -> 5482.725 | G17: =G6*IncState!G15 -> 5619.7931 | H17: =H6*IncState!H15 -> 5760.288 | I17: =I6*IncState!I15 -> 5904.2952 | J17: =J6*IncState!J15 -> 6051.9025
B18: Total current assets | C18: =SUM(C14:C17) -> 13408 | D18: =SUM(D14:D17) -> 14318 | E18: =SUM(E14:E17) -> 13248 | F18: =SUM(F14:F17) -> 18566.941 | G18: =SUM(G14:G17) -> 23961.632 | H18: =SUM(H14:H17) -> 29441.857 | I18: =SUM(I14:I17) -> 35017.066 | J18: =SUM(J14:J17) -> 40696.41
B20: Property, plant & equipment, net | C20: 160268 | D20: 169447 | E20: 175030 | F20: =Calcs!F9 -> 177942.54 | G20: =Calcs!G9 -> 181035.35 | H20: =Calcs!H9 -> 184305.05 | I20: =Calcs!I9 -> 187748.74 | J20: =Calcs!J9 -> 191364
B21: Intangible assets | C21: 26597 | D21: 27153 | E21: 27020 | F21: =E21-IncState!F7 -> 27020 | G21: =F21-IncState!G7 -> 27020 | H21: =G21-IncState!H7 -> 27020 | I21: =H21-IncState!I7 -> 27020 | J21: =I21-IncState!J7 -> 27020
B22: Other assets | C22: 22190 | D22: 19845 | E22: 20811 | F22: =F7*IncState!F15 -> 21331.275 | G22: =G7*IncState!G15 -> 21864.557 | H22: =H7*IncState!H15 -> 22411.171 | I22: =I7*IncState!I15 -> 22971.45 | J22: =J7*IncState!J15 -> 23545.736
B23: Total non-current assets | C23: =SUM(C20:C22) -> 209055 | D23: =SUM(D20:D22) -> 216445 | E23: =SUM(E20:E22) -> 222861 | F23: =SUM(F20:F22) -> 226293.82 | G23: =SUM(G20:G22) -> 229919.91 | H23: =SUM(H20:H22) -> 233736.22 | I23: =SUM(I20:I22) -> 237740.19 | J23: =SUM(J20:J22) -> 241929.74
A25: * | B25: TOTAL ASSETS | C25: =SUM(C23,C18) -> 222463 | D25: =SUM(D23,D18) -> 230763 | E25: =SUM(E23,E18) -> 236109 | F25: =SUM(F23,F18) -> 244860.76 | G25: =SUM(G23,G18) -> 253881.54 | H25: =SUM(H23,H18) -> 263178.07 | I25: =SUM(I23,I18) -> 272757.25 | J25: =SUM(J23,J18) -> 282626.15
B27: Revolver/Short term debt | C27: 0 | D27: 0 | E27: 0 | F27: =MIN(CashFlow!F22,0) -> 0 | G27: =MIN(CashFlow!G22,0) -> 0 | H27: =MIN(CashFlow!H22,0) -> 0 | I27: =MIN(CashFlow!I22,0) -> 0 | J27: =MIN(CashFlow!J22,0) -> 0
B28: Accounts payable/Accurals | C28: 16615 | D28: 18304 | E28: 18226 | F28: =F9*IncState!F16 -> 18681.65 | G28: =G9*IncState!G16 -> 19148.691 | H28: =H9*IncState!H16 -> 19627.409 | I28: =I9*IncState!I16 -> 20118.094 | J28: =J9*IncState!J16 -> 20621.046
B29: Other current liabilities | C29: 7369 | D29: 6818 | E29: 7033 | F29: =F10*IncState!F15 -> 7208.825 | G29: =G10*IncState!G15 -> 7389.0456 | H29: =H10*IncState!H15 -> 7573.7718 | I29: =I10*IncState!I15 -> 7763.1161 | J29: =J10*IncState!J15 -> 7957.194
B30: Total current liabilities | C30: =SUM(C27:C29) -> 23984 | D30: =SUM(D27:D29) -> 25122 | E30: =SUM(E27:E29) -> 25259 | F30: =SUM(F27:F29) -> 25890.475 | G30: =SUM(G27:G29) -> 26537.737 | H30: =SUM(H27:H29) -> 27201.18 | I30: =SUM(I27:I29) -> 27881.21 | J30: =SUM(J27:J29) -> 28578.24
B32: Long-term debt, including current maturities | C32: 0 | D32: 0 | E32: 0 | F32: =E32+SUM(Debt!F8:F9) -> 0 | G32: =F32+SUM(Debt!G8:G9) -> 0 | H32: =G32+SUM(Debt!H8:H9) -> 0 | I32: =H32+SUM(Debt!I8:I9) -> 0 | J32: =I32+SUM(Debt!J8:J9) -> 0
B33: Other long-term liabilities | C33: 76206 | D33: 79803 | E33: 79877 | F33: =F11*IncState!F15 -> 81873.925 | G33: =G11*IncState!G15 -> 83920.773 | H33: =H11*IncState!H15 -> 86018.792 | I33: =I11*IncState!I15 -> 88169.262 | J33: =J11*IncState!J15 -> 90373.494
B34: Total non-current liabilities | C34: =SUM(C32:C33) -> 76206 | D34: =SUM(D32:D33) -> 79803 | E34: =SUM(E32:E33) -> 79877 | F34: =SUM(F32:F33) -> 81873.925 | G34: =SUM(G32:G33) -> 83920.773 | H34: =SUM(H32:H33) -> 86018.792 | I34: =SUM(I32:I33) -> 88169.262 | J34: =SUM(J32:J33) -> 90373.494
B36: Equity | C36: 122273 | D36: 125838 | E36: 130973 | F36: =Calcs!F16 -> 137096.36 | G36: =Calcs!G16 -> 143423.03 | H36: =Calcs!H16 -> 149958.1 | I36: =Calcs!I16 -> 156706.78 | J36: =Calcs!J16 -> 163674.41
A37: * | B37: TOTAL LIABILITIES & EQUITY | C37: =SUM(C36,C34,C30) -> 222463 | D37: =SUM(D36,D34,D30) -> 230763 | E37: =SUM(E36,E34,E30) -> 236109 | F37: =SUM(F36,F34,F30) -> 244860.76 | G37: =SUM(G36,G34,G30) -> 253881.54 | H37: =SUM(H36,H34,H30) -> 263178.07 | I37: =SUM(I36,I34,I30) -> 272757.25 | J37: =SUM(J36,J34,J30) -> 282626.15
A39: * | B39: Balance check | C39: =C37-C25 -> 0 | D39: =D37-D25 -> 0 | E39: =E37-E25 -> 0 | F39: =F37-F25 -> 0 | G39: =G37-G25 -> 0 | H39: =H37-H25 -> 0 | I39: =I37-I25 -> 0 | J39: =J37-J25 -> 0

Sheet CashFlow
A1: =CoName -> Berkshire Hathaway Non-Insurance | C1: Hist. | D1: Hist. | E1: Hist. | F1: Proj. | G1: Proj. | H1: Proj. | I1: Proj. | J1: Proj.
A2: Cash flow statement | C2: 2022 | D2: =C2+1 -> 2023 | E2: =D2+1 -> 2024 | F2: =E2+1 -> 2025 | G2: =F2+1 -> 2026 | H2: =G2+1 -> 2027 | I2: =H2+1 -> 2028 | J2: =I2+1 -> 2029
B3: Net Income | F3: =IncState!F33 -> 6123.357 | G3: =IncState!G33 -> 6326.673 | H3: =IncState!H33 -> 6535.0719 | I3: =IncState!I33 -> 6748.6807 | J3: =IncState!J33 -> 6967.6298
B4: Depreciation | F4: =Calcs!F8 -> 12854.009 | G4: =Calcs!G8 -> 13067.903 | H4: =Calcs!H8 -> 13295.036 | I4: =Calcs!I8 -> 13535.159 | J4: =Calcs!J8 -> 13788.059
B5: Amortization | F5: =IncState!F21 -> 0 | G5: =IncState!G21 -> 0 | H5: =IncState!H21 -> 0 | I5: =IncState!I21 -> 0 | J5: =IncState!J21 -> 0
B6: (inc) / dec In OWC | F6: =Calcs!F24 -> 366.50375 | G6: =Calcs!G24 -> 375.66634 | H6: =Calcs!H24 -> 385.058 | I6: =Calcs!I24 -> 394.68445 | J6: =Calcs!J24 -> 404.55156
B7: (inc) / dec in LT assets | F7: =BalSheet!E22-BalSheet!F22 -> -520.275 | G7: =BalSheet!F22-BalSheet!G22 -> -533.28187 | H7: =BalSheet!G22-BalSheet!H22 -> -546.61392 | I7: =BalSheet!H22-BalSheet!I22 -> -560.27927 | J7: =BalSheet!I22-BalSheet!J22 -> -574.28625
B8: inc / (dec) in LT liabilities | F8: =BalSheet!F33-BalSheet!E33 -> 1996.925 | G8: =BalSheet!G33-BalSheet!F33 -> 2046.8481 | H8: =BalSheet!H33-BalSheet!G33 -> 2098.0193 | I8: =BalSheet!I33-BalSheet!H33 -> 2150.4698 | J8: =BalSheet!J33-BalSheet!I33 -> 2204.2316
B9: Cash Flow From Operations | F9: =SUM(F3:F8) -> 20820.52 | G9: =SUM(G3:G8) -> 21283.809 | H9: =SUM(H3:H8) -> 21766.571 | I9: =SUM(I3:I8) -> 22268.714 | J9: =SUM(J3:J8) -> 22790.186
B11: Capex | F11: =Calcs!F7 -> 15766.55 | G11: =Calcs!G7 -> 16160.714 | H11: =Calcs!H7 -> 16564.732 | I11: =Calcs!I7 -> 16978.85 | J11: =Calcs!J7 -> 17403.321
B12: Cash Flow from Investing | F12: =-F11 -> -15766.55 | G12: =-G11 -> -16160.714 | H12: =-H11 -> -16564.732 | I12: =-I11 -> -16978.85 | J12: =-J11 -> -17403.321
B14: Share issuance / (repayment) | F14: =Calcs!F11 -> 0 | G14: =Calcs!G11 -> 0 | H14: =Calcs!H11 -> 0 | I14: =Calcs!I11 -> 0 | J14: =Calcs!J11 -> 0
B15: Debt issuance / (repayment) | F15: =SUM(Debt!F8:F9) -> 0 | G15: =SUM(Debt!G8:G9) -> 0 | H15: =SUM(Debt!H8:H9) -> 0 | I15: =SUM(Debt!I8:I9) -> 0 | J15: =SUM(Debt!J8:J9) -> 0
B16: Cash Flow From Financing | F16: =SUM(F14:F15) -> 0 | G16: =SUM(G14:G15) -> 0 | H16: =SUM(H14:H15) -> 0 | I16: =SUM(I14:I15) -> 0 | J16: =SUM(J14:J15) -> 0
B18: Net Changes in Cash | F18: =SUM(F16,F12,F9) -> 5053.9701 | G18: =SUM(G16,G12,G9) -> 5123.0949 | H18: =SUM(H16,H12,H9) -> 5201.8394 | I18: =SUM(I16,I12,I9) -> 5289.8643 | J18: =SUM(J16,J12,J9) -> 5386.8649
B20: Beginning Cash | F20: =BalSheet!E15 -> 2649.15 | G20: =BalSheet!F15 -> 7703.1201 | H20: =BalSheet!G15 -> 12826.215 | I20: =BalSheet!H15 -> 18028.054 | J20: =BalSheet!I15 -> 23317.919
B21: Changes | F21: =F18 -> 5053.9701 | G21: =G18 -> 5123.0949 | H21: =H18 -> 5201.8394 | I21: =I18 -> 5289.8643 | J21: =J18 -> 5386.8649
B22: Ending Cash | F22: =SUM(F20:F21) -> 7703.1201 | G22: =SUM(G20:G21) -> 12826.215 | H22: =SUM(H20:H21) -> 18028.054 | I22: =SUM(I20:I21) -> 23317.919 | J22: =SUM(J20:J21) -> 28704.784

Sheet Free Cash Flow
A1: =CoName -> Berkshire Hathaway Non-Insurance | C1: Hist. | D1: Hist. | E1: Hist. | F1: Proj. | G1: Proj. | H1: Proj. | I1: Proj. | J1: Proj.
A2: Free Cash Flows | C2: 2022 | D2: =C2+1 -> 2023 | E2: =D2+1 -> 2024 | F2: =E2+1 -> 2025 | G2: =F2+1 -> 2026 | H2: =G2+1 -> 2027 | I2: =H2+1 -> 2028 | J2: =I2+1 -> 2029
A3: * | B3: Sales | F3: =IncState!F15 -> 51034.75 | G3: =IncState!G15 -> 52310.619 | H3: =IncState!H15 -> 53618.384 | I3: =IncState!I15 -> 54958.844 | J3: =IncState!J15 -> 56332.815
B4: EBIT | F4: =IncState!F18 -> 12810.45 | G4: =IncState!G18 -> 13130.711 | H4: =IncState!H18 -> 13458.979 | I4: =IncState!I18 -> 13795.454 | J4: =IncState!J18 -> 14140.34
B5: Effective Tax Rate | F5: =IncState!F10 -> 0.3651559 | G5: =IncState!G10 -> 0.3651559 | H5: =IncState!H10 -> 0.3651559 | I5: =IncState!I10 -> 0.3651559 | J5: =IncState!J10 -> 0.3651559
A7: * | B7: NOPAT | F7: =F4*(1-F5) -> 8132.6386 | G7: =G4*(1-G5) -> 8335.9546 | H7: =H4*(1-H5) -> 8544.3535 | I7: =I4*(1-I5) -> 8757.9623 | J7: =J4*(1-J5) -> 8976.9113
B8: Depreciation | F8: =CashFlow!F4 -> 12854.009 | G8: =CashFlow!G4 -> 13067.903 | H8: =CashFlow!H4 -> 13295.036 | I8: =CashFlow!I4 -> 13535.159 | J8: =CashFlow!J4 -> 13788.059
B9: Amortization | F9: =CashFlow!F5 -> 0 | G9: =CashFlow!G5 -> 0 | H9: =CashFlow!H5 -> 0 | I9: =CashFlow!I5 -> 0 | J9: =CashFlow!J5 -> 0
B10: (inc) / dec in OWC | F10: =CashFlow!F6 -> 366.50375 | G10: =CashFlow!G6 -> 375.66634 | H10: =CashFlow!H6 -> 385.058 | I10: =CashFlow!I6 -> 394.68445 | J10: =CashFlow!J6 -> 404.55156
B11: (inc) / dec in other long-term assets | F11: =CashFlow!F7 -> -520.275 | G11: =CashFlow!G7 -> -533.28187 | H11: =CashFlow!H7 -> -546.61392 | I11: =CashFlow!I7 -> -560.27927 | J11: =CashFlow!J7 -> -574.28625
B12: inc / (dec) other long-term liabilities | F12: =CashFlow!F8 -> 1996.925 | G12: =CashFlow!G8 -> 2046.8481 | H12: =CashFlow!H8 -> 2098.0193 | I12: =CashFlow!I8 -> 2150.4698 | J12: =CashFlow!J8 -> 2204.2316
B13: (Capex) | F13: =CashFlow!F12 -> -15766.55 | G13: =CashFlow!G12 -> -16160.714 | H13: =CashFlow!H12 -> -16564.732 | I13: =CashFlow!I12 -> -16978.85 | J13: =CashFlow!J12 -> -17403.321
A15: * | B15: Free Cash Flow | F15: =SUM(F7:F13) -> 7063.2517 | G15: =SUM(G7:G13) -> 7132.3765 | H15: =SUM(H7:H13) -> 7211.121 | I15: =SUM(I7:I13) -> 7299.1459 | J15: =SUM(J7:J13) -> 7396.1465

Sheet WACC
A1: =CoName -> Berkshire Hathaway Non-Insurance
A3: * | B3: WACC | G3: Comp | H3: Levered beta | I3: Gross debt | J3: Market cap | K3: Debt/Mcap | L3: MTR | M3: Unlevered beta
B4: Tax Rate | E4: =Assumptions!E16 -> 0.3651559 | G4: UNP | H4: 1.07 | I4: =1521+30286 -> 31807 | J4: 130600 | K4: =I4/J4 -> 0.24354518 | L4: =E4 -> 0.3651559 | M4: =H4/((1+K4*(1-L4))) -> 0.92671726
B5: Risk free rate | E5: 0.0408 | G5: CSX | H5: 1.29 | I5: =608+18554 -> 19162 | J5: 66900 | K5: =I5/J5 -> 0.2864275 | L5: =L4 -> 0.3651559 | M5: =H5/((1+K5*(1-L5))) -> 1.0915213
B6: Market risk Premium | E6: 0.05 | G6: NSC | H6: 1.32 | I6: =607+16476 -> 17083 | J6: 70200 | K6: =I6/J6 -> 0.24334758 | L6: =L5 -> 0.3651559 | M6: =H6/((1+K6*(1-L6))) -> 1.1433642
B7: Beta | E7: =M11 -> 1.4185032 | G7: CP | H7: 1.04 | I7: =1652+15502 -> 17154 | J7: 90900 | K7: =I7/J7 -> 0.18871287 | L7: =L6 -> 0.3651559 | M7: =H7/((1+K7*(1-L7))) -> 0.92873458
B8: Cost of Equity | E8: =E5+E6*E7 -> 0.11172516
B9: % Equity | E9: =1-E10 -> 0.39012621 | G9: Industry beta (average) | M9: =AVERAGE(M4:M7) -> 1.0225843
B10: % Debt | E10: =BalSheet!E33/BalSheet!E36 -> 0.60987379
B11: Cost of debt | E11: =AVERAGE(0.044,0.046,0.05,0.047) -> 0.04675 | G11: Re-levered beta | M11: =M9*(1+E10*(1-E4)) -> 1.4185032
B12: Post tax cost of debt | E12: =E11*(1-E4) -> 0.029678962
A13: * | B13: WACC | E13: =WACC!E8*WACC!E9+WACC!E12*WACC!E10 -> 0.061687334
B14: Long Term growth rate | E14: 0.02

Sheet DCF Model
A1: =CoName -> Berkshire Hathaway Non-Insurance | D1: Proj. | E1: Proj. | F1: Proj. | G1: Proj. | H1: Proj.
A2: Discount Model Year count | D2: 1 | E2: =D2+1 -> 2 | F2: =E2+1 -> 3 | G2: =F2+1 -> 4 | H2: =G2+1 -> 5
B3: Discount Factor | D3: =1/(1+$M$4)^D2 -> 0.94189689 | E3: =1/(1+$M$4)^E2 -> 0.88716976 | F3: =1/(1+$M$4)^F2 -> 0.83562244 | G3: =1/(1+$M$4)^G2 -> 0.78707017 | H3: =1/(1+$M$4)^H2 -> 0.74133895
B4: PV FCF | D4: =D3*'Free Cash Flow'!F15 -> 6652.8548 | E4: =E3*'Free Cash Flow'!G15 -> 6327.6287 | F4: =F3*'Free Cash Flow'!H15 -> 6025.7744 | G4: =G3*'Free Cash Flow'!I15 -> 5744.9401 | H4: =H3*'Free Cash Flow'!J15 -> 5483.0515 | J4: WACC | M4: =WACC!E13 -> 0.061687334
H5: =((H4*(1+M5))/(M4-M5)) -> 153189.87 | J5: Long Term growth rate | M5: 0.025
A6: Value Calculation | E6: Multiples Calculation
B7: Total PV of FCFs | C7: =SUM(D4:H4) -> 30234.25 | E7: Total PV of FCFs | G7: =C7 -> 30234.25 | K7: Perpetuity | P7: Multiple
B8: PV of TV | C8: =H5*H3 -> 113565.62 | E8: Multiple TV | G8: =G10*IncState!J22*'DCF Model'!H3 -> 269157.33 | I8: =C15 -> 64285.015 | J8: 0.02 | K8: 0.025 | L8: 0.03 | N8: =G15 -> 219876.73 | O8: 12 | P8: 13 | Q8: 14
B9: EV | C9: =SUM(C7:C8) -> 143799.86 | E9: EV | G9: =SUM(G7:G8) -> 299391.58 | I9: =I10+$E$22 -> 0.072 | J9: 22271.381 | K9: 30364.599 | L9: 40384.774 | N9: =N10+$E$22 -> 0.072 | O9: 186615.43 | P9: 206342.94 | Q9: 226070.44
E10: Implied EBITDA multiple | G10: 13 | I10: =I11+$E$22 -> 0.067 | J10: 34204.786 | K10: 44655.563 | L10: 57930.874 | N10: =N11+$E$22 -> 0.067 | O10: 192614.03 | P10: 212808.11 | Q10: 233002.18
I11: 0.062 | J11: 49119.879 | K11: 62968.414 | L11: 81144.617 | N11: 0.062 | O11: 198780.97 | P11: 219454.92 | Q11: 240128.87
B12: Cash & Cash Equiv | C12: =BalSheet!E15 -> 2649.15 | E12: Cash & Cash Equiv | G12: =C12 -> 2649.15 | I12: =I11-$E$22 -> 0.057 | J12: 68237.118 | K12: 87201.946 | L12: 113190.79 | N12: =N11-$E$22 -> 0.057 | O12: 205121.81 | P12: 226289.39 | Q12: 247456.96
B13: Debt & Claims | C13: =BalSheet!E33 -> 79877 | E13: Debt & Claims | G13: =C13 -> 79877 | I13: =I12-$E$22 -> 0.052 | J13: 93540.688 | K13: 120662.59 | L13: 160112.62 | N13: =N12-$E$22 -> 0.052 | O13: 211642.37 | P13: 233317.78 | Q13: 254993.19
B14: NCI | C14: 2287 | E14: NCI | G14: =C14 -> 2287 | K14: Average | P14: Average
B15: Equity Value | C15: =C9+C12-C13-C14 -> 64285.015 | E15: Equity Value | G15: =G9+G12-G13-G14 -> 219876.73 | J15: EV | K15: =AVERAGE(J9:L13) -> 71066.042 | O15: EV | P15: =AVERAGE(O9:Q13) -> 219642.62
B17: Diluted S/O | E17: Diluted S/O
A18: * | B18: Implied Share Price | E18: Implied Share Price
A20: Sensitivity analysis
C22: Discount rate variance | E22: 0.005 | J22: Discount rate variance | L22: 0.005
C23: Implied growth rate variance | E23: 0.0025 | J23: TV multiple variance | L23: 1
A25: DCF tables

Sheet COMPS
A1: =CoName -> Berkshire Hathaway Non-Insurance
A2: * | C2: Company Symbol | D2: Price 10/14/25 | E2: Enterprise Value | F2: LTM EV/EBITDA | G2: EV/EBITDA 2026E | H2: LTM EV/EBIT | I2: EV/EBIT 2026E | J2: LTM P/E Ratio | K2: P/E Ratio 2026E | L2: LTM EV/Sales | M2: EV/Sales 2026E | N2: Delta % Average
A8: * | B8: Average
A10: * | B10: Current price
B11: Delta -> Average

Sheet Presentation
A1: =CoName -> Berkshire Hathaway Non-Insurance
A2: Presentation slide
A3: Football field + SOTP Comps analysis
A21: DCF Analysis (Sensitivity tables)
A41: Projection ranges
