Workbook
Name Ccy: MAIN!$C$6
Name circ: MAIN!$C$9
Name CoName: MAIN!$C$4
Name g: Presentation!$R$17
Name IQ_CH: 110000
Name IQ_CQ: 5000
Name IQ_CY: 10000
Name IQ_DAILY: 500000
Name IQ_FH: 100000
Name IQ_FQ: 500
Name IQ_FY: 1000
Name IQ_LTM: 2000
Name IQ_MONTH: 15000
Name IQ_NTM: 6000
Name IQ_WEEK: 50000
Name IQ_YTD: 3000
Name OpCase: [1]DCF!$E$98
Name ScenarioREV: Assumptions!$D$4
Name TTS: #REF!
Name Units: MAIN!$C$7

Sheet MAIN
A1: =CoName -> Berkshire Hathaway Insurance
A2: Model Details
B3: PLEASE REFER TO MY OTHER BERKSHIRE MODEL TO COMBINE THE POTENTIAL EV NUMBERS
B4: Company name | C4: Berkshire Hathaway Insurance | E4: Total Cash & Equivalents | F4: 100486
B5: Latest BS date | C5: 247.43 | E5: Total Debt | F5: =127020 -> 127020
B6: Currency | C6: USD | E6: Total Mkt Cap | F6: =726000*F7 -> 1043784.7
B7: Units | C7: m | E7: Class A outstanding | F7: =[2]IncState!E36 -> 1.43772
B8: Analyst name | C8: Alan Chen | E8: Class A price | F8: 726000
B9: Circular switch | C9: 0 | E9: Class B outstanding | F9: =[2]IncState!E37 -> 2156.5803
E10: Class B Price | F10: 478.73
B11: Scenario | C11: Perpetuity | D11: Terminal Multiple
B12: Case 1 | C12: 1103259.9 | D12: 812390.88 | F12: SHARE PRICE CLASS A | J12: SHARE PRICE CLASS B
B13: Case 2 | C13: 1298405.2 | D13: 911869.15 | F13: Case 1 | G13: 821785.66 | H13: 718155.9 | J13: Case 1 | K13: 547.8571 | L13: 478.7706
B14: Case 3 | C14: 930268.37 | D14: 721450.24 | F14: Case 2 | G14: 985567.87 | H14: 807924.41 | J14: Case 2 | K14: 657.04525 | L14: 538.61627
F15: Case 3 | G15: 678018.26 | H15: 636117.51 | J15: Case 3 | K15: 452.01217 | L15: 424.07834
B16: COMBINED EV | C16: Perpetuity | D16: Terminal Multiple | F16: DIFFERENCE | J16: DIFFERENCE
B17: =B12 -> Case 1 | C17: =C12+C27 -> 1208031.7 | D17: =D12+D27 -> 1059041.1 | F17: =F13 -> Case 1 | G17: 0.13193617 | H17: -0.010804543 | J17: Case 1 | K17: 0.14439685 | L17: 8.4810023e-05
B18: =B13 -> Case 2 | C18: =C13+C28 -> 1443504.6 | D18: =D13+D28 -> 1188103.1 | F18: =F14 -> Case 2 | G18: 0.3575315 | H18: 0.11284354 | J18: Case 2 | K18: 0.37247561 | L18: 0.12509405
B19: =B14 -> Case 3 | C19: =C14+C29 -> 1001334.4 | D19: =D14+D29 -> 941092.86 | F19: =F15 -> Case 3 | G19: -0.066090552 | H19: -0.12380508 | J19: Case 3 | K19: -0.055809803 | L19: -0.11415967
G21: Weighted Average | K21: Weighted Average
G22: 774594.93 | K22: 516.39662
G23: 0.066935171 | K23: 0.078680306
B26: Scenario | C26: Perpetuity | D26: Terminal Multiple
B27: Case 1 | C27: 104771.76 | D27: 246650.22
B28: Case 2 | C28: 145099.4 | D28: 276233.93
B29: Case 3 | C29: 71066.042 | D29: 219642.62

Sheet Assumptions
A1: =CoName -> Berkshire Hathaway Insurance | C1: Hist. | D1: Hist. | E1: Hist. | F1: Proj. | G1: Proj. | H1: Proj. | I1: Proj. | J1: Proj.
A2: * | B2: Income Statement | C2: 44926 | D2: 45291 | E2: 45657 | F2: 46022 | G2: 46387 | H2: 46752 | I2: 47118 | J2: 47483
B4: Operating Case | D4: 1
D5: Variance
B6: Street Case | D6: 0 | F6: 0.05 | G6: 0.05 | H6: 0.05 | I6: 0.05 | J6: 0.05
B7: Optimistic Case | D7: 0.025 | F7: =F6+$D$7 -> 0.075 | G7: =G6+$D$7 -> 0.075 | H7: =H6+$D$7 -> 0.075 | I7: =I6+$D$7 -> 0.075 | J7: =J6+$D$7 -> 0.075
B8: Pessimistic Case | D8: -0.025 | F8: =F6+$D$8 -> 0.025 | G8: =G6+$D$8 -> 0.025 | H8: =H6+$D$8 -> 0.025 | I8: =I6+$D$8 -> 0.025 | J8: =J6+$D$8 -> 0.025
B10: Revenue Growth | C10: =IncState!C4 -> 0.096136974 | D10: =IncState!D15/IncState!C15-1 -> 0.25957394 | E10: =IncState!E15/IncState!D15-1 -> 0.021961612 | F10: =CHOOSE(ScenarioREV,F6,F7,F8) -> 0.05 | G10: =CHOOSE(ScenarioREV,G6,G7,G8) -> 0.05 | H10: =CHOOSE(ScenarioREV,H6,H7,H8) -> 0.05 | I10: =CHOOSE(ScenarioREV,I6,I7,I8) -> 0.05 | J10: =CHOOSE(ScenarioREV,J6,J7,J8) -> 0.05
B11: COGS % of sales | C11: =IncState!C16/IncState!C15 -> 0.81827823 | D11: =IncState!D16/IncState!D15 -> 0.800061 | E11: =IncState!E16/IncState!E15 -> 0.76968254 | F11: =E11 -> 0.76968254 | G11: =F11 -> 0.76968254 | H11: =G11 -> 0.76968254 | I11: =H11 -> 0.76968254 | J11: =I11 -> 0.76968254
B12: SG&A % of sales | C12: =IncState!C17/IncState!C15 -> 0.078064281 | D12: =IncState!D17/IncState!D15 -> 0.080888124 | E12: =IncState!E17/IncState!E15 -> 0.079721928 | F12: =E12 -> 0.079721928 | G12: =F12 -> 0.079721928 | H12: =G12 -> 0.079721928 | I12: =H12 -> 0.079721928 | J12: =I12 -> 0.079721928
B13: Amortization $ Amt | C13: 0 | D13: 0 | E13: 0 | F13: =E13 -> 0 | G13: =F13 -> 0 | H13: =G13 -> 0 | I13: =H13 -> 0 | J13: =I13 -> 0
B14: Non recurring income / (expense) | C14: =IncState!C24 -> -67899 | D14: =IncState!D24 -> 74855 | E14: =IncState!E24 -> 52799 | F14: 0 | G14: =F14 -> 0 | H14: =G14 -> 0 | I14: =H14 -> 0 | J14: =I14 -> 0
B15: Other Income / (expense) | C15: =IncState!C25 -> 1863 | D15: =IncState!D25 -> 1973 | E15: =IncState!E25 -> 1863 | F15: =AVERAGE(C15:E15) -> 1899.6667 | G15: =F15 -> 1899.6667 | H15: =G15 -> 1899.6667 | I15: =H15 -> 1899.6667 | J15: =I15 -> 1899.6667
B16: Effective tax rate | C16: =IncState!C32/IncState!C30 -> 0.27162138 | D16: =IncState!D32/IncState!D30 -> 0.18040118 | E16: =IncState!E32/IncState!E30 -> 0.17802209 | F16: =E16 -> 0.17802209 | G16: =F16 -> 0.17802209 | H16: =G16 -> 0.17802209 | I16: =H16 -> 0.17802209 | J16: =I16 -> 0.17802209
B17: Class A WASO | C17: =IncState!C36 -> 1.43772 | D17: =IncState!D36 -> 1.44888 | E17: =IncState!E36 -> 1.43772 | F17: =E17 -> 1.43772 | G17: =F17 -> 1.43772 | H17: =G17 -> 1.43772 | I17: =H17 -> 1.43772 | J17: =I17 -> 1.43772
B18: Class B WASO | C18: =IncState!C37 -> 2156.5803 | D18: =IncState!D37 -> 2173.3197 | E18: =IncState!E37 -> 2156.5803 | F18: =E18 -> 2156.5803 | G18: =F18 -> 2156.5803 | H18: =G18 -> 2156.5803 | I18: =H18 -> 2156.5803 | J18: =I18 -> 2156.5803
A20: * | B20: Debt | C20: 44926 | D20: 45291 | E20: 45657 | F20: 46022 | G20: 46387 | H20: 46752 | I20: 47118 | J20: 47483
B22: Interest rate on Revolver | F22: =E22 -> 0 | G22: =F22 -> 0 | H22: =G22 -> 0 | I22: =H22 -> 0 | J22: =I22 -> 0
B23: Interest rate on long-term debt | F23: =E23 -> 0 | G23: =F23 -> 0 | H23: =G23 -> 0 | I23: =H23 -> 0 | J23: =I23 -> 0
B24: Interest rate on cash | F24: =E24 -> 0 | G24: =F24 -> 0 | H24: =G24 -> 0 | I24: =H24 -> 0 | J24: =I24 -> 0
B26: Issuance of long-term debt | F26: 0 | G26: 0 | H26: 0 | I26: 0 | J26: 0
B27: Repayment of long-term debt | F27: 0 | G27: 0 | H27: 0 | I27: 0 | J27: 0
A29: * | B29: Calcs | C29: 44926 | D29: 45291 | E29: 45657 | F29: 46022 | G29: 46387 | H29: 46752 | I29: 47118 | J29: 47483
B31: CapEx % of Sales | D31: =68/IncState!D15 -> 0.00021605752 | E31: =82/IncState!E15 -> 0.00025494104 | F31: =E31 -> 0.00025494104 | G31: =F31 -> 0.00025494104 | H31: =G31 -> 0.00025494104 | I31: =H31 -> 0.00025494104 | J31: =I31 -> 0.00025494104
B32: Depreciation % of beginning PP&E | D32: =IncState!D20/BalSheet!C22 -> 0.010927324 | E32: =IncState!E20/BalSheet!D22 -> 0.0087176006 | F32: =E32 -> 0.0087176006 | G32: =F32 -> 0.0087176006 | H32: =G32 -> 0.0087176006 | I32: =H32 -> 0.0087176006 | J32: =I32 -> 0.0087176006
B33: Share issuance / (repurchases) | F33: 0 | G33: 0 | H33: 0 | I33: 0 | J33: 0
A35: * | B35: Shareholder information | C35: 44926 | D35: 45291 | E35: 45657 | F35: 46022 | G35: 46387 | H35: 46752 | I35: 47118 | J35: 47483
B37: Basic WASO | F37: =F17 -> 1.43772 | G37: =G17 -> 1.43772 | H37: =H17 -> 1.43772 | I37: =I17 -> 1.43772 | J37: =J17 -> 1.43772
B38: Diluted WASO | F38: =F18 -> 2156.5803 | G38: =G18 -> 2156.5803 | H38: =H18 -> 2156.5803 | I38: =I18 -> 2156.5803 | J38: =J18 -> 2156.5803
A40: * | B40: Balance Sheet - Assets | C40: 44926 | D40: 45291 | E40: 45657 | F40: 46022 | G40: 46387 | H40: 46752 | I40: 47118 | J40: 47483
B42: Operating Cash % of sales | C42: =BalSheet!C15/IncState!C15 -> 0.015 | D42: =BalSheet!D15/IncState!D15 -> 0.015 | E42: =BalSheet!E15/IncState!E15 -> 0.015 | F42: =E42 -> 0.015 | G42: =F42 -> 0.015 | H42: =G42 -> 0.015 | I42: =H42 -> 0.015 | J42: =I42 -> 0.015
B43: Additions to short term investments | D43: =BalSheet!D17-BalSheet!C17 -> 81540 | E43: =BalSheet!E17-BalSheet!D17 -> 68273 | F43: =AVERAGE(D43:E43) -> 74906.5 | G43: =F43 -> 74906.5 | H43: =G43 -> 74906.5 | I43: =H43 -> 74906.5 | J43: =I43 -> 74906.5
B44: Accounts receivable % of sales | C44: =BalSheet!C18/IncState!C15 -> 0.26692974 | D44: =BalSheet!D18/IncState!D15 -> 0.22540519 | E44: =BalSheet!E18/IncState!E15 -> 0.22287132 | F44: =E44 -> 0.22287132 | G44: =F44 -> 0.22287132 | H44: =G44 -> 0.22287132 | I44: =H44 -> 0.22287132 | J44: =I44 -> 0.22287132
B45: Inventories % of COGS | C45: =BalSheet!C19/IncState!C16 -> 0.12406096 | D45: =BalSheet!D19/IncState!D16 -> 0.10268304 | E45: =BalSheet!E19/IncState!E16 -> 0.096977335 | F45: =E45 -> 0.096977335 | G45: =F45 -> 0.096977335 | H45: =G45 -> 0.096977335 | I45: =H45 -> 0.096977335 | J45: =I45 -> 0.096977335
B46: Other long-term assets % of sales | C46: =BalSheet!C24/IncState!C15 -> 0.11816898 | D46: =BalSheet!D24/IncState!D15 -> 0.099643823 | E46: =BalSheet!E24/IncState!E15 -> 0.10505747 | F46: =E46 -> 0.10505747 | G46: =F46 -> 0.10505747 | H46: =G46 -> 0.10505747 | I46: =H46 -> 0.10505747 | J46: =I46 -> 0.10505747
A48: * | B48: Balance Sheet - Liabilities | C48: 44926 | D48: 45291 | E48: 45657 | F48: 46022 | G48: 46387 | H48: 46752 | I48: 47118 | J48: 47483
B50: Accounts payable % of COGS | C50: =BalSheet!C30/IncState!C16 -> 0.38999041 | D50: =BalSheet!D30/IncState!D16 -> 0.33767136 | E50: =BalSheet!E30/IncState!E16 -> 0.38431834 | F50: =E50 -> 0.38431834 | G50: =F50 -> 0.38431834 | H50: =G50 -> 0.38431834 | I50: =H50 -> 0.38431834 | J50: =I50 -> 0.38431834
B51: Other current liabilities % of sales | C51: =BalSheet!C31/IncState!C15 -> 0.11468718 | D51: =BalSheet!D31/IncState!D15 -> 0.096930395 | E51: =BalSheet!E31/IncState!E15 -> 0.12905924 | F51: =E51 -> 0.12905924 | G51: =F51 -> 0.12905924 | H51: =G51 -> 0.12905924 | I51: =H51 -> 0.12905924 | J51: =I51 -> 0.12905924
B52: Other long-term liabilities % of sales | C52: =BalSheet!C35/IncState!C15 -> 0.72369343 | D52: =BalSheet!D35/IncState!D15 -> 0.59015477 | E52: =BalSheet!E35/IncState!E15 -> 0.40282549 | F52: =E52 -> 0.40282549 | G52: =F52 -> 0.40282549 | H52: =G52 -> 0.40282549 | I52: =H52 -> 0.40282549 | J52: =I52 -> 0.40282549

Sheet Calcs
A1: =CoName -> Berkshire Hathaway Insurance | C1: Hist. | D1: Hist. | E1: Hist. | F1: Proj. | G1: Proj. | H1: Proj. | I1: Proj. | J1: Proj.
A2: Net PP&E | C2: 2022 | D2: =C2+1 -> 2023 | E2: =D2+1 -> 2024 | F2: =E2+1 -> 2025 | G2: =F2+1 -> 2026 | H2: =G2+1 -> 2027 | I2: =H2+1 -> 2028 | J2: =I2+1 -> 2029
B3: Capital expenditure % of sales | F3: =Assumptions!F31 -> 0.00025494104 | G3: =Assumptions!G31 -> 0.00025494104 | H3: =Assumptions!H31 -> 0.00025494104 | I3: =Assumptions!I31 -> 0.00025494104 | J3: =Assumptions!J31 -> 0.00025494104
B4: Depreciation % of PP&E | F4: =Assumptions!F32 -> 0.0087176006 | G4: =F4 -> 0.0087176006 | H4: =G4 -> 0.0087176006 | I4: =H4 -> 0.0087176006 | J4: =I4 -> 0.0087176006
B6: Beginning PP&E | F6: =E9 -> 47146 | G6: =F9 -> 46821.1 | H6: =G9 -> 46503.337 | I6: =H9 -> 46192.865 | J6: =I9 -> 45889.846
B7: Capex | F7: =F3*IncState!F15 -> 86.1 | G7: =G3*IncState!G15 -> 90.405 | H7: =H3*IncState!H15 -> 94.92525 | I7: =I3*IncState!I15 -> 99.671513 | J7: =J3*IncState!J15 -> 104.65509
B8: Depreciation | F8: =F4*F6 -> 411 | G8: =G4*G6 -> 408.16765 | H8: =H4*H6 -> 405.39752 | I8: =I4*I6 -> 402.69095 | J8: =J4*J6 -> 400.04935
B9: Ending PP&E | E9: =BalSheet!D22 -> 47146 | F9: =F6+F7-F8 -> 46821.1 | G9: =G6+G7-G8 -> 46503.337 | H9: =H6+H7-H8 -> 46192.865 | I9: =I6+I7-I8 -> 45889.846 | J9: =J6+J7-J8 -> 45594.451
A10: Equity | C10: =C2 -> 2022 | D10: =D2 -> 2023 | E10: =E2 -> 2024 | F10: =F2 -> 2025 | G10: =G2 -> 2026 | H10: =H2 -> 2027 | I10: =I2 -> 2028 | J10: =J2 -> 2029
B11: Share issuance/(repurchases) | F11: =Assumptions!F33 -> 0 | G11: =Assumptions!G33 -> 0 | H11: =Assumptions!H33 -> 0 | I11: =Assumptions!I33 -> 0 | J11: =Assumptions!J33 -> 0
B13: Beginning balance | F13: =E16 -> 606552 | G13: =F16 -> 646796.23 | H13: =G16 -> 689130.75 | I13: =H16 -> 733660.06 | J13: =I16 -> 780493.92
B14: Net income | F14: =IncState!F33 -> 40244.23 | G14: =IncState!G33 -> 42334.516 | H14: =IncState!H33 -> 44529.316 | I14: =IncState!I33 -> 46833.856 | J14: =IncState!J33 -> 49253.623
B15: Share issuance / (repurchase) | F15: =F11 -> 0 | G15: =G11 -> 0 | H15: =H11 -> 0 | I15: =I11 -> 0 | J15: =J11 -> 0
B16: Ending balance | E16: =BalSheet!E38 -> 606552 | F16: =SUM(F13:F15) -> 646796.23 | G16: =SUM(G13:G15) -> 689130.75 | H16: =SUM(H13:H15) -> 733660.06 | I16: =SUM(I13:I15) -> 780493.92 | J16: =SUM(J13:J15) -> 829747.54
A17: OWC | C17: =C10 -> 2022 | D17: =D10 -> 2023 | E17: =E10 -> 2024 | F17: =F10 -> 2025 | G17: =G10 -> 2026 | H17: =H10 -> 2027 | I17: =I10 -> 2028 | J17: =J10 -> 2029
B18: Operating Cash | E18: =BalSheet!E15 -> 4824.645 | F18: =BalSheet!F15 -> 5065.8772 | G18: =BalSheet!G15 -> 5319.1711 | H18: =BalSheet!H15 -> 5585.1297 | I18: =BalSheet!I15 -> 5864.3862 | J18: =BalSheet!J15 -> 6157.6055
B19: =BalSheet!B19 -> Inventories | E19: =BalSheet!E19 -> 24008 | F19: =BalSheet!F19 -> 25208.4 | G19: =BalSheet!G19 -> 26468.82 | H19: =BalSheet!H19 -> 27792.261 | I19: =BalSheet!I19 -> 29181.874 | J19: =BalSheet!J19 -> 30640.968
B20: =BalSheet!B18 -> Accounts receivable | E20: =BalSheet!E18 -> 71685 | F20: =BalSheet!F18 -> 75269.25 | G20: =BalSheet!G18 -> 79032.713 | H20: =BalSheet!H18 -> 82984.348 | I20: =BalSheet!I18 -> 87133.566 | J20: =BalSheet!J18 -> 91490.244
B21: Accounts payables | E21: =BalSheet!E30 -> 95143 | F21: =BalSheet!F30 -> 99900.15 | G21: =BalSheet!G30 -> 104895.16 | H21: =BalSheet!H30 -> 110139.92 | I21: =BalSheet!I30 -> 115646.91 | J21: =BalSheet!J30 -> 121429.26
B22: Other current liabilities | E22: =BalSheet!E31 -> 41511 | F22: =BalSheet!F31 -> 43586.55 | G22: =BalSheet!G31 -> 45765.878 | H22: =BalSheet!H31 -> 48054.171 | I22: =BalSheet!I31 -> 50456.88 | J22: =BalSheet!J31 -> 52979.724
A23: * | B23: OWC | E23: =SUM(E18:E20)-SUM(E21:E22) -> -36136.355 | F23: =SUM(F18:F20)-SUM(F21:F22) -> -37943.173 | G23: =SUM(G18:G20)-SUM(G21:G22) -> -39840.331 | H23: =SUM(H18:H20)-SUM(H21:H22) -> -41832.348 | I23: =SUM(I18:I20)-SUM(I21:I22) -> -43923.965 | J23: =SUM(J18:J20)-SUM(J21:J22) -> -46120.164
B24: Change in OWC | F24: =E23-F23 -> 1806.8178 | G24: =F23-G23 -> 1897.1586 | H24: =G23-H23 -> 1992.0166 | I24: =H23-I23 -> 2091.6174 | J24: =I23-J23 -> 2196.1983

Sheet Debt
A1: =CoName -> Berkshire Hathaway Insurance | C1: Hist. | D1: Hist. | E1: Hist. | F1: Proj. | G1: Proj. | H1: Proj. | I1: Proj. | J1: Proj.
A2: Assumptions | C2: 44926 | D2: 45291 | E2: 45657 | F2: 46022 | G2: 46387 | H2: 46752 | I2: 47118 | J2: 47483
B4: Interest rate on revolver | F4: =Assumptions!F22 -> 0 | G4: =Assumptions!G22 -> 0 | H4: =Assumptions!H22 -> 0 | I4: =Assumptions!I22 -> 0 | J4: =Assumptions!J22 -> 0
B5: Interest rate on long-term debt | F5: =Assumptions!F23 -> 0 | G5: =Assumptions!G23 -> 0 | H5: =Assumptions!H23 -> 0 | I5: =Assumptions!I23 -> 0 | J5: =Assumptions!J23 -> 0
B6: Interest rate on cash | F6: =Assumptions!F24 -> 0 | G6: =Assumptions!G24 -> 0 | H6: =Assumptions!H24 -> 0 | I6: =Assumptions!I24 -> 0 | J6: =Assumptions!J24 -> 0
B8: Issuance of long-term debt | F8: =Assumptions!F26 -> 0 | G8: =Assumptions!G26 -> 0 | H8: =Assumptions!H26 -> 0 | I8: =Assumptions!I26 -> 0 | J8: =Assumptions!J26 -> 0
B9: Repayment of long-term debt | F9: =Assumptions!F27 -> 0 | G9: =Assumptions!G27 -> 0 | H9: =Assumptions!H27 -> 0 | I9: =Assumptions!I27 -> 0 | J9: =Assumptions!J27 -> 0
A11: Revolver | C11: =C2 -> 44926 | D11: =D2 -> 45291 | E11: =E2 -> 45657 | F11: =F2 -> 46022 | G11: =G2 -> 46387 | H11: =H2 -> 46752 | I11: =I2 -> 47118 | J11: =J2 -> 47483
B12: Balance | F12: NO DEBT
B13: Interest rate
B14: Interest expense
A16: Long term debt | C16: =C11 -> 44926 | D16: =D11 -> 45291 | E16: =E11 -> 45657 | F16: =F11 -> 46022 | G16: =G11 -> 46387 | H16: =H11 -> 46752 | I16: =I11 -> 47118 | J16: =J11 -> 47483
B17: Beginning balance | F17: NO DEBT
B18: Issuance
B19: Repayment
B20: Ending balance
B21: Interest rate
B22: Interest expense
A24: Debt summary | C24: =C16 -> 44926 | D24: =D16 -> 45291 | E24: =E16 -> 45657 | F24: =F16 -> 46022 | G24: =G16 -> 46387 | H24: =H16 -> 46752 | I24: =I16 -> 47118 | J24: =J16 -> 47483
B25: Revolver | F25: NO DEBT
B26: Total long term debt
B27: Total debt
B28: Total interest expense
A30: Interest income | C30: =C11 -> 44926 | D30: =D11 -> 45291 | E30: =E11 -> 45657 | F30: =F11 -> 46022 | G30: =G11 -> 46387 | H30: =H11 -> 46752 | I30: =I11 -> 47118 | J30: =J11 -> 47483
B31: Excess Cash
B32: Interest rate
B33: Interest income

Sheet IncState
A1: =CoName -> Berkshire Hathaway Insurance | C1: Hist. | D1: Hist. | E1: Hist. | F1: Proj. | G1: Proj. | H1: Proj. | I1: Proj. | J1: Proj.
A2: Assumptions | C2: 44926 | D2: 45291 | E2: 45657 | F2: 46022 | G2: 46387 | H2: 46752 | I2: 47118 | J2: 47483
B4: Revenue growth | C4: =C15/227956-1 -> 0.096136974 | D4: =D15/C15-1 -> 0.25957394 | E4: =E15/D15-1 -> 0.021961612 | F4: =Assumptions!F10 -> 0.05 | G4: =Assumptions!G10 -> 0.05 | H4: =Assumptions!H10 -> 0.05 | I4: =Assumptions!I10 -> 0.05 | J4: =Assumptions!J10 -> 0.05
B5: Cost of goods sold as % of sales | F5: =Assumptions!F11 -> 0.76968254 | G5: =Assumptions!G11 -> 0.76968254 | H5: =Assumptions!H11 -> 0.76968254 | I5: =Assumptions!I11 -> 0.76968254 | J5: =Assumptions!J11 -> 0.76968254
B6: SG&A % of sales | F6: =Assumptions!F12 -> 0.079721928 | G6: =Assumptions!G12 -> 0.079721928 | H6: =Assumptions!H12 -> 0.079721928 | I6: =Assumptions!I12 -> 0.079721928 | J6: =Assumptions!J12 -> 0.079721928
B7: Amortization amount | C7: 0 | D7: 0 | E7: 0 | F7: =Assumptions!F13 -> 0 | G7: =Assumptions!G13 -> 0 | H7: =Assumptions!H13 -> 0 | I7: =Assumptions!I13 -> 0 | J7: =Assumptions!J13 -> 0
B8: Non recurring items, amount | F8: =Assumptions!F14 -> 0 | G8: =Assumptions!G14 -> 0 | H8: =Assumptions!H14 -> 0 | I8: =Assumptions!I14 -> 0 | J8: =Assumptions!J14 -> 0
B9: Other income (expense), amt | F9: =Assumptions!F15 -> 1899.6667 | G9: =Assumptions!G15 -> 1899.6667 | H9: =Assumptions!H15 -> 1899.6667 | I9: =Assumptions!I15 -> 1899.6667 | J9: =Assumptions!J15 -> 1899.6667
B10: Effective tax rate | F10: =Assumptions!F16 -> 0.17802209 | G10: =Assumptions!G16 -> 0.17802209 | H10: =Assumptions!H16 -> 0.17802209 | I10: =Assumptions!I16 -> 0.17802209 | J10: =Assumptions!J16 -> 0.17802209
B11: Basic WASO | F11: =Assumptions!F17 -> 1.43772 | G11: =Assumptions!G17 -> 1.43772 | H11: =Assumptions!H17 -> 1.43772 | I11: =Assumptions!I17 -> 1.43772 | J11: =Assumptions!J17 -> 1.43772
B12: Diluted WASO | F12: =Assumptions!F18 -> 2156.5803 | G12: =Assumptions!G18 -> 2156.5803 | H12: =Assumptions!H18 -> 2156.5803 | I12: =Assumptions!I18 -> 2156.5803 | J12: =Assumptions!J18 -> 2156.5803
A14: Income statement | C14: =C35 -> 44926 | D14: =D35 -> 45291 | E14: =E35 -> 45657 | F14: =F35 -> 46022 | G14: =G35 -> 46022 | H14: =H35 -> 46022 | I14: =I35 -> 46022 | J14: =J35 -> 46022
B15: Revenue | C15: =74576+157518+7514+10263 -> 249871 | D15: 314731 | E15: =321643 -> 321643 | F15: =E15*(1+F4) -> 337725.15 | G15: =F15*(1+G4) -> 354611.41 | H15: =G15*(1+H4) -> 372341.98 | I15: =H15*(1+I4) -> 390959.08 | J15: =I15*(1+J4) -> 410507.03
B16: COGS | C16: =225157-19506-1187 -> 204464 | D16: =278933-1671-25458 -> 251804 | E16: =274799-25642-1594 -> 247563 | F16: =F15*F5 -> 259941.15 | G16: =G15*G5 -> 272938.21 | H16: =H15*H5 -> 286585.12 | I16: =I15*I5 -> 300914.37 | J16: =J15*J5 -> 315960.09
B17: SG&A | C17: 19506 | D17: 25458 | E17: 25642 | F17: =F15*F6 -> 26924.1 | G17: =G15*G6 -> 28270.305 | H17: =H15*H6 -> 29683.82 | I17: =I15*I6 -> 31168.011 | J17: =J15*J6 -> 32726.412
A18: * | B18: EBIT | C18: =C15-SUM(C16:C17) -> 25901 | D18: =D15-SUM(D16:D17) -> 37469 | E18: =E15-SUM(E16:E17) -> 48438 | F18: =F15-SUM(F16:F17) -> 50859.9 | G18: =G15-SUM(G16:G17) -> 53402.895 | H18: =H15-SUM(H16:H17) -> 56073.04 | I18: =I15-SUM(I16:I17) -> 58876.692 | J18: =J15-SUM(J16:J17) -> 61820.526
B20: Depreciation | C20: 260 | D20: 401 | E20: 411 | F20: =Calcs!F8 -> 411 | G20: =Calcs!G8 -> 408.16765 | H20: =Calcs!H8 -> 405.39752 | I20: =Calcs!I8 -> 402.69095 | J20: =Calcs!J8 -> 400.04935
B21: Amortization | C21: 0 | D21: 0 | E21: 0 | F21: =F7 -> 0 | G21: =G7 -> 0 | H21: =H7 -> 0 | I21: =I7 -> 0 | J21: =J7 -> 0
A22: * | B22: EBITDA | C22: =C18+C20 -> 26161 | D22: =D18+D20 -> 37870 | E22: =E18+E20 -> 48849 | F22: =F18+F20 -> 51270.9 | G22: =G18+G20 -> 53811.063 | H22: =H18+H20 -> 56478.437 | I22: =I18+I20 -> 59279.383 | J22: =J18+J20 -> 62220.576
B24: Non-recurring items | C24: -67899 | D24: 74855 | E24: 52799 | F24: =F8 -> 0 | G24: =G8 -> 0 | H24: =H8 -> 0 | I24: =I8 -> 0 | J24: =J8 -> 0
B25: Other income (expense) | C25: 1863 | D25: 1973 | E25: 1863 | F25: =F9 -> 1899.6667 | G25: =G9 -> 1899.6667 | H25: =H9 -> 1899.6667 | I25: =I9 -> 1899.6667 | J25: =J9 -> 1899.6667
B27: Interest income
B28: Interest expense | C28: 1187 | D28: 1671 | E28: 1594
A30: * | B30: Pretax Income | C30: =C18-SUM(C25,C28)+C27+C24 -> -45048 | D30: =D18-SUM(D25,D28)+D27+D24 -> 108680 | E30: =E18-SUM(E25,E28)+E27+E24 -> 97780 | F30: =F18-SUM(F25,F28)+F27+F24 -> 48960.233 | G30: =G18-SUM(G25,G28)+G27+G24 -> 51503.228 | H30: =H18-SUM(H25,H28)+H27+H24 -> 54173.373 | I30: =I18-SUM(I25,I28)+I27+I24 -> 56977.025 | J30: =J18-SUM(J25,J28)+J27+J24 -> 59920.86
B32: Tax expense | C32: =-14166-88+334+437+1247 -> -12236 | D32: =3497+15930-90+223+46 -> 19606 | E32: =5462+11179-90+322+534 -> 17407 | F32: =F10*F30 -> 8716.0031 | G32: =G10*G30 -> 9168.7124 | H32: =H10*H30 -> 9644.0571 | I32: =I10*I30 -> 10143.169 | J32: =J10*J30 -> 10667.237
A33: * | B33: Net income | C33: =C30-C32 -> -32812 | D33: =D30-D32 -> 89074 | E33: =E30-E32 -> 80373 | F33: =F30-F32 -> 40244.23 | G33: =G30-G32 -> 42334.516 | H33: =H30-H32 -> 44529.316 | I33: =I30-I32 -> 46833.856 | J33: =J30-J32 -> 49253.623
A35: Shareholder information | C35: 44926 | D35: 45291 | E35: 45657 | F35: 46022 | G35: 46022 | H35: 46022 | I35: 46022 | J35: 46022
B36: Class A WASO | C36: 1.43772 | D36: 1.44888 | E36: 1.43772 | F36: 1.43772 | G36: 1.43772 | H36: 1.43772 | I36: 1.43772 | J36: 1.43772
B37: Class B WASO | C37: 2156.5803 | D37: 2173.3197 | E37: 2156.5803 | F37: 2156.5803 | G37: 2156.5803 | H37: 2156.5803 | I37: 2156.5803 | J37: 2156.5803
B38: Class A EPS | C38: =$C$33/C36 -> -22822.246 | D38: =$D$33/D36 -> 61477.831 | E38: =$E$33/E36 -> 55903.097 | F38: =F33/F36 -> 27991.702 | G38: =G33/G36 -> 29445.592 | H38: =H33/H36 -> 30972.175 | I38: =I33/I36 -> 32575.088 | J38: =J33/J36 -> 34258.147
A39: * | B39: Class B EPS | C39: =$C$33/C37 -> -15.214829 | D39: =$D$33/D37 -> 40.985226 | E39: =$E$33/E37 -> 37.268726 | F39: =F33/F37 -> 18.661132 | G39: =G33/G37 -> 19.630392 | H39: =H33/H37 -> 20.648114 | I39: =I33/I37 -> 21.716723 | J39: =J33/J37 -> 22.838761

Sheet BalSheet
A1: =CoName -> Berkshire Hathaway Insurance | C1: Hist. | D1: Hist. | E1: Hist. | F1: Proj. | G1: Proj. | H1: Proj. | I1: Proj. | J1: Proj.
A2: Assumptions | C2: 44926 | D2: 45291 | E2: 45657 | F2: 46022 | G2: 46387 | H2: 46752 | I2: 47118 | J2: 47483
B4: Operating Cash % of sales | F4: =Assumptions!F42 -> 0.015 | G4: =F4 -> 0.015 | H4: =G4 -> 0.015 | I4: =H4 -> 0.015 | J4: =I4 -> 0.015
B5: Additions to short term investments | F5: =IncState!F8 -> 0 | G5: =IncState!G8 -> 0 | H5: =IncState!H8 -> 0 | I5: =IncState!I8 -> 0 | J5: =IncState!J8 -> 0
B6: Accounts receivable % of sales | F6: =Assumptions!F44 -> 0.22287132 | G6: =Assumptions!G44 -> 0.22287132 | H6: =Assumptions!H44 -> 0.22287132 | I6: =Assumptions!I44 -> 0.22287132 | J6: =Assumptions!J44 -> 0.22287132
B7: Inventories % of COGS | F7: =Assumptions!F45 -> 0.096977335 | G7: =Assumptions!G45 -> 0.096977335 | H7: =Assumptions!H45 -> 0.096977335 | I7: =Assumptions!I45 -> 0.096977335 | J7: =Assumptions!J45 -> 0.096977335
B8: Other long-term assets % of sales | F8: =Assumptions!F46 -> 0.10505747 | G8: =Assumptions!G46 -> 0.10505747 | H8: =Assumptions!H46 -> 0.10505747 | I8: =Assumptions!I46 -> 0.10505747 | J8: =Assumptions!J46 -> 0.10505747
B10: Accounts payable/Accural % of COGS | F10: =Assumptions!F50 -> 0.38431834 | G10: =Assumptions!G50 -> 0.38431834 | H10: =Assumptions!H50 -> 0.38431834 | I10: =Assumptions!I50 -> 0.38431834 | J10: =Assumptions!J50 -> 0.38431834
B11: Other current liabilities % of sales | F11: =Assumptions!F51 -> 0.12905924 | G11: =Assumptions!G51 -> 0.12905924 | H11: =Assumptions!H51 -> 0.12905924 | I11: =Assumptions!I51 -> 0.12905924 | J11: =Assumptions!J51 -> 0.12905924
B12: Other long-term liabilities % of sales | F12: =Assumptions!F52 -> 0.40282549 | G12: =Assumptions!G52 -> 0.40282549 | H12: =Assumptions!H52 -> 0.40282549 | I12: =Assumptions!I52 -> 0.40282549 | J12: =Assumptions!J52 -> 0.40282549
A14: Balance sheet | C14: =C2 -> 44926 | D14: =D2 -> 45291 | E14: =E2 -> 45657 | F14: =F2 -> 46022 | G14: =G2 -> 46387 | H14: =H2 -> 46752 | I14: =I2 -> 47118 | J14: =J2 -> 47483
B15: Operating Cash | C15: =1.5%*IncState!C15 -> 3748.065 | D15: =1.5%*IncState!D15 -> 4720.965 | E15: =1.5%*IncState!E15 -> 4824.645 | F15: =F4*IncState!F15 -> 5065.8772 | G15: =G4*IncState!G15 -> 5319.1711 | H15: =H4*IncState!H15 -> 5585.1297 | I15: =I4*IncState!I15 -> 5864.3862 | J15: =J4*IncState!J15 -> 6157.6055
B16: Excess cash | C16: =32260-C15 -> 28511.935 | D16: =34268-D15 -> 29547.035 | E16: =44333-E15 -> 39508.355 | F16: =MAX(CashFlow!F23,0) -> 86673.053 | G16: =MAX(CashFlow!G23,0) -> 136250.68 | H16: =MAX(CashFlow!H23,0) -> 188362.08 | I16: =MAX(CashFlow!I23,0) -> 243134.15 | J16: =MAX(CashFlow!J23,0) -> 300700.12
B17: Short term investments | C17: =92774+25128+308793+28050 -> 454745 | D17: =129619+23758+353842+29066 -> 536285 | E17: =286472+15364+271588+31134 -> 604558 | F17: =E17+F5 -> 604558 | G17: =F17+G5 -> 604558 | H17: =G17+H5 -> 604558 | I17: =H17+I5 -> 604558 | J17: =I17+J5 -> 604558
B18: Accounts receivable | C18: =23208+43490 -> 66698 | D18: =24681+46261 -> 70942 | E18: =27798+43887 -> 71685 | F18: =F6*IncState!F15 -> 75269.25 | G18: =G6*IncState!G15 -> 79032.713 | H18: =H6*IncState!H15 -> 82984.348 | I18: =I6*IncState!I15 -> 87133.566 | J18: =J6*IncState!J15 -> 91490.244
B19: Inventories | C19: 25366 | D19: 25856 | E19: 24008 | F19: =F7*IncState!F16 -> 25208.4 | G19: =G7*IncState!G16 -> 26468.82 | H19: =H7*IncState!H16 -> 27792.261 | I19: =I7*IncState!I16 -> 29181.874 | J19: =J7*IncState!J16 -> 30640.968
B20: Total current assets | C20: =SUM(C15:C19) -> 579069 | D20: =SUM(D15:D19) -> 667351 | E20: =SUM(E15:E19) -> 744584 | F20: =SUM(F15:F19) -> 796774.58 | G20: =SUM(G15:G19) -> 851629.38 | H20: =SUM(H15:H19) -> 909281.82 | I20: =SUM(I15:I19) -> 969871.97 | J20: =SUM(J15:J19) -> 1033546.9
B22: Property, plant & equipment, net | C22: =21113+15584 -> 36697 | D22: =30199+16947 -> 47146 | E22: =30071+17828 -> 47899 | F22: =Calcs!F9 -> 46821.1 | G22: =Calcs!G9 -> 46503.337 | H22: =Calcs!H9 -> 46192.865 | I22: =Calcs!I9 -> 45889.846 | J22: =Calcs!J9 -> 45594.451
B23: Intangible assets | C23: =51522+29187 -> 80709 | D23: =35884+57473 -> 93357 | E23: =34638+56860 -> 91498 | F23: =E23-IncState!F7 -> 91498 | G23: =F23-IncState!G7 -> 91498 | H23: =G23-IncState!H7 -> 91498 | I23: =H23-IncState!I7 -> 91498 | J23: =I23-IncState!J7 -> 91498
B24: Other assets | C24: =9870+19657 -> 29527 | D24: =9495+21866 -> 31361 | E24: =8797+24994 -> 33791 | F24: =F8*IncState!F15 -> 35480.55 | G24: =G8*IncState!G15 -> 37254.578 | H24: =H8*IncState!H15 -> 39117.306 | I24: =I8*IncState!I15 -> 41073.172 | J24: =J8*IncState!J15 -> 43126.83
B25: Total non-current assets | C25: =SUM(C22:C24) -> 146933 | D25: =SUM(D22:D24) -> 171864 | E25: =SUM(E22:E24) -> 173188 | F25: =SUM(F22:F24) -> 173799.65 | G25: =SUM(G22:G24) -> 175255.91 | H25: =SUM(H22:H24) -> 176808.17 | I25: =SUM(I22:I24) -> 178461.02 | J25: =SUM(J22:J24) -> 180219.28
A27: * | B27: TOTAL ASSETS | C27: =SUM(C25,C20) -> 726002 | D27: =SUM(D25,D20) -> 839215 | E27: =SUM(E25,E20) -> 917772 | F27: =SUM(F25,F20)+753 -> 971327.23 | G27: =SUM(G25,G20)+753 -> 1027638.3 | H27: =SUM(H25,H20)+753 -> 1086843 | I27: =SUM(I25,I20)+753 -> 1149086 | J27: =SUM(J25,J20)+753 -> 1214519.2
B29: Revolver/Short term debt | C29: 0 | D29: 0 | E29: 0 | F29: =MIN(CashFlow!F23,0) -> 0 | G29: =MIN(CashFlow!G23,0) -> 0 | H29: =MIN(CashFlow!H23,0) -> 0 | I29: =MIN(CashFlow!I23,0) -> 0 | J29: =MIN(CashFlow!J23,0) -> 0
B30: Accounts payable/Accurals | C30: =33201+46538 -> 79739 | D30: =36559+48468 -> 85027 | E30: =37489+12769+44885 -> 95143 | F30: =F10*IncState!F16 -> 99900.15 | G30: =G10*IncState!G16 -> 104895.16 | H30: =H10*IncState!H16 -> 110139.92 | I30: =I10*IncState!I16 -> 115646.91 | J30: =J10*IncState!J16 -> 121429.26
B31: Other current liabilities | C31: =28657 -> 28657 | D31: =30507 -> 30507 | E31: =30808+10703 -> 41511 | F31: =F11*IncState!F15 -> 43586.55 | G31: =G11*IncState!G15 -> 45765.878 | H31: =H11*IncState!H15 -> 48054.171 | I31: =I11*IncState!I15 -> 50456.88 | J31: =J11*IncState!J15 -> 52979.724
B32: Total current liabilities | C32: =SUM(C29:C31) -> 108396 | D32: =SUM(D29:D31) -> 115534 | E32: =SUM(E29:E31) -> 136654 | F32: =SUM(F29:F31) -> 143486.7 | G32: =SUM(G29:G31) -> 150661.04 | H32: =SUM(H29:H31) -> 158194.09 | I32: =SUM(I29:I31) -> 166103.79 | J32: =SUM(J29:J31) -> 174408.98
B34: Long-term debt, including current maturities | C34: 0 | D34: 0 | E34: 45000 | F34: =E34-SUM(Debt!F8:F9) -> 45000 | G34: =F34-SUM(Debt!G8:G9) -> 45000 | H34: =G34-SUM(Debt!H8:H9) -> 45000 | I34: =H34-SUM(Debt!I8:I9) -> 45000 | J34: =I34-SUM(Debt!J8:J9) -> 45000
B35: Other long-term liabilities | C35: =289226-C32 -> 180830 | D35: =301274-D32 -> 185740 | E35: =311220-E32-E34 -> 129566 | F35: =F12*IncState!F15 -> 136044.3 | G35: =G12*IncState!G15 -> 142846.52 | H35: =H12*IncState!H15 -> 149988.84 | I35: =I12*IncState!I15 -> 157488.28 | J35: =J12*IncState!J15 -> 165362.7
B36: Total non-current liabilities | C36: =SUM(C34:C35) -> 180830 | D36: =SUM(D34:D35) -> 185740 | E36: =SUM(E34:E35) -> 174566 | F36: =SUM(F34:F35) -> 181044.3 | G36: =SUM(G34:G35) -> 187846.52 | H36: =SUM(H34:H35) -> 194988.84 | I36: =SUM(I34:I35) -> 202488.28 | J36: =SUM(J34:J35) -> 210362.7
B38: Equity | C38: 436776 | D38: 537941 | E38: 606552 | F38: =Calcs!F16 -> 646796.23 | G38: =Calcs!G16 -> 689130.75 | H38: =Calcs!H16 -> 733660.06 | I38: =Calcs!I16 -> 780493.92 | J38: =Calcs!J16 -> 829747.54
A39: * | B39: TOTAL LIABILITIES & EQUITY | C39: =SUM(C38,C36,C32) -> 726002 | D39: =SUM(D38,D36,D32) -> 839215 | E39: =SUM(E38,E36,E32) -> 917772 | F39: =SUM(F38,F36,F32) -> 971327.23 | G39: =SUM(G38,G36,G32) -> 1027638.3 | H39: =SUM(H38,H36,H32) -> 1086843 | I39: =SUM(I38,I36,I32) -> 1149086 | J39: =SUM(J38,J36,J32) -> 1214519.2
A41: * | B41: Balance check | C41: =C39-C27 -> 0 | D41: =D39-D27 -> 0 | E41: =E39-E27 -> 0 | F41: =F39-F27 -> 0 | G41: =G39-G27 -> 0 | H41: =H39-H27 -> 0 | I41: =I39-I27 -> 0 | J41: =J39-J27 -> 0

Sheet CashFlow
A1: =CoName -> Berkshire Hathaway Insurance | C1: Hist. | D1: Hist. | E1: Hist. | F1: Proj. | G1: Proj. | H1: Proj. | I1: Proj. | J1: Proj.
A2: Cash flow statement | C2: 2022 | D2: =C2+1 -> 2023 | E2: =D2+1 -> 2024 | F2: =E2+1 -> 2025 | G2: =F2+1 -> 2026 | H2: =G2+1 -> 2027 | I2: =H2+1 -> 2028 | J2: =I2+1 -> 2029
B3: Net Income | F3: =Calcs!F14 -> 40244.23 | G3: =IncState!G33 -> 42334.516 | H3: =IncState!H33 -> 44529.316 | I3: =IncState!I33 -> 46833.856 | J3: =IncState!J33 -> 49253.623
B4: Depreciation | F4: =Calcs!F8 -> 411 | G4: =Calcs!G8 -> 408.16765 | H4: =Calcs!H8 -> 405.39752 | I4: =Calcs!I8 -> 402.69095 | J4: =Calcs!J8 -> 400.04935
B5: Amortization | F5: =Assumptions!F13 -> 0 | G5: =Assumptions!G13 -> 0 | H5: =Assumptions!H13 -> 0 | I5: =Assumptions!I13 -> 0 | J5: =Assumptions!J13 -> 0
B6: (inc) / dec in OWC | F6: =Calcs!E23-Calcs!F23 -> 1806.8178 | G6: =Calcs!F23-Calcs!G23 -> 1897.1586 | H6: =Calcs!G23-Calcs!H23 -> 1992.0166 | I6: =Calcs!H23-Calcs!I23 -> 2091.6174 | J6: =Calcs!I23-Calcs!J23 -> 2196.1983
B7: (inc) / dec in LT assets | F7: =BalSheet!E24-BalSheet!F24 -> -1689.55 | G7: =BalSheet!F24-BalSheet!G24 -> -1774.0275 | H7: =BalSheet!G24-BalSheet!H24 -> -1862.7289 | I7: =BalSheet!H24-BalSheet!I24 -> -1955.8653 | J7: =BalSheet!I24-BalSheet!J24 -> -2053.6586
B8: inc / (dec) in LT liabilities | F8: =BalSheet!F35-BalSheet!E35 -> 6478.3 | G8: =BalSheet!G35-BalSheet!F35 -> 6802.215 | H8: =BalSheet!H35-BalSheet!G35 -> 7142.3258 | I8: =BalSheet!I35-BalSheet!H35 -> 7499.442 | J8: =BalSheet!J35-BalSheet!I35 -> 7874.4141
B9: Cash Flow From Operations | F9: =SUM(F3:F8) -> 47250.798 | G9: =SUM(G3:G8) -> 49668.03 | H9: =SUM(H3:H8) -> 52206.327 | I9: =SUM(I3:I8) -> 54871.741 | J9: =SUM(J3:J8) -> 57670.626
B11: Capex | F11: =Calcs!F7 -> 86.1 | G11: =Calcs!G7 -> 90.405 | H11: =Calcs!H7 -> 94.92525 | I11: =Calcs!I7 -> 99.671513 | J11: =Calcs!J7 -> 104.65509
B12: (inc) / dec in Investments | F12: =BalSheet!F17-BalSheet!E17 -> 0 | G12: =BalSheet!G17-BalSheet!F17 -> 0 | H12: =BalSheet!H17-BalSheet!G17 -> 0 | I12: =BalSheet!I17-BalSheet!H17 -> 0 | J12: =BalSheet!J17-BalSheet!I17 -> 0
B13: Cash Flow From Investing | F13: =SUM(F11:F12)*-1 -> -86.1 | G13: =SUM(G11:G12)*-1 -> -90.405 | H13: =SUM(H11:H12)*-1 -> -94.92525 | I13: =SUM(I11:I12)*-1 -> -99.671513 | J13: =SUM(J11:J12)*-1 -> -104.65509
B15: Share issuance / (repayment) | F15: =Calcs!F11 -> 0 | G15: =Calcs!G11 -> 0 | H15: =Calcs!H11 -> 0 | I15: =Calcs!I11 -> 0 | J15: =Calcs!J11 -> 0
B16: Debt issuance / (repayment) | F16: 0 | G16: 0 | H16: 0 | I16: 0 | J16: 0
B17: Cash Flow From Financing | F17: =SUM(F15:F16) -> 0 | G17: =SUM(G15:G16) -> 0 | H17: =SUM(H15:H16) -> 0 | I17: =SUM(I15:I16) -> 0 | J17: =SUM(J15:J16) -> 0
B19: Net changes in Cash | F19: =SUM(F17,F13,F9) -> 47164.698 | G19: =SUM(G17,G13,G9) -> 49577.625 | H19: =SUM(H17,H13,H9) -> 52111.402 | I19: =SUM(I17,I13,I9) -> 54772.07 | J19: =SUM(J17,J13,J9) -> 57565.971
B21: Beginning Cash | F21: =BalSheet!E16 -> 39508.355 | G21: =BalSheet!F16 -> 86673.053 | H21: =BalSheet!G16 -> 136250.68 | I21: =BalSheet!H16 -> 188362.08 | J21: =BalSheet!I16 -> 243134.15
B22: Changes | F22: =F19 -> 47164.698 | G22: =G19 -> 49577.625 | H22: =H19 -> 52111.402 | I22: =I19 -> 54772.07 | J22: =J19 -> 57565.971
B23: Ending Cash | F23: =SUM(F21:F22) -> 86673.053 | G23: =SUM(G21:G22) -> 136250.68 | H23: =SUM(H21:H22) -> 188362.08 | I23: =SUM(I21:I22) -> 243134.15 | J23: =SUM(J21:J22) -> 300700.12

Sheet Free Cash Flow
A1: =CoName -> Berkshire Hathaway Insurance | C1: Hist. | D1: Hist. | E1: Hist. | F1: Proj. | G1: Proj. | H1: Proj. | I1: Proj. | J1: Proj.
A2: Free Cash Flows | C2: 2022 | D2: =C2+1 -> 2023 | E2: =D2+1 -> 2024 | F2: =E2+1 -> 2025 | G2: =F2+1 -> 2026 | H2: =G2+1 -> 2027 | I2: =H2+1 -> 2028 | J2: =I2+1 -> 2029
A3: * | B3: Sales | F3: =IncState!F15 -> 337725.15 | G3: =IncState!G15 -> 354611.41 | H3: =IncState!H15 -> 372341.98 | I3: =IncState!I15 -> 390959.08 | J3: =IncState!J15 -> 410507.03
B4: EBIT | F4: =IncState!F18 -> 50859.9 | G4: =IncState!G18 -> 53402.895 | H4: =IncState!H18 -> 56073.04 | I4: =IncState!I18 -> 58876.692 | J4: =IncState!J18 -> 61820.526
B5: Effective Tax Rate | F5: =IncState!F10 -> 0.17802209 | G5: =IncState!G10 -> 0.17802209 | H5: =IncState!H10 -> 0.17802209 | I5: =IncState!I10 -> 0.17802209 | J5: =IncState!J10 -> 0.17802209
A7: * | B7: NOPAT | F7: =F4*(1-F5) -> 41805.714 | G7: =G4*(1-G5) -> 43896 | H7: =H4*(1-H5) -> 46090.8 | I7: =I4*(1-I5) -> 48395.34 | J7: =J4*(1-J5) -> 50815.107
B8: Depreciation | F8: =CashFlow!F4 -> 411 | G8: =CashFlow!G4 -> 408.16765 | H8: =CashFlow!H4 -> 405.39752 | I8: =CashFlow!I4 -> 402.69095 | J8: =CashFlow!J4 -> 400.04935
B9: Amortization | F9: =CashFlow!F5 -> 0 | G9: =CashFlow!G5 -> 0 | H9: =CashFlow!H5 -> 0 | I9: =CashFlow!I5 -> 0 | J9: =CashFlow!J5 -> 0
B10: (inc) / dec in OWC | F10: =CashFlow!F6 -> 1806.8178 | G10: =CashFlow!G6 -> 1897.1586 | H10: =CashFlow!H6 -> 1992.0166 | I10: =CashFlow!I6 -> 2091.6174 | J10: =CashFlow!J6 -> 2196.1983
B11: (inc) / dec in other long-term assets | F11: =CashFlow!F7 -> -1689.55 | G11: =CashFlow!G7 -> -1774.0275 | H11: =CashFlow!H7 -> -1862.7289 | I11: =CashFlow!I7 -> -1955.8653 | J11: =CashFlow!J7 -> -2053.6586
B12: inc / (dec) other long-term liabilities | F12: =CashFlow!F8 -> 6478.3 | G12: =CashFlow!G8 -> 6802.215 | H12: =CashFlow!H8 -> 7142.3258 | I12: =CashFlow!I8 -> 7499.442 | J12: =CashFlow!J8 -> 7874.4141
B13: (Capex) | F13: =-CashFlow!F11 -> -86.1 | G13: =-CashFlow!G11 -> -90.405 | H13: =-CashFlow!H11 -> -94.92525 | I13: =-CashFlow!I11 -> -99.671513 | J13: =-CashFlow!J11 -> -104.65509
A15: * | B15: Free Cash Flow | F15: =SUM(F7:F13) -> 48726.182 | G15: =SUM(G7:G13) -> 51139.109 | H15: =SUM(H7:H13) -> 53672.886 | I15: =SUM(I7:I13) -> 56333.554 | J15: =SUM(J7:J13) -> 59127.455

Sheet WACC
A1: =CoName -> Berkshire Hathaway Insurance
A3: * | B3: WACC | G3: Comp | H3: Levered beta | I3: Gross debt | J3: Market cap | K3: Debt/Mcap | L3: MTR | M3: Unlevered beta
B4: Tax Rate | E4: =Assumptions!E16 -> 0.17802209 | G4: UNH | H4: 0.48 | I4: =7737+72399 -> 80136 | J4: 308700 | K4: =I4/J4 -> 0.25959184 | L4: =E4 -> 0.17802209 | M4: =H4/((1+K4*(1-L4))) -> 0.39558959
B5: Risk free rate | E5: 0.041 | G5: CVS | H5: 0.61 | I5: =5328+60508 -> 65836 | J5: 99300 | K5: =I5/J5 -> 0.66300101 | L5: =L4 -> 0.17802209 | M5: =H5/((1+K5*(1-L5))) -> 0.39482912
B6: Market risk Premium | E6: 0.05 | G6: CI | H6: 0.46 | I6: =12439+30947 -> 43386 | J6: 65600 | K6: =I6/J6 -> 0.66137195 | L6: =L5 -> 0.17802209 | M6: =H6/((1+K6*(1-L6))) -> 0.29799827
B7: Beta | E7: =M11 -> 0.44699421 | G7: BRK.A | H7: 0.77 | I7: 127020 | J7: =660000+376900 -> 1036900 | K7: =I7/J7 -> 0.12249976 | L7: =L6 -> 0.17802209 | M7: =H7/((1+K7*(1-L7))) -> 0.69955985
B8: Cost of Equity | E8: =E5+E6*E7 -> 0.06334971
B9: % Equity | E9: 1 | G9: Industry beta (average) | M9: =AVERAGE(M4:M7) -> 0.44699421
B10: % Debt | E10: 0
B11: Cost of debt | E11: 0.04 | G11: Re-levered beta | M11: =M9*(1+E10*(1-E4)) -> 0.44699421
B12: Post tax cost of debt | E12: =E11*(1-E4) -> 0.032879116
A13: * | B13: WACC | E13: =E8*E9+E12*E10 -> 0.06334971
B14: Long Term growth rate | E14: 0.025

Sheet DCF Model
A1: =CoName -> Berkshire Hathaway Insurance | D1: Proj. | E1: Proj. | F1: Proj. | G1: Proj. | H1: Proj.
A2: Discount Model Year count | D2: 1 | E2: =D2+1 -> 2 | F2: =E2+1 -> 3 | G2: =F2+1 -> 4 | H2: =G2+1 -> 5
B3: Discount factor | D3: =1/(1+$M$3)^D2 -> 0.94042439 | E3: =1/(1+$M$3)^E2 -> 0.88439803 | F3: =1/(1+$M$3)^F2 -> 0.83170947 | G3: =1/(1+$M$3)^G2 -> 0.78215987 | H3: =1/(1+$M$3)^H2 -> 0.73556222 | J3: WACC | M3: =WACC!E13 -> 0.06334971
B4: PV FCF | D4: =D3*('Free Cash Flow'!F15) -> 45823.29 | E4: =E3*('Free Cash Flow'!G15) -> 45227.327 | F4: =F3*('Free Cash Flow'!H15) -> 44640.248 | G4: =G3*('Free Cash Flow'!I15) -> 44061.845 | H4: =H3*('Free Cash Flow'!J15) -> 43491.922 | J4: Long Term growth rate | M4: 0.0225
H5: =(H4*(1+M4))/(M3-M4) -> 1088636.6
A6: Value Calculation | E6: Multiples Calculation
B7: Total PV of FCFs | C7: =SUM(D4:H4) -> 223244.63 | E7: Total PV of FCFs | G7: =C7 -> 223244.63
B8: PV of TV | C8: =H5*H3 -> 800759.97 | E8: Multiple TV | G8: =G10*IncState!J22*'DCF Model'!H3 -> 549205.26 | L8: LTGR | Q8: Multiple
B9: EV | C9: =SUM(C7:C8) -> 1024004.6 | E9: EV | G9: =SUM(G7:G8) -> 772449.89 | J9: =C15 -> 1063513 | K9: =L9-$E$23 -> 0.02 | L9: 0.0225 | M9: 0.025 | O9: =G15 -> 811958.24 | P9: 11 | Q9: 12 | R9: 13
E10: Implied EBITDA multiple | G10: 12 | I10: WACC | J10: =J11+$E$22 -> 0.07334971 | K10: 813630.09 | L10: 842446.34 | M10: 874242.57 | O10: 0.07334971 | P10: 737062.7 | Q10: 780737.18 | R10: 824411.67
J11: =J12+$E$22 -> 0.06834971 | K11: 903628.3 | L11: 940405.43 | M11: 981424.47 | O11: 0.06834971 | P11: 751432.17 | Q11: 796138.28 | R11: 840844.38
B12: Cash & Cash Equiv | C12: =BalSheet!E16 -> 39508.355 | E12: Cash & Cash Equiv | G12: =C12 -> 39508.355 | J12: 0.06334971 | K12: 1015487.8 | L12: 1063513 | M12: 1117799.6 | O12: 0.06334971 | P12: 766191.14 | Q12: 811958.24 | R12: 857725.35
B13: Debt & Claims | C13: 45000 | E13: Debt & Claims | G13: =C13 -> 45000 | J13: =J12-$E$22 -> 0.05834971 | K13: 1157848.5 | L13: 1222387 | M13: 1296601.5 | O13: 0.05834971 | P13: 781352.28 | Q13: 828210.74 | R13: 875069.21
B14: NCI | C14: 0 | E14: NCI | G14: =C14 -> 0 | J14: =J13-$E$22 -> 0.05334971 | K14: 1344539.1 | L14: 1434537.1 | M14: 1540407.9 | O14: 0.05334971 | P14: 796928.75 | Q14: 844909.95 | R14: 892891.15
B15: Equity Value | C15: =C9+C12 -> 1063513 | E15: Equity Value | G15: =G9+G12 -> 811958.24 | L15: Average | Q15: Average
K16: EV | L16: =AVERAGE(K10:M14) -> 1103259.9 | P16: EV | Q16: =AVERAGE(P10:R14) -> 812390.88
B17: Diluted S/O | E17: Diluted S/O
A18: * | B18: Implied Share Price | E18: Implied Share Price
A20: Sensitivity analysis
C22: Discount rate variance | E22: 0.005 | J22: Discount rate variance | L22: 0.005
C23: Implied growth rate variance | E23: 0.0025 | J23: TV multiple variance | L23: 1
A25: DCF tables

Sheet COMPS
A1: =CoName -> Berkshire Hathaway Insurance
A2: * | C2: Company Symbol | D2: Price 10/14/25 | E2: Enterprise Value | F2: LTM EV/EBITDA | G2: EV/EBITDA 2026E | H2: LTM EV/EBIT | I2: EV/EBIT 2026E | J2: LTM P/E Ratio | K2: P/E Ratio 2026E | L2: LTM EV/Sales | M2: EV/Sales 2026E | N2: Delta % Average
A8: * | B8: Average
A10: * | B10: Current price
B11: Delta -> Average

Sheet Presentation
A1: =CoName -> Berkshire Hathaway Insurance
A2: Presentation slide
A3: Football field + SOTP Comps analysis
A21: DCF Analysis (Sensitivity tables)
A41: Projection ranges
