Workbook
Name Ccy: MAIN!$C$6
Name circ: MAIN!$C$9
Name CoName: MAIN!$C$4
Name g: #REF!
Name IQ_CH: 110000
Name IQ_CQ: 5000
Name IQ_CY: 10000
Name IQ_DAILY: 500000
Name IQ_FH: 100000
Name IQ_FQ: 500
Name IQ_FY: 1000
Name IQ_LTM: 2000
Name IQ_MONTH: 15000
Name IQ_NTM: 6000
Name IQ_WEEK: 50000
Name IQ_YTD: 3000
Name OpCase: [1]DCF!$E$98
Name ScenarioREV: Assumptions!$D$4
Name TTS: #REF!
Name Units: MAIN!$C$7

Sheet MAIN
A1: =CoName -> Crowdstrike Holdings
A2: Model Details
B4: Company name | C4: Crowdstrike Holdings | E4: Current Stock Price | F4: 514.38 | H4: Operating Case One | I4: Terminal Mult | J4: Perpetuity | K4: Average
B5: Latest BS date | C5: 2025 | E5: Diluted s/o | F5: 250955.14 | H5: Implied Price | I5: ='DCF Model'!O16 -> 116.80625 | J5: ='DCF Model'!C18 -> 112.52621 | K5: =AVERAGE(I5:J5) -> 114.66623
B6: Currency | C6: USD | E6: Mkt Cap | F6: =F5*F4 -> 1.290863e+08 | H6: Difference | I6: =I5/$F$4-1 -> -0.77291837 | J6: =J5/$F$4-1 -> -0.78123914 | K6: =K5/$F$4-1 -> -0.77707876
B7: Units | C7: m | E7: Cash | F7: 4972436
B8: Analyst name | C8: Alan Chen | E8: Debt | F8: 744727
B9: Circular switch | C9: 0 | E9: EV | F9: =F6-F7+F8 -> 1.248586e+08

Sheet Quarterly Projections

Sheet Assumptions
A1: =CoName -> Crowdstrike Holdings | C1: Hist. | D1: Hist. | E1: Hist. | F1: Proj. | G1: Proj. | H1: Proj. | I1: Proj. | J1: Proj.
A2: * | B2: Income Statement | C2: =D2-1 -> 2023 | D2: =E2-1 -> 2024 | E2: =MAIN!C5 -> 2025 | F2: =E2+1 -> 2026 | G2: =F2+1 -> 2027 | H2: =G2+1 -> 2028 | I2: =H2+1 -> 2029 | J2: =I2+1 -> 2030
B4: Operating Case | D4: 1
D5: Variance
B6: Street Case | D6: 0 | F6: 0.22 | G6: =F6 -> 0.22 | H6: =G6 -> 0.22 | I6: =H6 -> 0.22 | J6: =I6 -> 0.22
B7: Optimistic Case | D7: 0.025 | F7: =F6+$D$7 -> 0.245 | G7: =G6+$D$7 -> 0.245 | H7: =H6+$D$7 -> 0.245 | I7: =I6+$D$7 -> 0.245 | J7: =J6+$D$7 -> 0.245
B8: Pessimistic Case | D8: -0.025 | F8: =F6+$D$8 -> 0.195 | G8: =G6+$D$8 -> 0.195 | H8: =H6+$D$8 -> 0.195 | I8: =I6+$D$8 -> 0.195 | J8: =J6+$D$8 -> 0.195
B10: Revenue Growth | D10: =IncState!D16/IncState!C16-1 -> 0.36333478 | E10: =IncState!E16/IncState!D16-1 -> 0.29391354 | F10: =CHOOSE(ScenarioREV,F6,F7,F8) -> 0.22 | G10: =CHOOSE(ScenarioREV,G6,G7,G8) -> 0.22 | H10: =CHOOSE(ScenarioREV,H6,H7,H8) -> 0.22 | I10: =CHOOSE(ScenarioREV,I6,I7,I8) -> 0.22 | J10: =CHOOSE(ScenarioREV,J6,J7,J8) -> 0.22
B11: COGS % of sales | C11: =IncState!C17/IncState!C16 -> 0.26825868 | D11: =IncState!D17/IncState!D16 -> 0.24732757 | E11: =IncState!E17/IncState!E16 -> 0.25077777 | F11: =E11 -> 0.25077777 | G11: =F11 -> 0.25077777 | H11: =G11 -> 0.25077777 | I11: =H11 -> 0.25077777 | J11: =I11 -> 0.25077777
B12: R&D % of sales | C12: =IncState!C18/IncState!C16 -> 0.27144129 | D12: =IncState!D18/IncState!D16 -> 0.25150815 | E12: =IncState!E18/IncState!E16 -> 0.27238326 | F12: =E12 -> 0.27238326 | G12: =F12 -> 0.27238326 | H12: =G12 -> 0.27238326 | I12: =H12 -> 0.27238326 | J12: =I12 -> 0.27238326
B13: SG&A % of sales | C13: =IncState!C19/IncState!C16 -> 0.54512465 | D13: =IncState!D19/IncState!D16 -> 0.50181718 | E13: =IncState!E19/IncState!E16 -> 0.50729963 | F13: =E13-0.02 -> 0.48729963 | G13: =F13-0.02 -> 0.46729963 | H13: =G13-0.02 -> 0.44729963 | I13: =H13-0.02 -> 0.42729963 | J13: =I13-0.02 -> 0.40729963
B14: Amortization $ Amt | C14: =IncState!C23 -> 187373 | D14: =IncState!D23 -> 257317 | E14: =IncState!E23 -> 344841 | F14: =AVERAGE(C14:E14) -> 263177 | G14: =F14 -> 263177 | H14: =G14 -> 263177 | I14: =H14 -> 263177 | J14: =I14 -> 263177
B15: Non recurring income / (expense) | C15: =IncState!C26 -> 0 | D15: =IncState!D26 -> 0 | E15: =IncState!E26 -> 0 | F15: 0 | G15: 0 | H15: 0 | I15: 0 | J15: 0
B16: Other Income / (expense) | C16: =IncState!C27 -> 3053 | D16: =IncState!D27 -> 1638 | E16: =IncState!E27 -> 5101 | F16: 0 | G16: 0 | H16: 0 | I16: 0 | J16: 0
B17: Effective tax rate | C17: =IncState!C34/IncState!C32 -> -0.14011496 | D17: =IncState!D34/IncState!D32 -> 0.26243924 | E17: =IncState!E34/IncState!E32 -> 1.3043239 | F17: 0.21 | G17: =F17 -> 0.21 | H17: =G17 -> 0.21 | I17: =H17 -> 0.21 | J17: =I17 -> 0.21
B18: Basic WASO | C18: =IncState!C37 -> 233139 | D18: =IncState!D37 -> 238637 | E18: =IncState!E37 -> 244750 | F18: =E18 -> 244750 | G18: =F18 -> 244750 | H18: =G18 -> 244750 | I18: =H18 -> 244750 | J18: =I18 -> 244750
B19: Diluted WASO | C19: =IncState!C38 -> 233139 | D19: =IncState!D38 -> 243635 | E19: =IncState!E38 -> 244750 | F19: =E19 -> 244750 | G19: =F19 -> 244750 | H19: =G19 -> 244750 | I19: =H19 -> 244750 | J19: =I19 -> 244750
A21: * | B21: Debt | C21: =C2 -> 2023 | D21: =D2 -> 2024 | E21: =E2 -> 2025 | F21: =F2 -> 2026 | G21: =G2 -> 2027 | H21: =H2 -> 2028 | I21: =I2 -> 2029 | J21: =J2 -> 2030
B23: Interest rate on Revolver | E23: =E24 -> 0.035365055 | F23: =E23 -> 0.035365055 | G23: =F23 -> 0.035365055 | H23: =G23 -> 0.035365055 | I23: =H23 -> 0.035365055 | J23: =I23 -> 0.035365055
B24: Interest rate on long-term debt | D24: =-IncState!D30/BalSheet!D35 -> 0.034688496 | E24: =-IncState!E30/BalSheet!E35 -> 0.035365055 | F24: =E24 -> 0.035365055 | G24: =F24 -> 0.035365055 | H24: =G24 -> 0.035365055 | I24: =H24 -> 0.035365055 | J24: =I24 -> 0.035365055
B25: Interest rate on cash | D25: =IncState!D29/SUM(BalSheet!D16:D17) -> 0.044126505 | E25: =IncState!E29/SUM(BalSheet!E16:E17) -> 0.045376038 | F25: =E25 -> 0.045376038 | G25: =F25 -> 0.045376038 | H25: =G25 -> 0.045376038 | I25: =H25 -> 0.045376038 | J25: =I25 -> 0.045376038
B27: Issuance of long-term debt | F27: 0 | G27: 0 | H27: 0 | I27: 0 | J27: 0
B28: Repayment of long-term debt | F28: 0 | G28: 0 | H28: 0 | I28: 0 | J28: 0
A30: * | B30: Calcs | C30: =C21 -> 2023 | D30: =D21 -> 2024 | E30: =E21 -> 2025 | F30: =F21 -> 2026 | G30: =G21 -> 2027 | H30: =H21 -> 2028 | I30: =I21 -> 2029 | J30: =J21 -> 2030
B32: CapEx % of Sales | D32: =176529/IncState!D16 -> 0.057773138 | E32: =254852/IncState!E16 -> 0.064460353 | F32: =E32 -> 0.064460353 | G32: =F32 -> 0.064460353 | H32: =G32 -> 0.064460353 | I32: =H32 -> 0.064460353 | J32: =I32 -> 0.064460353
B33: Depreciation % of beginning PP&E | D33: =IncState!D22/BalSheet!C22 -> 0.23829591 | E33: =IncState!E22/BalSheet!D22 -> 0.28120404 | F33: =E33 -> 0.28120404 | G33: =F33 -> 0.28120404 | H33: =G33 -> 0.28120404 | I33: =H33 -> 0.28120404 | J33: =I33 -> 0.28120404
B34: Share issuance / (repurchases) | F34: 0 | G34: 0 | H34: 0 | I34: 0 | J34: 0
A36: * | B36: Balance Sheet - Assets | C36: =C30 -> 2023 | D36: =D30 -> 2024 | E36: =E30 -> 2025 | F36: =F30 -> 2026 | G36: =G30 -> 2027 | H36: =H30 -> 2028 | I36: =I30 -> 2029 | J36: =J30 -> 2030
B38: Operating Cash % of sales | C38: =BalSheet!C16/IncState!C16 -> 0.015 | D38: =BalSheet!D16/IncState!D16 -> 0.015 | E38: =BalSheet!E16/IncState!E16 -> 0.015 | F38: =E38 -> 0.015 | G38: =F38 -> 0.015 | H38: =G38 -> 0.015 | I38: =H38 -> 0.015 | J38: =I38 -> 0.015
B39: Accounts receivable % of sales | C39: =BalSheet!C18/IncState!C16 -> 0.27939093 | D39: =BalSheet!D18/IncState!D16 -> 0.27919805 | E39: =BalSheet!E18/IncState!E16 -> 0.28545051 | F39: =E39 -> 0.28545051 | G39: =F39 -> 0.28545051 | H39: =G39 -> 0.28545051 | I39: =H39 -> 0.28545051 | J39: =I39 -> 0.28545051
B40: Other current assets % of sales | C40: =BalSheet!C19/IncState!C16 -> 0.24928968 | D40: =BalSheet!D19/IncState!D16 -> 0.17317083 | E40: =BalSheet!E19/IncState!E16 -> 0.16731131 | F40: =E40 -> 0.16731131 | G40: =F40 -> 0.16731131 | H40: =G40 -> 0.16731131 | I40: =H40 -> 0.16731131 | J40: =I40 -> 0.16731131
B42: Investments in unconsolidated entities | C42: =BalSheet!C24 -> 47270 | D42: =BalSheet!D24 -> 56244 | E42: =BalSheet!E24 -> 72544 | F42: =E42 -> 72544 | G42: =F42 -> 72544 | H42: =G42 -> 72544 | I42: =H42 -> 72544 | J42: =I42 -> 72544
B43: Other long-term assets % of sales | C43: =BalSheet!C25/IncState!C16 -> 0.012923672 | D43: =BalSheet!D25/IncState!D16 -> 0.024903495 | E43: =BalSheet!E25/IncState!E16 -> 0.034767848 | F43: =E43 -> 0.034767848 | G43: =F43 -> 0.034767848 | H43: =G43 -> 0.034767848 | I43: =H43 -> 0.034767848 | J43: =I43 -> 0.034767848
A45: * | B45: Balance Sheet - Liabilities | C45: =C36 -> 2023 | D45: =D36 -> 2024 | E45: =E36 -> 2025 | F45: =F36 -> 2026 | G45: =G36 -> 2027 | H45: =H36 -> 2028 | I45: =I36 -> 2029 | J45: =J36 -> 2030
B47: Accounts payable % of COGS | C47: =BalSheet!C31/IncState!C17 -> 0.58550374 | D47: =BalSheet!D31/IncState!D17 -> 0.5143419 | E47: =BalSheet!E31/IncState!E17 -> 0.64699071 | F47: 0.6 | G47: =F47 -> 0.6 | H47: =G47 -> 0.6 | I47: =H47 -> 0.6 | J47: =I47 -> 0.6
B48: Other current liabilities % of sales | C48: =BalSheet!C32/IncState!C16 -> 0.78396429 | D48: =BalSheet!D32/IncState!D16 -> 0.75553508 | E48: =BalSheet!E32/IncState!E16 -> 0.71316114 | F48: =E48 -> 0.71316114 | G48: =F48 -> 0.71316114 | H48: =G48 -> 0.71316114 | I48: =H48 -> 0.71316114 | J48: =I48 -> 0.71316114
B49: Other long-term liabilities % of sales | C49: =BalSheet!C36/IncState!C16 -> 0.3074326 | D49: =BalSheet!D36/IncState!D16 -> 0.2846154 | E49: =BalSheet!E36/IncState!E16 -> 0.29786039 | F49: =E49 -> 0.29786039 | G49: =F49 -> 0.29786039 | H49: =G49 -> 0.29786039 | I49: =H49 -> 0.29786039 | J49: =I49 -> 0.29786039

Sheet Calcs
A1: =CoName -> Crowdstrike Holdings | C1: Hist. | D1: Hist. | E1: Hist. | F1: Proj. | G1: Proj. | H1: Proj. | I1: Proj. | J1: Proj.
A2: Net PP&E | C2: =D2-1 -> 2023 | D2: =E2-1 -> 2024 | E2: =MAIN!C5 -> 2025 | F2: 2026 | G2: 2027 | H2: 2028 | I2: 2029 | J2: 2030
B3: Capital expenditure % of sales | F3: =Assumptions!F32 -> 0.064460353 | G3: =Assumptions!G32 -> 0.064460353 | H3: =Assumptions!H32 -> 0.064460353 | I3: =Assumptions!I32 -> 0.064460353 | J3: =Assumptions!J32 -> 0.064460353
B4: Depreciation % of PP&E | F4: =Assumptions!F33 -> 0.28120404 | G4: =F4 -> 0.28120404 | H4: =G4 -> 0.28120404 | I4: =H4 -> 0.28120404 | J4: =I4 -> 0.28120404
B6: Beginning PP&E | F6: =E9 -> 831403 | G6: =F9 -> 908528.56 | H6: =G9 -> 1032368.4 | I6: =H9 -> 1204834.7 | J6: =I9 -> 1430612.8
B7: Capex | F7: =F3*IncState!F16 -> 310919.44 | G7: =G3*IncState!G16 -> 379321.72 | H7: =H3*IncState!H16 -> 462772.49 | I7: =I3*IncState!I16 -> 564582.44 | J7: =J3*IncState!J16 -> 688790.58
B8: Depreciation | F8: =F6*F4 -> 233793.88 | G8: =G6*G4 -> 255481.9 | H8: =H6*H4 -> 290306.16 | I8: =I6*I4 -> 338804.39 | J8: =J6*J4 -> 402294.09
B9: Ending PP&E | E9: =BalSheet!E22 -> 831403 | F9: =F6+F7-F8 -> 908528.56 | G9: =G6+G7-G8 -> 1032368.4 | H9: =H6+H7-H8 -> 1204834.7 | I9: =I6+I7-I8 -> 1430612.8 | J9: =J6+J7-J8 -> 1717109.3
A10: Equity | C10: =C2 -> 2023 | D10: =D2 -> 2024 | E10: =E2 -> 2025 | F10: =F2 -> 2026 | G10: =G2 -> 2027 | H10: =H2 -> 2028 | I10: =I2 -> 2029 | J10: =J2 -> 2030
B11: Share issuance/(repurchases) | F11: =Assumptions!F34 -> 0 | G11: =Assumptions!G34 -> 0 | H11: =Assumptions!H34 -> 0 | I11: =Assumptions!I34 -> 0 | J11: =Assumptions!J34 -> 0
B13: Beginning balance | F13: =E16 -> 3318917 | G13: =F16 -> 3279056.6 | H13: =G16 -> 3323403.2 | I13: =H16 -> 3490937.1 | J13: =I16 -> 3833714.4
B14: Net income | F14: =IncState!F35 -> -39860.378 | G14: =IncState!G35 -> 44346.608 | H14: =IncState!H35 -> 167533.91 | I14: =IncState!I35 -> 342777.25 | J14: =IncState!J35 -> 587019.01
B15: Share issuance / (repurchase) | F15: =F11 -> 0 | G15: =G11 -> 0 | H15: =H11 -> 0 | I15: =I11 -> 0 | J15: =J11 -> 0
B16: Ending balance | E16: =BalSheet!E39 -> 3318917 | F16: =SUM(F13:F15) -> 3279056.6 | G16: =SUM(G13:G15) -> 3323403.2 | H16: =SUM(H13:H15) -> 3490937.1 | I16: =SUM(I13:I15) -> 3833714.4 | J16: =SUM(J13:J15) -> 4420733.4
A17: OWC | C17: =C10 -> 2023 | D17: =D10 -> 2024 | E17: =E10 -> 2025 | F17: =F10 -> 2026 | G17: =G10 -> 2027 | H17: =H10 -> 2028 | I17: =I10 -> 2029 | J17: =J10 -> 2030
B18: Operating Cash | E18: =BalSheet!E16 -> 59304.36 | F18: =BalSheet!F16 -> 72351.319 | G18: =BalSheet!G16 -> 88268.609 | H18: =BalSheet!H16 -> 107687.7 | I18: =BalSheet!I16 -> 131379 | J18: =BalSheet!J16 -> 160282.38
B19: =BalSheet!B18 -> Accounts receivable | E19: =BalSheet!E18 -> 1128564 | F19: =BalSheet!F18 -> 1376848.1 | G19: =BalSheet!G18 -> 1679754.7 | H19: =BalSheet!H18 -> 2049300.7 | I19: =BalSheet!I18 -> 2500146.8 | J19: =BalSheet!J18 -> 3050179.1
B20: Other current assets | E20: =BalSheet!E19 -> 661486 | F20: =BalSheet!F19 -> 807012.92 | G20: =BalSheet!G19 -> 984555.76 | H20: =BalSheet!H19 -> 1201158 | I20: =BalSheet!I19 -> 1465412.8 | J20: =BalSheet!J19 -> 1787803.6
B21: Accounts payables | E21: =BalSheet!E31 -> 641479 | F21: =BalSheet!F31 -> 725764.09 | G21: =BalSheet!G31 -> 885432.19 | H21: =BalSheet!H31 -> 1080227.3 | I21: =BalSheet!I31 -> 1317877.3 | J21: =BalSheet!J31 -> 1607810.3
B22: Other current liabilities | E22: =BalSheet!E32 -> 2819571 | F22: =BalSheet!F32 -> 3439876.6 | G22: =BalSheet!G32 -> 4196649.5 | H22: =BalSheet!H32 -> 5119912.4 | I22: =BalSheet!I32 -> 6246293.1 | J22: =BalSheet!J32 -> 7620477.6
A23: * | B23: OWC | E23: =SUM(E18:E20)-SUM(E21:E22) -> -1611695.6 | F23: =SUM(F18:F20)-SUM(F21:F22) -> -1909428.4 | G23: =SUM(G18:G20)-SUM(G21:G22) -> -2329502.6 | H23: =SUM(H18:H20)-SUM(H21:H22) -> -2841993.2 | I23: =SUM(I18:I20)-SUM(I21:I22) -> -3467231.7 | J23: =SUM(J18:J20)-SUM(J21:J22) -> -4230022.7
B24: Change in OWC | F24: =E23-F23 -> 297732.75 | G24: =F23-G23 -> 420074.25 | H24: =G23-H23 -> 512490.58 | I24: =H23-I23 -> 625238.51 | J24: =I23-J23 -> 762790.98

Sheet Debt
A1: =CoName -> Crowdstrike Holdings | C1: Hist. | D1: Hist. | E1: Hist. | F1: Proj. | G1: Proj. | H1: Proj. | I1: Proj. | J1: Proj.
A2: Assumptions | C2: =D2-1 -> 2023 | D2: =E2-1 -> 2024 | E2: =MAIN!C5 -> 2025 | F2: 2026 | G2: 2027 | H2: 2028 | I2: 2029 | J2: 2030
B4: Interest rate on revolver | F4: =Assumptions!F23 -> 0.035365055 | G4: =Assumptions!G23 -> 0.035365055 | H4: =Assumptions!H23 -> 0.035365055 | I4: =Assumptions!I23 -> 0.035365055 | J4: =Assumptions!J23 -> 0.035365055
B5: Interest rate on long-term debt | F5: =Assumptions!F24 -> 0.035365055 | G5: =Assumptions!G24 -> 0.035365055 | H5: =Assumptions!H24 -> 0.035365055 | I5: =Assumptions!I24 -> 0.035365055 | J5: =Assumptions!J24 -> 0.035365055
B6: Interest rate on cash | F6: =Assumptions!F25 -> 0.045376038 | G6: =Assumptions!G25 -> 0.045376038 | H6: =Assumptions!H25 -> 0.045376038 | I6: =Assumptions!I25 -> 0.045376038 | J6: =Assumptions!J25 -> 0.045376038
B8: Issuance of long-term debt | F8: =Assumptions!F27 -> 0 | G8: =Assumptions!G27 -> 0 | H8: =Assumptions!H27 -> 0 | I8: =Assumptions!I27 -> 0 | J8: =Assumptions!J27 -> 0
B9: Repayment of long-term debt | F9: =Assumptions!F28 -> 0 | G9: =Assumptions!G28 -> 0 | H9: =Assumptions!H28 -> 0 | I9: =Assumptions!I28 -> 0 | J9: =Assumptions!J28 -> 0
A11: Revolver | C11: =C2 -> 2023 | D11: =D2 -> 2024 | E11: =E2 -> 2025 | F11: =F2 -> 2026 | G11: =G2 -> 2027 | H11: =H2 -> 2028 | I11: =I2 -> 2029 | J11: =J2 -> 2030
B12: Balance | F12: NO REVOLVER | G12: NO REVOLVER | H12: NO REVOLVER | I12: NO REVOLVER | J12: NO REVOLVER
B13: Interest rate
B14: Interest expense
A16: Long term debt | C16: =C11 -> 2023 | D16: =D11 -> 2024 | E16: =E11 -> 2025 | F16: =F11 -> 2026 | G16: =G11 -> 2027 | H16: =H11 -> 2028 | I16: =I11 -> 2029 | J16: =J11 -> 2030
B17: Beginning balance | F17: =E20 -> 743983 | G17: =F20 -> 743983 | H17: =G20 -> 743983 | I17: =H20 -> 743983 | J17: =I20 -> 743983
B18: Issuance | F18: =F8 -> 0 | G18: =G8 -> 0 | H18: =H8 -> 0 | I18: =I8 -> 0 | J18: =J8 -> 0
B19: Repayment | F19: =F9 -> 0 | G19: =G9 -> 0 | H19: =H9 -> 0 | I19: =I9 -> 0 | J19: =J9 -> 0
B20: Ending balance | E20: =BalSheet!E35 -> 743983 | F20: =SUM(F17:F19) -> 743983 | G20: =SUM(G17:G19) -> 743983 | H20: =SUM(H17:H19) -> 743983 | I20: =SUM(I17:I19) -> 743983 | J20: =SUM(J17:J19) -> 743983
B21: Interest rate | F21: =F5 -> 0.035365055 | G21: =G5 -> 0.035365055 | H21: =H5 -> 0.035365055 | I21: =I5 -> 0.035365055 | J21: =J5 -> 0.035365055
B22: Interest expense | F22: =F20*F21 -> 26311 | G22: =G20*G21 -> 26311 | H22: =H20*H21 -> 26311 | I22: =I20*I21 -> 26311 | J22: =J20*J21 -> 26311
A24: Debt summary | C24: =C16 -> 2023 | D24: =D16 -> 2024 | E24: =E16 -> 2025 | F24: =F16 -> 2026 | G24: =G16 -> 2027 | H24: =H16 -> 2028 | I24: =I16 -> 2029 | J24: =J16 -> 2030
B25: Revolver | F25: =F12 -> NO REVOLVER | G25: =G12 -> NO REVOLVER | H25: =H12 -> NO REVOLVER | I25: =I12 -> NO REVOLVER | J25: =J12 -> NO REVOLVER
B26: Total long term debt | F26: =F20 -> 743983 | G26: =G20 -> 743983 | H26: =H20 -> 743983 | I26: =I20 -> 743983 | J26: =J20 -> 743983
B27: Total debt | F27: =SUM(F25:F26) -> 743983 | G27: =SUM(G25:G26) -> 743983 | H27: =SUM(H25:H26) -> 743983 | I27: =SUM(I25:I26) -> 743983 | J27: =SUM(J25:J26) -> 743983
B28: Total interest expense | F28: =F22 -> 26311 | G28: =G22 -> 26311 | H28: =H22 -> 26311 | I28: =I22 -> 26311 | J28: =J22 -> 26311
A30: Interest income | C30: =C11 -> 2023 | D30: =D11 -> 2024 | E30: =E11 -> 2025 | F30: =F11 -> 2026 | G30: =G11 -> 2027 | H30: =H11 -> 2028 | I30: =I11 -> 2029 | J30: =J11 -> 2030
B31: Excess Cash | F31: =SUM(BalSheet!F16:F17) -> 5009103 | G31: =SUM(BalSheet!G16:G17) -> 5907959.6 | H31: =SUM(BalSheet!H16:H17) -> 7038715.2 | I31: =SUM(BalSheet!I16:I17) -> 8483354.7 | J31: =SUM(BalSheet!J16:J17) -> 10345699
B32: Interest rate | F32: =F6 -> 0.045376038 | G32: =G6 -> 0.045376038 | H32: =H6 -> 0.045376038 | I32: =I6 -> 0.045376038 | J32: =J6 -> 0.045376038
B33: Interest income | F33: =F31*F32 -> 227293.25 | G33: =G31*G32 -> 268079.8 | H33: =H31*H32 -> 319389.01 | I33: =I31*I32 -> 384941.03 | J33: =J31*J32 -> 469446.86

Sheet IncState
A1: =CoName -> Crowdstrike Holdings | C1: Hist. | D1: Hist. | E1: Hist. | F1: Proj. | G1: Proj. | H1: Proj. | I1: Proj. | J1: Proj.
A2: Assumptions | C2: =D2-1 -> 2023 | D2: =E2-1 -> 2024 | E2: =MAIN!C5 -> 2025 | F2: 2026 | G2: 2027 | H2: 2028 | I2: 2029 | J2: 2030
B4: Revenue growth | F4: =Assumptions!F10 -> 0.22 | G4: =Assumptions!G10 -> 0.22 | H4: =Assumptions!H10 -> 0.22 | I4: =Assumptions!I10 -> 0.22 | J4: =Assumptions!J10 -> 0.22
B5: Cost of goods sold as % of sales | F5: =Assumptions!F11 -> 0.25077777 | G5: =Assumptions!G11 -> 0.25077777 | H5: =Assumptions!H11 -> 0.25077777 | I5: =Assumptions!I11 -> 0.25077777 | J5: =Assumptions!J11 -> 0.25077777
B6: R&D % of sales | F6: =Assumptions!F12 -> 0.27238326 | G6: =Assumptions!G12 -> 0.27238326 | H6: =Assumptions!H12 -> 0.27238326 | I6: =Assumptions!I12 -> 0.27238326 | J6: =Assumptions!J12 -> 0.27238326
B7: SG&A % of sales | F7: =Assumptions!F13 -> 0.48729963 | G7: =Assumptions!G13 -> 0.46729963 | H7: =Assumptions!H13 -> 0.44729963 | I7: =Assumptions!I13 -> 0.42729963 | J7: =Assumptions!J13 -> 0.40729963
B8: Amortization amount | F8: =Assumptions!F14 -> 263177 | G8: =Assumptions!G14 -> 263177 | H8: =Assumptions!H14 -> 263177 | I8: =Assumptions!I14 -> 263177 | J8: =Assumptions!J14 -> 263177
B9: Non recurring items, amount | F9: =Assumptions!F15 -> 0 | G9: =Assumptions!G15 -> 0 | H9: =Assumptions!H15 -> 0 | I9: =Assumptions!I15 -> 0 | J9: =Assumptions!J15 -> 0
B10: Other income (expense), amt | F10: =Assumptions!F16 -> 0 | G10: =Assumptions!G16 -> 0 | H10: =Assumptions!H16 -> 0 | I10: =Assumptions!I16 -> 0 | J10: =Assumptions!J16 -> 0
B11: Effective tax rate | F11: =Assumptions!F17 -> 0.21 | G11: =Assumptions!G17 -> 0.21 | H11: =Assumptions!H17 -> 0.21 | I11: =Assumptions!I17 -> 0.21 | J11: =Assumptions!J17 -> 0.21
B12: Basic WASO | F12: =Assumptions!F18 -> 244750 | G12: =Assumptions!G18 -> 244750 | H12: =Assumptions!H18 -> 244750 | I12: =Assumptions!I18 -> 244750 | J12: =Assumptions!J18 -> 244750
B13: Diluted WASO | F13: =Assumptions!F19 -> 244750 | G13: =Assumptions!G19 -> 244750 | H13: =Assumptions!H19 -> 244750 | I13: =Assumptions!I19 -> 244750 | J13: =Assumptions!J19 -> 244750
A15: Income statement | C15: =C2 -> 2023 | D15: =D2 -> 2024 | E15: =E2 -> 2025 | F15: =F2 -> 2026 | G15: =G2 -> 2027 | H15: =H2 -> 2028 | I15: =I2 -> 2029 | J15: =J2 -> 2030
B16: Revenue | C16: 2241236 | D16: 3055555 | E16: 3953624 | F16: =E16*(1+F4) -> 4823421.3 | G16: =F16*(1+G4) -> 5884574 | H16: =G16*(1+H4) -> 7179180.2 | I16: =H16*(1+I4) -> 8758599.9 | J16: =I16*(1+J4) -> 10685492
B17: COGS | C17: 601231 | D17: 755723 | E17: 991481 | F17: =F16*F5 -> 1209606.8 | G17: =G16*G5 -> 1475720.3 | H17: =H16*H5 -> 1800378.8 | I17: =I16*I5 -> 2196462.1 | J17: =J16*J5 -> 2679683.8
B18: R&D | C18: 608364 | D18: 768497 | E18: 1076901 | F18: =F16*F6 -> 1313819.2 | G18: =G16*G6 -> 1602859.4 | H18: =H16*H6 -> 1955488.5 | I18: =I16*I6 -> 2385696 | J18: =J16*J6 -> 2910549.1
B19: SG&A | C19: =904409+317344 -> 1221753 | D19: =1140566+392764 -> 1533330 | E19: =1523356+482316 -> 2005672 | F19: =F16*F7 -> 2350451.4 | G19: =G16*G7 -> 2749859.2 | H19: =H16*H7 -> 3211244.7 | I19: =I16*I7 -> 3742546.5 | J19: =J16*J7 -> 4352196.9
A20: * | B20: EBIT | C20: =C16-SUM(C17:C19) -> -190112 | D20: =D16-SUM(D17:D19) -> -1995 | E20: =E16-SUM(E17:E19) -> -120430 | F20: =F16-SUM(F17:F19) -> -50456.174 | G20: =G16-SUM(G17:G19) -> 56134.946 | H20: =H16-SUM(H17:H19) -> 212068.24 | I20: =I16-SUM(I17:I19) -> 433895.25 | J20: =J16-SUM(J17:J19) -> 743062.04
B22: Depreciation | C22: 77245 | D22: 126838 | E22: 187952 | F22: =Calcs!F8 -> 233793.88 | G22: =Calcs!G8 -> 255481.9 | H22: =Calcs!H8 -> 290306.16 | I22: =Calcs!I8 -> 338804.39 | J22: =Calcs!J8 -> 402294.09
B23: Amortization | C23: =16565+170808 -> 187373 | D23: =18416+238901 -> 257317 | E23: =26004+318837 -> 344841 | F23: =F8 -> 263177 | G23: =G8 -> 263177 | H23: =H8 -> 263177 | I23: =I8 -> 263177 | J23: =J8 -> 263177
A24: * | B24: EBITDA | C24: =SUM(C20,C22:C23) -> 74506 | D24: =SUM(D20,D22:D23) -> 382160 | E24: =SUM(E20,E22:E23) -> 412363 | F24: =SUM(F20,F22:F23) -> 446514.71 | G24: =SUM(G20,G22:G23) -> 574793.85 | H24: =SUM(H20,H22:H23) -> 765551.4 | I24: =SUM(I20,I22:I23) -> 1035876.6 | J24: =SUM(J20,J22:J23) -> 1408533.1
B26: Non-recurring items | F26: =F9 -> 0 | G26: =G9 -> 0 | H26: =H9 -> 0 | I26: =I9 -> 0 | J26: =J9 -> 0
B27: Other income (expense) | C27: 3053 | D27: 1638 | E27: 5101 | F27: =F10 -> 0 | G27: =G10 -> 0 | H27: =H10 -> 0 | I27: =I10 -> 0 | J27: =J10 -> 0
B29: Interest income | C29: 52495 | D29: 148930 | E29: 196174 | F29: =IF(circ=1,Debt!F33,0) -> 0 | G29: =IF(circ=1,Debt!G33,0) -> 0 | H29: =IF(circ=1,Debt!H33,0) -> 0 | I29: =IF(circ=1,Debt!I33,0) -> 0 | J29: =IF(circ=1,Debt!J33,0) -> 0
B30: Interest expense | C30: -25319 | D30: -25756 | E30: -26311 | F30: =IF(circ=1,-Debt!F22,0) -> 0 | G30: =IF(circ=1,-Debt!G22,0) -> 0 | H30: =IF(circ=1,-Debt!H22,0) -> 0 | I30: =IF(circ=1,-Debt!I22,0) -> 0 | J30: =IF(circ=1,-Debt!J22,0) -> 0
A32: * | B32: Pretax Income | C32: =C20+SUM(C26:C30) -> -159883 | D32: =D20+SUM(D26:D30) -> 122817 | E32: =E20+SUM(E26:E30) -> 54534 | F32: =F20+SUM(F26:F30) -> -50456.174 | G32: =G20+SUM(G26:G30) -> 56134.946 | H32: =H20+SUM(H26:H30) -> 212068.24 | I32: =I20+SUM(I26:I30) -> 433895.25 | J32: =J20+SUM(J26:J30) -> 743062.04
B34: Tax expense | C34: 22402 | D34: 32232 | E34: 71130 | F34: =F32*F11 -> -10595.797 | G34: =G32*G11 -> 11788.339 | H34: =H32*H11 -> 44534.33 | I34: =I32*I11 -> 91118.002 | J34: =J32*J11 -> 156043.03
A35: * | B35: Net income | C35: =C32-C34 -> -182285 | D35: =D32-D34 -> 90585 | E35: =E32-E34 -> -16596 | F35: =F32-F34 -> -39860.378 | G35: =G32-G34 -> 44346.608 | H35: =H32-H34 -> 167533.91 | I35: =I32-I34 -> 342777.25 | J35: =J32-J34 -> 587019.01
A36: Shareholder information | C36: =C15 -> 2023 | D36: =D15 -> 2024 | E36: =E15 -> 2025 | F36: =F15 -> 2026 | G36: =G15 -> 2027 | H36: =H15 -> 2028 | I36: =I15 -> 2029 | J36: =J15 -> 2030
B37: Basic WASO | C37: 233139 | D37: 238637 | E37: 244750 | F37: =F12 -> 244750 | G37: =G12 -> 244750 | H37: =H12 -> 244750 | I37: =I12 -> 244750 | J37: =J12 -> 244750
B38: Diluted WASO | C38: 233139 | D38: 243635 | E38: 244750 | F38: =F13 -> 244750 | G38: =G13 -> 244750 | H38: =H13 -> 244750 | I38: =I13 -> 244750 | J38: =J13 -> 244750
B39: Basic earnings per share | C39: =C35/C37 -> -0.78187262 | D39: =D35/D37 -> 0.37959327 | E39: =E35/E37 -> -0.067807967 | F39: =F35/F37 -> -0.1628616 | G39: =G35/G37 -> 0.18119145 | H39: =H35/H37 -> 0.68451035 | I39: =I35/I37 -> 1.4005199 | J39: =J35/J37 -> 2.3984434
A40: * | B40: Diluted earnings per share | C40: =C35/C38 -> -0.78187262 | D40: =D35/D38 -> 0.37180619 | E40: =E35/E38 -> -0.067807967 | F40: =F35/F38 -> -0.1628616 | G40: =G35/G38 -> 0.18119145 | H40: =H35/H38 -> 0.68451035 | I40: =I35/I38 -> 1.4005199 | J40: =J35/J38 -> 2.3984434

Sheet BalSheet
A1: =CoName -> Crowdstrike Holdings | C1: Hist. | D1: Hist. | E1: Hist. | F1: Proj. | G1: Proj. | H1: Proj. | I1: Proj. | J1: Proj.
A2: Assumptions | C2: =D2-1 -> 2023 | D2: =E2-1 -> 2024 | E2: =MAIN!C5 -> 2025 | F2: 2026 | G2: 2027 | H2: 2028 | I2: 2029 | J2: 2030
B4: Operating Cash % of sales | F4: =Assumptions!F38 -> 0.015 | G4: =F4 -> 0.015 | H4: =G4 -> 0.015 | I4: =H4 -> 0.015 | J4: =I4 -> 0.015
B5: Accounts receivable % of sales | F5: =Assumptions!F39 -> 0.28545051 | G5: =Assumptions!G39 -> 0.28545051 | H5: =Assumptions!H39 -> 0.28545051 | I5: =Assumptions!I39 -> 0.28545051 | J5: =Assumptions!J39 -> 0.28545051
B6: Other current assets % of sales | F6: =Assumptions!F40 -> 0.16731131 | G6: =Assumptions!G40 -> 0.16731131 | H6: =Assumptions!H40 -> 0.16731131 | I6: =Assumptions!I40 -> 0.16731131 | J6: =Assumptions!J40 -> 0.16731131
B8: Other long-term assets % of sales | F8: =Assumptions!F43 -> 0.034767848 | G8: =Assumptions!G43 -> 0.034767848 | H8: =Assumptions!H43 -> 0.034767848 | I8: =Assumptions!I43 -> 0.034767848 | J8: =Assumptions!J43 -> 0.034767848
B9: Investment in unconsolidated entities $ balance | F9: =Assumptions!F42 -> 72544 | G9: =Assumptions!G42 -> 72544 | H9: =Assumptions!H42 -> 72544 | I9: =Assumptions!I42 -> 72544 | J9: =Assumptions!J42 -> 72544
B11: Accounts payable/Accural % of COGS | F11: =Assumptions!F47 -> 0.6 | G11: =Assumptions!G47 -> 0.6 | H11: =Assumptions!H47 -> 0.6 | I11: =Assumptions!I47 -> 0.6 | J11: =Assumptions!J47 -> 0.6
B12: Other current liabilities % of sales | F12: =Assumptions!F48 -> 0.71316114 | G12: =Assumptions!G48 -> 0.71316114 | H12: =Assumptions!H48 -> 0.71316114 | I12: =Assumptions!I48 -> 0.71316114 | J12: =Assumptions!J48 -> 0.71316114
B13: Other long-term liabilities % of sales | F13: =Assumptions!F49 -> 0.29786039 | G13: =Assumptions!G49 -> 0.29786039 | H13: =Assumptions!H49 -> 0.29786039 | I13: =Assumptions!I49 -> 0.29786039 | J13: =Assumptions!J49 -> 0.29786039
A15: Balance sheet | C15: =C2 -> 2023 | D15: =D2 -> 2024 | E15: =E2 -> 2025 | F15: =F2 -> 2026 | G15: =G2 -> 2027 | H15: =H2 -> 2028 | I15: =I2 -> 2029 | J15: =J2 -> 2030
B16: Operating Cash | C16: =1.5%*IncState!C16 -> 33618.54 | D16: =1.5%*IncState!D16 -> 45833.325 | E16: =1.5%*IncState!E16 -> 59304.36 | F16: =F4*IncState!F16 -> 72351.319 | G16: =G4*IncState!G16 -> 88268.609 | H16: =H4*IncState!H16 -> 107687.7 | I16: =I4*IncState!I16 -> 131379 | J16: =J4*IncState!J16 -> 160282.38
B17: Excess cash | C17: =2455369-C16 -> 2421750.5 | D17: =3375069-D16 -> 3329235.7 | E17: =4323295-E16 -> 4263990.6 | F17: =MAX(CashFlow!F22,0) -> 4936751.6 | G17: =MAX(CashFlow!G22,0) -> 5819691 | H17: =MAX(CashFlow!H22,0) -> 6931027.4 | I17: =MAX(CashFlow!I22,0) -> 8351975.7 | J17: =MAX(CashFlow!J22,0) -> 10185417
B18: Accounts receivable | C18: 626181 | D18: 853105 | E18: 1128564 | F18: =F5*IncState!F16 -> 1376848.1 | G18: =G5*IncState!G16 -> 1679754.7 | H18: =H5*IncState!H16 -> 2049300.7 | I18: =I5*IncState!I16 -> 2500146.8 | J18: =J5*IncState!J16 -> 3050179.1
B19: Other current assets | C19: =186855+121862+250000 -> 558717 | D19: =246370+183172+99591 -> 529133 | E19: =347042+314444 -> 661486 | F19: =F6*IncState!F16 -> 807012.92 | G19: =G6*IncState!G16 -> 984555.76 | H19: =H6*IncState!H16 -> 1201158 | I19: =I6*IncState!I16 -> 1465412.8 | J19: =J6*IncState!J16 -> 1787803.6
B20: Total current assets | C20: =SUM(C16:C19) -> 3640267 | D20: =SUM(D16:D19) -> 4757307 | E20: =SUM(E16:E19) -> 6113345 | F20: =SUM(F16:F19) -> 7192964 | G20: =SUM(G16:G19) -> 8572270.1 | H20: =SUM(H16:H19) -> 10289174 | I20: =SUM(I16:I19) -> 12448914 | J20: =SUM(J16:J19) -> 15183682
B22: Property, plant & equipment, net | C22: =492335+39936 -> 532271 | D22: =620172+48211 -> 668383 | E22: =788640+42763 -> 831403 | F22: =Calcs!F9 -> 908528.56 | G22: =Calcs!G9 -> 1032368.4 | H22: =Calcs!H9 -> 1204834.7 | I22: =Calcs!I9 -> 1430612.8 | J22: =Calcs!J9 -> 1717109.3
B23: Intangible assets | C23: =430645+86889+260233 -> 777767 | D23: =638041+114518+335933 -> 1088492 | E23: =133114+912805+500908 -> 1546827 | F23: =E23-IncState!F23 -> 1283650 | G23: =F23-IncState!G23 -> 1020473 | H23: =G23-IncState!H23 -> 757296 | I23: =H23-IncState!I23 -> 494119 | J23: =I23-IncState!J23 -> 230942
B24: Investment in unconsolidated entities | C24: 47270 | D24: =56244 -> 56244 | E24: 72544 | F24: =E24 -> 72544 | G24: =F24 -> 72544 | H24: =G24 -> 72544 | I24: =H24 -> 72544 | J24: =I24 -> 72544
B25: Other assets | C25: =28965 -> 28965 | D25: =76094 -> 76094 | E25: =137459 -> 137459 | F25: =F8*IncState!F16 -> 167699.98 | G25: =G8*IncState!G16 -> 204593.98 | H25: =H8*IncState!H16 -> 249604.65 | I25: =I8*IncState!I16 -> 304517.67 | J25: =J8*IncState!J16 -> 371511.56
B26: Total non-current assets | C26: =SUM(C22:C25) -> 1386273 | D26: =SUM(D22:D25) -> 1889213 | E26: =SUM(E22:E25) -> 2588233 | F26: =SUM(F22:F25) -> 2432422.5 | G26: =SUM(G22:G25) -> 2329979.3 | H26: =SUM(H22:H25) -> 2284279.4 | I26: =SUM(I22:I25) -> 2301793.4 | J26: =SUM(J22:J25) -> 2392106.8
A28: * | B28: TOTAL ASSETS | C28: =SUM(C26,C20) -> 5026540 | D28: =SUM(D26,D20) -> 6646520 | E28: =SUM(E26,E20) -> 8701578 | F28: =SUM(F26,F20) -> 9625386.5 | G28: =SUM(G26,G20) -> 10902249 | H28: =SUM(H26,H20) -> 12573453 | I28: =SUM(I26,I20) -> 14750708 | J28: =SUM(J26,J20) -> 17575789
B30: Revolver/Short term debt | C30: 0 | D30: 0 | E30: 0 | F30: =MIN(CashFlow!F22,0) -> 0 | G30: =MIN(CashFlow!G22,0) -> 0 | H30: =MIN(CashFlow!H22,0) -> 0 | I30: =MIN(CashFlow!I22,0) -> 0 | J30: =MIN(CashFlow!J22,0) -> 0
B31: Accounts payable/Accurals | C31: =45372+137884+168767 -> 352023 | D31: =28180+125896+234624 -> 388700 | E31: =130887+191349+319243 -> 641479 | F31: =F11*IncState!F17 -> 725764.09 | G31: =G11*IncState!G17 -> 885432.19 | H31: =H11*IncState!H17 -> 1080227.3 | I31: =I11*IncState!I17 -> 1317877.3 | J31: =J11*IncState!J17 -> 1607810.3
B32: Other current liabilities | C32: =13046+1727484+16519 -> 1757049 | D32: =14150+2270757+23672 -> 2308579 | E32: =13811+2733005+72755 -> 2819571 | F32: =F12*IncState!F16 -> 3439876.6 | G32: =G12*IncState!G16 -> 4196649.5 | H32: =H12*IncState!H16 -> 5119912.4 | I32: =I12*IncState!I16 -> 6246293.1 | J32: =J12*IncState!J16 -> 7620477.6
B33: Total current liabilities | C33: =SUM(C30:C32) -> 2109072 | D33: =SUM(D30:D32) -> 2697279 | E33: =SUM(E30:E32) -> 3461050 | F33: =SUM(F30:F32) -> 4165640.7 | G33: =SUM(G30:G32) -> 5082081.7 | H33: =SUM(H30:H32) -> 6200139.6 | I33: =SUM(I30:I32) -> 7564170.4 | J33: =SUM(J30:J32) -> 9228287.8
B35: Long-term debt, including current maturities | C35: 741005 | D35: 742494 | E35: 743983 | F35: =Debt!F26 -> 743983 | G35: =Debt!G26 -> 743983 | H35: =Debt!H26 -> 743983 | I35: =Debt!I26 -> 743983 | J35: =Debt!J26 -> 743983
B36: Other long-term liabilities | C36: =627629+29567+31833 -> 689029 | D36: =783342+36230+50086 -> 869658 | E36: =995672+31107+150849 -> 1177628 | F36: =F13*IncState!F16 -> 1436706.2 | G36: =G13*IncState!G16 -> 1752781.5 | H36: =H13*IncState!H16 -> 2138393.4 | I36: =I13*IncState!I16 -> 2608840 | J36: =J13*IncState!J16 -> 3182784.8
B37: Total non-current liabilities | C37: =SUM(C35:C36) -> 1430034 | D37: =SUM(D35:D36) -> 1612152 | E37: =SUM(E35:E36) -> 1921611 | F37: =SUM(F35:F36) -> 2180689.2 | G37: =SUM(G35:G36) -> 2496764.5 | H37: =SUM(H35:H36) -> 2882376.4 | I37: =SUM(I35:I36) -> 3352823 | J37: =SUM(J35:J36) -> 3926767.8
B39: Equity | C39: 1487434 | D39: 2337089 | E39: 3318917 | F39: =Calcs!F16 -> 3279056.6 | G39: =Calcs!G16 -> 3323403.2 | H39: =Calcs!H16 -> 3490937.1 | I39: =Calcs!I16 -> 3833714.4 | J39: =Calcs!J16 -> 4420733.4
A40: * | B40: TOTAL LIABILITIES & EQUITY | C40: =SUM(C39,C37,C33) -> 5026540 | D40: =SUM(D39,D37,D33) -> 6646520 | E40: =SUM(E39,E37,E33) -> 8701578 | F40: =SUM(F39,F37,F33) -> 9625386.5 | G40: =SUM(G39,G37,G33) -> 10902249 | H40: =SUM(H39,H37,H33) -> 12573453 | I40: =SUM(I39,I37,I33) -> 14750708 | J40: =SUM(J39,J37,J33) -> 17575789
A42: * | B42: Balance check | C42: =C40-C28 -> 0 | D42: =D40-D28 -> 0 | E42: =E40-E28 -> 0 | F42: =F40-F28 -> 0 | G42: =G40-G28 -> 0 | H42: =H40-H28 -> 0 | I42: =I40-I28 -> 0 | J42: =J40-J28 -> 0

Sheet CashFlow
A1: =CoName -> Crowdstrike Holdings | C1: Hist. | D1: Hist. | E1: Hist. | F1: Proj. | G1: Proj. | H1: Proj. | I1: Proj. | J1: Proj.
A2: Cash flow statement | C2: =D2-1 -> 2023 | D2: =E2-1 -> 2024 | E2: =MAIN!C5 -> 2025 | F2: 2026 | G2: 2027 | H2: 2028 | I2: 2029 | J2: 2030
B3: Net Income | F3: =IncState!F35 -> -39860.378 | G3: =IncState!G35 -> 44346.608 | H3: =IncState!H35 -> 167533.91 | I3: =IncState!I35 -> 342777.25 | J3: =IncState!J35 -> 587019.01
B4: Depreciation | F4: =IncState!F22 -> 233793.88 | G4: =IncState!G22 -> 255481.9 | H4: =IncState!H22 -> 290306.16 | I4: =IncState!I22 -> 338804.39 | J4: =IncState!J22 -> 402294.09
B5: Amortization | F5: =IncState!F23 -> 263177 | G5: =IncState!G23 -> 263177 | H5: =IncState!H23 -> 263177 | I5: =IncState!I23 -> 263177 | J5: =IncState!J23 -> 263177
B6: (inc) / dec in OWC | F6: =Calcs!F24 -> 297732.75 | G6: =Calcs!G24 -> 420074.25 | H6: =Calcs!H24 -> 512490.58 | I6: =Calcs!I24 -> 625238.51 | J6: =Calcs!J24 -> 762790.98
B7: (inc) / dec in LT assets | F7: =BalSheet!E25-BalSheet!F25 -> -30240.98 | G7: =BalSheet!F25-BalSheet!G25 -> -36893.996 | H7: =BalSheet!G25-BalSheet!H25 -> -45010.675 | I7: =BalSheet!H25-BalSheet!I25 -> -54913.023 | J7: =BalSheet!I25-BalSheet!J25 -> -66993.888
B8: inc / (dec) in LT liabilities | F8: =BalSheet!F36-BalSheet!E36 -> 259078.16 | G8: =BalSheet!G36-BalSheet!F36 -> 316075.36 | H8: =BalSheet!H36-BalSheet!G36 -> 385611.93 | I8: =BalSheet!I36-BalSheet!H36 -> 470446.56 | J8: =BalSheet!J36-BalSheet!I36 -> 573944.8
B9: CFFO | F9: =SUM(F3:F8) -> 983680.44 | G9: =SUM(G3:G8) -> 1262261.1 | H9: =SUM(H3:H8) -> 1574108.9 | I9: =SUM(I3:I8) -> 1985530.7 | J9: =SUM(J3:J8) -> 2522232
B11: Capex | F11: =Calcs!F7 -> 310919.44 | G11: =Calcs!G7 -> 379321.72 | H11: =Calcs!H7 -> 462772.49 | I11: =Calcs!I7 -> 564582.44 | J11: =Calcs!J7 -> 688790.58
B12: CFFI | F12: =-F11 -> -310919.44 | G12: =-G11 -> -379321.72 | H12: =-H11 -> -462772.49 | I12: =-I11 -> -564582.44 | J12: =-J11 -> -688790.58
B14: Share Issuances | F14: =Calcs!F11 -> 0 | G14: =Calcs!G11 -> 0 | H14: =Calcs!H11 -> 0 | I14: =Calcs!I11 -> 0 | J14: =Calcs!J11 -> 0
B15: Debt Issuances | F15: =SUM(Debt!F8:F9) -> 0 | G15: =SUM(Debt!G8:G9) -> 0 | H15: =SUM(Debt!H8:H9) -> 0 | I15: =SUM(Debt!I8:I9) -> 0 | J15: =SUM(Debt!J8:J9) -> 0
B16: CFFF | F16: =SUM(F14:F15) -> 0 | G16: =SUM(G14:G15) -> 0 | H16: =SUM(H14:H15) -> 0 | I16: =SUM(I14:I15) -> 0 | J16: =SUM(J14:J15) -> 0
B18: Net changes in cash | F18: =SUM(F16,F12,F9) -> 672761 | G18: =SUM(G16,G12,G9) -> 882939.4 | H18: =SUM(H16,H12,H9) -> 1111336.4 | I18: =SUM(I16,I12,I9) -> 1420948.2 | J18: =SUM(J16,J12,J9) -> 1833441.4
B20: Beginning Cash | F20: =BalSheet!E17 -> 4263990.6 | G20: =BalSheet!F17 -> 4936751.6 | H20: =BalSheet!G17 -> 5819691 | I20: =BalSheet!H17 -> 6931027.4 | J20: =BalSheet!I17 -> 8351975.7
B21: =B18 -> Net changes in cash | F21: =F18 -> 672761 | G21: =G18 -> 882939.4 | H21: =H18 -> 1111336.4 | I21: =I18 -> 1420948.2 | J21: =J18 -> 1833441.4
B22: Ending Case | F22: =SUM(F20:F21) -> 4936751.6 | G22: =SUM(G20:G21) -> 5819691 | H22: =SUM(H20:H21) -> 6931027.4 | I22: =SUM(I20:I21) -> 8351975.7 | J22: =SUM(J20:J21) -> 10185417

Sheet Free Cash Flow
A1: =CoName -> Crowdstrike Holdings | C1: Hist. | D1: Hist. | E1: Hist. | F1: Proj. | G1: Proj. | H1: Proj. | I1: Proj. | J1: Proj.
A2: Free Cash Flows | C2: =D2-1 -> 2023 | D2: =E2-1 -> 2024 | E2: =MAIN!C5 -> 2025 | F2: 2026 | G2: 2027 | H2: 2028 | I2: 2029 | J2: 2030
A3: * | B3: Sales | F3: =IncState!F16 -> 4823421.3 | G3: =IncState!G16 -> 5884574 | H3: =IncState!H16 -> 7179180.2 | I3: =IncState!I16 -> 8758599.9 | J3: =IncState!J16 -> 10685492
B4: EBIT | F4: =IncState!F20 -> -50456.174 | G4: =IncState!G20 -> 56134.946 | H4: =IncState!H20 -> 212068.24 | I4: =IncState!I20 -> 433895.25 | J4: =IncState!J20 -> 743062.04
B5: Effective Tax Rate | F5: =Assumptions!F17 -> 0.21 | G5: =Assumptions!G17 -> 0.21 | H5: =Assumptions!H17 -> 0.21 | I5: =Assumptions!I17 -> 0.21 | J5: =Assumptions!J17 -> 0.21
A7: * | B7: NOPAT | F7: =F4*(1-F5) -> -39860.378 | G7: =G4*(1-G5) -> 44346.608 | H7: =H4*(1-H5) -> 167533.91 | I7: =I4*(1-I5) -> 342777.25 | J7: =J4*(1-J5) -> 587019.01
B8: Depreciation | F8: =CashFlow!F4 -> 233793.88 | G8: =CashFlow!G4 -> 255481.9 | H8: =CashFlow!H4 -> 290306.16 | I8: =CashFlow!I4 -> 338804.39 | J8: =CashFlow!J4 -> 402294.09
B9: Amortization | F9: =CashFlow!F5 -> 263177 | G9: =CashFlow!G5 -> 263177 | H9: =CashFlow!H5 -> 263177 | I9: =CashFlow!I5 -> 263177 | J9: =CashFlow!J5 -> 263177
B10: (inc) / dec in OWC | F10: =CashFlow!F6 -> 297732.75 | G10: =CashFlow!G6 -> 420074.25 | H10: =CashFlow!H6 -> 512490.58 | I10: =CashFlow!I6 -> 625238.51 | J10: =CashFlow!J6 -> 762790.98
B11: (inc) / dec in other long-term assets | F11: =CashFlow!F7 -> -30240.98 | G11: =CashFlow!G7 -> -36893.996 | H11: =CashFlow!H7 -> -45010.675 | I11: =CashFlow!I7 -> -54913.023 | J11: =CashFlow!J7 -> -66993.888
B12: inc / (dec) other long-term liabilities | F12: =CashFlow!F8 -> 259078.16 | G12: =CashFlow!G8 -> 316075.36 | H12: =CashFlow!H8 -> 385611.93 | I12: =CashFlow!I8 -> 470446.56 | J12: =CashFlow!J8 -> 573944.8
B13: (Capex) | F13: =CashFlow!F12 -> -310919.44 | G13: =CashFlow!G12 -> -379321.72 | H13: =CashFlow!H12 -> -462772.49 | I13: =CashFlow!I12 -> -564582.44 | J13: =CashFlow!J12 -> -688790.58
A15: * | B15: Free Cash Flow | F15: =SUM(F7:F13) -> 672761 | G15: =SUM(G7:G13) -> 882939.4 | H15: =SUM(H7:H13) -> 1111336.4 | I15: =SUM(I7:I13) -> 1420948.2 | J15: =SUM(J7:J13) -> 1833441.4

Sheet WACC
A1: =CoName -> Crowdstrike Holdings
A3: * | B3: WACC | G3: Comp | H3: Levered beta | I3: Gross debt | J3: Market cap | K3: Debt/Mcap | L3: MTR | M3: Unlevered beta
B4: Tax Rate | E4: =Assumptions!F17 -> 0.21 | L4: =E4 -> 0.21 | M4: =H4/((1+K4*(1-L4))) -> 0
B5: Risk free rate | E5: 0.04 | L5: =L4 -> 0.21 | M5: =H5/((1+K5*(1-L5))) -> 0
B6: Market risk Premium | E6: 0.05 | L6: =L5 -> 0.21 | M6: =H6/((1+K6*(1-L6))) -> 0
B7: Beta | E7: =1.09*0.66 -> 0.7194 | L7: =L6 -> 0.21 | M7: =H7/((1+K7*(1-L7))) -> 0
B8: Cost of Equity | E8: =E5+E6*E7 -> 0.07597
B9: % Equity | E9: =1-E10 -> 0.99423078 | G9: Industry beta (average) | M9: =AVERAGE(M4:M7) -> 0
B10: % Debt | E10: =MAIN!F8/MAIN!F6 -> 0.0057692177
B11: Cost of debt | E11: =Assumptions!F24 -> 0.035365055 | G11: Re-levered beta | M11: =M9*(1+E10*(1-E4)) -> 0
B12: Post tax cost of debt | E12: =E11*(1-E4) -> 0.027938394
A13: * | B13: WACC | E13: =WACC!E8*WACC!E9+WACC!E12*WACC!E10 -> 0.075692895
B14: Long Term growth rate | E14: 0.025

Sheet DCF Model
A1: =CoName -> Crowdstrike Holdings | D1: Proj. | E1: Proj. | F1: Proj. | G1: Proj. | H1: Proj.
A2: Discount Model Year count | D2: 0.5 | E2: =D2+1 -> 1.5 | F2: =E2+1 -> 2.5 | G2: =F2+1 -> 3.5 | H2: =G2+1 -> 4.5
B3: Discount Factor | D3: =1/(1+$K$3)^D2 -> 0.96417496 | E3: =1/(1+$K$3)^E2 -> 0.89632921 | F3: =1/(1+$K$3)^F2 -> 0.83325753 | G3: =1/(1+$K$3)^G2 -> 0.774624 | H3: =1/(1+$K$3)^H2 -> 0.72011631 | I3: WACC | K3: =WACC!E13 -> 0.075692895
B4: PV FCF | D4: =D3*'Free Cash Flow'!F15 -> 648659.31 | E4: =E3*'Free Cash Flow'!G15 -> 791404.37 | F4: =F3*'Free Cash Flow'!H15 -> 926029.44 | G4: =G3*'Free Cash Flow'!I15 -> 1100700.6 | H4: =H3*'Free Cash Flow'!J15 -> 1320291.1 | I4: Long Term growth rate | K4: 0.025
H5: =(H4*(1+K4))/(K3-K4) -> 26696016
A6: Value Calculation | E6: Multiples Calculation
B7: Total PV of FCFs | C7: =SUM(D4:H4) -> 4787084.8 | E7: Total PV of FCFs | G7: =C7 -> 4787084.8 | K7: LTGR | O7: Exit Mult.
B8: PV of TV | C8: =H5*H3 -> 19224237 | E8: Multiple TV | G8: =G10*H3*IncState!J24 -> 20286154 | I8: =C18 -> 112.52621 | J8: =K8-E23 -> 0.0225 | K8: 0.025 | L8: =K8+E23 -> 0.0275 | M8: =G18 -> 116.75771 | N8: =O8-L23 -> 18 | O8: 20 | P8: =O8+L23 -> 22
B9: EV | C9: =SUM(C7:C8) -> 24011322 | E9: EV | G9: =SUM(G7:G8) -> 25073239 | I9: =I10+$E$22 -> 0.085692895 | J9: 91.83091 | K9: 94.297795 | L9: 96.976638 | M9: =I9 -> 0.085692895 | N9: 105.21279 | O9: 112.96667 | P9: 120.72056
E10: Implied EBITDA multiple | G10: 20 | I10: =I11+$E$22 -> 0.080692895 | J10: 99.519747 | K10: 102.54891 | L10: 105.86281 | M10: =I10 -> 0.080692895 | N10: 106.922 | O10: 114.83864 | P10: 122.75527
I11: 0.075692895 | J11: 108.74784 | K11: 112.52621 | L11: 116.69658 | M11: =I11 -> 0.075692895 | N11: 108.67413 | O11: 116.75771 | P11: 124.84129
B12: Cash & Cash Equiv | C12: =MAIN!F7 -> 4972436 | E12: Cash & Cash Equiv | G12: =C12 -> 4972436 | I12: =I11-$E$22 -> 0.070692895 | J12: 120.00061 | K12: 124.80302 | L12: 130.16137 | M12: =I12 -> 0.070692895 | N12: 110.47047 | O12: 118.72531 | P12: 126.98016
B13: Debt & Claims | C13: =MAIN!F8 -> 744727 | E13: Debt & Claims | G13: =C13 -> 744727 | I13: =I12-$E$22 -> 0.065692895 | J13: 133.98863 | K13: 140.23494 | L13: 147.29898 | M13: =I13 -> 0.065692895 | N13: 112.31235 | O13: 120.74292 | P13: 129.17348
B14: NCI | C14: 0 | E14: NCI | G14: =C14 -> 0
B15: Equity Value | C15: =C9+C12-SUM(C13:C14) -> 28239031 | E15: Equity Value | G15: =G9+G12-SUM(G13:G14) -> 29300948 | K15: Average | O15: Average
K16: =AVERAGE(J9:L13) -> 115.033 | O16: =AVERAGE(N9:P13) -> 116.80625
B17: Diluted S/O | C17: =MAIN!F5 -> 250955.14 | E17: Diluted S/O | G17: =C17 -> 250955.14
A18: * | B18: Implied Share Price | C18: =C15/C17 -> 112.52621 | E18: Implied Share Price | G18: =G15/G17 -> 116.75771
A20: Sensitivity analysis
C22: Discount rate variance | E22: 0.005 | J22: Discount rate variance | L22: 0.005
C23: Implied growth rate variance | E23: 0.0025 | J23: TV multiple variance | L23: 2
