Workbook
Name Ccy: MAIN!$C$6
Name circ: MAIN!$C$9
Name CoName: MAIN!$C$4
Name g: #REF!
Name IQ_CH: 110000
Name IQ_CQ: 5000
Name IQ_CY: 10000
Name IQ_DAILY: 500000
Name IQ_FH: 100000
Name IQ_FQ: 500
Name IQ_FY: 1000
Name IQ_LTM: 2000
Name IQ_MONTH: 15000
Name IQ_NTM: 6000
Name IQ_WEEK: 50000
Name IQ_YTD: 3000
Name OpCase: [1]DCF!$E$98
Name ScenarioREV: Assumptions!$D$4
Name TTS: #REF!
Name Units: MAIN!$C$7

Sheet MAIN
A1: =CoName -> Netflix Inc.
A2: Model Details
B4: Company name | C4: Netflix Inc. | E4: Current Stock Price | F4: 1104.5 | H4: Scenario | I4: Terminal Mult | J4: Perpetuity
B5: Latest BS date | E5: S/O | F5: 424.455 | G5: Q325 | H5: Implied Price | I5: ='DCF Model'!P16 -> 918.20099 | J5: ='DCF Model'!K16 -> 944.18117
B6: Currency | C6: USD | E6: Mkt Cap | F6: =F5*F4 -> 468810.55 | H6: Difference | I6: =I5/$F$4-1 -> -0.16867271 | J6: =J5/$F$4-1 -> -0.14515059
B7: Units | C7: m | E7: Cash | F7: =9287.287+37.105 -> 9324.392 | G7: Q325
B8: Analyst name | C8: Alan Chen | E8: Debt | F8: =14463.02 -> 14463.02 | G8: Q325
B9: Circular switch | C9: 0 | E9: EV | F9: =F6-F7+F8 -> 473949.18

Sheet Assumptions
A1: =CoName -> Netflix Inc. | C1: Hist. | D1: Hist. | E1: Hist. | F1: Proj. | G1: Proj. | H1: Proj. | I1: Proj. | J1: Proj.
A2: * | B2: Income Statement | C2: 44926 | D2: 45291 | E2: 45657 | F2: 46022 | G2: 46387 | H2: 46752 | I2: 47118 | J2: 47483
B4: Operating Case | D4: 1
D5: Variance
B6: Street Case | D6: 0 | F6: =Revenue!O12 -> 0.1466403 | G6: =Revenue!P12 -> 0.13 | H6: =Revenue!Q12 -> 0.13 | I6: =Revenue!R12 -> 0.13 | J6: =Revenue!S12 -> 0.13
B7: Optimistic Case | D7: 0.025 | F7: =F6+$D$7 -> 0.1716403 | G7: =G6+$D$7 -> 0.155 | H7: =H6+$D$7 -> 0.155 | I7: =I6+$D$7 -> 0.155 | J7: =J6+$D$7 -> 0.155
B8: Pessimistic Case | D8: -0.025 | F8: =F6+$D$8 -> 0.1216403 | G8: =G6+$D$8 -> 0.105 | H8: =H6+$D$8 -> 0.105 | I8: =I6+$D$8 -> 0.105 | J8: =J6+$D$8 -> 0.105
B10: Revenue Growth | C10: =Revenue!D12 -> 0.065667847 | D10: =Revenue!E12 -> 0.070034559 | E10: =Revenue!J12 -> 0.15955311 | F10: =CHOOSE(ScenarioREV,F6,F7,F8) -> 0.1466403 | G10: =CHOOSE(ScenarioREV,G6,G7,G8) -> 0.13 | H10: =CHOOSE(ScenarioREV,H6,H7,H8) -> 0.13 | I10: =CHOOSE(ScenarioREV,I6,I7,I8) -> 0.13 | J10: =CHOOSE(ScenarioREV,J6,J7,J8) -> 0.13
B11: COGS % of sales | C11: =IncState!C14/IncState!C13 -> 0.60629295 | D11: =IncState!D14/IncState!D13 -> 0.5846216 | E11: =IncState!E14/IncState!E13 -> 0.53943443 | F11: =E11 -> 0.53943443 | G11: =F11 -> 0.53943443 | H11: =G11 -> 0.53943443 | I11: =H11 -> 0.53943443 | J11: =I11 -> 0.53943443
B12: SG&A % of sales | C12: =IncState!C15/IncState!C13 -> 0.21554058 | D12: =IncState!D15/IncState!D13 -> 0.20917071 | E12: =IncState!E15/IncState!E13 -> 0.19345387 | F12: =E12 -> 0.19345387 | G12: =F12 -> 0.19345387 | H12: =G12 -> 0.19345387 | I12: =H12 -> 0.19345387 | J12: =I12 -> 0.19345387
B13: Amortization $ Amt | C13: =IncState!C19 -> 14026.132 | D13: =IncState!D19 -> 14197.437 | E13: =IncState!E19 -> 15301.517 | F13: =E13 -> 15301.517 | G13: =F13 -> 15301.517 | H13: =G13 -> 15301.517 | I13: =H13 -> 15301.517 | J13: =I13 -> 15301.517
B14: Effective tax rate | C14: =IncState!C27/IncState!C25 -> 0.14665946 | D14: =IncState!D27/IncState!D25 -> 0.1285033 | E14: =IncState!E27/IncState!E25 -> 0.12583475 | F14: =E14 -> 0.12583475 | G14: =F14 -> 0.12583475 | H14: =G14 -> 0.12583475 | I14: =H14 -> 0.12583475 | J14: =I14 -> 0.12583475
B15: Basic WASO | C15: =IncState!C31 -> 444.698 | D15: =IncState!D31 -> 441.571 | E15: =IncState!E31 -> 429.519 | F15: =E15 -> 429.519 | G15: =F15 -> 429.519 | H15: =G15 -> 429.519 | I15: =H15 -> 429.519 | J15: =I15 -> 429.519
B16: Diluted WASO | C16: =IncState!C32 -> 451.29 | D16: =IncState!D32 -> 449.498 | E16: =IncState!E32 -> 439.261 | F16: =E16 -> 439.261 | G16: =F16 -> 439.261 | H16: =G16 -> 439.261 | I16: =H16 -> 439.261 | J16: =I16 -> 439.261
A18: * | B18: Debt | C18: 44926 | D18: 45291 | E18: 45657 | F18: 46022 | G18: 46387 | H18: 46752 | I18: 47118 | J18: 47483
B20: Interest rate on Revolver | E20: 0.05 | F20: =E20 -> 0.05 | G20: =F20 -> 0.05 | H20: =G20 -> 0.05 | I20: =H20 -> 0.05 | J20: =I20 -> 0.05
B21: Interest rate on long-term debt | E21: 0.044 | F21: =E21 -> 0.044 | G21: =F21 -> 0.044 | H21: =G21 -> 0.044 | I21: =H21 -> 0.044 | J21: =I21 -> 0.044
B22: Interest rate on cash | E22: =IncState!E22/BalSheet!E14 -> 0.034947185 | F22: =E22 -> 0.034947185 | G22: =F22 -> 0.034947185 | H22: =G22 -> 0.034947185 | I22: =H22 -> 0.034947185 | J22: =I22 -> 0.034947185
B24: Issuance of long-term debt | E24: 0 | F24: 0 | G24: 0 | H24: 0 | I24: 0 | J24: 0
B25: Repayment of long-term debt | E25: 0 | F25: 0 | G25: 0 | H25: 0 | I25: 0 | J25: 0
A27: * | B27: Calcs | C27: 44926 | D27: 45291 | E27: 45657 | F27: 46022 | G27: 46387 | H27: 46752 | I27: 47118 | J27: 47483
B29: CapEx % of Sales | E29: =439.538/IncState!E13 -> 0.011269926 | F29: =E29 -> 0.011269926 | G29: =F29 -> 0.011269926 | H29: =G29 -> 0.011269926 | I29: =H29 -> 0.011269926 | J29: =I29 -> 0.011269926
B30: Depreciation % of beginning PP&E | D30: =IncState!D18/BalSheet!C18 -> 0.25527997 | E30: =IncState!E18/BalSheet!D18 -> 0.22053393 | F30: =E30 -> 0.22053393 | G30: =F30 -> 0.22053393 | H30: =G30 -> 0.22053393 | I30: =H30 -> 0.22053393 | J30: =I30 -> 0.22053393
B31: Share issuance / (repurchases) | F31: 0 | G31: 0 | H31: 0 | I31: 0 | J31: 0
A33: * | B33: Balance Sheet - Assets | C33: 44926 | D33: 45291 | E33: 45657 | F33: 46022 | G33: 46387 | H33: 46752 | I33: 47118 | J33: 47483
B35: Operating Cash % of sales | C35: =BalSheet!C13/IncState!C13 -> 0.05 | D35: =BalSheet!D13/IncState!D13 -> 0.05 | E35: =BalSheet!E13/IncState!E13 -> 0.05 | F35: =E35 -> 0.05 | G35: =F35 -> 0.05 | H35: =G35 -> 0.05 | I35: =H35 -> 0.05 | J35: =I35 -> 0.05
B36: Other current assets % of sales | C36: =BalSheet!C15/IncState!C13 -> 0.10146972 | D36: =BalSheet!D15/IncState!D13 -> 0.082442918 | E36: =BalSheet!E15/IncState!E13 -> 0.090168023 | F36: =E36 -> 0.090168023 | G36: =F36 -> 0.090168023 | H36: =G36 -> 0.090168023 | I36: =H36 -> 0.090168023 | J36: =I36 -> 0.090168023
B37: Other long-term assets % of sales | C37: =BalSheet!C20/IncState!C13 -> 0.16426489 | D37: =BalSheet!D20/IncState!D13 -> 0.16796575 | E37: =BalSheet!E20/IncState!E13 -> 0.16624657 | F37: =E37 -> 0.16624657 | G37: =F37 -> 0.16624657 | H37: =G37 -> 0.16624657 | I37: =H37 -> 0.16624657 | J37: =I37 -> 0.16624657
A39: * | B39: Balance Sheet - Liabilities | C39: 44926 | D39: 45291 | E39: 45657 | F39: 46022 | G39: 46387 | H39: 46752 | I39: 47118 | J39: 47483
B41: Accounts payable % of COGS | C41: =BalSheet!C26/IncState!C14 -> 0.11405105 | D41: =BalSheet!D26/IncState!D14 -> 0.12941032 | E41: =BalSheet!E26/IncState!E14 -> 0.14527928 | F41: =E41 -> 0.14527928 | G41: =F41 -> 0.14527928 | H41: =G41 -> 0.14527928 | I41: =H41 -> 0.14527928 | J41: =I41 -> 0.14527928
B42: Other current liabilities % of sales | C42: =BalSheet!C27/IncState!C13 -> 0.1817084 | D42: =BalSheet!D27/IncState!D13 -> 0.17523313 | E42: =BalSheet!E27/IncState!E13 -> 0.15164994 | F42: =E42 -> 0.15164994 | G42: =F42 -> 0.15164994 | H42: =G42 -> 0.15164994 | I42: =H42 -> 0.15164994 | J42: =I42 -> 0.15164994
B43: Other long-term liabilities % of sales | C43: =BalSheet!C31/IncState!C13 -> 0.17501884 | D43: =BalSheet!D31/IncState!D13 -> 0.15240523 | E43: =BalSheet!E31/IncState!E13 -> 0.11110125 | F43: =E43 -> 0.11110125 | G43: =F43 -> 0.11110125 | H43: =G43 -> 0.11110125 | I43: =H43 -> 0.11110125 | J43: =I43 -> 0.11110125

Sheet Revenue
A1: =CoName -> Netflix Inc.
A2: Revenues | C2: 2021 | D2: 2022 | E2: 2023 | F2: Q124 | G2: Q224 | H2: Q324 | I2: Q424 | J2: 2024 | K2: Q125 | L2: Q225 | M2: Q325 | N2: Q425 | O2: 2025 | P2: =O2+1 -> 2026 | Q2: =P2+1 -> 2027 | R2: =Q2+1 -> 2028 | S2: =R2+1 -> 2029
B3: United States & Canada | C3: =12972.1+1.279+75.215 -> 13048.594 | D3: =14084.643+-0.919+74.296 -> 14158.02 | E3: =14873.783+5.832+80.128 -> 14959.743 | F3: 4224.315 | G3: 4295.56 | H3: 4322.476 | I3: =J3-SUM(F3:H3) -> 4616.14 | J3: =17359.369+9.497+89.625 -> 17458.491 | K3: 4617.098 | L3: 4929.003 | M3: 5071.781 | N3: =I3*(1+N4) -> 5170.0768 | O3: =SUM(K3:N3) -> 19787.959 | P3: =O3*(1+P4) -> 22360.393 | Q3: =P3*(1+Q4) -> 25267.245 | R3: =Q3*(1+R4) -> 28551.986 | S3: =R3*(1+S4) -> 32263.745
B4: y/y | D4: =D3/C3-1 -> 0.085022647 | E4: =E3/D3-1 -> 0.056626774 | J4: =J3/E3-1 -> 0.16703148 | K4: =K3/F3-1 -> 0.092981466 | L4: =L3/G3-1 -> 0.14746459 | M4: =M3/H3-1 -> 0.17335088 | N4: 0.12 | O4: =O3/J3-1 -> 0.13342893 | P4: 0.13 | Q4: =P4 -> 0.13 | R4: =Q4 -> 0.13 | S4: =R4 -> 0.13
B5: Europe, Middle East, Africa | C5: =9699.819+7.338+74.036 -> 9781.193 | D5: =9745.015+2.693+76.729 -> 9824.437 | E5: =10556.487+12.084+88.813 -> 10657.384 | F5: 2958.193 | G5: 3007.772 | H5: 3133.466 | I5: =J5-SUM(F5:H5) -> 3401.057 | J5: =12387.035+12.32+101.133 -> 12500.488 | K5: 3404.676 | L5: 3538.175 | M5: 3699.052 | N5: =I5*(1+N6) -> 3911.2155 | O5: =SUM(K5:N5) -> 14553.119 | P5: =O5*(1+P6) -> 16445.024 | Q5: =P5*(1+Q6) -> 18582.877 | R5: =Q5*(1+R6) -> 20998.651 | S5: =R5*(1+S6) -> 23728.476
B6: y/y | D6: =D5/C5-1 -> 0.0044211376 | E6: =E5/D5-1 -> 0.084783179 | J6: =J5/E5-1 -> 0.1729415 | K6: =K5/F5-1 -> 0.15093099 | L6: =L5/G5-1 -> 0.17634415 | M6: =M5/H5-1 -> 0.18049853 | N6: 0.15 | O6: =O5/J5-1 -> 0.16420403 | P6: 0.13 | Q6: =P6 -> 0.13 | R6: =Q6 -> 0.13 | S6: =R6 -> 0.13
B7: LATAM | C7: =3576.976+2.424+39.961 -> 3619.361 | D7: =4069.973+1.738+41.699 -> 4113.41 | E7: =4446.461+4.298+45.997 -> 4496.756 | F7: 1165.008 | G7: 1204.145 | H7: 1240.892 | I7: =J7-SUM(F7:H7) -> 1290.428 | J7: =4839.816+7.33+53.327 -> 4900.473 | K7: 1261.934 | L7: 1306.735 | M7: 1370.913 | N7: =I7*(1+N8) -> 1425.6394 | O7: =SUM(K7:N7) -> 5365.2214 | P7: =O7*(1+P8) -> 6062.7002 | Q7: =P7*(1+Q8) -> 6850.8512 | R7: =Q7*(1+R8) -> 7741.4619 | S7: =R7*(1+S8) -> 8747.8519
B8: y/y | D8: =D7/C7-1 -> 0.13650172 | E8: =E7/D7-1 -> 0.093194211 | J8: =J7/E7-1 -> 0.08977961 | K8: =K7/F7-1 -> 0.083197712 | L8: =L7/G7-1 -> 0.085197381 | M8: =M7/H7-1 -> 0.10478027 | N8: =M8 -> 0.10478027 | O8: =O7/J7-1 -> 0.094837457 | P8: 0.13 | Q8: =P8 -> 0.13 | R8: =Q8 -> 0.13 | S8: =R8 -> 0.13
B9: Asia-Pacific | C9: =3266.601+7.14+32.632 -> 3306.373 | D9: =3570.221+5.391+38.023 -> 3613.635 | E9: =3763.727+7.315+45.338 -> 3816.38 | F9: 1022.924 | G9: 1051.833 | H9: 1127.869 | I9: =J9-SUM(F9:H9) -> 1281.864 | J9: =4414.746+12.203+57.541 -> 4484.49 | K9: 1259.093 | L9: 1305.253 | M9: 1368.561 | N9: =I9*(1+N10) -> 1474.1436 | O9: =SUM(K9:N9) -> 5407.0506 | P9: =O9*(1+P10) -> 6109.9672 | Q9: =P9*(1+Q10) -> 6904.2629 | R9: =Q9*(1+R10) -> 7801.8171 | S9: =R9*(1+S10) -> 8816.0533
B10: y/y | D10: =D9/C9-1 -> 0.092930229 | E10: =E9/D9-1 -> 0.056105556 | J10: =J9/E9-1 -> 0.1750638 | K10: =K9/F9-1 -> 0.23087639 | L10: =L9/G9-1 -> 0.24093178 | M10: =M9/H9-1 -> 0.21340422 | N10: 0.15 | O10: =O9/J9-1 -> 0.20572252 | P10: 0.13 | Q10: =P10 -> 0.13 | R10: =Q10 -> 0.13 | S10: =R10 -> 0.13
A11: * | B11: TOTAL REVENUES | C11: =SUM(C9,C7,C5,C3) -> 29755.521 | D11: =SUM(D9,D7,D5,D3) -> 31709.502 | E11: =SUM(E9,E7,E5,E3) -> 33930.263 | F11: =SUM(F9,F7,F5,F3) -> 9370.44 | G11: =SUM(G9,G7,G5,G3) -> 9559.31 | H11: =SUM(H9,H7,H5,H3) -> 9824.703 | I11: =SUM(I9,I7,I5,I3) -> 10589.489 | J11: =SUM(J9,J7,J5,J3) -> 39343.942 | ... S11: =SUM(S9,S7,S5,S3) -> 73556.126
B12: y/y | D12: =D11/C11-1 -> 0.065667847 | E12: =E11/D11-1 -> 0.070034559 | J12: =J11/E11-1 -> 0.15955311 | K12: =K11/F11-1 -> 0.12511269 | L12: =L11/G11-1 -> 0.15899223 | M12: =M11/H11-1 -> 0.17156793 | N12: =N11/I11-1 -> 0.13141204 | O12: =O11/J11-1 -> 0.1466403 | P12: =P11/O11-1 -> 0.13 | Q12: =Q11/P11-1 -> 0.13 | R12: =R11/Q11-1 -> 0.13 | S12: =S11/R11-1 -> 0.13

Sheet Calcs
A1: =CoName -> Netflix Inc. | C1: Hist. | D1: Hist. | E1: Hist. | F1: Proj. | G1: Proj. | H1: Proj. | I1: Proj. | J1: Proj.
A2: Net PP&E | C2: 2022 | D2: =C2+1 -> 2023 | E2: =D2+1 -> 2024 | F2: =E2+1 -> 2025 | G2: =F2+1 -> 2026 | H2: =G2+1 -> 2027 | I2: =H2+1 -> 2028 | J2: =I2+1 -> 2029
B3: Capital expenditure % of sales | F3: =Assumptions!F29 -> 0.011269926 | G3: =Assumptions!G29 -> 0.011269926 | H3: =Assumptions!H29 -> 0.011269926 | I3: =Assumptions!I29 -> 0.011269926 | J3: =Assumptions!J29 -> 0.011269926
B4: Depreciation % of PP&E | F4: =Assumptions!F30 -> 0.22053393 | G4: =F4 -> 0.22053393 | H4: =G4 -> 0.22053393 | I4: =H4 -> 0.22053393 | J4: =I4 -> 0.22053393
B6: Beginning PP&E | F6: =E9 -> 1593.756 | G6: =F9 -> 1746.2707 | H6: =G9 -> 1930.6697 | I6: =H9 -> 2148.4389 | J6: =I9 -> 2401.8438
B7: Capex | F7: =F3*IncState!F13 -> 503.99198 | G7: =G3*IncState!G13 -> 569.51094 | H7: =H3*IncState!H13 -> 643.54736 | I7: =I3*IncState!I13 -> 727.20852 | J7: =J3*IncState!J13 -> 821.74563
B8: Depreciation | F8: =F4*F6 -> 351.47727 | G8: =G4*G6 -> 385.11194 | H8: =H4*H6 -> 425.77817 | I8: =I4*I6 -> 473.80367 | J8: =J4*J6 -> 529.68803
B9: Ending PP&E | E9: =BalSheet!E18 -> 1593.756 | F9: =F6+F7-F8 -> 1746.2707 | G9: =G6+G7-G8 -> 1930.6697 | H9: =H6+H7-H8 -> 2148.4389 | I9: =I6+I7-I8 -> 2401.8438 | J9: =J6+J7-J8 -> 2693.9014
A10: Equity | C10: =C2 -> 2022 | D10: =D2 -> 2023 | E10: =E2 -> 2024 | F10: =F2 -> 2025 | G10: =G2 -> 2026 | H10: =H2 -> 2027 | I10: =I2 -> 2028 | J10: =J2 -> 2029
B11: Share issuance/(repurchases) | F11: =Assumptions!F31 -> 0 | G11: =Assumptions!G31 -> 0 | H11: =Assumptions!H31 -> 0 | I11: =Assumptions!I31 -> 0 | J11: =Assumptions!J31 -> 0
B13: Beginning balance | F13: =E16 -> 24743.567 | G13: =F16 -> 35185.695 | H13: =G16 -> 46985.299 | I13: =H16 -> 60318.852 | J13: =I16 -> 75385.766
B14: Net income | F14: =IncState!F28 -> 10442.128 | G14: =IncState!G28 -> 11799.604 | H14: =IncState!H28 -> 13333.553 | I14: =IncState!I28 -> 15066.915 | J14: =IncState!J28 -> 17025.614
B15: Share issuance / (repurchase) | F15: =F11 -> 0 | G15: =G11 -> 0 | H15: =H11 -> 0 | I15: =I11 -> 0 | J15: =J11 -> 0
B16: Ending balance | E16: =BalSheet!E34 -> 24743.567 | F16: =SUM(F13:F15) -> 35185.695 | G16: =SUM(G13:G15) -> 46985.299 | H16: =SUM(H13:H15) -> 60318.852 | I16: =SUM(I13:I15) -> 75385.766 | J16: =SUM(J13:J15) -> 92411.38
A17: OWC | C17: =C10 -> 2022 | D17: =D10 -> 2023 | E17: =E10 -> 2024 | F17: =F10 -> 2025 | G17: =G10 -> 2026 | H17: =H10 -> 2027 | I17: =I10 -> 2028 | J17: =J10 -> 2029
B18: Operating Cash | E18: =BalSheet!E13 -> 1950.0483 | F18: =BalSheet!F13 -> 2236.004 | G18: =BalSheet!G13 -> 2526.6845 | H18: =BalSheet!H13 -> 2855.1535 | I18: =BalSheet!I13 -> 3226.3234 | J18: =BalSheet!J13 -> 3645.7455
B19: Other current assets | E19: =BalSheet!E15 -> 3516.64 | F19: =BalSheet!F15 -> 4032.3211 | G19: =BalSheet!G15 -> 4556.5229 | H19: =BalSheet!H15 -> 5148.8709 | I19: =BalSheet!I15 -> 5818.2241 | J19: =BalSheet!J15 -> 6574.5932
B20: Accounts payables | E20: =BalSheet!E26 -> 3056.453 | F20: =BalSheet!F26 -> 3504.6522 | G20: =BalSheet!G26 -> 3960.257 | H20: =BalSheet!H26 -> 4475.0904 | I20: =BalSheet!I26 -> 5056.8521 | J20: =BalSheet!J26 -> 5714.2429
B21: Other current liabilities | E21: =BalSheet!E27 -> 5914.494 | F21: =BalSheet!F27 -> 6781.7972 | G21: =BalSheet!G27 -> 7663.4308 | H21: =BalSheet!H27 -> 8659.6768 | I21: =BalSheet!I27 -> 9785.4348 | J21: =BalSheet!J27 -> 11057.541
A22: * | B22: OWC | E22: =SUM(E18:E19)-SUM(E20:E21) -> -3504.2587 | F22: =SUM(F18:F19)-SUM(F20:F21) -> -4018.1242 | G22: =SUM(G18:G19)-SUM(G20:G21) -> -4540.4804 | H22: =SUM(H18:H19)-SUM(H20:H21) -> -5130.7428 | I22: =SUM(I18:I19)-SUM(I20:I21) -> -5797.7394 | J22: =SUM(J18:J19)-SUM(J20:J21) -> -6551.4455
B23: Change in OWC | F23: =E22-F22 -> 513.86554 | G23: =F22-G22 -> 522.35615 | H23: =G22-H22 -> 590.26245 | I23: =H22-I22 -> 666.99657 | J23: =I22-J22 -> 753.70612

Sheet Debt
A1: =CoName -> Netflix Inc. | C1: Hist. | D1: Hist. | E1: Hist. | F1: Proj. | G1: Proj. | H1: Proj. | I1: Proj. | J1: Proj.
A2: Assumptions | C2: 44926 | D2: 45291 | E2: 45657 | F2: 46022 | G2: 46387 | H2: 46752 | I2: 47118 | J2: 47483
B4: Interest rate on revolver | F4: =Assumptions!F20 -> 0.05 | G4: =Assumptions!G20 -> 0.05 | H4: =Assumptions!H20 -> 0.05 | I4: =Assumptions!I20 -> 0.05 | J4: =Assumptions!J20 -> 0.05
B5: Interest rate on long-term debt | F5: =Assumptions!F21 -> 0.044 | G5: =Assumptions!G21 -> 0.044 | H5: =Assumptions!H21 -> 0.044 | I5: =Assumptions!I21 -> 0.044 | J5: =Assumptions!J21 -> 0.044
B6: Interest rate on cash | F6: =Assumptions!F22 -> 0.034947185 | G6: =Assumptions!G22 -> 0.034947185 | H6: =Assumptions!H22 -> 0.034947185 | I6: =Assumptions!I22 -> 0.034947185 | J6: =Assumptions!J22 -> 0.034947185
B8: Issuance of long-term debt | F8: =Assumptions!F24 -> 0 | G8: =Assumptions!G24 -> 0 | H8: =Assumptions!H24 -> 0 | I8: =Assumptions!I24 -> 0 | J8: =Assumptions!J24 -> 0
B9: Repayment of long-term debt | F9: =Assumptions!F25 -> 0 | G9: =Assumptions!G25 -> 0 | H9: =Assumptions!H25 -> 0 | I9: =Assumptions!I25 -> 0 | J9: =Assumptions!J25 -> 0
A11: Revolver | C11: =C2 -> 44926 | D11: =D2 -> 45291 | E11: =E2 -> 45657 | F11: =F2 -> 46022 | G11: =G2 -> 46387 | H11: =H2 -> 46752 | I11: =I2 -> 47118 | J11: =J2 -> 47483
B12: Balance | F12: NO REVOLVER
B13: Interest rate
B14: Interest expense
A16: Long term debt | C16: =C11 -> 44926 | D16: =D11 -> 45291 | E16: =E11 -> 45657 | F16: =F11 -> 46022 | G16: =G11 -> 46387 | H16: =H11 -> 46752 | I16: =I11 -> 47118 | J16: =J11 -> 47483
B17: Beginning balance | F17: =E20 -> 13798.351 | G17: =F20 -> 13798.351 | H17: =G20 -> 13798.351 | I17: =H20 -> 13798.351 | J17: =I20 -> 13798.351
B18: Issuance | F18: =F8 -> 0 | G18: =G8 -> 0 | H18: =H8 -> 0 | I18: =I8 -> 0 | J18: =J8 -> 0
B19: Repayment | F19: =F9 -> 0 | G19: =G9 -> 0 | H19: =H9 -> 0 | I19: =I9 -> 0 | J19: =J9 -> 0
B20: Ending balance | E20: =BalSheet!E30 -> 13798.351 | F20: =SUM(F17:F19) -> 13798.351 | G20: =SUM(G17:G19) -> 13798.351 | H20: =SUM(H17:H19) -> 13798.351 | I20: =SUM(I17:I19) -> 13798.351 | J20: =SUM(J17:J19) -> 13798.351
B21: Interest rate | F21: =F5 -> 0.044 | G21: =G5 -> 0.044 | H21: =H5 -> 0.044 | I21: =I5 -> 0.044 | J21: =J5 -> 0.044
B22: Interest expense | F22: =F20*F21 -> 607.12744 | G22: =G20*G21 -> 607.12744 | H22: =H20*H21 -> 607.12744 | I22: =I20*I21 -> 607.12744 | J22: =J20*J21 -> 607.12744
A24: Debt summary | C24: =C16 -> 44926 | D24: =D16 -> 45291 | E24: =E16 -> 45657 | F24: =F16 -> 46022 | G24: =G16 -> 46387 | H24: =H16 -> 46752 | I24: =I16 -> 47118 | J24: =J16 -> 47483
B25: Revolver | F25: NO REVOLVER | G25: NO REVOLVER | H25: NO REVOLVER | I25: NO REVOLVER | J25: NO REVOLVER
B26: Total long term debt | F26: =F20 -> 13798.351 | G26: =G20 -> 13798.351 | H26: =H20 -> 13798.351 | I26: =I20 -> 13798.351 | J26: =J20 -> 13798.351
B27: Total debt | F27: =F26 -> 13798.351 | G27: =G26 -> 13798.351 | H27: =H26 -> 13798.351 | I27: =I26 -> 13798.351 | J27: =J26 -> 13798.351
B28: Total interest expense | F28: =F22 -> 607.12744 | G28: =G22 -> 607.12744 | H28: =H22 -> 607.12744 | I28: =I22 -> 607.12744 | J28: =J22 -> 607.12744
A30: Interest income | C30: =C11 -> 44926 | D30: =D11 -> 45291 | E30: =E11 -> 45657 | F30: =F11 -> 46022 | G30: =G11 -> 46387 | H30: =H11 -> 46752 | I30: =I11 -> 47118 | J30: =J11 -> 47483
B31: Excess Cash | F31: =BalSheet!F14 -> 31638.851 | G31: =BalSheet!G14 -> 58757.336 | H31: =BalSheet!H14 -> 87402.628 | I31: =BalSheet!I14 -> 117775.29 | J31: =BalSheet!J14 -> 150101.48
B32: Interest rate | F32: =F4 -> 0.05 | G32: =G4 -> 0.05 | H32: =H4 -> 0.05 | I32: =I4 -> 0.05 | J32: =J4 -> 0.05
B33: Interest income | F33: =F31*F32 -> 1581.9425 | G33: =G31*G32 -> 2937.8668 | H33: =H31*H32 -> 4370.1314 | I33: =I31*I32 -> 5888.7643 | J33: =J31*J32 -> 7505.0741

Sheet IncState
A1: =CoName -> Netflix Inc. | C1: Hist. | D1: Hist. | E1: Hist. | F1: Proj. | G1: Proj. | H1: Proj. | I1: Proj. | J1: Proj.
A2: Assumptions | C2: 44926 | D2: 45291 | E2: 45657 | F2: 46022 | G2: 46387 | H2: 46752 | I2: 47118 | J2: 47483
B4: Revenue growth | F4: =Assumptions!F10 -> 0.1466403 | G4: =Assumptions!G10 -> 0.13 | H4: =Assumptions!H10 -> 0.13 | I4: =Assumptions!I10 -> 0.13 | J4: =Assumptions!J10 -> 0.13
B5: Cost of goods sold as % of sales | F5: =Assumptions!F11 -> 0.53943443 | G5: =Assumptions!G11 -> 0.53943443 | H5: =Assumptions!H11 -> 0.53943443 | I5: =Assumptions!I11 -> 0.53943443 | J5: =Assumptions!J11 -> 0.53943443
B6: SG&A % of sales | F6: =Assumptions!F12 -> 0.19345387 | G6: =Assumptions!G12 -> 0.19345387 | H6: =Assumptions!H12 -> 0.19345387 | I6: =Assumptions!I12 -> 0.19345387 | J6: =Assumptions!J12 -> 0.19345387
B7: Amortization amount | F7: =Assumptions!F13 -> 15301.517 | G7: =Assumptions!G13 -> 15301.517 | H7: =Assumptions!H13 -> 15301.517 | I7: =Assumptions!I13 -> 15301.517 | J7: =Assumptions!J13 -> 15301.517
B8: Effective tax rate | F8: =Assumptions!F14 -> 0.12583475 | G8: =Assumptions!G14 -> 0.12583475 | H8: =Assumptions!H14 -> 0.12583475 | I8: =Assumptions!I14 -> 0.12583475 | J8: =Assumptions!J14 -> 0.12583475
B9: Basic WASO | F9: =Assumptions!F15 -> 429.519 | G9: =Assumptions!G15 -> 429.519 | H9: =Assumptions!H15 -> 429.519 | I9: =Assumptions!I15 -> 429.519 | J9: =Assumptions!J15 -> 429.519
B10: Diluted WASO | F10: =Assumptions!F16 -> 439.261 | G10: =Assumptions!G16 -> 439.261 | H10: =Assumptions!H16 -> 439.261 | I10: =Assumptions!I16 -> 439.261 | J10: =Assumptions!J16 -> 439.261
A12: Income statement | C12: =C30 -> 44926 | D12: =D30 -> 45291 | E12: =E30 -> 45657 | F12: =F30 -> 46022 | G12: =G30 -> 46022 | H12: =H30 -> 46022 | I12: =I30 -> 46022 | J12: =J30 -> 46022
B13: Revenue | C13: 31615.55 | D13: 33723.297 | E13: 39000.966 | F13: =E13*(1+F4) -> 44720.079 | G13: =F13*(1+G4) -> 50533.69 | H13: =G13*(1+H4) -> 57103.069 | I13: =H13*(1+I4) -> 64526.468 | J13: =I13*(1+J4) -> 72914.909
B14: COGS | C14: 19168.285 | D14: 19715.368 | E14: 21038.464 | F14: =F13*F5 -> 24123.551 | G14: =G13*G5 -> 27259.612 | H14: =H13*H5 -> 30803.362 | I14: =I13*I5 -> 34807.799 | J14: =J13*J5 -> 39332.813
B15: SG&A | C15: =2530.502+2711.041+1572.891 -> 6814.434 | D15: =2657.883+2675.758+1720.285 -> 7053.926 | E15: =2917.554+2925.295+1702.039 -> 7544.888 | F15: =F13*F6 -> 8651.2726 | G15: =G13*G6 -> 9775.9381 | H15: =H13*H6 -> 11046.81 | I15: =I13*I6 -> 12482.895 | J15: =J13*J6 -> 14105.672
A16: * | B16: EBIT | C16: =C13-SUM(C14:C15) -> 5632.831 | D16: =D13-SUM(D14:D15) -> 6954.003 | E16: =E13-SUM(E14:E15) -> 10417.614 | F16: =F13-SUM(F14:F15) -> 11945.256 | G16: =G13-SUM(G14:G15) -> 13498.139 | H16: =H13-SUM(H14:H15) -> 15252.897 | I16: =I13-SUM(I14:I15) -> 17235.774 | J16: =J13-SUM(J14:J15) -> 19476.425
B18: Depreciation | C18: 336.683 | D18: 356.947 | E18: 328.914 | F18: =Calcs!F8 -> 351.47727 | G18: =Calcs!G8 -> 385.11194 | H18: =Calcs!H8 -> 425.77817 | I18: =Calcs!I8 -> 473.80367 | J18: =Calcs!J8 -> 529.68803
B19: Amortization | C19: 14026.132 | D19: 14197.437 | E19: 15301.517 | F19: =F7 -> 15301.517 | G19: =G7 -> 15301.517 | H19: =H7 -> 15301.517 | I19: =I7 -> 15301.517 | J19: =J7 -> 15301.517
A20: * | B20: EBITDA | C20: =SUM(C16,C18:C19) -> 19995.646 | D20: =SUM(D16,D18:D19) -> 21508.387 | E20: =SUM(E16,E18:E19) -> 26048.045 | F20: =SUM(F16,F18:F19) -> 27598.25 | G20: =SUM(G16,G18:G19) -> 29184.768 | H20: =SUM(H16,H18:H19) -> 30980.193 | I20: =SUM(I16,I18:I19) -> 33011.095 | J20: =SUM(J16,J18:J19) -> 35307.63
B22: Interest income | C22: 337.31 | D22: -48.772 | E22: 266.776 | F22: =IF(circ=1,Debt!F33,0) -> 0 | G22: =IF(circ=1,Debt!G33,0) -> 0 | H22: =IF(circ=1,Debt!H33,0) -> 0 | I22: =IF(circ=1,Debt!I33,0) -> 0 | J22: =IF(circ=1,Debt!J33,0) -> 0
B23: Interest expense | C23: -706.212 | D23: -699.826 | E23: -718.733 | F23: =IF(circ=1,Debt!F28,0) -> 0 | G23: =IF(circ=1,Debt!G28,0) -> 0 | H23: =IF(circ=1,Debt!H28,0) -> 0 | I23: =IF(circ=1,Debt!I28,0) -> 0 | J23: =IF(circ=1,Debt!J28,0) -> 0
A25: * | B25: Pretax Income | C25: =C16+SUM(C22:C23) -> 5263.929 | D25: =D16+SUM(D22:D23) -> 6205.405 | E25: =E16+SUM(E22:E23) -> 9965.657 | F25: =F16+SUM(F22:F23) -> 11945.256 | G25: =G16+SUM(G22:G23) -> 13498.139 | H25: =H16+SUM(H22:H23) -> 15252.897 | I25: =I16+SUM(I22:I23) -> 17235.774 | J25: =J16+SUM(J22:J23) -> 19476.425
B27: Tax expense | C27: 772.005 | D27: 797.415 | E27: 1254.026 | F27: =F25*F8 -> 1503.1284 | G27: =G25*G8 -> 1698.535 | H27: =H25*H8 -> 1919.3446 | I27: =I25*I8 -> 2168.8594 | J27: =J25*J8 -> 2450.8111
A28: * | B28: Net income | C28: =C25-C27 -> 4491.924 | D28: =D25-D27 -> 5407.99 | E28: =E25-E27 -> 8711.631 | F28: =F25-F27 -> 10442.128 | G28: =G25-G27 -> 11799.604 | H28: =H25-H27 -> 13333.553 | I28: =I25-I27 -> 15066.915 | J28: =J25-J27 -> 17025.614
A30: Shareholder information | C30: 44926 | D30: 45291 | E30: 45657 | F30: 46022 | G30: 46022 | H30: 46022 | I30: 46022 | J30: 46022
B31: Basic WASO | C31: 444.698 | D31: 441.571 | E31: 429.519 | F31: =F9 -> 429.519 | G31: =G9 -> 429.519 | H31: =H9 -> 429.519 | I31: =I9 -> 429.519 | J31: =J9 -> 429.519
B32: Diluted WASO | C32: 451.29 | D32: 449.498 | E32: 439.261 | F32: =F10 -> 439.261 | G32: =G10 -> 439.261 | H32: =H10 -> 439.261 | I32: =I10 -> 439.261 | J32: =J10 -> 439.261
B33: Basic earnings per share | C33: =C28/C31 -> 10.101066 | D33: =D28/D31 -> 12.247158 | E33: =E28/E31 -> 20.282295 | F33: =F28/F31 -> 24.311212 | G33: =G28/G31 -> 27.47167 | H33: =H28/H31 -> 31.042987 | I33: =I28/I31 -> 35.078575 | J33: =J28/J31 -> 39.63879
A34: * | B34: Diluted earnings per share | C34: =C28/C32 -> 9.9535199 | D34: =D28/D32 -> 12.031177 | E34: =E28/E32 -> 19.832471 | F34: =F28/F32 -> 23.772035 | G34: =G28/G32 -> 26.862399 | H34: =H28/H32 -> 30.354511 | I34: =I28/I32 -> 34.300597 | J34: =J28/J32 -> 38.759675

Sheet BalSheet
A1: =CoName -> Netflix Inc. | C1: Hist. | D1: Hist. | E1: Hist. | F1: Proj. | G1: Proj. | H1: Proj. | I1: Proj. | J1: Proj.
A2: Assumptions | C2: 44926 | D2: 45291 | E2: 45657 | F2: 46022 | G2: 46387 | H2: 46752 | I2: 47118 | J2: 47483
B4: Operating Cash % of sales | F4: =Assumptions!F35 -> 0.05 | G4: =F4 -> 0.05 | H4: =G4 -> 0.05 | I4: =H4 -> 0.05 | J4: =I4 -> 0.05
B5: Other current assets % of sales | F5: =Assumptions!F36 -> 0.090168023 | G5: =Assumptions!G36 -> 0.090168023 | H5: =Assumptions!H36 -> 0.090168023 | I5: =Assumptions!I36 -> 0.090168023 | J5: =Assumptions!J36 -> 0.090168023
B6: Other long-term assets % of sales | F6: =Assumptions!F37 -> 0.16624657 | G6: =Assumptions!G37 -> 0.16624657 | H6: =Assumptions!H37 -> 0.16624657 | I6: =Assumptions!I37 -> 0.16624657 | J6: =Assumptions!J37 -> 0.16624657
B8: Accounts payable/Accural % of COGS | F8: =Assumptions!F41 -> 0.14527928 | G8: =Assumptions!G41 -> 0.14527928 | H8: =Assumptions!H41 -> 0.14527928 | I8: =Assumptions!I41 -> 0.14527928 | J8: =Assumptions!J41 -> 0.14527928
B9: Other current liabilities % of sales | F9: =Assumptions!F42 -> 0.15164994 | G9: =Assumptions!G42 -> 0.15164994 | H9: =Assumptions!H42 -> 0.15164994 | I9: =Assumptions!I42 -> 0.15164994 | J9: =Assumptions!J42 -> 0.15164994
B10: Other long-term liabilities % of sales | F10: =Assumptions!F43 -> 0.11110125 | G10: =Assumptions!G43 -> 0.11110125 | H10: =Assumptions!H43 -> 0.11110125 | I10: =Assumptions!I43 -> 0.11110125 | J10: =Assumptions!J43 -> 0.11110125
A12: Balance sheet | C12: =C2 -> 44926 | D12: =D2 -> 45291 | E12: =E2 -> 45657 | F12: =F2 -> 46022 | G12: =G2 -> 46387 | H12: =H2 -> 46752 | I12: =I2 -> 47118 | J12: =J2 -> 47483
B13: Operating Cash | C13: =5%*IncState!C13 -> 1580.7775 | D13: =5%*IncState!D13 -> 1686.1649 | E13: =5%*IncState!E13 -> 1950.0483 | F13: =F4*IncState!F13 -> 2236.004 | G13: =G4*IncState!G13 -> 2526.6845 | H13: =H4*IncState!H13 -> 2855.1535 | I13: =I4*IncState!I13 -> 3226.3234 | J13: =J4*IncState!J13 -> 3645.7455
B14: Excess cash | C14: =5147.176+911.276-C13 -> 4477.6745 | D14: =7116.913+20.973-D13 -> 5451.7211 | E14: =7804.733+1779.006-E13 -> 7633.6907 | F14: =MAX(CashFlow!F22,0) -> 31638.851 | G14: =MAX(CashFlow!G22,0) -> 58757.336 | H14: =MAX(CashFlow!H22,0) -> 87402.628 | I14: =MAX(CashFlow!I22,0) -> 117775.29 | J14: =MAX(CashFlow!J22,0) -> 150101.48
B15: Other current assets | C15: 3208.021 | D15: 2780.247 | E15: 3516.64 | F15: =F5*IncState!F13 -> 4032.3211 | G15: =G5*IncState!G13 -> 4556.5229 | H15: =H5*IncState!H13 -> 5148.8709 | I15: =I5*IncState!I13 -> 5818.2241 | J15: =J5*IncState!J13 -> 6574.5932
B16: Total current assets | C16: =SUM(C13:C15) -> 9266.473 | D16: =SUM(D13:D15) -> 9918.133 | E16: =SUM(E13:E15) -> 13100.379 | F16: =SUM(F13:F15) -> 37907.176 | G16: =SUM(G13:G15) -> 65840.543 | H16: =SUM(H13:H15) -> 95406.653 | I16: =SUM(I13:I15) -> 126819.83 | J16: =SUM(J13:J15) -> 160321.82
B18: Property, plant & equipment, net | C18: 1398.257 | D18: 1491.444 | E18: 1593.756 | F18: =Calcs!F9 -> 1746.2707 | G18: =Calcs!G9 -> 1930.6697 | H18: =Calcs!H9 -> 2148.4389 | I18: =Calcs!I9 -> 2401.8438 | J18: =Calcs!J9 -> 2693.9014
B19: Intangible assets | C19: 32736.713 | D19: 31658.056 | E19: 32452.462 | F19: =E19-IncState!F19 -> 17150.945 | G19: =F19-IncState!G19 -> 1849.428 | H19: =G19-IncState!H19 -> -13452.089 | I19: =H19-IncState!I19 -> -28753.606 | J19: =I19-IncState!J19 -> -44055.123
B20: Other assets | C20: 5193.325 | D20: 5664.359 | E20: 6483.777 | F20: =F6*IncState!F13 -> 7434.56 | G20: =G6*IncState!G13 -> 8401.0528 | H20: =H6*IncState!H13 -> 9493.1896 | I20: =I6*IncState!I13 -> 10727.304 | J20: =J6*IncState!J13 -> 12121.854
B21: Total non-current assets | C21: =SUM(C18:C20) -> 39328.295 | D21: =SUM(D18:D20) -> 38813.859 | E21: =SUM(E18:E20) -> 40529.995 | F21: =SUM(F18:F20) -> 26331.776 | G21: =SUM(G18:G20) -> 12181.151 | H21: =SUM(H18:H20) -> -1810.4604 | I21: =SUM(I18:I20) -> -15624.458 | J21: =SUM(J18:J20) -> -29239.368
A23: * | B23: TOTAL ASSETS | C23: =SUM(C21,C16) -> 48594.768 | D23: =SUM(D21,D16) -> 48731.992 | E23: =SUM(E21,E16) -> 53630.374 | F23: =SUM(F21,F16) -> 64238.952 | G23: =SUM(G21,G16) -> 78021.694 | H23: =SUM(H21,H16) -> 93596.192 | I23: =SUM(I21,I16) -> 111195.38 | J23: =SUM(J21,J16) -> 131082.45
B25: Revolver/Short term debt | C25: 0 | D25: 399.844 | E25: 1784.453 | F25: =MIN(CashFlow!F22,0) -> 0 | G25: =MIN(CashFlow!G22,0) -> 0 | H25: =MIN(CashFlow!H22,0) -> 0 | I25: =MIN(CashFlow!I22,0) -> 0 | J25: =MIN(CashFlow!J22,0) -> 0
B26: Accounts payable/Accurals | C26: =671.513+1514.65 -> 2186.163 | D26: =747.412+1803.96 -> 2551.372 | E26: =899.909+2156.544 -> 3056.453 | F26: =F8*IncState!F14 -> 3504.6522 | G26: =G8*IncState!G14 -> 3960.257 | H26: =H8*IncState!H14 -> 4475.0904 | I26: =I8*IncState!I14 -> 5056.8521 | J26: =J8*IncState!J14 -> 5714.2429
B27: Other current liabilities | C27: =7930.974-C26 -> 5744.811 | D27: =8860.655-SUM(D25:D26) -> 5909.439 | E27: =10755.4-SUM(E25:E26) -> 5914.494 | F27: =F9*IncState!F13 -> 6781.7972 | G27: =G9*IncState!G13 -> 7663.4308 | H27: =H9*IncState!H13 -> 8659.6768 | I27: =I9*IncState!I13 -> 9785.4348 | J27: =J9*IncState!J13 -> 11057.541
B28: Total current liabilities | C28: =SUM(C25:C27) -> 7930.974 | D28: =SUM(D25:D27) -> 8860.655 | E28: =SUM(E25:E27) -> 10755.4 | F28: =SUM(F25:F27) -> 10286.449 | G28: =SUM(G25:G27) -> 11623.688 | H28: =SUM(H25:H27) -> 13134.767 | I28: =SUM(I25:I27) -> 14842.287 | J28: =SUM(J25:J27) -> 16771.784
B30: Long-term debt, including current maturities | C30: 14353.076 | D30: 14143.417 | E30: 13798.351 | F30: =E30-SUM(Debt!F8:F9) -> 13798.351 | G30: =F30-SUM(Debt!G8:G9) -> 13798.351 | H30: =G30-SUM(Debt!H8:H9) -> 13798.351 | I30: =H30-SUM(Debt!I8:I9) -> 13798.351 | J30: =I30-SUM(Debt!J8:J9) -> 13798.351
B31: Other long-term liabilities | C31: =27817.367-C30-C28 -> 5533.317 | D31: =28143.679-D30-D28 -> 5139.607 | E31: =28886.807-E30-E28 -> 4333.056 | F31: =F10*IncState!F13 -> 4968.4566 | G31: =G10*IncState!G13 -> 5614.356 | H31: =H10*IncState!H13 -> 6344.2223 | I31: =I10*IncState!I13 -> 7168.9712 | J31: =J10*IncState!J13 -> 8100.9374
B32: Total non-current liabilities | C32: =SUM(C30:C31) -> 19886.393 | D32: =SUM(D30:D31) -> 19283.024 | E32: =SUM(E30:E31) -> 18131.407 | F32: =SUM(F30:F31) -> 18766.808 | G32: =SUM(G30:G31) -> 19412.707 | H32: =SUM(H30:H31) -> 20142.573 | I32: =SUM(I30:I31) -> 20967.322 | J32: =SUM(J30:J31) -> 21899.288
B34: Equity | C34: 20777.401 | D34: 20588.313 | E34: 24743.567 | F34: =Calcs!F16 -> 35185.695 | G34: =Calcs!G16 -> 46985.299 | H34: =Calcs!H16 -> 60318.852 | I34: =Calcs!I16 -> 75385.766 | J34: =Calcs!J16 -> 92411.38
A35: * | B35: TOTAL LIABILITIES & EQUITY | C35: =SUM(C34,C32,C28) -> 48594.768 | D35: =SUM(D34,D32,D28) -> 48731.992 | E35: =SUM(E34,E32,E28) -> 53630.374 | F35: =SUM(F34,F32,F28) -> 64238.952 | G35: =SUM(G34,G32,G28) -> 78021.694 | H35: =SUM(H34,H32,H28) -> 93596.192 | I35: =SUM(I34,I32,I28) -> 111195.38 | J35: =SUM(J34,J32,J28) -> 131082.45
A37: * | B37: Balance check | C37: =C35-C23 -> 0 | D37: =D35-D23 -> 0 | E37: =E35-E23 -> 0 | F37: =F35-F23 -> 0 | G37: =G35-G23 -> 0 | H37: =H35-H23 -> 0 | I37: =I35-I23 -> 0 | J37: =J35-J23 -> 0

Sheet CashFlow
A1: =CoName -> Netflix Inc. | C1: Hist. | D1: Hist. | E1: Hist. | F1: Proj. | G1: Proj. | H1: Proj. | I1: Proj. | J1: Proj.
A2: Cash flow statement | C2: 2022 | D2: =C2+1 -> 2023 | E2: =D2+1 -> 2024 | F2: =E2+1 -> 2025 | G2: =F2+1 -> 2026 | H2: =G2+1 -> 2027 | I2: =H2+1 -> 2028 | J2: =I2+1 -> 2029
B3: Net Income | F3: =IncState!F28 -> 10442.128 | G3: =IncState!G28 -> 11799.604 | H3: =IncState!H28 -> 13333.553 | I3: =IncState!I28 -> 15066.915 | J3: =IncState!J28 -> 17025.614
B4: Depreciation | F4: =IncState!F18 -> 351.47727 | G4: =IncState!G18 -> 385.11194 | H4: =IncState!H18 -> 425.77817 | I4: =IncState!I18 -> 473.80367 | J4: =IncState!J18 -> 529.68803
B5: Amortization | F5: =IncState!F19 -> 15301.517 | G5: =IncState!G19 -> 15301.517 | H5: =IncState!H19 -> 15301.517 | I5: =IncState!I19 -> 15301.517 | J5: =IncState!J19 -> 15301.517
B6: (inc) / dec In OWC | F6: =Calcs!F23 -> 513.86554 | G6: =Calcs!G23 -> 522.35615 | H6: =Calcs!H23 -> 590.26245 | I6: =Calcs!I23 -> 666.99657 | J6: =Calcs!J23 -> 753.70612
B7: (inc) / dec LT assets | F7: =BalSheet!E20-BalSheet!F20 -> -950.78299 | G7: =BalSheet!F20-BalSheet!G20 -> -966.4928 | H7: =BalSheet!G20-BalSheet!H20 -> -1092.1369 | I7: =BalSheet!H20-BalSheet!I20 -> -1234.1147 | J7: =BalSheet!I20-BalSheet!J20 -> -1394.5496
B8: inc / (dec) LT liabilities | F8: =BalSheet!F31-BalSheet!E31 -> 635.40062 | G8: =BalSheet!G31-BalSheet!F31 -> 645.89936 | H8: =BalSheet!H31-BalSheet!G31 -> 729.86628 | I8: =BalSheet!I31-BalSheet!H31 -> 824.74889 | J8: =BalSheet!J31-BalSheet!I31 -> 931.96625
B9: Cash Flow From Operations | F9: =SUM(F3:F8) -> 26293.605 | G9: =SUM(G3:G8) -> 27687.996 | H9: =SUM(H3:H8) -> 29288.84 | I9: =SUM(I3:I8) -> 31099.866 | J9: =SUM(J3:J8) -> 33147.941
B11: Capex | F11: =Calcs!F7 -> 503.99198 | G11: =Calcs!G7 -> 569.51094 | H11: =Calcs!H7 -> 643.54736 | I11: =Calcs!I7 -> 727.20852 | J11: =Calcs!J7 -> 821.74563
B12: Cash Flow From Investing | F12: =-F11 -> -503.99198 | G12: =-G11 -> -569.51094 | H12: =-H11 -> -643.54736 | I12: =-I11 -> -727.20852 | J12: =-J11 -> -821.74563
B14: Shares Issued / (repurchased) | F14: 0 | G14: 0 | H14: 0 | I14: 0 | J14: 0
B15: Debt Issuance / (repayment) | F15: 0 | G15: 0 | H15: 0 | I15: 0 | J15: 0
B16: Cash Flor From Financing | F16: 0 | G16: 0 | H16: 0 | I16: 0 | J16: 0
B18: Net Changes In cash | F18: =SUM(F16,F12,F9) -> 25789.613 | G18: =SUM(G16,G12,G9) -> 27118.485 | H18: =SUM(H16,H12,H9) -> 28645.292 | I18: =SUM(I16,I12,I9) -> 30372.658 | J18: =SUM(J16,J12,J9) -> 32326.196
B20: Beginning cash | F20: =BalSheet!E14 -> 7633.6907 | G20: =BalSheet!F14 -> 31638.851 | H20: =BalSheet!G14 -> 58757.336 | I20: =BalSheet!H14 -> 87402.628 | J20: =BalSheet!I14 -> 117775.29
B21: Changes | F21: =F18 -> 25789.613 | G21: =G18 -> 27118.485 | H21: =H18 -> 28645.292 | I21: =I18 -> 30372.658 | J21: =J18 -> 32326.196
B22: Ending cash Adjusted for Revolver | F22: =SUM(F20:F21)-BalSheet!E25 -> 31638.851 | G22: =SUM(G20:G21)-BalSheet!F25 -> 58757.336 | H22: =SUM(H20:H21)-BalSheet!G25 -> 87402.628 | I22: =SUM(I20:I21)-BalSheet!H25 -> 117775.29 | J22: =SUM(J20:J21)-BalSheet!I25 -> 150101.48

Sheet Free Cash Flow
A1: =CoName -> Netflix Inc. | C1: Hist. | D1: Hist. | E1: Hist. | F1: Proj. | G1: Proj. | H1: Proj. | I1: Proj. | J1: Proj.
A2: Free Cash Flows | C2: 2022 | D2: =C2+1 -> 2023 | E2: =D2+1 -> 2024 | F2: =E2+1 -> 2025 | G2: =F2+1 -> 2026 | H2: =G2+1 -> 2027 | I2: =H2+1 -> 2028 | J2: =I2+1 -> 2029
A3: * | B3: Sales | F3: =IncState!F13 -> 44720.079 | G3: =IncState!G13 -> 50533.69 | H3: =IncState!H13 -> 57103.069 | I3: =IncState!I13 -> 64526.468 | J3: =IncState!J13 -> 72914.909
B4: EBIT | F4: =IncState!F16 -> 11945.256 | G4: =IncState!G16 -> 13498.139 | H4: =IncState!H16 -> 15252.897 | I4: =IncState!I16 -> 17235.774 | J4: =IncState!J16 -> 19476.425
B5: Effective Tax Rate | F5: =IncState!F8 -> 0.12583475 | G5: =IncState!G8 -> 0.12583475 | H5: =IncState!H8 -> 0.12583475 | I5: =IncState!I8 -> 0.12583475 | J5: =IncState!J8 -> 0.12583475
A7: * | B7: NOPAT | F7: =F4*(1-F5) -> 10442.128 | G7: =G4*(1-G5) -> 11799.604 | H7: =H4*(1-H5) -> 13333.553 | I7: =I4*(1-I5) -> 15066.915 | J7: =J4*(1-J5) -> 17025.614
B8: Depreciation | F8: =CashFlow!F4 -> 351.47727 | G8: =CashFlow!G4 -> 385.11194 | H8: =CashFlow!H4 -> 425.77817 | I8: =CashFlow!I4 -> 473.80367 | J8: =CashFlow!J4 -> 529.68803
B9: Amortization | F9: =CashFlow!F5 -> 15301.517 | G9: =CashFlow!G5 -> 15301.517 | H9: =CashFlow!H5 -> 15301.517 | I9: =CashFlow!I5 -> 15301.517 | J9: =CashFlow!J5 -> 15301.517
B10: (inc) / dec in OWC | F10: =CashFlow!F6 -> 513.86554 | G10: =CashFlow!G6 -> 522.35615 | H10: =CashFlow!H6 -> 590.26245 | I10: =CashFlow!I6 -> 666.99657 | J10: =CashFlow!J6 -> 753.70612
B11: (inc) / dec in other long-term assets | F11: =CashFlow!F7 -> -950.78299 | G11: =CashFlow!G7 -> -966.4928 | H11: =CashFlow!H7 -> -1092.1369 | I11: =CashFlow!I7 -> -1234.1147 | J11: =CashFlow!J7 -> -1394.5496
B12: inc / (dec) other long-term liabilities | F12: =CashFlow!F8 -> 635.40062 | G12: =CashFlow!G8 -> 645.89936 | H12: =CashFlow!H8 -> 729.86628 | I12: =CashFlow!I8 -> 824.74889 | J12: =CashFlow!J8 -> 931.96625
B13: (Capex) | F13: =CashFlow!F12 -> -503.99198 | G13: =CashFlow!G12 -> -569.51094 | H13: =CashFlow!H12 -> -643.54736 | I13: =CashFlow!I12 -> -727.20852 | J13: =CashFlow!J12 -> -821.74563
A15: * | B15: Free Cash Flow | F15: =SUM(F7:F13) -> 25789.613 | G15: =SUM(G7:G13) -> 27118.485 | H15: =SUM(H7:H13) -> 28645.292 | I15: =SUM(I7:I13) -> 30372.658 | J15: =SUM(J7:J13) -> 32326.196

Sheet WACC
A1: =CoName -> Netflix Inc.
A3: * | B3: WACC | G3: Comp | H3: Levered beta | I3: Gross debt | J3: Market cap | K3: Debt/Mcap | L3: MTR | M3: Unlevered beta
B4: Tax Rate | E4: =Assumptions!F14 -> 0.12583475 | G4: PARA | H4: 1.21 | I4: =14168+346 -> 14514 | J4: 16550 | K4: =I4/J4 -> 0.87697885 | L4: =E4 -> 0.12583475 | M4: =H4/((1+K4*(1-L4))) -> 0.68492203
B5: Risk free rate | E5: 0.04 | G5: DIS | H5: 1.49 | I5: =5732+36531 -> 42263 | J5: =1800*110.88 -> 199584 | K5: =I5/J5 -> 0.21175545 | L5: =L4 -> 0.12583475 | M5: =H5/((1+K5*(1-L5))) -> 1.257268
B6: Market risk Premium | E6: 0.05 | G6: WBD | H6: 1.61 | I6: =139+33382 -> 33521 | J6: =22.59*2500 -> 56475 | K6: =I6/J6 -> 0.59355467 | L6: =L5 -> 0.12583475 | M6: =H6/((1+K6*(1-L6))) -> 1.0600021
B7: Beta | E7: =M11 -> 0.88428331 | G7: CMCSA | H7: 0.83 | I7: =5852+93211 -> 99063 | J7: =3600*27.41 -> 98676 | K7: =I7/J7 -> 1.0039219 | L7: =L6 -> 0.12583475 | M7: =H7/((1+K7*(1-L7))) -> 0.44205518
B8: Cost of Equity | E8: =E5+E6*E7 -> 0.084214165
B9: % Equity | E9: =1-E10 -> 0.96914954 | G9: Industry beta (average) | M9: =AVERAGE(M4:M7) -> 0.86106185
B10: % Debt | E10: =MAIN!F8/MAIN!F6 -> 0.030850458
B11: Cost of debt | E11: 0 | G11: Re-levered beta | M11: =M9*(1+E10*(1-E4)) -> 0.88428331
B12: Post tax cost of debt | E12: =E11*(1-E4) -> 0
A13: * | B13: WACC | E13: =WACC!E8*WACC!E9+WACC!E12*WACC!E10 -> 0.08161612
B14: Long Term growth rate | E14: 0.025

Sheet DCF Model
A1: =CoName -> Netflix Inc. | D1: Proj. | E1: Proj. | F1: Proj. | G1: Proj. | H1: Proj.
A2: Discount Model Year count | D2: 0.5 | E2: =D2+1 -> 1.5 | F2: =E2+1 -> 2.5 | G2: =F2+1 -> 3.5 | H2: =G2+1 -> 4.5
B3: Discount Factor | D3: =1/(1+$M$3)^D2 -> 0.9615313 | E3: =1/(1+$M$3)^E2 -> 0.88897649 | F3: =1/(1+$M$3)^F2 -> 0.82189648 | G3: =1/(1+$M$3)^G2 -> 0.75987818 | H3: =1/(1+$M$3)^H2 -> 0.70253962 | J3: WACC | M3: =WACC!E13 -> 0.08161612
B4: PV FCF | D4: =D3*'Free Cash Flow'!F15 -> 24797.52 | E4: =E3*'Free Cash Flow'!G15 -> 24107.695 | F4: =F3*'Free Cash Flow'!H15 -> 23543.465 | G4: =G3*'Free Cash Flow'!I15 -> 23079.52 | H4: =H3*'Free Cash Flow'!J15 -> 22710.433 | J4: Long Term growth rate | M4: 0.025
H5: =((H4*(1+M4)))/(M3-M4) -> 411158.41
A6: Value Calculation | E6: Multiples Calculation
B7: Total PV of FCFs | C7: =SUM(D4:H4) -> 118238.63 | E7: Total PV of FCFs | G7: =C7 -> 118238.63 | K7: LTGR | P7: Exit Mult.
B8: PV of TV | C8: =H5*H3 -> 288855.08 | E8: Multiple TV | G8: =G10*IncState!J20*'DCF Model'!H3 -> 285257.6 | I8: =C18 -> 926.08056 | J8: =K8-E23 -> 0.0225 | K8: 0.025 | L8: =K8+E23 -> 0.0275 | N8: =G18 -> 917.79219 | O8: =P8-1 -> 10.5 | P8: 11.5 | Q8: =P8+1 -> 12.5
B9: EV | C9: =SUM(C7:C8) -> 407093.71 | E9: EV | G9: =SUM(G7:G8) -> 403496.23 | I9: =I10+$E$22 -> 0.09161612 | J9: 755.098 | K9: 775.15416 | L9: 796.77436 | N9: =I9 -> 0.09161612 | O9: 830.23416 | P9: 885.06502 | Q9: 939.89588
E10: Implied EBITDA multiple | G10: 11.5 | I10: =I11+$E$22 -> 0.08661612 | J10: 819.90189 | K10: 844.15096 | L10: 870.45101 | N10: =I10 -> 0.08661612 | O10: 845.25477 | P10: 901.23016 | Q10: 957.20556
I11: 0.08161612 | J11: 896.38205 | K11: 926.08056 | L11: 958.52303 | N11: =I11 -> 0.08161612 | O11: 860.64293 | P11: 917.79219 | Q11: 974.94145
B12: Cash & Cash Equiv | C12: =MAIN!F7 -> 9324.392 | E12: Cash & Cash Equiv | G12: =C12 -> 9324.392 | I12: =I11-$E$22 -> 0.07661612 | J12: 987.82609 | K12: 1024.755 | L12: 1065.4433 | N12: =I12 -> 0.07661612 | O12: 876.40958 | P12: 934.76294 | Q12: 993.11629
B13: Debt & Claims | C13: =MAIN!F8 -> 14463.02 | E13: Debt & Claims | G13: =C13 -> 14463.02 | I13: =I12-$E$22 -> 0.07161612 | J13: 1098.8639 | K13: 1145.6257 | L13: 1197.6875 | N13: =I13 -> 0.07161612 | O13: 892.56602 | P13: 952.15462 | Q13: 1011.7432
B14: NCI | C14: 0 | E14: NCI | G14: =C14 -> 0
B15: Equity Value | C15: =C9+C12-C13 -> 401955.08 | E15: Equity Value | G15: =G9+G12-G13 -> 398357.61 | K15: Average | P15: Average
K16: =AVERAGE(J9:L13) -> 944.18117 | P16: =AVERAGE(O9:Q13) -> 918.20099
B17: Diluted S/O | C17: 434.039 | E17: Diluted S/O | G17: =C17 -> 434.039
A18: * | B18: Implied Share Price | C18: =C15/C17 -> 926.08056 | E18: Implied Share Price | G18: =G15/G17 -> 917.79219
A20: Sensitivity analysis
C22: Discount rate variance | E22: 0.005 | J22: Discount rate variance | L22: 0.005
C23: Implied growth rate variance | E23: 0.0025 | J23: TV multiple variance | L23: 1
A25: DCF tables
