Workbook
Name Ccy: MAIN!$C$6
Name circ: MAIN!$C$9
Name CoName: MAIN!$C$4
Name g: Presentation!$R$17
Name IQ_CH: 110000
Name IQ_CQ: 5000
Name IQ_CY: 10000
Name IQ_DAILY: 500000
Name IQ_FH: 100000
Name IQ_FQ: 500
Name IQ_FY: 1000
Name IQ_LTM: 2000
Name IQ_MONTH: 15000
Name IQ_NTM: 6000
Name IQ_WEEK: 50000
Name IQ_YTD: 3000
Name OpCase: [1]DCF!$E$98
Name ScenarioREV: Assumptions!$D$4
Name TTS: #REF!
Name Units: MAIN!$C$7

Sheet MAIN
A1: =CoName -> Palantir Technologies Inc
A2: Model Details
B4: Company name | C4: Palantir Technologies Inc | E4: Current Stock Price | F4: 178.12 | I4: Perpetuity | J4: Terminal Value
B5: Latest BS date | C5: 247.43 | E5: Diluted s/o | F5: 2562.912 | H5: Implied Price | I5: ='DCF Model'!K16 -> 77.022348 | J5: ='DCF Model'!P16 -> 215.1678
B6: Currency | C6: USD | E6: Mkt Cap | F6: =F5*F4 -> 456505.89 | H6: Difference | I6: =I5/$F$4-1 -> -0.5675817 | J6: =J5/$F$4-1 -> 0.20799349
B7: Units | C7: t | E7: Cash | F7: =929.547+5070.875 -> 6000.422
B8: Analyst name | C8: Alan Chen | E8: Debt | F8: 0
B9: Circular switch | C9: 0 | E9: EV | F9: =F6-F7+F8 -> 450505.46

Sheet Assumptions
A1: =CoName -> Palantir Technologies Inc | C1: Hist. | D1: Hist. | E1: Hist. | F1: Proj. | G1: Proj. | H1: Proj. | I1: Proj. | J1: Proj. | K1: Proj. | L1: Proj. | M1: Proj. | N1: Proj. | O1: Proj. | P1: Proj. | Q1: Proj. | R1: Proj. | S1: Proj. | T1: Proj. | U1: Proj.
A2: * | B2: Income Statement | C2: 44926 | D2: 45291 | E2: 45657 | F2: 46022 | G2: 46387 | H2: 46752 | I2: 47118 | J2: 47483 | K2: 47848 | L2: 48213 | M2: 48579 | N2: =2032+1 -> 2033 | O2: =N2+1 -> 2034 | P2: =O2+1 -> 2035 | Q2: =P2+1 -> 2036 | R2: =Q2+1 -> 2037 | S2: =R2+1 -> 2038 | T2: =S2+1 -> 2039 | U2: =T2+1 -> 2040
B4: Operating Case | D4: 1
D5: Variance
B6: Street Case | D6: 0 | F6: =Revenue!U4 -> 0.52823538 | G6: =Revenue!Z4 -> 0.5212929 | H6: =Revenue!AA4 -> 0.42 | I6: =Revenue!AB4 -> 0.415 | J6: =Revenue!AC4 -> 0.41 | K6: =Revenue!AD4 -> 0.405 | L6: =Revenue!AE4 -> 0.4 | M6: =Revenue!AF4 -> 0.395 | N6: =Revenue!AG4 -> 0.39 | ... U6: =Revenue!AN4 -> 0.355
B7: Optimistic Case | D7: 0.025 | F7: =F6+$D$7 -> 0.55323538 | G7: =G6+$D$7 -> 0.5462929 | H7: =H6+$D$7 -> 0.445 | I7: =I6+$D$7 -> 0.44 | J7: =J6+$D$7 -> 0.435 | K7: =K6+$D$7 -> 0.43 | L7: =L6+$D$7 -> 0.425 | M7: =M6+$D$7 -> 0.42 | ... U7: =U6+$D$7 -> 0.38
B8: Pessimistic Case | D8: -0.025 | F8: =F6+$D$8 -> 0.50323538 | G8: =G6+$D$8 -> 0.4962929 | H8: =H6+$D$8 -> 0.395 | I8: =I6+$D$8 -> 0.39 | J8: =J6+$D$8 -> 0.385 | K8: =K6+$D$8 -> 0.38 | L8: =L6+$D$8 -> 0.375 | M8: =M6+$D$8 -> 0.37 | ... U8: =U6+$D$8 -> 0.33
B10: Revenue Growth | C10: =IncState!C14/1540-1 -> 0.23757857 | D10: =IncState!D14/IncState!C14-1 -> 0.16745152 | E10: =IncState!E14/IncState!D14-1 -> 0.28786137 | F10: =CHOOSE(ScenarioREV,F6,F7,F8) -> 0.52823538 | G10: =CHOOSE(ScenarioREV,G6,G7,G8) -> 0.5212929 | H10: =CHOOSE(ScenarioREV,H6,H7,H8) -> 0.42 | I10: =CHOOSE(ScenarioREV,I6,I7,I8) -> 0.415 | J10: =CHOOSE(ScenarioREV,J6,J7,J8) -> 0.41 | K10: =CHOOSE(ScenarioREV,K6,K7,K8) -> 0.405 | L10: =CHOOSE(ScenarioREV,L6,L7,L8) -> 0.4 | M10: =CHOOSE(ScenarioREV,M6,M7,M8) -> 0.395 | ... U10: =CHOOSE(ScenarioREV,U6,U7,U8) -> 0.355
B11: COGS % of sales | C11: =IncState!C15/IncState!C14 -> 0.21436288 | D11: =IncState!D15/IncState!D14 -> 0.19375401 | E11: =IncState!E15/IncState!E14 -> 0.19751828 | F11: =E11-0.001 -> 0.19651828 | G11: =F11-0.001 -> 0.19551828 | H11: =G11-0.001 -> 0.19451828 | I11: =H11-0.001 -> 0.19351828 | J11: =I11-0.001 -> 0.19251828 | K11: =J11-0.001 -> 0.19151828 | L11: =K11-0.001 -> 0.19051828 | M11: =L11-0.001 -> 0.18951828 | ... U11: =T11-0.001 -> 0.18151828
B12: R&D % of sales | C12: =IncState!C16/IncState!C14 -> 0.18872159 | D12: =IncState!D16/IncState!D14 -> 0.1818525 | E12: =IncState!E16/IncState!E14 -> 0.17723844 | F12: =E12-0.001 -> 0.17623844 | G12: =F12-0.001 -> 0.17523844 | H12: =G12-0.001 -> 0.17423844 | I12: =H12-0.001 -> 0.17323844 | J12: =I12-0.001 -> 0.17223844 | K12: =J12-0.001 -> 0.17123844 | L12: =K12-0.001 -> 0.17023844 | M12: =L12-0.001 -> 0.16923844 | ... U12: =T12-0.001 -> 0.16123844
B13: SG&A % of sales | C13: =IncState!C17/IncState!C14 -> 0.68149628 | D13: =IncState!D17/IncState!D14 -> 0.57047647 | E13: =IncState!E17/IncState!E14 -> 0.51691934 | F13: =E13-0.025 -> 0.49191934 | G13: =F13-0.025 -> 0.46691934 | H13: =G13-0.025 -> 0.44191934 | I13: =H13-0.025 -> 0.41691934 | J13: =I13-0.025 -> 0.39191934 | K13: =J13-0.025 -> 0.36691934 | L13: =K13 -> 0.36691934 | M13: =L13 -> 0.36691934 | N13: =M13 -> 0.36691934 | O13: =N13 -> 0.36691934 | P13: =O13 -> 0.36691934 | Q13: =P13 -> 0.36691934 | R13: =Q13 -> 0.36691934 | S13: =R13 -> 0.36691934 | ... U13: =T13 -> 0.36691934
B14: Other Income / (expense) | C14: =IncState!C23 -> -220.135 | D14: =IncState!D23 -> -15.447 | E14: =IncState!E23 -> -18.022 | F14: 0 | G14: 0 | H14: 0 | I14: 0 | J14: 0 | K14: 0 | L14: 0 | M14: 0 | N14: 0 | O14: 0 | P14: 0 | Q14: 0 | R14: 0 | S14: 0 | T14: 0 | U14: 0
B15: Effective tax rate | C15: =IncState!C30/IncState!C28 -> -0.027884418 | D15: =IncState!D30/IncState!D28 -> 0.083157944 | E15: =IncState!E30/IncState!E28 -> 0.043450885 | F15: 0.23 | G15: =F15 -> 0.23 | H15: =G15 -> 0.23 | I15: =H15 -> 0.23 | J15: =I15 -> 0.23 | K15: =J15 -> 0.23 | L15: =K15 -> 0.23 | M15: =L15 -> 0.23 | N15: =M15 -> 0.23 | ... U15: =T15 -> 0.23
B16: Basic WASO | C16: =IncState!C34 -> 2063.793 | D16: =IncState!D34 -> 2147.446 | E16: =IncState!E34 -> 2250.163 | F16: =E16 -> 2250.163 | G16: =F16 -> 2250.163 | H16: =G16 -> 2250.163 | I16: =H16 -> 2250.163 | J16: =I16 -> 2250.163 | K16: =J16 -> 2250.163 | L16: =K16 -> 2250.163 | M16: =L16 -> 2250.163 | ... U16: =T16 -> 2250.163
B17: Diluted WASO | C17: =IncState!C35 -> 2063.793 | D17: =IncState!D35 -> 2297.927 | E17: =IncState!E35 -> 2450.818 | F17: =E17 -> 2450.818 | G17: =F17 -> 2450.818 | H17: =G17 -> 2450.818 | I17: =H17 -> 2450.818 | J17: =I17 -> 2450.818 | K17: =J17 -> 2450.818 | L17: =K17 -> 2450.818 | M17: =L17 -> 2450.818 | ... U17: =T17 -> 2450.818
A19: * | B19: Debt | C19: 44926 | D19: 45291 | E19: 45657 | F19: 46022 | G19: 46387 | H19: 46752 | I19: 47118 | J19: 47483 | K19: =K2 -> 47848 | L19: =L2 -> 48213 | M19: =M2 -> 48579 | N19: =2032+1 -> 2033 | O19: =N19+1 -> 2034 | P19: =O19+1 -> 2035 | Q19: =P19+1 -> 2036 | R19: =Q19+1 -> 2037 | S19: =R19+1 -> 2038 | T19: =S19+1 -> 2039 | U19: =T19+1 -> 2040
B21: Interest rate on Revolver | F21: =E21 -> 0 | G21: =F21 -> 0 | H21: =G21 -> 0 | I21: =H21 -> 0 | J21: =I21 -> 0 | K21: =J21 -> 0 | L21: =K21 -> 0 | M21: =L21 -> 0 | ... U21: =T21 -> 0
B22: Interest rate on long-term debt | F22: =E22 -> 0 | G22: =F22 -> 0 | H22: =G22 -> 0 | I22: =H22 -> 0 | J22: =I22 -> 0 | K22: =J22 -> 0 | L22: =K22 -> 0 | M22: =L22 -> 0 | ... U22: =T22 -> 0
B23: Interest rate on cash | C23: =IncState!C25/BalSheet!C15 -> 0.0080007676 | D23: =IncState!D25/BalSheet!D15 -> 0.037208719 | E23: =IncState!E25/BalSheet!E15 -> 0.038687469 | F23: =E23 -> 0.038687469 | G23: =F23 -> 0.038687469 | H23: =G23 -> 0.038687469 | I23: =H23 -> 0.038687469 | J23: =I23 -> 0.038687469 | K23: =J23 -> 0.038687469 | L23: =K23 -> 0.038687469 | M23: =L23 -> 0.038687469 | ... U23: =T23 -> 0.038687469
B25: Issuance of long-term debt | F25: 0 | G25: 0 | H25: 0 | I25: 0 | J25: 0 | K25: 0 | L25: 0 | M25: 0 | N25: 0 | O25: 0 | P25: 0 | Q25: 0 | R25: 0 | S25: 0 | T25: 0 | U25: 0
B26: Repayment of long-term debt | F26: 0 | G26: 0 | H26: 0 | I26: 0 | J26: 0 | K26: 0 | L26: 0 | M26: 0 | N26: 0 | O26: 0 | P26: 0 | Q26: 0 | R26: 0 | S26: 0 | T26: 0 | U26: 0
A28: * | B28: Calcs | C28: 44926 | D28: 45291 | E28: 45657 | F28: 46022 | G28: 46387 | H28: 46752 | I28: 47118 | J28: 47483 | K28: 2030 | L28: =K28+1 -> 2031 | M28: =L28+1 -> 2032 | N28: =M28+1 -> 2033 | O28: =N28+1 -> 2034 | P28: =O28+1 -> 2035 | Q28: =P28+1 -> 2036 | R28: =Q28+1 -> 2037 | S28: =R28+1 -> 2038 | ... U28: =T28+1 -> 2040
B30: CapEx % of Sales | C30: =12.624/IncState!C14 -> 0.0066237432 | D30: =15.114/IncState!D14 -> 0.0067927724 | E30: =40.027/IncState!E14 -> 0.013968558 | F30: =E30 -> 0.013968558 | G30: =F30 -> 0.013968558 | H30: =G30 -> 0.013968558 | I30: =H30 -> 0.013968558 | J30: =I30 -> 0.013968558 | K30: =J30 -> 0.013968558 | L30: =K30 -> 0.013968558 | M30: =L30 -> 0.013968558 | ... U30: =T30 -> 0.013968558
B31: Depreciation % of beginning PP&E | D31: =IncState!D20/BalSheet!C20 -> 0.12380387 | E31: =IncState!E20/BalSheet!D20 -> 0.13696498 | F31: =E31 -> 0.13696498 | G31: =F31 -> 0.13696498 | H31: =G31 -> 0.13696498 | I31: =H31 -> 0.13696498 | J31: =I31 -> 0.13696498 | K31: =J31 -> 0.13696498 | L31: =K31 -> 0.13696498 | M31: =L31 -> 0.13696498 | ... U31: =T31 -> 0.13696498
B32: Share issuance / (repurchases) | F32: 0 | G32: 0 | H32: 0 | I32: 0 | J32: 0 | K32: 0 | L32: 0 | M32: 0 | N32: 0 | O32: 0 | P32: 0 | Q32: 0 | R32: 0 | S32: 0 | T32: 0 | U32: 0
A34: * | B34: Shareholder information | C34: 44926 | D34: 45291 | E34: 45657 | F34: 46022 | G34: 46387 | H34: 46752 | I34: 47118 | J34: 47483 | K34: 2030 | L34: =K34+1 -> 2031 | M34: =L34+1 -> 2032 | N34: =M34+1 -> 2033 | O34: =N34+1 -> 2034 | P34: =O34+1 -> 2035 | Q34: =P34+1 -> 2036 | R34: =Q34+1 -> 2037 | S34: =R34+1 -> 2038 | ... U34: =T34+1 -> 2040
B36: Basic WASO | C36: =C16 -> 2063.793 | D36: =D16 -> 2147.446 | E36: =E16 -> 2250.163 | F36: =F16 -> 2250.163 | G36: =G16 -> 2250.163 | H36: =H16 -> 2250.163 | I36: =I16 -> 2250.163 | J36: =J16 -> 2250.163 | ... U36: =U16 -> 2250.163
B37: Diluted WASO | C37: =C17 -> 2063.793 | D37: =D17 -> 2297.927 | E37: =E17 -> 2450.818 | F37: =F17 -> 2450.818 | G37: =G17 -> 2450.818 | H37: =H17 -> 2450.818 | I37: =I17 -> 2450.818 | J37: =J17 -> 2450.818 | ... U37: =U17 -> 2450.818
A39: * | B39: Balance Sheet - Assets | C39: 44926 | D39: 45291 | E39: 45657 | F39: 46022 | G39: 46387 | H39: 46752 | I39: 47118 | J39: 47483 | K39: 2030 | L39: =K39+1 -> 2031 | M39: =L39+1 -> 2032 | N39: =M39+1 -> 2033 | O39: =N39+1 -> 2034 | P39: =O39+1 -> 2035 | Q39: =P39+1 -> 2036 | R39: =Q39+1 -> 2037 | S39: =R39+1 -> 2038 | ... U39: =T39+1 -> 2040
B41: Operating Cash % of sales | C41: =BalSheet!C14/IncState!C14 -> 0.05 | D41: =BalSheet!D14/IncState!D14 -> 0.05 | E41: =BalSheet!E14/IncState!E14 -> 0.05 | F41: =E41 -> 0.05 | G41: =F41 -> 0.05 | H41: =G41 -> 0.05 | I41: =H41 -> 0.05 | J41: =I41 -> 0.05 | K41: =J41 -> 0.05 | L41: =K41 -> 0.05 | M41: =L41 -> 0.05 | ... U41: =T41 -> 0.05
B42: Accounts receivable % of sales | C42: =BalSheet!C16/IncState!C14 -> 0.13555272 | D42: =BalSheet!D16/IncState!D14 -> 0.16394698 | E42: =BalSheet!E16/IncState!E14 -> 0.20067932 | F42: =E42 -> 0.20067932 | G42: =F42 -> 0.20067932 | H42: =G42 -> 0.20067932 | I42: =H42 -> 0.20067932 | J42: =I42 -> 0.20067932 | K42: =J42 -> 0.20067932 | L42: =K42 -> 0.20067932 | M42: =L42 -> 0.20067932 | ... U42: =T42 -> 0.20067932
B43: Other current assets % of sales | C43: =BalSheet!C17/IncState!C14 -> 0.078476455 | D43: =BalSheet!D17/IncState!D14 -> 0.044788522 | E43: =BalSheet!E17/IncState!E14 -> 0.045106852 | F43: =E43 -> 0.045106852 | G43: =F43 -> 0.045106852 | H43: =G43 -> 0.045106852 | I43: =H43 -> 0.045106852 | J43: =I43 -> 0.045106852 | K43: =J43 -> 0.045106852 | L43: =K43 -> 0.045106852 | M43: =L43 -> 0.045106852 | ... U43: =T43 -> 0.045106852
B44: Other long-term assets % of sales | C44: =BalSheet!C21/IncState!C14 -> 0.078836396 | D44: =BalSheet!D21/IncState!D14 -> 0.068847269 | E44: =BalSheet!E21/IncState!E14 -> 0.05800614 | F44: =E44 -> 0.05800614 | G44: =F44 -> 0.05800614 | H44: =G44 -> 0.05800614 | I44: =H44 -> 0.05800614 | J44: =I44 -> 0.05800614 | K44: =J44 -> 0.05800614 | L44: =K44 -> 0.05800614 | M44: =L44 -> 0.05800614 | ... U44: =T44 -> 0.05800614
A46: * | B46: Balance Sheet - Liabilities | C46: 44926 | D46: 45291 | E46: 45657 | F46: 46022 | G46: 46387 | H46: 46752 | I46: 47118 | J46: 47483 | K46: 2030 | L46: =K46+1 -> 2031 | M46: =L46+1 -> 2032 | N46: =M46+1 -> 2033 | O46: =N46+1 -> 2034 | P46: =O46+1 -> 2035 | Q46: =P46+1 -> 2036 | R46: =Q46+1 -> 2037 | S46: =R46+1 -> 2038 | ... U46: =T46+1 -> 2040
B48: Accounts payable % of COGS | C48: =BalSheet!C27/IncState!C15 -> 0.53238053 | D48: =BalSheet!D27/IncState!D15 -> 0.54537294 | E48: =BalSheet!E27/IncState!E15 -> 0.75469355 | F48: =E48 -> 0.75469355 | G48: =F48 -> 0.75469355 | H48: =G48 -> 0.75469355 | I48: =H48 -> 0.75469355 | J48: =I48 -> 0.75469355 | K48: =J48 -> 0.75469355 | L48: =K48 -> 0.75469355 | M48: =L48 -> 0.75469355 | ... U48: =T48 -> 0.75469355
B49: Other current liabilities % of sales | C49: =BalSheet!C28/IncState!C14 -> 0.19436678 | D49: =BalSheet!D28/IncState!D14 -> 0.22961899 | E49: =BalSheet!E28/IncState!E14 -> 0.19852298 | F49: =E49 -> 0.19852298 | G49: =F49 -> 0.19852298 | H49: =G49 -> 0.19852298 | I49: =H49 -> 0.19852298 | J49: =I49 -> 0.19852298 | K49: =J49 -> 0.19852298 | L49: =K49 -> 0.19852298 | M49: =L49 -> 0.19852298 | ... U49: =T49 -> 0.19852298
B50: Other long-term liabilities % of sales | C50: =BalSheet!C32/IncState!C14 -> 0.12113149 | D50: =BalSheet!D32/IncState!D14 -> 0.096827343 | E50: =BalSheet!E32/IncState!E14 -> 0.087404777 | F50: =E50 -> 0.087404777 | G50: =F50 -> 0.087404777 | H50: =G50 -> 0.087404777 | I50: =H50 -> 0.087404777 | J50: =I50 -> 0.087404777 | K50: =J50 -> 0.087404777 | L50: =K50 -> 0.087404777 | M50: =L50 -> 0.087404777 | ... U50: =T50 -> 0.087404777

Sheet Revenue
A1: =CoName -> Palantir Technologies Inc
A2: Revenues | C2: 2019 | D2: 2020 | E2: 2021 | F2: 2022 | G2: Q123 | H2: Q223 | I2: Q323 | J2: Q423 | K2: 2023 | L2: Q124 | M2: Q224 | N2: Q324 | O2: Q424 | P2: 2024 | Q2: Q125 | R2: Q225 | S2: Q325 | T2: Q425 | U2: 2025 | V2: Q126 | W2: Q226 | X2: Q326 | Y2: Q426 | Z2: =U2+1 -> 2026 | AA2: =Z2+1 -> 2027 | AB2: =AA2+1 -> 2028 | AC2: =AB2+1 -> 2029 | AD2: =AC2+1 -> 2030 | AE2: =AD2+1 -> 2031 | AF2: =AE2+1 -> 2032 | AG2: =AF2+1 -> 2033 | AH2: =AG2+1 -> 2034 | ... AN2: =AM2+1 -> 2040
A3: * | B3: TOTAL REVENUE | C3: 742.555 | D3: 1092.673 | E3: 1541.889 | F3: 1905.871 | G3: 525.2 | H3: 533.3 | I3: 558.2 | J3: 608.4 | K3: =SUM(G3:J3) -> 2225.1 | L3: 634.1 | M3: 678.1 | N3: 725.5 | O3: 827.5 | P3: =SUM(L3:O3) -> 2865.2 | Q3: 883.9 | R3: 1003.7 | S3: 1181.1 | T3: 1310 | U3: =SUM(Q3:T3) -> 4378.7 | V3: =Q3*(1+V4) -> 1344.6708 | W3: =R3*(1+W4) -> 1526.9217 | X3: =S3*(1+X4) -> 1796.799 | Y3: =T3*(1+Y4) -> 1992.8937 | Z3: =SUM(V3:Y3) -> 6661.2852 | AA3: =Z3*(1+AA4) -> 9459.025 | AB3: =AA3*(1+AB4) -> 13384.52 | AC3: =AB3*(1+AC4) -> 18872.174 | AD3: =AC3*(1+AD4) -> 26515.404 | AE3: =AD3*(1+AE4) -> 37121.566 | AF3: =AE3*(1+AF4) -> 51784.584 | AG3: =AF3*(1+AG4) -> 71980.572 | AH3: =AG3*(1+AH4) -> 99693.093 | ... AN3: =AM3*(1+AN4) -> 651895.94
B4: y/y | C4: =C3/595.4-1 -> 0.24715317 | D4: =D3/C3-1 -> 0.47150447 | E4: =E3/D3-1 -> 0.41111659 | F4: =F3/E3-1 -> 0.23606239 | G4: =G3/432.9-1 -> 0.21321321 | H4: =H3/473-1 -> 0.12748414 | I4: =I3/477.9-1 -> 0.16802678 | J4: =J3/508.6-1 -> 0.19622493 | K4: =K3/F3-1 -> 0.1674977 | L4: =L3/G3-1 -> 0.20734958 | M4: =M3/H3-1 -> 0.27151697 | N4: =N3/I3-1 -> 0.29971336 | O4: =O3/J3-1 -> 0.36012492 | P4: =P3/K3-1 -> 0.28767246 | Q4: =Q3/L3-1 -> 0.39394417 | R4: =R3/M3-1 -> 0.48016517 | ... U4: =U3/P3-1 -> 0.52823538 | V4: =AVERAGE(Q4:T4) -> 0.5212929 | W4: =V4 -> 0.5212929 | X4: =W4 -> 0.5212929 | Y4: =X4 -> 0.5212929 | Z4: =Z3/U3-1 -> 0.5212929 | AA4: 0.42 | AB4: =AA4-0.005 -> 0.415 | AC4: =AB4-0.005 -> 0.41 | AD4: =AC4-0.005 -> 0.405 | AE4: =AD4-0.005 -> 0.4 | AF4: =AE4-0.005 -> 0.395 | AG4: =AF4-0.005 -> 0.39 | AH4: =AG4-0.005 -> 0.385 | AI4: =AH4-0.005 -> 0.38 | ... AN4: =AM4-0.005 -> 0.355
B5: q/q | G5: =G3/508.6-1 -> 0.032638616 | H5: =H3/G3-1 -> 0.015422696 | I5: =I3/H3-1 -> 0.046690418 | J5: =J3/I3-1 -> 0.089931924 | L5: =L3/J3-1 -> 0.042241946 | M5: =M3/L3-1 -> 0.069389686 | N5: =N3/M3-1 -> 0.069901195 | O5: =O3/N3-1 -> 0.14059269 | Q5: =Q3/L3-1 -> 0.39394417 | R5: =R3/Q3-1 -> 0.13553569 | S5: =S3/R3-1 -> 0.17674604 | T5: =T3/S3-1 -> 0.10913555 | V5: =V3/Q3-1 -> 0.5212929 | W5: =W3/V3-1 -> 0.13553569 | X5: =X3/W3-1 -> 0.17674604 | Y5: =Y3/X3-1 -> 0.10913555

Sheet Calcs
A1: =CoName -> Palantir Technologies Inc | C1: Hist. | D1: Hist. | E1: Hist. | F1: Proj. | G1: Proj. | H1: Proj. | I1: Proj. | J1: Proj. | K1: Proj. | L1: Proj. | M1: Proj. | N1: Proj. | O1: Proj. | P1: Proj. | Q1: Proj. | R1: Proj. | S1: Proj. | T1: Proj. | U1: Proj.
A2: Net PP&E | C2: 2022 | D2: =C2+1 -> 2023 | E2: =D2+1 -> 2024 | F2: =E2+1 -> 2025 | G2: =F2+1 -> 2026 | H2: =G2+1 -> 2027 | I2: =H2+1 -> 2028 | J2: =I2+1 -> 2029 | K2: =J2+1 -> 2030 | ... U2: =T2+1 -> 2040
B3: Capital expenditure % of sales | F3: =Assumptions!F30 -> 0.013968558 | G3: =Assumptions!G30 -> 0.013968558 | H3: =Assumptions!H30 -> 0.013968558 | I3: =Assumptions!I30 -> 0.013968558 | J3: =Assumptions!J30 -> 0.013968558 | K3: =Assumptions!K30 -> 0.013968558 | L3: =Assumptions!L30 -> 0.013968558 | M3: =Assumptions!M30 -> 0.013968558 | ... U3: =Assumptions!U30 -> 0.013968558
B4: Depreciation % of PP&E | F4: =Assumptions!F31 -> 0.13696498 | G4: =F4 -> 0.13696498 | H4: =G4 -> 0.13696498 | I4: =H4 -> 0.13696498 | J4: =I4 -> 0.13696498 | K4: =J4 -> 0.13696498 | L4: =K4 -> 0.13696498 | M4: =L4 -> 0.13696498 | N4: =M4 -> 0.13696498 | ... U4: =T4 -> 0.13696498
B6: Beginning PP&E | F6: =E9 -> 240.378 | G6: =F9 -> 268.62531 | H6: =G9 -> 324.89157 | I6: =H9 -> 412.5359 | J6: =I9 -> 543.01541 | K6: =J9 -> 732.28661 | L6: =K9 -> 1002.4106 | M6: =L9 -> 1383.7058 | ... U6: =T9 -> 18213.933
B7: Capex | F7: =F3*IncState!F14 -> 61.170677 | G7: =G3*IncState!G14 -> 93.058517 | H7: =H3*IncState!H14 -> 132.14309 | I7: =I3*IncState!I14 -> 186.98248 | J7: =J3*IncState!J14 -> 263.6453 | K7: =K3*IncState!K14 -> 370.42164 | L7: =L3*IncState!L14 -> 518.5903 | M7: =M3*IncState!M14 -> 723.43346 | ... U7: =U3*IncState!U14 -> 9107.0218
B8: Depreciation | F8: =F4*F6 -> 32.923367 | G8: =G4*G6 -> 36.792259 | H8: =H4*H6 -> 44.498766 | I8: =I4*I6 -> 56.50297 | J8: =J4*J6 -> 74.374093 | K8: =K4*K6 -> 100.29762 | L8: =L4*L6 -> 137.29515 | M8: =M4*M6 -> 189.51923 | ... U8: =U4*U6 -> 2494.6709
B9: Ending PP&E | E9: =BalSheet!E20 -> 240.378 | F9: =F6+F7-F8 -> 268.62531 | G9: =G6+G7-G8 -> 324.89157 | H9: =H6+H7-H8 -> 412.5359 | I9: =I6+I7-I8 -> 543.01541 | J9: =J6+J7-J8 -> 732.28661 | K9: =K6+K7-K8 -> 1002.4106 | L9: =L6+L7-L8 -> 1383.7058 | M9: =M6+M7-M8 -> 1917.62 | ... U9: =U6+U7-U8 -> 24826.284
A10: Equity | C10: =C2 -> 2022 | D10: =D2 -> 2023 | E10: =E2 -> 2024 | F10: =F2 -> 2025 | G10: =G2 -> 2026 | H10: =H2 -> 2027 | I10: =I2 -> 2028 | J10: =J2 -> 2029 | ... U10: =U2 -> 2040
B11: Share issuance/(repurchases) | F11: =Assumptions!F32 -> 0 | G11: =Assumptions!G32 -> 0 | H11: =Assumptions!H32 -> 0 | I11: =Assumptions!I32 -> 0 | J11: =Assumptions!J32 -> 0 | K11: =Assumptions!K32 -> 0 | L11: =Assumptions!L32 -> 0 | M11: =Assumptions!M32 -> 0 | ... U11: =Assumptions!U32 -> 0
B13: Beginning balance | F13: =E16 -> 5094.407 | G13: =F16 -> 5550.7139 | H13: =G16 -> 6383.3934 | I13: =H16 -> 7762.4724 | J13: =I16 -> 9992.1633 | K13: =J16 -> 13528.422 | L13: =K16 -> 19048.18 | M13: =L16 -> 26833.014 | ... U13: =T16 -> 386848.32
B14: Net income | F14: =IncState!F31 -> 456.30694 | G14: =IncState!G31 -> 832.67947 | H14: =IncState!H31 -> 1379.079 | I14: =IncState!I31 -> 2229.6908 | J14: =IncState!J31 -> 3536.2586 | K14: =IncState!K31 -> 5519.7577 | L14: =IncState!L31 -> 7784.8341 | M14: =IncState!M31 -> 10939.6 | ... U14: =IncState!U31 -> 145746.58
B15: Share issuance / (repurchase) | F15: =F11 -> 0 | G15: =G11 -> 0 | H15: =H11 -> 0 | I15: =I11 -> 0 | J15: =J11 -> 0 | K15: =K11 -> 0 | L15: =L11 -> 0 | M15: =M11 -> 0 | ... U15: =U11 -> 0
B16: Ending balance | E16: =BalSheet!E35 -> 5094.407 | F16: =SUM(F13:F15) -> 5550.7139 | G16: =SUM(G13:G15) -> 6383.3934 | H16: =SUM(H13:H15) -> 7762.4724 | I16: =SUM(I13:I15) -> 9992.1633 | J16: =SUM(J13:J15) -> 13528.422 | K16: =SUM(K13:K15) -> 19048.18 | L16: =SUM(L13:L15) -> 26833.014 | M16: =SUM(M13:M15) -> 37772.614 | ... U16: =SUM(U13:U15) -> 532594.9
A17: OWC | C17: =C10 -> 2022 | D17: =D10 -> 2023 | E17: =E10 -> 2024 | F17: =F10 -> 2025 | G17: =G10 -> 2026 | H17: =H10 -> 2027 | I17: =I10 -> 2028 | J17: =J10 -> 2029 | ... U17: =U10 -> 2040
B18: Operating Cash | E18: =BalSheet!E14 -> 143.27535 | F18: =BalSheet!F14 -> 218.95846 | G18: =BalSheet!G14 -> 333.09995 | H18: =BalSheet!H14 -> 473.00193 | I18: =BalSheet!I14 -> 669.29773 | J18: =BalSheet!J14 -> 943.7098 | K18: =BalSheet!K14 -> 1325.9123 | L18: =BalSheet!L14 -> 1856.2772 | ... U18: =BalSheet!U14 -> 32598.289
B19: =BalSheet!B16 -> Accounts receivable | E19: =BalSheet!E16 -> 575.048 | F19: =BalSheet!F16 -> 878.8087 | G19: =BalSheet!G16 -> 1336.9254 | H19: =BalSheet!H16 -> 1898.4341 | I19: =BalSheet!I16 -> 2686.2843 | J19: =BalSheet!J16 -> 3787.6608 | K19: =BalSheet!K16 -> 5321.6635 | L19: =BalSheet!L16 -> 7450.3288 | ... U19: =BalSheet!U16 -> 130836.05
B20: Other current assets | E20: =BalSheet!E17 -> 129.254 | F20: =BalSheet!F17 -> 197.53054 | G20: =BalSheet!G17 -> 300.5018 | H20: =BalSheet!H17 -> 426.71256 | I20: =BalSheet!I17 -> 603.79827 | J20: =BalSheet!J17 -> 851.35556 | K20: =BalSheet!K17 -> 1196.1546 | L20: =BalSheet!L17 -> 1674.6164 | ... U20: =BalSheet!U17 -> 29408.124
B21: Accounts payables | E21: =BalSheet!E27 -> 427.149 | F21: =BalSheet!F27 -> 649.47928 | G21: =BalSheet!G27 -> 983.02046 | H21: =BalSheet!H27 -> 1388.7496 | I21: =BalSheet!I27 -> 1954.9784 | J21: =BalSheet!J27 -> 2742.2753 | K21: =BalSheet!K27 -> 3832.8837 | L21: =BalSheet!L27 -> 5338.0188 | ... U21: =BalSheet!U27 -> 89313.231
B22: Other current liabilities | E22: =BalSheet!E28 -> 568.869 | F22: =BalSheet!F28 -> 869.36573 | G22: =BalSheet!G28 -> 1322.5599 | H22: =BalSheet!H28 -> 1878.0351 | I22: =BalSheet!I28 -> 2657.4196 | J22: =BalSheet!J28 -> 3746.9617 | K22: =BalSheet!K28 -> 5264.4812 | L22: =BalSheet!L28 -> 7370.2736 | ... U22: =BalSheet!U28 -> 129430.19
A23: * | B23: OWC | E23: =SUM(E18:E20)-SUM(E21:E22) -> -148.44065 | F23: =SUM(F18:F20)-SUM(F21:F22) -> -223.54732 | G23: =SUM(G18:G20)-SUM(G21:G22) -> -335.05319 | H23: =SUM(H18:H20)-SUM(H21:H22) -> -468.6361 | I23: =SUM(I18:I20)-SUM(I21:I22) -> -653.01778 | J23: =SUM(J18:J20)-SUM(J21:J22) -> -906.51084 | K23: =SUM(K18:K20)-SUM(K21:K22) -> -1253.6346 | L23: =SUM(L18:L20)-SUM(L21:L22) -> -1727.07 | ... U23: =SUM(U18:U20)-SUM(U21:U22) -> -25900.959
B24: Change in OWC | F24: =E23-F23 -> 75.106672 | G24: =F23-G23 -> 111.50586 | H24: =G23-H23 -> 133.58291 | I24: =H23-I23 -> 184.38169 | J24: =I23-J23 -> 253.49306 | K24: =J23-K23 -> 347.12374 | L24: =K23-L23 -> 473.43542 | M24: =L23-M23 -> 643.10697 | ... U24: =T23-U23 -> 6422.735

Sheet Debt
A1: =CoName -> Palantir Technologies Inc | C1: Hist. | D1: Hist. | E1: Hist. | F1: Proj. | G1: Proj. | H1: Proj. | I1: Proj. | J1: Proj. | K1: Proj. | L1: Proj. | M1: Proj. | N1: Proj. | O1: Proj. | P1: Proj. | Q1: Proj. | R1: Proj. | S1: Proj. | T1: Proj. | U1: Proj.
A2: Assumptions | C2: 44926 | D2: 45291 | E2: 45657 | F2: 46022 | G2: 46387 | H2: 46752 | I2: 47118 | J2: 47483 | K2: =2030 -> 2030 | L2: =K2+1 -> 2031 | M2: =L2+1 -> 2032 | N2: =M2+1 -> 2033 | O2: =N2+1 -> 2034 | P2: =O2+1 -> 2035 | Q2: =P2+1 -> 2036 | R2: =Q2+1 -> 2037 | S2: =R2+1 -> 2038 | ... U2: =T2+1 -> 2040
B4: Interest rate on revolver | F4: =Assumptions!F21 -> 0 | G4: =Assumptions!G21 -> 0 | H4: =Assumptions!H21 -> 0 | I4: =Assumptions!I21 -> 0 | J4: =Assumptions!J21 -> 0 | K4: =Assumptions!K21 -> 0 | L4: =Assumptions!L21 -> 0 | M4: =Assumptions!M21 -> 0 | ... U4: =Assumptions!U21 -> 0
B5: Interest rate on long-term debt | F5: =Assumptions!F22 -> 0 | G5: =Assumptions!G22 -> 0 | H5: =Assumptions!H22 -> 0 | I5: =Assumptions!I22 -> 0 | J5: =Assumptions!J22 -> 0 | K5: =Assumptions!K22 -> 0 | L5: =Assumptions!L22 -> 0 | M5: =Assumptions!M22 -> 0 | ... U5: =Assumptions!U22 -> 0
B6: Interest rate on cash | F6: =Assumptions!F23 -> 0.038687469 | G6: =Assumptions!G23 -> 0.038687469 | H6: =Assumptions!H23 -> 0.038687469 | I6: =Assumptions!I23 -> 0.038687469 | J6: =Assumptions!J23 -> 0.038687469 | K6: =Assumptions!K23 -> 0.038687469 | L6: =Assumptions!L23 -> 0.038687469 | M6: =Assumptions!M23 -> 0.038687469 | ... U6: =Assumptions!U23 -> 0.038687469
B8: Issuance of long-term debt | F8: =Assumptions!F25 -> 0 | G8: =Assumptions!G25 -> 0 | H8: =Assumptions!H25 -> 0 | I8: =Assumptions!I25 -> 0 | J8: =Assumptions!J25 -> 0 | K8: =Assumptions!K25 -> 0 | L8: =Assumptions!L25 -> 0 | M8: =Assumptions!M25 -> 0 | ... U8: =Assumptions!U25 -> 0
B9: Repayment of long-term debt | F9: =Assumptions!F26 -> 0 | G9: =Assumptions!G26 -> 0 | H9: =Assumptions!H26 -> 0 | I9: =Assumptions!I26 -> 0 | J9: =Assumptions!J26 -> 0 | K9: =Assumptions!K26 -> 0 | L9: =Assumptions!L26 -> 0 | M9: =Assumptions!M26 -> 0 | ... U9: =Assumptions!U26 -> 0
A11: Revolver | C11: =C2 -> 44926 | D11: =D2 -> 45291 | E11: =E2 -> 45657 | F11: =F2 -> 46022 | G11: =G2 -> 46387 | H11: =H2 -> 46752 | I11: =I2 -> 47118 | J11: =J2 -> 47483 | ... U11: =U2 -> 2040
B12: Balance
B13: Interest rate
B14: Interest expense
A16: Long term debt | C16: =C11 -> 44926 | D16: =D11 -> 45291 | E16: =E11 -> 45657 | F16: =F11 -> 46022 | G16: =G11 -> 46387 | H16: =H11 -> 46752 | I16: =I11 -> 47118 | J16: =J11 -> 47483 | ... U16: =U11 -> 2040
B17: Beginning balance
B18: Issuance
B19: Repayment
B20: Ending balance
B21: Interest rate
B22: Interest expense
A24: Debt summary | C24: =C16 -> 44926 | D24: =D16 -> 45291 | E24: =E16 -> 45657 | F24: =F16 -> 46022 | G24: =G16 -> 46387 | H24: =H16 -> 46752 | I24: =I16 -> 47118 | J24: =J16 -> 47483 | ... U24: =U16 -> 2040
B25: Revolver
B26: Total long term debt
B27: Total debt
B28: Total interest expense
A30: Interest income | C30: =C11 -> 44926 | D30: =D11 -> 45291 | E30: =E11 -> 45657 | F30: =F11 -> 46022 | G30: =G11 -> 46387 | H30: =H11 -> 46752 | I30: =I11 -> 47118 | J30: =J11 -> 47483 | ... U30: =U11 -> 2040
B31: Excess Cash | F31: =BalSheet!F15 -> 5634.3776 | G31: =BalSheet!G15 -> 6589.4087 | H31: =BalSheet!H15 -> 8096.6849 | I31: =BalSheet!I15 -> 10495.694 | J31: =BalSheet!J15 -> 14257.522 | K31: =BalSheet!K15 -> 20079.004 | L31: =BalSheet!L15 -> 28267.818 | M31: =BalSheet!M15 -> 39747.73 | ... U31: =BalSheet!U15 -> 552836.48
B32: Interest rate | F32: =F6 -> 0.038687469 | G32: =G6 -> 0.038687469 | H32: =H6 -> 0.038687469 | I32: =I6 -> 0.038687469 | J32: =J6 -> 0.038687469 | K32: =K6 -> 0.038687469 | L32: =L6 -> 0.038687469 | M32: =M6 -> 0.038687469 | ... U32: =U6 -> 0.038687469
B33: Interest income | F33: =F31*F32 -> 217.97981 | G33: =G31*G32 -> 254.92755 | H33: =H31*H32 -> 313.24025 | I33: =I31*I32 -> 406.05186 | J33: =J31*J32 -> 551.58743 | K33: =K31*K32 -> 776.80584 | L33: =L31*L32 -> 1093.6103 | M33: =M31*M32 -> 1537.7391 | ... U33: =U31*U32 -> 21387.844

Sheet IncState
A1: =CoName -> Palantir Technologies Inc | C1: Hist. | D1: Hist. | E1: Hist. | F1: Proj. | G1: Proj. | H1: Proj. | I1: Proj. | J1: Proj. | K1: Proj. | L1: Proj. | M1: Proj.
A2: Assumptions | C2: 44926 | D2: 45291 | E2: 45657 | F2: 46022 | G2: 46387 | H2: 46752 | I2: 47118 | J2: 47483 | K2: 2030 | L2: 2031 | M2: 2032 | N2: =M2+1 -> 2033 | O2: =N2+1 -> 2034 | P2: =O2+1 -> 2035 | Q2: =P2+1 -> 2036 | R2: =Q2+1 -> 2037 | S2: =R2+1 -> 2038 | T2: =S2+1 -> 2039 | U2: =T2+1 -> 2040
B4: Revenue growth | F4: =Assumptions!F10 -> 0.52823538 | G4: =Assumptions!G10 -> 0.5212929 | H4: =Assumptions!H10 -> 0.42 | I4: =Assumptions!I10 -> 0.415 | J4: =Assumptions!J10 -> 0.41 | K4: =Assumptions!K10 -> 0.405 | L4: =Assumptions!L10 -> 0.4 | M4: =Assumptions!M10 -> 0.395 | ... U4: =Assumptions!U10 -> 0.355
B5: Cost of goods sold as % of sales | F5: =Assumptions!F11 -> 0.19651828 | G5: =Assumptions!G11 -> 0.19551828 | H5: =Assumptions!H11 -> 0.19451828 | I5: =Assumptions!I11 -> 0.19351828 | J5: =Assumptions!J11 -> 0.19251828 | K5: =Assumptions!K11 -> 0.19151828 | L5: =Assumptions!L11 -> 0.19051828 | M5: =Assumptions!M11 -> 0.18951828 | ... U5: =Assumptions!U11 -> 0.18151828
B6: R&D % of sales | F6: =Assumptions!F12 -> 0.17623844 | G6: =Assumptions!G12 -> 0.17523844 | H6: =Assumptions!H12 -> 0.17423844 | I6: =Assumptions!I12 -> 0.17323844 | J6: =Assumptions!J12 -> 0.17223844 | K6: =Assumptions!K12 -> 0.17123844 | L6: =Assumptions!L12 -> 0.17023844 | M6: =Assumptions!M12 -> 0.16923844 | ... U6: =Assumptions!U12 -> 0.16123844
B7: SG&A % of sales | F7: =Assumptions!F13 -> 0.49191934 | G7: =Assumptions!G13 -> 0.46691934 | H7: =Assumptions!H13 -> 0.44191934 | I7: =Assumptions!I13 -> 0.41691934 | J7: =Assumptions!J13 -> 0.39191934 | K7: =Assumptions!K13 -> 0.36691934 | L7: =Assumptions!L13 -> 0.36691934 | M7: =Assumptions!M13 -> 0.36691934 | ... U7: =Assumptions!U13 -> 0.36691934
B8: Other income (expense), amt | F8: =Assumptions!F14 -> 0 | G8: =Assumptions!G14 -> 0 | H8: =Assumptions!H14 -> 0 | I8: =Assumptions!I14 -> 0 | J8: =Assumptions!J14 -> 0 | K8: =Assumptions!K14 -> 0 | L8: =Assumptions!L14 -> 0 | M8: =Assumptions!M14 -> 0 | ... U8: =Assumptions!U14 -> 0
B9: Effective tax rate | F9: =Assumptions!F15 -> 0.23 | G9: =Assumptions!G15 -> 0.23 | H9: =Assumptions!H15 -> 0.23 | I9: =Assumptions!I15 -> 0.23 | J9: =Assumptions!J15 -> 0.23 | K9: =Assumptions!K15 -> 0.23 | L9: =Assumptions!L15 -> 0.23 | M9: =Assumptions!M15 -> 0.23 | ... U9: =Assumptions!U15 -> 0.23
B10: Basic WASO | F10: =Assumptions!F16 -> 2250.163 | G10: =Assumptions!G16 -> 2250.163 | H10: =Assumptions!H16 -> 2250.163 | I10: =Assumptions!I16 -> 2250.163 | J10: =Assumptions!J16 -> 2250.163 | K10: =Assumptions!K16 -> 2250.163 | L10: =Assumptions!L16 -> 2250.163 | M10: =Assumptions!M16 -> 2250.163 | ... U10: =Assumptions!U16 -> 2250.163
B11: Diluted WASO | F11: =Assumptions!F17 -> 2450.818 | G11: =Assumptions!G17 -> 2450.818 | H11: =Assumptions!H17 -> 2450.818 | I11: =Assumptions!I17 -> 2450.818 | J11: =Assumptions!J17 -> 2450.818 | K11: =Assumptions!K17 -> 2450.818 | L11: =Assumptions!L17 -> 2450.818 | M11: =Assumptions!M17 -> 2450.818 | ... U11: =Assumptions!U17 -> 2450.818
A13: Income statement | C13: =C33 -> 44926 | D13: =D33 -> 45291 | E13: =E33 -> 45657 | F13: =F33 -> 46022 | G13: =G33 -> 46022 | H13: =H33 -> 46022 | I13: =I33 -> 46022 | J13: =J33 -> 46022 | ... U13: =U33 -> 46022
B14: Revenue | C14: 1905.871 | D14: 2225.012 | E14: 2865.507 | F14: =E14*(1+F4) -> 4379.1692 | G14: =F14*(1+G4) -> 6661.999 | H14: =G14*(1+H4) -> 9460.0386 | I14: =H14*(1+I4) -> 13385.955 | J14: =I14*(1+J4) -> 18874.196 | K14: =J14*(1+K4) -> 26518.245 | L14: =K14*(1+L4) -> 37125.543 | M14: =L14*(1+M4) -> 51790.133 | ... U14: =T14*(1+U4) -> 651965.79
B15: COGS | C15: 408.548 | D15: 431.105 | E15: 565.99 | F15: =F14*F5 -> 860.58677 | G15: =G14*G5 -> 1302.5425 | H15: =H14*H5 -> 1840.1504 | I15: =I14*I5 -> 2590.4268 | J15: =J14*J5 -> 3633.6276 | K15: =K14*K5 -> 5078.7286 | L15: =L14*L5 -> 7073.0945 | M15: =M14*M5 -> 9815.1767 | ... U15: =U14*U5 -> 118343.71
B16: R&D | C16: 359.679 | D16: 404.624 | E16: 507.878 | F16: =F14*F6 -> 771.77796 | G16: =G14*G6 -> 1167.4383 | H16: =H14*H6 -> 1648.3024 | I16: =I14*I6 -> 2318.9619 | J16: =J14*J6 -> 3250.8621 | K16: =K14*K6 -> 4540.943 | L16: =L14*L6 -> 6320.1947 | M16: =M14*M6 -> 8764.8815 | ... U16: =U14*U6 -> 105121.95
B17: SG&A | C17: =702.511+596.333 -> 1298.844 | D17: =744.992+524.325 -> 1269.317 | E17: =887.755+593.481 -> 1481.236 | F17: =F7*F14 -> 2154.198 | G17: =G7*G14 -> 3110.6162 | H17: =H7*H14 -> 4180.574 | I17: =I7*I14 -> 5580.8634 | J17: =J7*J14 -> 7397.1625 | K17: =K7*K14 -> 9730.0572 | L17: =L7*L14 -> 13622.08 | M17: =M7*M14 -> 19002.802 | ... U17: =U7*U14 -> 239218.86
A18: * | B18: EBIT | C18: =C14-SUM(C15:C17) -> -161.2 | D18: =D14-SUM(D15:D17) -> 119.966 | E18: =E14-SUM(E15:E17) -> 310.403 | F18: =F14-SUM(F15:F17) -> 592.60641 | G18: =G14-SUM(G15:G17) -> 1081.4019 | H18: =H14-SUM(H15:H17) -> 1791.0117 | I18: =I14-SUM(I15:I17) -> 2895.7024 | J18: =J14-SUM(J15:J17) -> 4592.5437 | ... U18: =U14-SUM(U15:U17) -> 189281.27
B20: Depreciation | C20: 22.522 | D20: 33.354 | E20: 31.587 | F20: =Calcs!F8 -> 32.923367 | G20: =Calcs!G8 -> 36.792259 | H20: =Calcs!H8 -> 44.498766 | I20: =Calcs!I8 -> 56.50297 | J20: =Calcs!J8 -> 74.374093 | K20: =Calcs!K8 -> 100.29762 | L20: =Calcs!L8 -> 137.29515 | M20: =Calcs!M8 -> 189.51923 | ... U20: =Calcs!U8 -> 2494.6709
A21: * | B21: EBITDA | C21: =C18+C20 -> -138.678 | D21: =D18+D20 -> 153.32 | E21: =E18+E20 -> 341.99 | F21: =F18+F20 -> 625.52978 | G21: =G18+G20 -> 1118.1942 | H21: =H18+H20 -> 1835.5105 | I21: =I18+I20 -> 2952.2054 | J21: =J18+J20 -> 4666.9178 | ... U21: =U18+U20 -> 191775.95
B23: Other income (expense) | C23: -220.135 | D23: -15.447 | E23: -18.022 | F23: =F8 -> 0 | G23: =G8 -> 0 | H23: =H8 -> 0 | I23: =I8 -> 0 | J23: =J8 -> 0 | K23: =K8 -> 0 | L23: =L8 -> 0 | M23: =M8 -> 0 | ... U23: =U8 -> 0
B25: Interest income | C25: 20.309 | D25: 132.572 | E25: 196.792 | F25: =IF(circ=1,Debt!F33,0) -> 0 | G25: =IF(circ=1,Debt!G33,0) -> 0 | H25: =IF(circ=1,Debt!H33,0) -> 0 | I25: =IF(circ=1,Debt!I33,0) -> 0 | J25: =IF(circ=1,Debt!J33,0) -> 0 | K25: =IF(circ=1,Debt!K33,0) -> 0 | L25: =IF(circ=1,Debt!L33,0) -> 0 | M25: =IF(circ=1,Debt!M33,0) -> 0 | ... U25: =IF(circ=1,Debt!U33,0) -> 0
B26: Interest expense | C26: 0 | D26: 0 | E26: 0 | F26: 0 | G26: 0 | H26: 0 | I26: 0 | J26: 0 | K26: 0 | L26: 0 | M26: 0 | N26: 0 | O26: 0 | P26: 0 | Q26: 0 | R26: 0 | S26: 0 | T26: 0 | U26: 0
A28: * | B28: Pretax Income | C28: =C18+SUM(C23:C26) -> -361.026 | D28: =D18+SUM(D23:D26) -> 237.091 | E28: =E18+SUM(E23:E26) -> 489.173 | F28: =F18+SUM(F23:F26) -> 592.60641 | G28: =G18+SUM(G23:G26) -> 1081.4019 | H28: =H18+SUM(H23:H26) -> 1791.0117 | I28: =I18+SUM(I23:I26) -> 2895.7024 | J28: =J18+SUM(J23:J26) -> 4592.5437 | ... U28: =U18+SUM(U23:U26) -> 189281.27
B30: Tax expense | C30: 10.067 | D30: 19.716 | E30: 21.255 | F30: =F9*F28 -> 136.29947 | G30: =G9*G28 -> 248.72244 | H30: =H9*H28 -> 411.9327 | I30: =I9*I28 -> 666.01155 | J30: =J9*J28 -> 1056.285 | K30: =K9*K28 -> 1648.7588 | L30: =L9*L28 -> 2325.3401 | M30: =M9*M28 -> 3267.6728 | ... U30: =U9*U28 -> 43534.693
A31: * | B31: Net income | C31: =C28-C30 -> -371.093 | D31: =D28-D30 -> 217.375 | E31: =E28-E30 -> 467.918 | F31: =F28-F30 -> 456.30694 | G31: =G28-G30 -> 832.67947 | H31: =H28-H30 -> 1379.079 | I31: =I28-I30 -> 2229.6908 | J31: =J28-J30 -> 3536.2586 | ... U31: =U28-U30 -> 145746.58
A33: Shareholder information | C33: 44926 | D33: 45291 | E33: 45657 | F33: 46022 | G33: 46022 | H33: 46022 | I33: 46022 | J33: 46022 | K33: 46022 | L33: 46022 | M33: 46022 | N33: 46022 | O33: 46022 | P33: 46022 | Q33: 46022 | R33: 46022 | S33: 46022 | T33: 46022 | U33: 46022
B34: Basic WASO | C34: 2063.793 | D34: 2147.446 | E34: 2250.163 | F34: =F10 -> 2250.163 | G34: =G10 -> 2250.163 | H34: =H10 -> 2250.163 | I34: =I10 -> 2250.163 | J34: =J10 -> 2250.163 | K34: =K10 -> 2250.163 | L34: =L10 -> 2250.163 | M34: =M10 -> 2250.163 | ... U34: =U10 -> 2250.163
B35: Diluted WASO | C35: 2063.793 | D35: 2297.927 | E35: 2450.818 | F35: =F11 -> 2450.818 | G35: =G11 -> 2450.818 | H35: =H11 -> 2450.818 | I35: =I11 -> 2450.818 | J35: =J11 -> 2450.818 | K35: =K11 -> 2450.818 | L35: =L11 -> 2450.818 | M35: =M11 -> 2450.818 | ... U35: =U11 -> 2450.818
B36: Basic earnings per share | C36: =C31/C34 -> -0.17981115 | D36: =D31/D34 -> 0.1012249 | E36: =E31/E34 -> 0.20794849 | F36: =F31/F34 -> 0.20278839 | G36: =G31/G34 -> 0.37005295 | H36: =H31/H34 -> 0.61287962 | I36: =I31/I34 -> 0.99090192 | J36: =J31/J34 -> 1.5715566 | ... U36: =U31/U34 -> 64.771566
A37: * | B37: Diluted earnings per share | C37: =C31/C35 -> -0.17981115 | D37: =D31/D35 -> 0.094596129 | E37: =E31/E35 -> 0.19092319 | F37: =F31/F35 -> 0.18618557 | G37: =G31/G35 -> 0.33975573 | H37: =H31/H35 -> 0.56270153 | I37: =I31/I35 -> 0.90977414 | J37: =J31/J35 -> 1.4428891 | ... U37: =U31/U35 -> 59.468545

Sheet BalSheet
A1: =CoName -> Palantir Technologies Inc | C1: Hist. | D1: Hist. | E1: Hist. | F1: Proj. | G1: Proj. | H1: Proj. | I1: Proj. | J1: Proj. | K1: Proj. | L1: Proj. | M1: Proj. | N1: Proj. | O1: Proj. | P1: Proj. | Q1: Proj. | R1: Proj. | S1: Proj. | T1: Proj. | U1: Proj.
A2: Assumptions | C2: 44926 | D2: 45291 | E2: 45657 | F2: 46022 | G2: 46387 | H2: 46752 | I2: 47118 | J2: 47483 | K2: =2030 -> 2030 | L2: =K2+1 -> 2031 | M2: =L2+1 -> 2032 | N2: =M2+1 -> 2033 | O2: =N2+1 -> 2034 | P2: =O2+1 -> 2035 | Q2: =P2+1 -> 2036 | R2: =Q2+1 -> 2037 | S2: =R2+1 -> 2038 | ... U2: =T2+1 -> 2040
B4: Operating Cash % of sales | F4: =Assumptions!F41 -> 0.05 | G4: =F4 -> 0.05 | H4: =G4 -> 0.05 | I4: =H4 -> 0.05 | J4: =I4 -> 0.05 | K4: =J4 -> 0.05 | L4: =K4 -> 0.05 | M4: =L4 -> 0.05 | N4: =M4 -> 0.05 | ... U4: =T4 -> 0.05
B5: Accounts receivable % of sales | F5: =Assumptions!F42 -> 0.20067932 | G5: =Assumptions!G42 -> 0.20067932 | H5: =Assumptions!H42 -> 0.20067932 | I5: =Assumptions!I42 -> 0.20067932 | J5: =Assumptions!J42 -> 0.20067932 | K5: =Assumptions!K42 -> 0.20067932 | L5: =Assumptions!L42 -> 0.20067932 | M5: =Assumptions!M42 -> 0.20067932 | ... U5: =Assumptions!U42 -> 0.20067932
B6: Other current assets % of sales | F6: =Assumptions!F43 -> 0.045106852 | G6: =Assumptions!G43 -> 0.045106852 | H6: =Assumptions!H43 -> 0.045106852 | I6: =Assumptions!I43 -> 0.045106852 | J6: =Assumptions!J43 -> 0.045106852 | K6: =Assumptions!K43 -> 0.045106852 | L6: =Assumptions!L43 -> 0.045106852 | M6: =Assumptions!M43 -> 0.045106852 | ... U6: =Assumptions!U43 -> 0.045106852
B7: Other long-term assets % of sales | F7: =Assumptions!F44 -> 0.05800614 | G7: =Assumptions!G44 -> 0.05800614 | H7: =Assumptions!H44 -> 0.05800614 | I7: =Assumptions!I44 -> 0.05800614 | J7: =Assumptions!J44 -> 0.05800614 | K7: =Assumptions!K44 -> 0.05800614 | L7: =Assumptions!L44 -> 0.05800614 | M7: =Assumptions!M44 -> 0.05800614 | ... U7: =Assumptions!U44 -> 0.05800614
B9: Accounts payable/Accural % of COGS | F9: =Assumptions!F48 -> 0.75469355 | G9: =Assumptions!G48 -> 0.75469355 | H9: =Assumptions!H48 -> 0.75469355 | I9: =Assumptions!I48 -> 0.75469355 | J9: =Assumptions!J48 -> 0.75469355 | K9: =Assumptions!K48 -> 0.75469355 | L9: =Assumptions!L48 -> 0.75469355 | M9: =Assumptions!M48 -> 0.75469355 | ... U9: =Assumptions!U48 -> 0.75469355
B10: Other current liabilities % of sales | F10: =Assumptions!F49 -> 0.19852298 | G10: =Assumptions!G49 -> 0.19852298 | H10: =Assumptions!H49 -> 0.19852298 | I10: =Assumptions!I49 -> 0.19852298 | J10: =Assumptions!J49 -> 0.19852298 | K10: =Assumptions!K49 -> 0.19852298 | L10: =Assumptions!L49 -> 0.19852298 | M10: =Assumptions!M49 -> 0.19852298 | ... U10: =Assumptions!U49 -> 0.19852298
B11: Other long-term liabilities % of sales | F11: =Assumptions!F50 -> 0.087404777 | G11: =Assumptions!G50 -> 0.087404777 | H11: =Assumptions!H50 -> 0.087404777 | I11: =Assumptions!I50 -> 0.087404777 | J11: =Assumptions!J50 -> 0.087404777 | K11: =Assumptions!K50 -> 0.087404777 | L11: =Assumptions!L50 -> 0.087404777 | M11: =Assumptions!M50 -> 0.087404777 | ... U11: =Assumptions!U50 -> 0.087404777
A13: Balance sheet | C13: =C2 -> 44926 | D13: =D2 -> 45291 | E13: =E2 -> 45657 | F13: =F2 -> 46022 | G13: =G2 -> 46387 | H13: =H2 -> 46752 | I13: =I2 -> 47118 | J13: =J2 -> 47483 | ... U13: =U2 -> 2040
B14: Operating Cash | C14: =5%*IncState!C14 -> 95.29355 | D14: =5%*IncState!D14 -> 111.2506 | E14: =5%*IncState!E14 -> 143.27535 | F14: =F4*IncState!F14 -> 218.95846 | G14: =G4*IncState!G14 -> 333.09995 | H14: =H4*IncState!H14 -> 473.00193 | I14: =I4*IncState!I14 -> 669.29773 | J14: =J4*IncState!J14 -> 943.7098 | K14: =K4*IncState!K14 -> 1325.9123 | L14: =L4*IncState!L14 -> 1856.2772 | M14: =M4*IncState!M14 -> 2589.5066 | ... U14: =U4*IncState!U14 -> 32598.289
B15: Excess cash | C15: =2598.54+35.135-C14 -> 2538.3815 | D15: =831.047+2843.132-D14 -> 3562.9284 | E15: =2098.524+3131.463-E14 -> 5086.7117 | F15: =MAX(CashFlow!F21,0) -> 5634.3776 | G15: =MAX(CashFlow!G21,0) -> 6589.4087 | H15: =MAX(CashFlow!H21,0) -> 8096.6849 | I15: =MAX(CashFlow!I21,0) -> 10495.694 | J15: =MAX(CashFlow!J21,0) -> 14257.522 | K15: =MAX(CashFlow!K21,0) -> 20079.004 | L15: =MAX(CashFlow!L21,0) -> 28267.818 | M15: =MAX(CashFlow!M21,0) -> 39747.73 | ... U15: =MAX(CashFlow!U21,0) -> 552836.48
B16: Accounts receivable | C16: 258.346 | D16: 364.784 | E16: 575.048 | F16: =F5*IncState!F14 -> 878.8087 | G16: =G5*IncState!G14 -> 1336.9254 | H16: =H5*IncState!H14 -> 1898.4341 | I16: =I5*IncState!I14 -> 2686.2843 | J16: =J5*IncState!J14 -> 3787.6608 | K16: =K5*IncState!K14 -> 5321.6635 | L16: =L5*IncState!L14 -> 7450.3288 | M16: =M5*IncState!M14 -> 10393.209 | ... U16: =U5*IncState!U14 -> 130836.05
B17: Other current assets | C17: 149.566 | D17: 99.655 | E17: 129.254 | F17: =F6*IncState!F14 -> 197.53054 | G17: =G6*IncState!G14 -> 300.5018 | H17: =H6*IncState!H14 -> 426.71256 | I17: =I6*IncState!I14 -> 603.79827 | J17: =J6*IncState!J14 -> 851.35556 | K17: =K6*IncState!K14 -> 1196.1546 | L17: =L6*IncState!L14 -> 1674.6164 | M17: =M6*IncState!M14 -> 2336.0899 | ... U17: =U6*IncState!U14 -> 29408.124
B18: Total current assets | C18: =SUM(C14:C17) -> 3041.587 | D18: =SUM(D14:D17) -> 4138.618 | E18: =SUM(E14:E17) -> 5934.289 | F18: =SUM(F14:F17) -> 6929.6752 | G18: =SUM(G14:G17) -> 8559.9359 | H18: =SUM(H14:H17) -> 10894.833 | I18: =SUM(I14:I17) -> 14455.075 | J18: =SUM(J14:J17) -> 19840.248 | ... U18: =SUM(U14:U17) -> 745678.94
B20: Property, plant & equipment, net | C20: =69.17+200.24 -> 269.41 | D20: =47.758+182.863 -> 230.621 | E20: =39.638+200.74 -> 240.378 | F20: =Calcs!F9 -> 268.62531 | G20: =Calcs!G9 -> 324.89157 | H20: =Calcs!H9 -> 412.5359 | I20: =Calcs!I9 -> 543.01541 | J20: =Calcs!J9 -> 732.28661 | K20: =Calcs!K9 -> 1002.4106 | L20: =Calcs!L9 -> 1383.7058 | M20: =Calcs!M9 -> 1917.62 | ... U20: =Calcs!U9 -> 24826.284
B21: Other assets | C21: 150.252 | D21: 153.186 | E21: 166.217 | F21: =F7*IncState!F14 -> 254.0187 | G21: =G7*IncState!G14 -> 386.43684 | H21: =H7*IncState!H14 -> 548.74032 | I21: =I7*IncState!I14 -> 776.46755 | J21: =J7*IncState!J14 -> 1094.8192 | K21: =K7*IncState!K14 -> 1538.221 | L21: =L7*IncState!L14 -> 2153.5095 | M21: =M7*IncState!M14 -> 3004.1457 | ... U21: =U7*IncState!U14 -> 37818.019
B22: Total non-current assets | C22: =SUM(C20:C21) -> 419.662 | D22: =SUM(D20:D21) -> 383.807 | E22: =SUM(E20:E21) -> 406.595 | F22: =SUM(F20:F21) -> 522.64401 | G22: =SUM(G20:G21) -> 711.32841 | H22: =SUM(H20:H21) -> 961.27622 | I22: =SUM(I20:I21) -> 1319.483 | J22: =SUM(J20:J21) -> 1827.1059 | ... U22: =SUM(U20:U21) -> 62644.303
A24: * | B24: TOTAL ASSETS | C24: =SUM(C22,C18) -> 3461.249 | D24: =SUM(D22,D18) -> 4522.425 | E24: =SUM(E22,E18) -> 6340.884 | F24: =SUM(F22,F18) -> 7452.3193 | G24: =SUM(G22,G18) -> 9271.2643 | H24: =SUM(H22,H18) -> 11856.11 | I24: =SUM(I22,I18) -> 15774.558 | J24: =SUM(J22,J18) -> 21667.354 | ... U24: =SUM(U22,U18) -> 808323.25
B26: Revolver/Short term debt | C26: 0 | D26: 0 | E26: 0 | F26: =MIN(CashFlow!F21,0) -> 0 | G26: =MIN(CashFlow!G21,0) -> 0 | H26: =MIN(CashFlow!H21,0) -> 0 | I26: =MIN(CashFlow!I21,0) -> 0 | J26: =MIN(CashFlow!J21,0) -> 0 | K26: =MIN(CashFlow!K21,0) -> 0 | L26: =MIN(CashFlow!L21,0) -> 0 | M26: =MIN(CashFlow!M21,0) -> 0 | ... U26: =MIN(CashFlow!U21,0) -> 0
B27: Accounts payable/Accurals | C27: =44.788+172.715 -> 217.503 | D27: =12.122+222.991 -> 235.113 | E27: =0.103+427.046 -> 427.149 | F27: =F9*IncState!F15 -> 649.47928 | G27: =G9*IncState!G15 -> 983.02046 | H27: =H9*IncState!H15 -> 1388.7496 | I27: =I9*IncState!I15 -> 1954.9784 | J27: =J9*IncState!J15 -> 2742.2753 | K27: =K9*IncState!K15 -> 3832.8837 | L27: =L9*IncState!L15 -> 5338.0188 | M27: =M9*IncState!M15 -> 7407.4505 | ... U27: =U9*IncState!U15 -> 89313.231
B28: Other current liabilities | C28: =587.941-C27 -> 370.438 | D28: =746.018-D27 -> 510.905 | E28: =996.018-E27 -> 568.869 | F28: =F10*IncState!F14 -> 869.36573 | G28: =G10*IncState!G14 -> 1322.5599 | H28: =H10*IncState!H14 -> 1878.0351 | I28: =I10*IncState!I14 -> 2657.4196 | J28: =J10*IncState!J14 -> 3746.9617 | K28: =K10*IncState!K14 -> 5264.4812 | L28: =L10*IncState!L14 -> 7370.2736 | M28: =M10*IncState!M14 -> 10281.532 | ... U28: =U10*IncState!U14 -> 129430.19
B29: Total current liabilities | C29: =SUM(C26:C28) -> 587.941 | D29: =SUM(D26:D28) -> 746.018 | E29: =SUM(E26:E28) -> 996.018 | F29: =SUM(F26:F28) -> 1518.845 | G29: =SUM(G26:G28) -> 2305.5804 | H29: =SUM(H26:H28) -> 3266.7847 | I29: =SUM(I26:I28) -> 4612.3981 | J29: =SUM(J26:J28) -> 6489.237 | ... U29: =SUM(U26:U28) -> 218743.42
B31: Long-term debt, including current maturities | C31: 0 | D31: 0 | E31: 0 | F31: 0 | G31: 0 | H31: 0 | I31: 0 | J31: 0 | K31: 0 | L31: 0 | M31: 0 | N31: 0 | O31: 0 | P31: 0 | Q31: 0 | R31: 0 | S31: 0 | T31: 0 | U31: 0
B32: Other long-term liabilities | C32: =818.802-C29 -> 230.861 | D32: =961.46-D29 -> 215.442 | E32: =1246.477-E29 -> 250.459 | F32: =F11*IncState!F14 -> 382.7603 | G32: =G11*IncState!G14 -> 582.29053 | H32: =H11*IncState!H14 -> 826.85256 | I32: =I11*IncState!I14 -> 1169.9964 | J32: =J11*IncState!J14 -> 1649.6949 | K32: =K11*IncState!K14 -> 2317.8213 | L32: =L11*IncState!L14 -> 3244.9498 | M32: =M11*IncState!M14 -> 4526.705 | ... U32: =U11*IncState!U14 -> 56984.924
B33: Total non-current liabilities | C33: =SUM(C31:C32) -> 230.861 | D33: =SUM(D31:D32) -> 215.442 | E33: =SUM(E31:E32) -> 250.459 | F33: =SUM(F31:F32) -> 382.7603 | G33: =SUM(G31:G32) -> 582.29053 | H33: =SUM(H31:H32) -> 826.85256 | I33: =SUM(I31:I32) -> 1169.9964 | J33: =SUM(J31:J32) -> 1649.6949 | ... U33: =SUM(U31:U32) -> 56984.924
B35: Equity | C35: 2642.437 | D35: 3560.965 | E35: 5094.407 | F35: =Calcs!F16 -> 5550.7139 | G35: =Calcs!G16 -> 6383.3934 | H35: =Calcs!H16 -> 7762.4724 | I35: =Calcs!I16 -> 9992.1633 | J35: =Calcs!J16 -> 13528.422 | K35: =Calcs!K16 -> 19048.18 | L35: =Calcs!L16 -> 26833.014 | M35: =Calcs!M16 -> 37772.614 | ... U35: =Calcs!U16 -> 532594.9
A36: * | B36: TOTAL LIABILITIES & EQUITY | C36: =SUM(C35,C33,C29) -> 3461.239 | D36: =SUM(D35,D33,D29) -> 4522.425 | E36: =SUM(E35,E33,E29) -> 6340.884 | F36: =SUM(F35,F33,F29) -> 7452.3193 | G36: =SUM(G35,G33,G29) -> 9271.2643 | H36: =SUM(H35,H33,H29) -> 11856.11 | I36: =SUM(I35,I33,I29) -> 15774.558 | J36: =SUM(J35,J33,J29) -> 21667.354 | ... U36: =SUM(U35,U33,U29) -> 808323.25
A38: * | B38: Balance check | C38: =C36-C24 -> -0.01 | D38: =D36-D24 -> 0 | E38: =E36-E24 -> 0 | F38: =F36-F24 -> 0 | G38: =G36-G24 -> 0 | H38: =H36-H24 -> 0 | I38: =I36-I24 -> 0 | J38: =J36-J24 -> 0 | ... U38: =U36-U24 -> 0

Sheet CashFlow
A1: =CoName -> Palantir Technologies Inc | C1: Hist. | D1: Hist. | E1: Hist. | F1: Proj. | G1: Proj. | H1: Proj. | I1: Proj. | J1: Proj. | K1: Proj. | L1: Proj. | M1: Proj. | N1: Proj. | O1: Proj. | P1: Proj. | Q1: Proj. | R1: Proj. | S1: Proj. | T1: Proj. | U1: Proj.
A2: Cash flow statement | C2: 2022 | D2: =C2+1 -> 2023 | E2: =D2+1 -> 2024 | F2: =E2+1 -> 2025 | G2: =F2+1 -> 2026 | H2: =G2+1 -> 2027 | I2: =H2+1 -> 2028 | J2: =I2+1 -> 2029 | K2: =J2+1 -> 2030 | ... U2: =T2+1 -> 2040
B3: Net Income | F3: =IncState!F31 -> 456.30694 | G3: =IncState!G31 -> 832.67947 | H3: =IncState!H31 -> 1379.079 | I3: =IncState!I31 -> 2229.6908 | J3: =IncState!J31 -> 3536.2586 | K3: =IncState!K31 -> 5519.7577 | L3: =IncState!L31 -> 7784.8341 | M3: =IncState!M31 -> 10939.6 | ... U3: =IncState!U31 -> 145746.58
B4: Depreciation | F4: =Calcs!F8 -> 32.923367 | G4: =Calcs!G8 -> 36.792259 | H4: =Calcs!H8 -> 44.498766 | I4: =Calcs!I8 -> 56.50297 | J4: =Calcs!J8 -> 74.374093 | K4: =Calcs!K8 -> 100.29762 | L4: =Calcs!L8 -> 137.29515 | M4: =Calcs!M8 -> 189.51923 | ... U4: =Calcs!U8 -> 2494.6709
B5: (inc) / dec in OWC | F5: =Calcs!F24 -> 75.106672 | G5: =Calcs!G24 -> 111.50586 | H5: =Calcs!H24 -> 133.58291 | I5: =Calcs!I24 -> 184.38169 | J5: =Calcs!J24 -> 253.49306 | K5: =Calcs!K24 -> 347.12374 | L5: =Calcs!L24 -> 473.43542 | M5: =Calcs!M24 -> 643.10697 | ... U5: =Calcs!U24 -> 6422.735
B6: (inc) / dec in LT assets | F6: =BalSheet!E21-BalSheet!F21 -> -87.8017 | G6: =BalSheet!F21-BalSheet!G21 -> -132.41815 | H6: =BalSheet!G21-BalSheet!H21 -> -162.30347 | I6: =BalSheet!H21-BalSheet!I21 -> -227.72723 | J6: =BalSheet!I21-BalSheet!J21 -> -318.3517 | K6: =BalSheet!J21-BalSheet!K21 -> -443.4018 | L6: =BalSheet!K21-BalSheet!L21 -> -615.28842 | M6: =BalSheet!L21-BalSheet!M21 -> -850.63624 | ... U6: =BalSheet!T21-BalSheet!U21 -> -9908.0418
B7: inc / (dec) in LT liabilities | F7: =BalSheet!F32-BalSheet!E32 -> 132.3013 | G7: =BalSheet!G32-BalSheet!F32 -> 199.53023 | H7: =BalSheet!H32-BalSheet!G32 -> 244.56202 | I7: =BalSheet!I32-BalSheet!H32 -> 343.14381 | J7: =BalSheet!J32-BalSheet!I32 -> 479.69851 | K7: =BalSheet!K32-BalSheet!J32 -> 668.12643 | L7: =BalSheet!L32-BalSheet!K32 -> 927.12852 | M7: =BalSheet!M32-BalSheet!L32 -> 1281.7552 | ... U7: =BalSheet!U32-BalSheet!T32 -> 14929.63
B8: Cash Flow From Operations | F8: =SUM(F3:F7) -> 608.83658 | G8: =SUM(G3:G7) -> 1048.0897 | H8: =SUM(H3:H7) -> 1639.4193 | I8: =SUM(I3:I7) -> 2585.9921 | J8: =SUM(J3:J7) -> 4025.4726 | K8: =SUM(K3:K7) -> 6191.9037 | L8: =SUM(L3:L7) -> 8707.4048 | M8: =SUM(M3:M7) -> 12203.346 | ... U8: =SUM(U3:U7) -> 159685.58
B10: Capex | F10: =Calcs!F7 -> 61.170677 | G10: =Calcs!G7 -> 93.058517 | H10: =Calcs!H7 -> 132.14309 | I10: =Calcs!I7 -> 186.98248 | J10: =Calcs!J7 -> 263.6453 | K10: =Calcs!K7 -> 370.42164 | L10: =Calcs!L7 -> 518.5903 | M10: =Calcs!M7 -> 723.43346 | ... U10: =Calcs!U7 -> 9107.0218
B11: Cash Flow From Investing | F11: =-F10 -> -61.170677 | G11: =-G10 -> -93.058517 | H11: =-H10 -> -132.14309 | I11: =-I10 -> -186.98248 | J11: =-J10 -> -263.6453 | K11: =-K10 -> -370.42164 | L11: =-L10 -> -518.5903 | M11: =-M10 -> -723.43346 | ... U11: =-U10 -> -9107.0218
B13: Share Issuance / (repurchases) | F13: =Calcs!F11 -> 0 | G13: =Calcs!G11 -> 0 | H13: =Calcs!H11 -> 0 | I13: =Calcs!I11 -> 0 | J13: =Calcs!J11 -> 0 | K13: =Calcs!K11 -> 0 | L13: =Calcs!L11 -> 0 | M13: =Calcs!M11 -> 0 | ... U13: =Calcs!U11 -> 0
B14: Debt Issuance / (repayments) | F14: =SUM(Debt!F8:F9) -> 0 | G14: =SUM(Debt!G8:G9) -> 0 | H14: =SUM(Debt!H8:H9) -> 0 | I14: =SUM(Debt!I8:I9) -> 0 | J14: =SUM(Debt!J8:J9) -> 0 | K14: =SUM(Debt!K8:K9) -> 0 | L14: =SUM(Debt!L8:L9) -> 0 | M14: =SUM(Debt!M8:M9) -> 0 | ... U14: =SUM(Debt!U8:U9) -> 0
B15: Cash Flow From Financing | F15: =SUM(F13:F14) -> 0 | G15: =SUM(G13:G14) -> 0 | H15: =SUM(H13:H14) -> 0 | I15: =SUM(I13:I14) -> 0 | J15: =SUM(J13:J14) -> 0 | K15: =SUM(K13:K14) -> 0 | L15: =SUM(L13:L14) -> 0 | M15: =SUM(M13:M14) -> 0 | ... U15: =SUM(U13:U14) -> 0
B17: Net changes in cash | F17: =SUM(F15,F11,F8) -> 547.6659 | G17: =SUM(G15,G11,G8) -> 955.03116 | H17: =SUM(H15,H11,H8) -> 1507.2762 | I17: =SUM(I15,I11,I8) -> 2399.0096 | J17: =SUM(J15,J11,J8) -> 3761.8273 | K17: =SUM(K15,K11,K8) -> 5821.482 | L17: =SUM(L15,L11,L8) -> 8188.8145 | M17: =SUM(M15,M11,M8) -> 11479.912 | ... U17: =SUM(U15,U11,U8) -> 150578.55
B19: Beginning cash | F19: =BalSheet!E15 -> 5086.7117 | G19: =BalSheet!F15 -> 5634.3776 | H19: =BalSheet!G15 -> 6589.4087 | I19: =BalSheet!H15 -> 8096.6849 | J19: =BalSheet!I15 -> 10495.694 | K19: =BalSheet!J15 -> 14257.522 | L19: =BalSheet!K15 -> 20079.004 | M19: =BalSheet!L15 -> 28267.818 | ... U19: =BalSheet!T15 -> 402257.93
B20: Changes | F20: =F17 -> 547.6659 | G20: =G17 -> 955.03116 | H20: =H17 -> 1507.2762 | I20: =I17 -> 2399.0096 | J20: =J17 -> 3761.8273 | K20: =K17 -> 5821.482 | L20: =L17 -> 8188.8145 | M20: =M17 -> 11479.912 | ... U20: =U17 -> 150578.55
B21: Ending cash | F21: =SUM(F19:F20) -> 5634.3776 | G21: =SUM(G19:G20) -> 6589.4087 | H21: =SUM(H19:H20) -> 8096.6849 | I21: =SUM(I19:I20) -> 10495.694 | J21: =SUM(J19:J20) -> 14257.522 | K21: =SUM(K19:K20) -> 20079.004 | L21: =SUM(L19:L20) -> 28267.818 | M21: =SUM(M19:M20) -> 39747.73 | ... U21: =SUM(U19:U20) -> 552836.48

Sheet Free Cash Flow
A1: =CoName -> Palantir Technologies Inc | C1: Hist. | D1: Hist. | E1: Hist. | F1: Proj. | G1: Proj. | H1: Proj. | I1: Proj. | J1: Proj. | K1: Proj. | L1: Proj. | M1: Proj. | N1: Proj. | O1: Proj. | P1: Proj. | Q1: Proj. | R1: Proj. | S1: Proj. | T1: Proj. | U1: Proj.
A2: Free Cash Flows | C2: 2022 | D2: =C2+1 -> 2023 | E2: =D2+1 -> 2024 | F2: =E2+1 -> 2025 | G2: =F2+1 -> 2026 | H2: =G2+1 -> 2027 | I2: =H2+1 -> 2028 | J2: =I2+1 -> 2029 | K2: =J2+1 -> 2030 | ... U2: =T2+1 -> 2040
A3: * | B3: Sales | F3: =IncState!F14 -> 4379.1692 | G3: =IncState!G14 -> 6661.999 | H3: =IncState!H14 -> 9460.0386 | I3: =IncState!I14 -> 13385.955 | J3: =IncState!J14 -> 18874.196 | K3: =IncState!K14 -> 26518.245 | L3: =IncState!L14 -> 37125.543 | M3: =IncState!M14 -> 51790.133 | ... U3: =IncState!U14 -> 651965.79
B4: EBIT | F4: =IncState!F18 -> 592.60641 | G4: =IncState!G18 -> 1081.4019 | H4: =IncState!H18 -> 1791.0117 | I4: =IncState!I18 -> 2895.7024 | J4: =IncState!J18 -> 4592.5437 | K4: =IncState!K18 -> 7168.5165 | L4: =IncState!L18 -> 10110.174 | M4: =IncState!M18 -> 14207.273 | ... U4: =IncState!U18 -> 189281.27
B5: Effective Tax Rate | F5: =IncState!F9 -> 0.23 | G5: =IncState!G9 -> 0.23 | H5: =IncState!H9 -> 0.23 | I5: =IncState!I9 -> 0.23 | J5: =IncState!J9 -> 0.23 | K5: =IncState!K9 -> 0.23 | L5: =IncState!L9 -> 0.23 | M5: =IncState!M9 -> 0.23 | ... U5: =IncState!U9 -> 0.23
A7: * | B7: NOPAT | F7: =F4*(1-F5) -> 456.30694 | G7: =G4*(1-G5) -> 832.67947 | H7: =H4*(1-H5) -> 1379.079 | I7: =I4*(1-I5) -> 2229.6908 | J7: =J4*(1-J5) -> 3536.2586 | K7: =K4*(1-K5) -> 5519.7577 | L7: =L4*(1-L5) -> 7784.8341 | M7: =M4*(1-M5) -> 10939.6 | ... U7: =U4*(1-U5) -> 145746.58
B8: Depreciation | F8: =CashFlow!F4 -> 32.923367 | G8: =CashFlow!G4 -> 36.792259 | H8: =CashFlow!H4 -> 44.498766 | I8: =CashFlow!I4 -> 56.50297 | J8: =CashFlow!J4 -> 74.374093 | K8: =CashFlow!K4 -> 100.29762 | L8: =CashFlow!L4 -> 137.29515 | M8: =CashFlow!M4 -> 189.51923 | ... U8: =CashFlow!U4 -> 2494.6709
B9: (inc) / dec in OWC | F9: =CashFlow!F5 -> 75.106672 | G9: =CashFlow!G5 -> 111.50586 | H9: =CashFlow!H5 -> 133.58291 | I9: =CashFlow!I5 -> 184.38169 | J9: =CashFlow!J5 -> 253.49306 | K9: =CashFlow!K5 -> 347.12374 | L9: =CashFlow!L5 -> 473.43542 | M9: =CashFlow!M5 -> 643.10697 | ... U9: =CashFlow!U5 -> 6422.735
B10: (inc) / dec in other long-term assets | F10: =CashFlow!F6 -> -87.8017 | G10: =CashFlow!G6 -> -132.41815 | H10: =CashFlow!H6 -> -162.30347 | I10: =CashFlow!I6 -> -227.72723 | J10: =CashFlow!J6 -> -318.3517 | K10: =CashFlow!K6 -> -443.4018 | L10: =CashFlow!L6 -> -615.28842 | M10: =CashFlow!M6 -> -850.63624 | ... U10: =CashFlow!U6 -> -9908.0418
B11: inc / (dec) other long-term liabilities | F11: =CashFlow!F7 -> 132.3013 | G11: =CashFlow!G7 -> 199.53023 | H11: =CashFlow!H7 -> 244.56202 | I11: =CashFlow!I7 -> 343.14381 | J11: =CashFlow!J7 -> 479.69851 | K11: =CashFlow!K7 -> 668.12643 | L11: =CashFlow!L7 -> 927.12852 | M11: =CashFlow!M7 -> 1281.7552 | ... U11: =CashFlow!U7 -> 14929.63
B12: (Capex) | F12: =CashFlow!F11 -> -61.170677 | G12: =CashFlow!G11 -> -93.058517 | H12: =CashFlow!H11 -> -132.14309 | I12: =CashFlow!I11 -> -186.98248 | J12: =CashFlow!J11 -> -263.6453 | K12: =CashFlow!K11 -> -370.42164 | L12: =CashFlow!L11 -> -518.5903 | M12: =CashFlow!M11 -> -723.43346 | ... U12: =CashFlow!U11 -> -9107.0218
A14: * | B14: Free Cash Flow | F14: =SUM(F7:F12) -> 547.6659 | G14: =SUM(G7:G12) -> 955.03116 | H14: =SUM(H7:H12) -> 1507.2762 | I14: =SUM(I7:I12) -> 2399.0096 | J14: =SUM(J7:J12) -> 3761.8273 | K14: =SUM(K7:K12) -> 5821.482 | L14: =SUM(L7:L12) -> 8188.8145 | M14: =SUM(M7:M12) -> 11479.912 | ... U14: =SUM(U7:U12) -> 150578.55

Sheet WACC
A1: =CoName -> Palantir Technologies Inc
A3: * | B3: WACC | G3: Comp | H3: Levered beta | I3: Gross debt | J3: Market cap | K3: Debt/Mcap | L3: MTR | M3: Unlevered beta
B4: Tax Rate | E4: =Assumptions!F15 -> 0.23 | L4: =E4 -> 0.23 | M4: =H4/((1+K4*(1-L4))) -> 0
B5: Risk free rate | E5: 0.04 | L5: =L4 -> 0.23 | M5: =H5/((1+K5*(1-L5))) -> 0
B6: Market risk Premium | E6: 0.05 | L6: =L5 -> 0.23 | M6: =H6/((1+K6*(1-L6))) -> 0
B7: Beta | E7: 1.48 | L7: =L6 -> 0.23 | M7: =H7/((1+K7*(1-L7))) -> 0
B8: Cost of Equity | E8: =E5+E6*E7 -> 0.114
B9: % Equity | E9: 1 | G9: Industry beta (average) | M9: =AVERAGE(M4:M7) -> 0
B10: % Debt | E10: 0
B11: Cost of debt | E11: 0 | G11: Re-levered beta | M11: =M9*(1+E10*(1-E4)) -> 0
B12: Post tax cost of debt | E12: =E11*(1-E4) -> 0
A13: * | B13: WACC | E13: =WACC!E8*WACC!E9+WACC!E12*WACC!E10 -> 0.114
B14: Long Term growth rate | E14: 0.025

Sheet DCF Model
A1: =CoName -> Palantir Technologies Inc | D1: Proj. | E1: Proj. | F1: Proj. | G1: Proj. | H1: Proj. | I1: Proj. | J1: Proj. | K1: Proj. | L1: Proj. | M1: Proj. | N1: Proj. | O1: Proj. | P1: Proj. | Q1: Proj. | R1: Proj. | S1: Proj.
A2: Discount Model Year count | D2: 1 | E2: =D2+1 -> 2 | F2: =E2+1 -> 3 | G2: =F2+1 -> 4 | H2: =G2+1 -> 5 | I2: =H2+1 -> 6 | J2: =I2+1 -> 7 | K2: =J2+1 -> 8 | L2: =K2+1 -> 9 | ... S2: =R2+1 -> 16
B3: Discount Factor | D3: =1/(1+$W$3)^D2 -> 0.89766607 | E3: =1/(1+$W$3)^E2 -> 0.80580437 | F3: =1/(1+$W$3)^F2 -> 0.72334324 | G3: =1/(1+$W$3)^G2 -> 0.64932068 | H3: =1/(1+$W$3)^H2 -> 0.58287314 | I3: =1/(1+$W$3)^I2 -> 0.52322544 | J3: =1/(1+$W$3)^J2 -> 0.46968173 | K3: =1/(1+$W$3)^K2 -> 0.42161735 | ... S3: =1/(1+$W$3)^S2 -> 0.17776119 | T3: WACC | W3: =WACC!E13 -> 0.114
B4: PV FCF | D4: =D3*'Free Cash Flow'!F14 -> 491.6211 | E4: =E3*'Free Cash Flow'!G14 -> 769.56828 | F4: =F3*'Free Cash Flow'!H14 -> 1090.278 | G4: =G3*'Free Cash Flow'!I14 -> 1557.7265 | H4: =H3*'Free Cash Flow'!J14 -> 2192.6681 | I4: =I3*'Free Cash Flow'!K14 -> 3045.9475 | J4: =J3*'Free Cash Flow'!L14 -> 3846.1365 | K4: =K3*'Free Cash Flow'!M14 -> 4840.1301 | ... S4: =S3*'Free Cash Flow'!U14 -> 26767.023 | T4: Long Term growth rate | W4: 0.025
S5: =((S4*(1+W4)))/(W3-W4) -> 308271.89
A6: Value Calculation | E6: Multiples Calculation
B7: Total PV of FCFs | C7: =SUM(D4:S4) -> 133638.05 | E7: Total PV of FCFs | G7: =C7 -> 133638.05 | K7: LTGR | P7: Exit Mult.
B8: PV of TV | C8: =S3*S5 -> 54798.778 | E8: Multiple TV | G8: =G10*IncState!U21*'DCF Model'!S3 -> 409083.84 | I8: =C18 -> 75.865752 | J8: =K8-E23 -> 0.0225 | K8: 0.025 | L8: =K8+$E$23 -> 0.0275 | N8: =G18 -> 214.10111 | O8: =P8-1 -> 11 | P8: 12 | Q8: =P8+1 -> 13
B9: EV | C9: =SUM(C7:C8) -> 188436.82 | E9: EV | G9: =SUM(G7:G8) -> 542721.89 | I9: =I10+$E$22 -> 0.124 | J9: 63.027159 | K9: 63.417202 | L9: 63.827455 | N9: =I9 -> 0.124 | O9: 175.79752 | P9: 187.32673 | Q9: 198.85594
E10: Implied EBITDA multiple | G10: 12 | I10: =I11+$E$22 -> 0.119 | J10: 68.686952 | K10: 69.183066 | L10: 69.706291 | N10: =I10 -> 0.119 | O10: 187.84005 | P10: 200.22171 | Q10: 212.60338
H11: WACC | I11: 0.114 | J11: 75.230835 | K11: 75.865752 | L11: 76.53737 | N11: =I11 -> 0.114 | O11: 200.79971 | P11: 214.10111 | Q11: 227.40251
B12: Cash & Cash Equiv | C12: =MAIN!F7 -> 6000.422 | E12: Cash & Cash Equiv | G12: =C12 -> 6000.422 | I12: =I11-$E$22 -> 0.109 | J12: 82.860558 | K12: 83.678639 | L12: 84.546908 | N12: =I12 -> 0.109 | O12: 214.75172 | P12: 229.04578 | Q12: 243.33985
B13: Debt & Claims | C13: =MAIN!F8 -> 0 | E13: Debt & Claims | G13: =C13 -> 0 | I13: =I12-$E$22 -> 0.104 | J13: 91.837161 | K13: 92.899208 | L13: 94.030669 | N13: =I13 -> 0.104 | O13: 229.77786 | P13: 245.14367 | Q13: 260.50947
B14: NCI | C14: 0 | E14: NCI | G14: =C14 -> 0
B15: Equity Value | C15: =C9+C12-C13 -> 194437.25 | E15: Equity Value | G15: =G9+G12-G13 -> 548722.31 | K15: Average | P15: Average
K16: =AVERAGE(J9:L13) -> 77.022348 | P16: =AVERAGE(O9:Q13) -> 215.1678
B17: Diluted S/O | C17: =MAIN!F5 -> 2562.912 | E17: Diluted S/O | G17: =C17 -> 2562.912
A18: * | B18: Implied Share Price | C18: =C15/C17 -> 75.865752 | E18: Implied Share Price | G18: =G15/G17 -> 214.10111
A20: Sensitivity analysis
C22: Discount rate variance | E22: 0.005 | J22: Discount rate variance | L22: 0.005
C23: Implied growth rate variance | E23: 0.0025 | J23: TV multiple variance | L23: 1
A25: DCF tables

Sheet COMPS
A1: =CoName -> Palantir Technologies Inc
A2: * | C2: Company Symbol | D2: Price 10/14/25 | E2: Enterprise Value | F2: LTM EV/EBITDA | G2: EV/EBITDA 2026E | H2: LTM EV/EBIT | I2: EV/EBIT 2026E | J2: LTM P/E Ratio | K2: P/E Ratio 2026E | L2: LTM EV/Sales | M2: EV/Sales 2026E | N2: Delta % Average
A8: * | B8: Average
A10: * | B10: Current price
B11: Delta -> Average

Sheet Presentation
A1: =CoName -> Palantir Technologies Inc
A2: Presentation slide
A3: Football field + SOTP Comps analysis
A21: DCF Analysis (Sensitivity tables)
A41: Projection ranges
