Workbook
Name Ccy: MAIN!$C$6
Name circ: MAIN!$C$9
Name CoName: MAIN!$C$4
Name g: #REF!
Name IQ_CH: 110000
Name IQ_CQ: 5000
Name IQ_CY: 10000
Name IQ_DAILY: 500000
Name IQ_FH: 100000
Name IQ_FQ: 500
Name IQ_FY: 1000
Name IQ_LTM: 2000
Name IQ_MONTH: 15000
Name IQ_NTM: 6000
Name IQ_WEEK: 50000
Name IQ_YTD: 3000
Name OpCase: [1]DCF!$E$98
Name ScenarioREV: Assumptions!$D$4
Name TTS: #REF!
Name Units: MAIN!$C$7

Sheet MAIN
A1: =CoName -> Roblox Corporation
A2: Model Details
B4: Company name | C4: Roblox Corporation | E4: Current Stock Price | F4: 105 | H4: Operating Case One | I4: Terminal Mult | J4: Perpetuity | K4: Average
B5: Latest BS date | C5: 247.43 | E5: Diluted s/o | F5: 654900 | H5: Implied Price | I5: ='DCF Model'!G18 -> 96.212535 | J5: ='DCF Model'!C18 -> 104.88803 | K5: =AVERAGE(I5:J5) -> 100.55028
B6: Currency | C6: USD | E6: Mkt Cap | F6: =F5*F4 -> 68764500 | H6: Difference | I6: =I5/$F$4-1 -> -0.083690147 | J6: =J5/$F$4-1 -> -0.0010664108 | K6: =K5/$F$4-1 -> -0.042378279
B7: Units | C7: t | E7: Cash | F7: =1016825+1843675 -> 2860500
B8: Analyst name | C8: Alan Chen | E8: Debt | F8: =992736 -> 992736
B9: Circular switch | C9: 0 | E9: NCI | F9: 12792
E10: EV | F10: =F6-F7+F8+F9 -> 66909528

Sheet Assumptions
A1: =CoName -> Roblox Corporation | C1: Hist. | D1: Hist. | E1: Hist. | F1: Proj. | G1: Proj. | H1: Proj. | I1: Proj. | J1: Proj.
A2: * | B2: Income Statement | C2: 44926 | D2: 45291 | E2: 45657 | F2: 46022 | G2: 46387 | H2: 46752 | I2: 47118 | J2: 47483
B4: Operating Case | D4: 1
D5: Variance
B6: Street Case | D6: 0 | F6: =Revenue!V8 -> 0.53827451 | G6: =Revenue!AA8 -> 0.448596 | H6: =Revenue!AB8 -> 0.35 | I6: =Revenue!AC8 -> 0.2 | J6: =Revenue!AD8 -> 0.15
B7: Optimistic Case | D7: 0.025 | F7: =F6+$D$7 -> 0.56327451 | G7: =G6+$D$7 -> 0.473596 | H7: =H6+$D$7 -> 0.375 | I7: =I6+$D$7 -> 0.225 | J7: =J6+$D$7 -> 0.175
B8: Pessimistic Case | D8: -0.025 | F8: =F6+$D$8 -> 0.51327451 | G8: =G6+$D$8 -> 0.423596 | H8: =H6+$D$8 -> 0.325 | I8: =I6+$D$8 -> 0.175 | J8: =J6+$D$8 -> 0.125
B10: Revenue Growth | F10: =CHOOSE(ScenarioREV,F6,F7,F8) -> 0.53827451 | G10: =CHOOSE(ScenarioREV,G6,G7,G8) -> 0.448596 | H10: =CHOOSE(ScenarioREV,H6,H7,H8) -> 0.35 | I10: =CHOOSE(ScenarioREV,I6,I7,I8) -> 0.2 | J10: =CHOOSE(ScenarioREV,J6,J7,J8) -> 0.15
B11: COGS % of sales | C11: =IncState!C17/IncState!C16 -> 0.24613267 | D11: =IncState!D17/IncState!D16 -> 0.23188691 | E11: =IncState!E17/IncState!E16 -> 0.22242273 | F11: =E11-0.01 -> 0.21242273 | G11: =F11-0.01 -> 0.20242273 | H11: =G11-0.01 -> 0.19242273 | I11: =H11-0.01 -> 0.18242273 | J11: =I11-0.01 -> 0.17242273
B12: R&D % of sales | C12: =IncState!C18/IncState!C16 -> 0.39256476 | D12: =IncState!D18/IncState!D16 -> 0.44782969 | E12: =IncState!E18/IncState!E16 -> 0.4009482 | F12: =E12-0.01 -> 0.3909482 | G12: =F12 -> 0.3909482 | H12: =G12 -> 0.3909482 | I12: =H12 -> 0.3909482 | J12: =I12 -> 0.3909482
B13: SG&A % of sales | C13: =IncState!C19/IncState!C16 -> 0.77647668 | D13: =IncState!D19/IncState!D16 -> 0.77006681 | E13: =IncState!E19/IncState!E16 -> 0.67183262 | F13: =E13-0.075 -> 0.59683262 | G13: =F13-0.075 -> 0.52183262 | H13: =G13-0.075 -> 0.44683262 | I13: =H13-0.075 -> 0.37183262 | J13: =I13-0.075 -> 0.29683262
B14: Amortization $ Amt | C14: =IncState!C23 -> 0 | D14: =IncState!D23 -> 0 | E14: =IncState!E23 -> 0 | F14: =E14 -> 0 | G14: =F14 -> 0 | H14: =G14 -> 0 | I14: =H14 -> 0 | J14: =I14 -> 0
B15: Stock Based compensation growth | D15: =IncState!D24/IncState!C24-1 -> 0.47238328 | E15: =IncState!E24/IncState!D24-1 -> 0.17031408 | F15: =AVERAGE(D15:E15) -> 0.32134868 | G15: =F15 -> 0.32134868 | H15: =G15 -> 0.32134868 | I15: =H15 -> 0.32134868 | J15: =I15 -> 0.32134868
B16: Non recurring income / (expense) | C16: =IncState!C27 -> 0 | D16: =IncState!D27 -> 0 | E16: =IncState!E27 -> 0 | F16: 0 | G16: 0 | H16: 0 | I16: 0 | J16: 0
B17: Other Income / (expense) | C17: =IncState!C28 -> -5744 | D17: =IncState!D28 -> -527 | E17: =IncState!E28 -> -11530 | F17: 0 | G17: 0 | H17: 0 | I17: 0 | J17: 0
B18: Effective tax rate | C18: =IncState!C35/IncState!C33 -> -0.0038169374 | D18: =IncState!D35/IncState!D33 -> -0.00039189181 | E18: =IncState!E35/IncState!E33 -> -0.0043929525 | F18: 0.12 | G18: =F18 -> 0.12 | H18: =G18 -> 0.12 | I18: =H18 -> 0.12 | J18: =I18 -> 0.12
B19: Diluted WASO | C19: =IncState!C39 -> 595559 | D19: =IncState!D39 -> 616445 | E19: =IncState!E39 -> 647482 | F19: =E19 -> 647482 | G19: =F19 -> 647482 | H19: =G19 -> 647482 | I19: =H19 -> 647482 | J19: =I19 -> 647482
A21: * | B21: Debt | C21: 44926 | D21: 45291 | E21: 45657 | F21: 46022 | G21: 46387 | H21: 46752 | I21: 47118 | J21: 47483
B23: Interest rate on Revolver | E23: 0 | F23: =E23 -> 0 | G23: =F23 -> 0 | H23: =G23 -> 0 | I23: =H23 -> 0 | J23: =I23 -> 0
B24: Interest rate on long-term debt | E24: 0.04 | F24: =E24 -> 0.04 | G24: =F24 -> 0.04 | H24: =G24 -> 0.04 | I24: =H24 -> 0.04 | J24: =I24 -> 0.04
B25: Interest rate on cash | C25: =IncState!C30/BalSheet!C16 -> 0.013193174 | D25: =IncState!D30/BalSheet!D16 -> 0.2228172 | E25: =IncState!E30/BalSheet!E16 -> 0.2729873 | F25: =E25 -> 0.2729873 | G25: =F25 -> 0.2729873 | H25: =G25 -> 0.2729873 | I25: =H25 -> 0.2729873 | J25: =I25 -> 0.2729873
B27: Issuance of long-term debt | F27: 0 | G27: 0 | H27: 0 | I27: 0 | J27: 0
B28: Repayment of long-term debt | F28: 0 | G28: 0 | H28: 0 | I28: 0 | J28: 0
A30: * | B30: Calcs | C30: 44926 | D30: 45291 | E30: 45657 | F30: 46022 | G30: 46387 | H30: 46752 | I30: 47118 | J30: 47483
B32: CapEx % of Sales | D32: =320667/IncState!D16 -> 0.11455363 | E32: =179646/IncState!E16 -> 0.04987425 | F32: =E32 -> 0.04987425 | G32: =F32 -> 0.04987425 | H32: =G32 -> 0.04987425 | I32: =H32 -> 0.04987425 | J32: =I32 -> 0.04987425
B33: Depreciation % of beginning PP&E | D33: =IncState!D22/BalSheet!C21 -> 0.18611093 | E33: =IncState!E22/BalSheet!D21 -> 0.16644064 | F33: =AVERAGE(D33:E33) -> 0.17627579 | G33: =F33 -> 0.17627579 | H33: =G33 -> 0.17627579 | I33: =H33 -> 0.17627579 | J33: =I33 -> 0.17627579
B34: Share issuance / (repurchases) | F34: 0 | G34: 0 | H34: 0 | I34: 0 | J34: 0
A36: * | B36: Balance Sheet - Assets | C36: 44926 | D36: 45291 | E36: 45657 | F36: 46022 | G36: 46387 | H36: 46752 | I36: 47118 | J36: 47483
B38: Operating Cash % of sales | C38: =BalSheet!C15/IncState!C16 -> 0.015 | D38: =BalSheet!D15/IncState!D16 -> 0.015 | E38: =BalSheet!E15/IncState!E16 -> 0.015 | F38: =E38 -> 0.015 | G38: =F38 -> 0.015 | H38: =G38 -> 0.015 | I38: =H38 -> 0.015 | J38: =I38 -> 0.015
B39: Accounts receivable % of sales | C39: =BalSheet!C17/IncState!C16 -> 0.17049175 | D39: =BalSheet!D17/IncState!D16 -> 0.18067863 | E39: =BalSheet!E17/IncState!E16 -> 0.1706945 | F39: =E39 -> 0.1706945 | G39: =F39 -> 0.1706945 | H39: =G39 -> 0.1706945 | I39: =H39 -> 0.1706945 | J39: =I39 -> 0.1706945
B40: Other current assets % of sales | C40: =BalSheet!C18/IncState!C16 -> 0.21652393 | D40: =BalSheet!D18/IncState!D16 -> 0.74704298 | E40: =BalSheet!E18/IncState!E16 -> 0.66671932 | F40: =E40-0.1 -> 0.56671932 | G40: =F40 -> 0.56671932 | H40: =G40 -> 0.56671932 | I40: =H40 -> 0.56671932 | J40: =I40 -> 0.56671932
B41: Investments in unconsolidated entities | C41: =BalSheet!C23 -> 0 | D41: =BalSheet!D23 -> 1043399 | E41: =BalSheet!E23 -> 1610215 | F41: =E41+1000000 -> 2610215 | G41: =F41+1000000 -> 3610215 | H41: =G41+1000000 -> 4610215 | I41: =H41+1000000 -> 5610215 | J41: =I41+1000000 -> 6610215
B42: Other long-term assets % of sales | C42: =BalSheet!C24/IncState!C16 -> 0.10312343 | D42: =BalSheet!D24/IncState!D16 -> 0.10488791 | E42: =BalSheet!E24/IncState!E16 -> 0.093127417 | F42: =E42 -> 0.093127417 | G42: =F42 -> 0.093127417 | H42: =G42 -> 0.093127417 | I42: =H42 -> 0.093127417 | J42: =I42 -> 0.093127417
A44: * | B44: Balance Sheet - Liabilities | C44: 44926 | D44: 45291 | E44: 45657 | F44: 46022 | G44: 46387 | H44: 46752 | I44: 47118 | J44: 47483
B46: Accounts payable % of COGS | C46: =BalSheet!C30/IncState!C17 -> 0.5609121 | D46: =BalSheet!D30/IncState!D17 -> 0.51024549 | E46: =BalSheet!E30/IncState!E17 -> 0.39772106 | F46: =E46 -> 0.39772106 | G46: =F46 -> 0.39772106 | H46: =G46 -> 0.39772106 | I46: =H46 -> 0.39772106 | J46: =I46 -> 0.39772106
B47: Other current liabilities % of sales | C47: =BalSheet!C31/IncState!C16 -> 0.97689717 | D47: =BalSheet!D31/IncState!D16 -> 0.97209419 | E47: =BalSheet!E31/IncState!E16 -> 0.92853651 | F47: =E47 -> 0.92853651 | G47: =F47 -> 0.92853651 | H47: =G47 -> 0.92853651 | I47: =H47 -> 0.92853651 | J47: =I47 -> 0.92853651
B48: Other long-term liabilities % of sales | C48: =BalSheet!C35/IncState!C16 -> 0.71936881 | D48: =BalSheet!D35/IncState!D16 -> 0.85757236 | E48: =BalSheet!E35/IncState!E16 -> 0.73101204 | F48: =E48 -> 0.73101204 | G48: =F48 -> 0.73101204 | H48: =G48 -> 0.73101204 | I48: =H48 -> 0.73101204 | J48: =I48 -> 0.73101204

Sheet Revenue
A1: =CoName -> Roblox Corporation
A2: Revenues | C2: Q122 | D2: Q222 | E2: Q322 | F2: Q422 | G2: 2022 | H2: Q123 | I2: Q223 | J2: Q323 | K2: Q423 | L2: 2023 | M2: Q124 | N2: Q224 | O2: Q324 | P2: Q424 | Q2: 2024 | R2: Q125 | S2: Q225 | T2: Q325 | U2: Q425 | V2: 2025 | W2: Q126 | X2: Q226 | Y2: Q326 | Z2: Q426 | AA2: 2026 | AB2: =AA2+1 -> 2027 | AC2: =AB2+1 -> 2028 | AD2: =AC2+1 -> 2029
A3: * | B3: U.S. / Canada | C3: 356646 | D3: 390360 | E3: 341519 | F3: =G3-SUM(C3:E3) -> 377430 | G3: 1465955 | H3: 425763 | I3: 439523 | J3: 458563 | K3: =L3-SUM(H3:J3) -> 479963 | L3: 1803812 | M3: 509564 | N3: 565867 | O3: 583011 | P3: =Q3-SUM(M3:O3) -> 622877 | Q3: 2281319 | R3: 647266 | S3: 669648 | T3: 816680 | U3: =P3*(1+U15) -> 1301812.9 | V3: =SUM(R3:U3) -> 3435406.9 | W3: =R3*(1+W15) -> 1071225.2 | X3: =S3*(1+X15) -> 1138401.6 | Y3: =T3*(1+Y15) -> 1249520.4 | Z3: =U3*(1+Z15) -> 1510103 | AA3: =SUM(W3:Z3) -> 4969250.2 | AB3: =AA3*(1+AB8) -> 6708487.8 | AC3: =AB3*(1+AC8) -> 8050185.4 | AD3: =AC3*(1+AD8) -> 9257713.2
B4: Europe | C4: 99202 | D4: 108311 | E4: 92347 | F4: =G4-SUM(C4:E4) -> 104571 | G4: 404431 | H4: 118530 | I4: 123532 | J4: 128412 | K4: =L4-SUM(H4:J4) -> 135159 | L4: 505633 | M4: 145564 | N4: 163407 | O4: 167758 | P4: =Q4-SUM(M4:O4) -> 182864 | Q4: 659593 | R4: 193636 | S4: 204672 | T4: 264570 | U4: =P4*(1+U16) -> 382185.76 | V4: =SUM(R4:U4) -> 1045063.8 | W4: =R4*(1+W16) -> 320467.58 | X4: =S4*(1+X16) -> 347942.4 | Y4: =T4*(1+Y16) -> 404792.1 | Z4: =U4*(1+Z16) -> 443335.48 | AA4: =SUM(W4:Z4) -> 1516537.6 | AB4: =AA4*(1+AB8) -> 2047325.7 | AC4: =AB4*(1+AC8) -> 2456790.8 | AD4: =AC4*(1+AD8) -> 2825309.5
B5: APAC | C5: 45990 | D5: 53005 | E5: 48573 | F5: =G5-SUM(C5:E5) -> 56693 | G5: 204261 | H5: 65128 | I5: 69102 | J5: 73772 | K5: =L5-SUM(H5:J5) -> 78928 | L5: 286930 | M5: 85274 | N5: 95055 | O5: 95507 | P5: =Q5-SUM(M5:O5) -> 103191 | Q5: 379027 | R5: 109036 | S5: 115706 | T5: 152880 | U5: =P5*(1+U17) -> 215669.19 | V5: =SUM(R5:U5) -> 593291.19 | W5: =R5*(1+W17) -> 180454.58 | X5: =S5*(1+X17) -> 196700.2 | Y5: =T5*(1+Y17) -> 233906.4 | Z5: =U5*(1+Z17) -> 250176.26 | AA5: =SUM(W5:Z5) -> 861237.44 | AB5: =AA5*(1+AB8) -> 1162670.5 | AC5: =AB5*(1+AC8) -> 1395204.7 | AD5: =AC5*(1+AD8) -> 1604485.4
B6: Other | C6: 35286 | D6: 39531 | E6: 35268 | F6: =G6-SUM(C6:E6) -> 40320 | G6: 150405 | H6: 45923 | I6: 48609 | J6: 52478 | K6: =L6-SUM(H6:J6) -> 55889 | L6: 202899 | M6: 60898 | N6: 69214 | O6: 72677 | P6: =Q6-SUM(M6:O6) -> 79251 | Q6: 282040 | R6: 85269 | S6: 90651 | T6: 125516 | U6: =P6*(1+U18) -> 165634.59 | V6: =SUM(R6:U6) -> 467070.59 | W6: =R6*(1+W18) -> 141120.2 | X6: =S6*(1+X18) -> 154106.7 | Y6: =T6*(1+Y18) -> 192039.48 | Z6: =U6*(1+Z18) -> 192136.12 | AA6: =SUM(W6:Z6) -> 679402.5 | AB6: =AA6*(1+AB8) -> 917193.37 | AC6: =AB6*(1+AC8) -> 1100632 | AD6: =AC6*(1+AD8) -> 1265726.9
B7: TOTAL REVENUES | C7: =SUM(C3:C6) -> 537124 | D7: =SUM(D3:D6) -> 591207 | E7: =SUM(E3:E6) -> 517707 | F7: =SUM(F3:F6) -> 579014 | G7: =SUM(G3:G6) -> 2225052 | H7: =SUM(H3:H6) -> 655344 | I7: =SUM(I3:I6) -> 680766 | J7: =SUM(J3:J6) -> 713225 | ... AD7: =SUM(AD3:AD6) -> 14953235
B8: y/y | H8: =H7/C7-1 -> 0.22009815 | I8: =I7/D7-1 -> 0.15148501 | J8: =J7/E7-1 -> 0.3776615 | K8: =K7/F7-1 -> 0.29520012 | L8: =L7/G7-1 -> 0.25807127 | M8: =M7/H7-1 -> 0.22271662 | N8: =N7/I7-1 -> 0.31255527 | O8: =O7/J7-1 -> 0.28844754 | ... T8: =T7/O7-1 -> 0.47955989 | V8: =V7/Q7-1 -> 0.53827451 | AA8: =AA7/V7-1 -> 0.448596 | AB8: 0.35 | AC8: 0.2 | AD8: 0.15
A10: % | B10: =B3 -> U.S. / Canada | C10: =C3/C7 -> 0.66399193 | D10: =D3/D7 -> 0.66027635 | E10: =E3/E7 -> 0.65967623 | F10: =F3/F7 -> 0.65184952 | G10: =G3/G7 -> 0.65884078 | H10: =H3/H7 -> 0.64967864 | I10: =I3/I7 -> 0.64563007 | J10: =J3/J7 -> 0.64294297 | ... AA10: =AA3/AA7 -> 0.61911107
A11: % | B11: =B4 -> Europe | C11: =C4/C7 -> 0.18469106 | D11: =D4/D7 -> 0.18320318 | E11: =E4/E7 -> 0.17837696 | F11: =F4/F7 -> 0.18060185 | G11: =G4/G7 -> 0.18176249 | H11: =H4/H7 -> 0.18086684 | I11: =I4/I7 -> 0.1814603 | J11: =J4/J7 -> 0.18004417 | ... AA11: =AA4/AA7 -> 0.18894303
A12: % | B12: =B5 -> APAC | C12: =C5/C7 -> 0.085622687 | D12: =D5/D7 -> 0.089655569 | E12: =E5/E7 -> 0.09382334 | F12: =F5/F7 -> 0.097913004 | G12: =G5/G7 -> 0.091800551 | H12: =H5/H7 -> 0.099379868 | I12: =I5/I7 -> 0.10150624 | J12: =J5/J7 -> 0.1034344 | ... AA12: =AA5/AA7 -> 0.10730022
A13: % | B13: =B6 -> Other | C13: =C6/C7 -> 0.065694328 | D13: =D6/D7 -> 0.066864905 | E13: =E6/E7 -> 0.068123475 | F13: =F6/F7 -> 0.069635622 | G13: =G6/G7 -> 0.067596173 | H13: =H6/H7 -> 0.070074648 | I13: =I6/I7 -> 0.07140339 | J13: =J6/J7 -> 0.073578464 | ... AA13: =AA6/AA7 -> 0.084645688
A15: y | B15: =B10 -> U.S. / Canada | H15: =H3/C3-1 -> 0.19379721 | I15: =I3/D3-1 -> 0.12594272 | J15: =J3/E3-1 -> 0.34271593 | K15: =K3/F3-1 -> 0.27166097 | L15: =L3/G3-1 -> 0.23046888 | M15: =M3/H3-1 -> 0.19682546 | N15: =N3/I3-1 -> 0.28745708 | O15: =O3/J3-1 -> 0.27138692 | ... T15: =T3/O3-1 -> 0.4007969 | U15: 1.09 | V15: =V3/Q3-1 -> 0.50588626 | W15: 0.655 | X15: 0.7 | Y15: 0.53 | Z15: 0.16 | AA15: =AA3/V3-1 -> 0.44648082
A16: y | B16: =B11 -> Europe | H16: =H4/C4-1 -> 0.19483478 | I16: =I4/D4-1 -> 0.14053051 | J16: =J4/E4-1 -> 0.39053786 | K16: =K4/F4-1 -> 0.2925094 | L16: =L4/G4-1 -> 0.25023304 | M16: =M4/H4-1 -> 0.22807728 | N16: =N4/I4-1 -> 0.32279086 | O16: =O4/J4-1 -> 0.30640439 | ... T16: =T4/O4-1 -> 0.57709319 | U16: 1.09 | V16: =V4/Q4-1 -> 0.58440699 | W16: 0.655 | X16: 0.7 | Y16: 0.53 | Z16: 0.16 | AA16: =AA4/V4-1 -> 0.45114358
A17: y | B17: =B12 -> APAC | H17: =H5/C5-1 -> 0.41613394 | I17: =I5/D5-1 -> 0.30368833 | J17: =J5/E5-1 -> 0.51878616 | K17: =K5/F5-1 -> 0.3922001 | L17: =L5/G5-1 -> 0.40472239 | M17: =M5/H5-1 -> 0.30932932 | N17: =N5/I5-1 -> 0.37557524 | O17: =O5/J5-1 -> 0.29462398 | ... T17: =T5/O5-1 -> 0.60072037 | U17: 1.09 | V17: =V5/Q5-1 -> 0.5653006 | W17: 0.655 | X17: 0.7 | Y17: 0.53 | Z17: 0.16 | AA17: =AA5/V5-1 -> 0.45162688
A18: y | B18: =B13 -> Other | H18: =H6/C6-1 -> 0.301451 | I18: =I6/D6-1 -> 0.22964256 | J18: =J6/E6-1 -> 0.48797777 | K18: =K6/F6-1 -> 0.38613591 | L18: =L6/G6-1 -> 0.34901765 | M18: =M6/H6-1 -> 0.32608932 | N18: =N6/I6-1 -> 0.42389269 | O18: =O6/J6-1 -> 0.38490415 | ... T18: =T6/O6-1 -> 0.72703882 | U18: 1.09 | V18: =V6/Q6-1 -> 0.65604379 | W18: 0.655 | X18: 0.7 | Y18: 0.53 | Z18: 0.16 | AA18: =AA6/V6-1 -> 0.45460347

Sheet Calcs
A1: =CoName -> Roblox Corporation | C1: Hist. | D1: Hist. | E1: Hist. | F1: Proj. | G1: Proj. | H1: Proj. | I1: Proj. | J1: Proj.
A2: Net PP&E | C2: 2022 | D2: =C2+1 -> 2023 | E2: =D2+1 -> 2024 | F2: =E2+1 -> 2025 | G2: =F2+1 -> 2026 | H2: =G2+1 -> 2027 | I2: =H2+1 -> 2028 | J2: =I2+1 -> 2029
B3: Capital expenditure % of sales | F3: =Assumptions!F32 -> 0.04987425 | G3: =Assumptions!G32 -> 0.04987425 | H3: =Assumptions!H32 -> 0.04987425 | I3: =Assumptions!I32 -> 0.04987425 | J3: =Assumptions!J32 -> 0.04987425
B4: Depreciation % of PP&E | F4: =Assumptions!F33 -> 0.17627579 | G4: =F4 -> 0.17627579 | H4: =G4 -> 0.17627579 | I4: =H4 -> 0.17627579 | J4: =I4 -> 0.17627579
B6: Beginning PP&E | F6: =E9 -> 1325474 | G6: =F9 -> 1368169.9 | H6: =G9 -> 1527306.7 | I6: =H9 -> 1798500.8 | J6: =I9 -> 2129974.2
B7: Capex | F7: =F3*IncState!F16 -> 276344.86 | G7: =G3*IncState!G16 -> 400312.06 | H7: =H3*IncState!H16 -> 540421.28 | I7: =I3*IncState!I16 -> 648505.54 | J7: =J3*IncState!J16 -> 745781.37
B8: Depreciation | F8: =F6*F4 -> 233648.97 | G8: =G6*G4 -> 241175.22 | H8: =H6*H4 -> 269227.19 | I8: =I6*I4 -> 317032.15 | J8: =J6*J4 -> 375462.88
B9: Ending PP&E | E9: =BalSheet!E21 -> 1325474 | F9: =F6+F7-F8 -> 1368169.9 | G9: =G6+G7-G8 -> 1527306.7 | H9: =H6+H7-H8 -> 1798500.8 | I9: =I6+I7-I8 -> 2129974.2 | J9: =J6+J7-J8 -> 2500292.7
A10: Equity | C10: =C2 -> 2022 | D10: =D2 -> 2023 | E10: =E2 -> 2024 | F10: =F2 -> 2025 | G10: =G2 -> 2026 | H10: =H2 -> 2027 | I10: =I2 -> 2028 | J10: =J2 -> 2029
B11: Share issuance/(repurchases) | F11: =Assumptions!F34 -> 0 | G11: =Assumptions!G34 -> 0 | H11: =Assumptions!H34 -> 0 | I11: =Assumptions!I34 -> 0 | J11: =Assumptions!J34 -> 0
B13: Beginning balance | F13: =E17 -> 208654 | G13: =F17 -> 574693.03 | H13: =G17 -> 1534518.9 | I13: =H17 -> 3589978.2 | J13: =I17 -> 7313515.8
B14: Net income | F14: =IncState!F36 -> -976179.03 | G14: =IncState!G36 -> -813712.24 | H14: =IncState!H36 -> -288002.85 | I14: =IncState!I36 -> 627006.99 | J14: =IncState!J36 -> 1839560
B15: Additional Paid Capital | F15: =IncState!F24 -> 1342218.1 | G15: =IncState!G24 -> 1773538.1 | H15: =IncState!H24 -> 2343462.2 | I15: =IncState!I24 -> 3096530.7 | J15: =IncState!J24 -> 4091596.7
B16: Share issuance / (repurchase) | F16: =F11 -> 0 | G16: =G11 -> 0 | H16: =H11 -> 0 | I16: =I11 -> 0 | J16: =J11 -> 0
B17: Ending balance | E17: =BalSheet!E38 -> 208654 | F17: =SUM(F13:F16) -> 574693.03 | G17: =SUM(G13:G16) -> 1534518.9 | H17: =SUM(H13:H16) -> 3589978.2 | I17: =SUM(I13:I16) -> 7313515.8 | J17: =SUM(J13:J16) -> 13244673
A18: OWC | C18: =C10 -> 2022 | D18: =D10 -> 2023 | E18: =E10 -> 2024 | F18: =F10 -> 2025 | G18: =G10 -> 2026 | H18: =H10 -> 2027 | I18: =I10 -> 2028 | J18: =J10 -> 2029
B19: Operating Cash | E19: =BalSheet!E15 -> 54029.685 | F19: =BalSheet!F15 -> 83112.487 | G19: =BalSheet!G15 -> 120396.42 | H19: =BalSheet!H15 -> 162535.16 | I19: =BalSheet!I15 -> 195042.19 | J19: =BalSheet!J15 -> 224298.52
B20: =BalSheet!B17 -> Accounts receivable | E20: =BalSheet!E17 -> 614838 | F20: =BalSheet!F17 -> 945789.62 | G20: =BalSheet!G17 -> 1370067.1 | H20: =BalSheet!H17 -> 1849590.5 | I20: =BalSheet!I17 -> 2219508.6 | J20: =BalSheet!J17 -> 2552434.9
B21: Other current assets | E21: =BalSheet!E18 -> 2401509 | F21: =BalSheet!F18 -> 3140096.8 | G21: =BalSheet!G18 -> 4548731.7 | H21: =BalSheet!H18 -> 6140787.8 | I21: =BalSheet!I18 -> 7368945.3 | J21: =BalSheet!J18 -> 8474287.1
B22: Accounts payables | E22: =BalSheet!E30 -> 318639 | F22: =BalSheet!F30 -> 468117.19 | G22: =BalSheet!G30 -> 646189.9 | H22: =BalSheet!H30 -> 829260.59 | I22: =BalSheet!I30 -> 943397.78 | J22: =BalSheet!J30 -> 1025435.3
B23: Other current liabilities | E23: =BalSheet!E31 -> 3344569 | F23: =BalSheet!F31 -> 5144865.2 | G23: =BalSheet!G31 -> 7452831.2 | H23: =BalSheet!H31 -> 10061322 | I23: =BalSheet!I31 -> 12073586 | J23: =BalSheet!J31 -> 13884624
A24: * | B24: OWC | E24: =SUM(E19:E21)-SUM(E22:E23) -> -592831.31 | F24: =SUM(F19:F21)-SUM(F22:F23) -> -1443983.5 | G24: =SUM(G19:G21)-SUM(G22:G23) -> -2059825.9 | H24: =SUM(H19:H21)-SUM(H22:H23) -> -2737669.2 | I24: =SUM(I19:I21)-SUM(I22:I23) -> -3233488.1 | J24: =SUM(J19:J21)-SUM(J22:J23) -> -3659039.2
B25: Change in OWC | F25: =E24-F24 -> 851152.17 | G25: =F24-G24 -> 615842.42 | H25: =G24-H24 -> 677843.3 | I25: =H24-I24 -> 495818.91 | J25: =I24-J24 -> 425551.05

Sheet Debt
A1: =CoName -> Roblox Corporation | C1: Hist. | D1: Hist. | E1: Hist. | F1: Proj. | G1: Proj. | H1: Proj. | I1: Proj. | J1: Proj.
A2: Assumptions | C2: 44926 | D2: 45291 | E2: 45657 | F2: 46022 | G2: 46387 | H2: 46752 | I2: 47118 | J2: 47483
B4: Interest rate on revolver | F4: =Assumptions!F23 -> 0 | G4: =Assumptions!G23 -> 0 | H4: =Assumptions!H23 -> 0 | I4: =Assumptions!I23 -> 0 | J4: =Assumptions!J23 -> 0
B5: Interest rate on long-term debt | F5: =Assumptions!F24 -> 0.04 | G5: =Assumptions!G24 -> 0.04 | H5: =Assumptions!H24 -> 0.04 | I5: =Assumptions!I24 -> 0.04 | J5: =Assumptions!J24 -> 0.04
B6: Interest rate on cash | F6: =Assumptions!F25 -> 0.2729873 | G6: =Assumptions!G25 -> 0.2729873 | H6: =Assumptions!H25 -> 0.2729873 | I6: =Assumptions!I25 -> 0.2729873 | J6: =Assumptions!J25 -> 0.2729873
B8: Issuance of long-term debt | F8: =Assumptions!F27 -> 0 | G8: =Assumptions!G27 -> 0 | H8: =Assumptions!H27 -> 0 | I8: =Assumptions!I27 -> 0 | J8: =Assumptions!J27 -> 0
B9: Repayment of long-term debt | F9: =Assumptions!F28 -> 0 | G9: =Assumptions!G28 -> 0 | H9: =Assumptions!H28 -> 0 | I9: =Assumptions!I28 -> 0 | J9: =Assumptions!J28 -> 0
A11: Revolver | C11: =C2 -> 44926 | D11: =D2 -> 45291 | E11: =E2 -> 45657 | F11: =F2 -> 46022 | G11: =G2 -> 46387 | H11: =H2 -> 46752 | I11: =I2 -> 47118 | J11: =J2 -> 47483
B12: Balance | F12: NO REVOLVER
B13: Interest rate
B14: Interest expense
A16: Long term debt | C16: =C11 -> 44926 | D16: =D11 -> 45291 | E16: =E11 -> 45657 | F16: =F11 -> 46022 | G16: =G11 -> 46387 | H16: =H11 -> 46752 | I16: =I11 -> 47118 | J16: =J11 -> 47483
B17: Beginning balance | F17: =E20 -> 670051 | G17: =F20 -> 670051 | H17: =G20 -> 670051 | I17: =H20 -> 670051 | J17: =I20 -> 670051
B18: Issuance | F18: =F8 -> 0 | G18: =G8 -> 0 | H18: =H8 -> 0 | I18: =I8 -> 0 | J18: =J8 -> 0
B19: Repayment | F19: =F9 -> 0 | G19: =G9 -> 0 | H19: =H9 -> 0 | I19: =I9 -> 0 | J19: =J9 -> 0
B20: Ending balance | E20: =BalSheet!E34 -> 670051 | F20: =SUM(F17:F19) -> 670051 | G20: =SUM(G17:G19) -> 670051 | H20: =SUM(H17:H19) -> 670051 | I20: =SUM(I17:I19) -> 670051 | J20: =SUM(J17:J19) -> 670051
B21: Interest rate | F21: =F5 -> 0.04 | G21: =G5 -> 0.04 | H21: =H5 -> 0.04 | I21: =I5 -> 0.04 | J21: =J5 -> 0.04
B22: Interest expense | F22: =F20*F21 -> 26802.04 | G22: =G20*G21 -> 26802.04 | H22: =H20*H21 -> 26802.04 | I22: =I20*I21 -> 26802.04 | J22: =J20*J21 -> 26802.04
A24: Debt summary | C24: =C16 -> 44926 | D24: =D16 -> 45291 | E24: =E16 -> 45657 | F24: =F16 -> 46022 | G24: =G16 -> 46387 | H24: =H16 -> 46752 | I24: =I16 -> 47118 | J24: =J16 -> 47483
B25: Revolver | F25: =F12 -> NO REVOLVER | G25: =G12 -> 0 | H25: =H12 -> 0 | I25: =I12 -> 0 | J25: =J12 -> 0
B26: Total long term debt | F26: =F20 -> 670051 | G26: =G20 -> 670051 | H26: =H20 -> 670051 | I26: =I20 -> 670051 | J26: =J20 -> 670051
B27: Total debt | F27: =SUM(F25:F26) -> 670051 | G27: =SUM(G25:G26) -> 670051 | H27: =SUM(H25:H26) -> 670051 | I27: =SUM(I25:I26) -> 670051 | J27: =SUM(J25:J26) -> 670051
B28: Total interest expense | F28: =F22 -> 26802.04 | G28: =G22 -> 26802.04 | H28: =H22 -> 26802.04 | I28: =I22 -> 26802.04 | J28: =J22 -> 26802.04
A30: Interest income | C30: =C11 -> 44926 | D30: =D11 -> 45291 | E30: =E11 -> 45657 | F30: =F11 -> 46022 | G30: =G11 -> 46387 | H30: =H11 -> 46752 | I30: =I11 -> 47118 | J30: =J11 -> 47483
B31: Excess Cash | F31: =BalSheet!F16 -> 2068913.4 | G31: =BalSheet!G16 -> 4070967.8 | H31: =BalSheet!H16 -> 7325053.6 | I31: =BalSheet!I16 -> 11595319 | J31: =BalSheet!J16 -> 17825853
B32: Interest rate | F32: =F6 -> 0.2729873 | G32: =G6 -> 0.2729873 | H32: =H6 -> 0.2729873 | I32: =I6 -> 0.2729873 | J32: =J6 -> 0.2729873
B33: Interest income | F33: =F31*F32 -> 564787.08 | G33: =G31*G32 -> 1111322.5 | H33: =H31*H32 -> 1999646.6 | I33: =I31*I32 -> 3165374.8 | J33: =J31*J32 -> 4866231.3

Sheet IncState
A1: =CoName -> Roblox Corporation | C1: Hist. | D1: Hist. | E1: Hist. | F1: Proj. | G1: Proj. | H1: Proj. | I1: Proj. | J1: Proj.
A2: Assumptions | C2: 44926 | D2: 45291 | E2: 45657 | F2: 46022 | G2: 46387 | H2: 46752 | I2: 47118 | J2: 47483
B4: Revenue growth | F4: =Assumptions!F10 -> 0.53827451 | G4: =Assumptions!G10 -> 0.448596 | H4: =Assumptions!H10 -> 0.35 | I4: =Assumptions!I10 -> 0.2 | J4: =Assumptions!J10 -> 0.15
B5: Cost of goods sold as % of sales | F5: =Assumptions!F11 -> 0.21242273 | G5: =Assumptions!G11 -> 0.20242273 | H5: =Assumptions!H11 -> 0.19242273 | I5: =Assumptions!I11 -> 0.18242273 | J5: =Assumptions!J11 -> 0.17242273
B6: R&D % of sales | F6: =Assumptions!F12 -> 0.3909482 | G6: =Assumptions!G12 -> 0.3909482 | H6: =Assumptions!H12 -> 0.3909482 | I6: =Assumptions!I12 -> 0.3909482 | J6: =Assumptions!J12 -> 0.3909482
B7: SG&A % of sales | F7: =Assumptions!F13 -> 0.59683262 | G7: =Assumptions!G13 -> 0.52183262 | H7: =Assumptions!H13 -> 0.44683262 | I7: =Assumptions!I13 -> 0.37183262 | J7: =Assumptions!J13 -> 0.29683262
B8: Amortization amount | F8: =Assumptions!F14 -> 0 | G8: =Assumptions!G14 -> 0 | H8: =Assumptions!H14 -> 0 | I8: =Assumptions!I14 -> 0 | J8: =Assumptions!J14 -> 0
B9: =B24 -> Stock Based Compensation | F9: =Assumptions!F15 -> 0.32134868 | G9: =Assumptions!G15 -> 0.32134868 | H9: =Assumptions!H15 -> 0.32134868 | I9: =Assumptions!I15 -> 0.32134868 | J9: =Assumptions!J15 -> 0.32134868
B10: Non recurring items, amount | F10: =Assumptions!F16 -> 0 | G10: =Assumptions!G16 -> 0 | H10: =Assumptions!H16 -> 0 | I10: =Assumptions!I16 -> 0 | J10: =Assumptions!J16 -> 0
B11: Other income (expense), amt | F11: =Assumptions!F17 -> 0 | G11: =Assumptions!G17 -> 0 | H11: =Assumptions!H17 -> 0 | I11: =Assumptions!I17 -> 0 | J11: =Assumptions!J17 -> 0
B12: Effective tax rate | F12: =Assumptions!F18 -> 0.12 | G12: =Assumptions!G18 -> 0.12 | H12: =Assumptions!H18 -> 0.12 | I12: =Assumptions!I18 -> 0.12 | J12: =Assumptions!J18 -> 0.12
B13: Diluted WASO | F13: =Assumptions!F19 -> 647482 | G13: =Assumptions!G19 -> 647482 | H13: =Assumptions!H19 -> 647482 | I13: =Assumptions!I19 -> 647482 | J13: =Assumptions!J19 -> 647482
A15: Income statement | C15: =C38 -> 44926 | D15: =D38 -> 45291 | E15: =E38 -> 45657 | F15: =F38 -> 46022 | G15: =G38 -> 46022 | H15: =H38 -> 46022 | I15: =I38 -> 46022 | J15: =J38 -> 46022
B16: Revenue | C16: 2225052 | D16: 2799274 | E16: 3601979 | F16: =E16*(1+F4) -> 5540832.5 | G16: =F16*(1+G4) -> 8026427.7 | H16: =G16*(1+H4) -> 10835677 | I16: =H16*(1+I4) -> 13002813 | J16: =I16*(1+J4) -> 14953235
B17: COGS | C17: 547658 | D17: 649115 | E17: 801162 | F17: =F16*F5 -> 1176998.8 | G17: =G16*G5 -> 1624731.4 | H17: =H16*H5 -> 2085030.6 | I17: =I16*I5 -> 2372008.6 | J17: =J16*J5 -> 2578277.6
B18: R&D | C18: 873477 | D18: 1253598 | E18: 1444207 | F18: =F16*F6 -> 2166178.5 | G18: =G16*G6 -> 3137917.5 | H18: =H16*H6 -> 4236188.6 | I18: =I16*I6 -> 5083426.3 | J18: =J16*J6 -> 5845940.3
B19: SG&A | C19: =3148836-SUM(C17:C18) -> 1727701 | D19: =4058341-SUM(D17:D18) -> 2155628 | E19: =4665296-SUM(E17:E18) -> 2419927 | F19: =F16*F7 -> 3306949.6 | G19: =G16*G7 -> 4188451.8 | H19: =H16*H7 -> 4841734.2 | I19: =I16*I7 -> 4834870 | J19: =J16*J7 -> 4438607.9
A20: * | B20: EBIT | C20: =C16-SUM(C17:C19) -> -923784 | D20: =D16-SUM(D17:D19) -> -1259067 | E20: =E16-SUM(E17:E19) -> -1063317 | F20: =F16-SUM(F17:F19) -> -1109294.3 | G20: =G16-SUM(G17:G19) -> -924673 | H20: =H16-SUM(H17:H19) -> -327275.96 | I20: =I16-SUM(I17:I19) -> 712507.94 | J20: =J16-SUM(J17:J19) -> 2090409.1
B22: Depreciation | C22: 130083 | D22: 208142 | E22: 226437 | F22: =Calcs!F8 -> 233648.97 | G22: =Calcs!G8 -> 241175.22 | H22: =Calcs!H8 -> 269227.19 | I22: =Calcs!I8 -> 317032.15 | J22: =Calcs!J8 -> 375462.88
B23: Amortization | C23: 0 | D23: 0 | E23: 0 | F23: =F8 -> 0 | G23: =G8 -> 0 | H23: =H8 -> 0 | I23: =I8 -> 0 | J23: =J8 -> 0
B24: Stock Based Compensation | C24: 589498 | D24: 867967 | E24: 1015794 | F24: =E24*(1+F9) -> 1342218.1 | G24: =F24*(1+G9) -> 1773538.1 | H24: =G24*(1+H9) -> 2343462.2 | I24: =H24*(1+I9) -> 3096530.7 | J24: =I24*(1+J9) -> 4091596.7
A25: * | B25: EBITDA | C25: =C20+SUM(C22:C24) -> -204203 | D25: =D20+SUM(D22:D24) -> -182958 | E25: =E20+SUM(E22:E24) -> 178914 | F25: =F20+SUM(F22:F24) -> 466572.68 | G25: =G20+SUM(G22:G24) -> 1090040.3 | H25: =H20+SUM(H22:H24) -> 2285413.4 | I25: =I20+SUM(I22:I24) -> 4126070.8 | J25: =J20+SUM(J22:J24) -> 6557468.7
B27: Non-recurring items | F27: =F10 -> 0 | G27: =G10 -> 0 | H27: =H10 -> 0 | I27: =I10 -> 0 | J27: =J10 -> 0
B28: Other income (expense) | C28: -5744 | D28: -527 | E28: -11530 | F28: =F11 -> 0 | G28: =G11 -> 0 | H28: =H11 -> 0 | I28: =I11 -> 0 | J28: =J11 -> 0
B30: Interest income | C30: 38842 | D30: 141818 | E30: 179531 | F30: =IF(circ=1,Debt!F33,0) -> 0 | G30: =IF(circ=1,Debt!G33,0) -> 0 | H30: =IF(circ=1,Debt!H33,0) -> 0 | I30: =IF(circ=1,Debt!I33,0) -> 0 | J30: =IF(circ=1,Debt!J33,0) -> 0
B31: Interest expense | C31: -39903 | D31: -40707 | E31: -41184 | F31: =IF(circ=1,Debt!F28,0) -> 0 | G31: =IF(circ=1,Debt!G28,0) -> 0 | H31: =IF(circ=1,Debt!H28,0) -> 0 | I31: =IF(circ=1,Debt!I28,0) -> 0 | J31: =IF(circ=1,Debt!J28,0) -> 0
A33: * | B33: Pretax Income | C33: =C20+SUM(C30:C31,C27:C28) -> -930589 | D33: =D20+SUM(D30:D31,D27:D28) -> -1158483 | E33: =E20+SUM(E30:E31,E27:E28) -> -936500 | F33: =F20+SUM(F30:F31,F27:F28) -> -1109294.3 | G33: =G20+SUM(G30:G31,G27:G28) -> -924673 | H33: =H20+SUM(H30:H31,H27:H28) -> -327275.96 | I33: =I20+SUM(I30:I31,I27:I28) -> 712507.94 | J33: =J20+SUM(J30:J31,J27:J28) -> 2090409.1
B35: Tax expense | C35: 3552 | D35: 454 | E35: 4114 | F35: =F33*F12 -> -133115.32 | G35: =G33*G12 -> -110960.76 | H35: =H33*H12 -> -39273.115 | I35: =I33*I12 -> 85500.953 | J35: =J33*J12 -> 250849.09
A36: * | B36: Net income | C36: =C33-C35 -> -934141 | D36: =D33-D35 -> -1158937 | E36: =E33-E35 -> -940614 | F36: =F33-F35 -> -976179.03 | G36: =G33-G35 -> -813712.24 | H36: =H33-H35 -> -288002.85 | I36: =I33-I35 -> 627006.99 | J36: =J33-J35 -> 1839560
A38: Shareholder information | C38: 44926 | D38: 45291 | E38: 45657 | F38: 46022 | G38: 46022 | H38: 46022 | I38: 46022 | J38: 46022
B39: Diluted WASO | C39: 595559 | D39: 616445 | E39: 647482 | F39: =F13 -> 647482 | G39: =G13 -> 647482 | H39: =H13 -> 647482 | I39: =I13 -> 647482 | J39: =J13 -> 647482
A40: * | B40: Diluted earnings per share | C40: =C36/C39 -> -1.5685113 | D40: =D36/D39 -> -1.8800331 | E40: =E36/E39 -> -1.4527261 | F40: =F36/F39 -> -1.5076543 | G40: =G36/G39 -> -1.2567334 | H40: =H36/H39 -> -0.44480441 | I40: =I36/I39 -> 0.96837749 | J40: =J36/J39 -> 2.8410983

Sheet BalSheet
A1: =CoName -> Roblox Corporation | C1: Hist. | D1: Hist. | E1: Hist. | F1: Proj. | G1: Proj. | H1: Proj. | I1: Proj. | J1: Proj.
A2: Assumptions | C2: 44926 | D2: 45291 | E2: 45657 | F2: 46022 | G2: 46387 | H2: 46752 | I2: 47118 | J2: 47483
B4: Operating Cash % of sales | F4: =Assumptions!F38 -> 0.015 | G4: =F4 -> 0.015 | H4: =G4 -> 0.015 | I4: =H4 -> 0.015 | J4: =I4 -> 0.015
B5: Accounts receivable % of sales | F5: =Assumptions!F39 -> 0.1706945 | G5: =Assumptions!G39 -> 0.1706945 | H5: =Assumptions!H39 -> 0.1706945 | I5: =Assumptions!I39 -> 0.1706945 | J5: =Assumptions!J39 -> 0.1706945
B6: Other current assets % of sales | F6: =Assumptions!F40 -> 0.56671932 | G6: =Assumptions!G40 -> 0.56671932 | H6: =Assumptions!H40 -> 0.56671932 | I6: =Assumptions!I40 -> 0.56671932 | J6: =Assumptions!J40 -> 0.56671932
B7: Other long-term assets % of sales | F7: =Assumptions!F42 -> 0.093127417 | G7: =Assumptions!G42 -> 0.093127417 | H7: =Assumptions!H42 -> 0.093127417 | I7: =Assumptions!I42 -> 0.093127417 | J7: =Assumptions!J42 -> 0.093127417
B8: Investment in unconsolidated entities $ balance | F8: =Assumptions!F41 -> 2610215 | G8: =Assumptions!G41 -> 3610215 | H8: =Assumptions!H41 -> 4610215 | I8: =Assumptions!I41 -> 5610215 | J8: =Assumptions!J41 -> 6610215
B10: Accounts payable/Accural % of COGS | F10: =Assumptions!F46 -> 0.39772106 | G10: =Assumptions!G46 -> 0.39772106 | H10: =Assumptions!H46 -> 0.39772106 | I10: =Assumptions!I46 -> 0.39772106 | J10: =Assumptions!J46 -> 0.39772106
B11: Other current liabilities % of sales | F11: =Assumptions!F47 -> 0.92853651 | G11: =Assumptions!G47 -> 0.92853651 | H11: =Assumptions!H47 -> 0.92853651 | I11: =Assumptions!I47 -> 0.92853651 | J11: =Assumptions!J47 -> 0.92853651
B12: Other long-term liabilities % of sales | F12: =Assumptions!F48 -> 0.73101204 | G12: =Assumptions!G48 -> 0.73101204 | H12: =Assumptions!H48 -> 0.73101204 | I12: =Assumptions!I48 -> 0.73101204 | J12: =Assumptions!J48 -> 0.73101204
A14: Balance sheet | C14: =C2 -> 44926 | D14: =D2 -> 45291 | E14: =E2 -> 45657 | F14: =F2 -> 46022 | G14: =G2 -> 46387 | H14: =H2 -> 46752 | I14: =I2 -> 47118 | J14: =J2 -> 47483
B15: Operating Cash | C15: =1.5%*IncState!C16 -> 33375.78 | D15: =1.5%*IncState!D16 -> 41989.11 | E15: =1.5%*IncState!E16 -> 54029.685 | F15: =F4*IncState!F16 -> 83112.487 | G15: =G4*IncState!G16 -> 120396.42 | H15: =H4*IncState!H16 -> 162535.16 | I15: =I4*IncState!I16 -> 195042.19 | J15: =J4*IncState!J16 -> 224298.52
B16: Excess cash | C16: =2977474-C15 -> 2944098.2 | D16: =678466-D15 -> 636476.89 | E16: =711683-E15 -> 657653.31 | F16: =MAX(CashFlow!F25,0) -> 2068913.4 | G16: =MAX(CashFlow!G25,0) -> 4070967.8 | H16: =MAX(CashFlow!H25,0) -> 7325053.6 | I16: =MAX(CashFlow!I25,0) -> 11595319 | J16: =MAX(CashFlow!J25,0) -> 17825853
B17: Accounts receivable | C17: 379353 | D17: 505769 | E17: 614838 | F17: =F5*IncState!F16 -> 945789.62 | G17: =G5*IncState!G16 -> 1370067.1 | H17: =H5*IncState!H16 -> 1849590.5 | I17: =I5*IncState!I16 -> 2219508.6 | J17: =J5*IncState!J16 -> 2552434.9
B18: Other current assets | C18: =61641+420136 -> 481777 | D18: =74549+501821+1514808 -> 2091178 | E18: =1697862+628232+75415 -> 2401509 | F18: =F6*IncState!F16 -> 3140096.8 | G18: =G6*IncState!G16 -> 4548731.7 | H18: =H6*IncState!H16 -> 6140787.8 | I18: =I6*IncState!I16 -> 7368945.3 | J18: =J6*IncState!J16 -> 8474287.1
B19: Total current assets | C19: =SUM(C15:C18) -> 3838604 | D19: =SUM(D15:D18) -> 3275413 | E19: =SUM(E15:E18) -> 3728030 | F19: =SUM(F15:F18) -> 6237912.4 | G19: =SUM(G15:G18) -> 10110163 | H19: =SUM(H15:H18) -> 15477967 | I19: =SUM(I15:I18) -> 21378815 | J19: =SUM(J15:J18) -> 29076873
B21: Property, plant & equipment, net | C21: =592346+526030 -> 1118376 | D21: =695360+665107 -> 1360467 | E21: =659589+665885 -> 1325474 | F21: =Calcs!F9 -> 1368169.9 | G21: =Calcs!G9 -> 1527306.7 | H21: =Calcs!H9 -> 1798500.8 | I21: =Calcs!I9 -> 2129974.2 | J21: =Calcs!J9 -> 2500292.7
B22: Intangible assets | C22: =54717+134335 -> 189052 | D22: =142129+53060 -> 195189 | E22: =34153+141688 -> 175841 | F22: =E22-IncState!F23 -> 175841 | G22: =F22-IncState!G23 -> 175841 | H22: =G22-IncState!H23 -> 175841 | I22: =H22-IncState!I23 -> 175841 | J22: =I22-IncState!J23 -> 175841
B23: Investment in unconsolidated entities | C23: 0 | D23: 1043399 | E23: 1610215 | F23: =F8 -> 2610215 | G23: =G8 -> 3610215 | H23: =H8 -> 4610215 | I23: =I8 -> 5610215 | J23: =J8 -> 6610215
B24: Other assets | C24: =4323+225132 -> 229455 | D24: =10284+283326 -> 293610 | E24: =13619+321824 -> 335443 | F24: =F7*IncState!F16 -> 516003.42 | G24: =G7*IncState!G16 -> 747480.48 | H24: =H7*IncState!H16 -> 1009098.6 | I24: =I7*IncState!I16 -> 1210918.4 | J24: =J7*IncState!J16 -> 1392556.1
B25: Total non-current assets | C25: =SUM(C21:C24) -> 1536883 | D25: =SUM(D21:D24) -> 2892665 | E25: =SUM(E21:E24) -> 3446973 | F25: =SUM(F21:F24) -> 4670229.3 | G25: =SUM(G21:G24) -> 6060843.2 | H25: =SUM(H21:H24) -> 7593655.5 | I25: =SUM(I21:I24) -> 9126948.6 | J25: =SUM(J21:J24) -> 10678905
A27: * | B27: TOTAL ASSETS | C27: =SUM(C25,C19) -> 5375487 | D27: =SUM(D25,D19) -> 6168078 | E27: =SUM(E25,E19) -> 7175003 | F27: =SUM(F25,F19) -> 10908142 | G27: =SUM(G25,G19) -> 16171006 | H27: =SUM(H25,H19) -> 23071622 | I27: =SUM(I25,I19) -> 30505764 | J27: =SUM(J25,J19) -> 39755778
B29: Revolver/Short term debt | C29: 0 | D29: 0 | E29: 0 | F29: =MIN(CashFlow!F25,0) -> 0 | G29: =MIN(CashFlow!G25,0) -> 0 | H29: =MIN(CashFlow!H25,0) -> 0 | I29: =MIN(CashFlow!I25,0) -> 0 | J29: =MIN(CashFlow!J25,0) -> 0
B30: Accounts payable/Accurals | C30: =71182+236006 -> 307188 | D30: =60087+271121 -> 331208 | E30: =42885+275754 -> 318639 | F30: =F10*IncState!F17 -> 468117.19 | G30: =G10*IncState!G17 -> 646189.9 | H30: =H10*IncState!H17 -> 829260.59 | I30: =I10*IncState!I17 -> 943397.78 | J30: =J10*IncState!J17 -> 1025435.3
B31: Other current liabilities | C31: =231704+1941943 -> 2173647 | D31: =314866+2406292 -> 2721158 | E31: =339600+3004969 -> 3344569 | F31: =F11*IncState!F16 -> 5144865.2 | G31: =G11*IncState!G16 -> 7452831.2 | H31: =H11*IncState!H16 -> 10061322 | I31: =I11*IncState!I16 -> 12073586 | J31: =J11*IncState!J16 -> 13884624
B32: Total current liabilities | C32: =SUM(C29:C31) -> 2480835 | D32: =SUM(D29:D31) -> 3052366 | E32: =SUM(E29:E31) -> 3663208 | F32: =SUM(F29:F31) -> 5612982.4 | G32: =SUM(G29:G31) -> 8099021.1 | H32: =SUM(H29:H31) -> 10890583 | I32: =SUM(I29:I31) -> 13016984 | J32: =SUM(J29:J31) -> 14910060
B34: Long-term debt, including current maturities | C34: 988984 | D34: 646506 | E34: 670051 | F34: =Debt!F26 -> 670051 | G34: =Debt!G26 -> 670051 | H34: =Debt!H26 -> 670051 | I34: =Debt!I26 -> 670051 | J34: =Debt!J26 -> 670051
B35: Other long-term liabilities | C35: =10752+1095291+494590 -> 1600633 | D35: =1373250+1005000+22330 -> 2400580 | E35: =59712+1567007+1006371 -> 2633090 | F35: =F12*IncState!F16 -> 4050415.2 | G35: =G12*IncState!G16 -> 5867415.3 | H35: =H12*IncState!H16 -> 7921010.6 | I35: =I12*IncState!I16 -> 9505212.7 | J35: =J12*IncState!J16 -> 10930995
B36: Total non-current liabilities | C36: =SUM(C34:C35) -> 2589617 | D36: =SUM(D34:D35) -> 3047086 | E36: =SUM(E34:E35) -> 3303141 | F36: =SUM(F34:F35) -> 4720466.2 | G36: =SUM(G34:G35) -> 6537466.3 | H36: =SUM(H34:H35) -> 8591061.6 | I36: =SUM(I34:I35) -> 10175264 | J36: =SUM(J34:J35) -> 11601046
B38: Equity | C38: 305035 | D38: 68626 | E38: 208654 | F38: =Calcs!F17 -> 574693.03 | G38: =Calcs!G17 -> 1534518.9 | H38: =Calcs!H17 -> 3589978.2 | I38: =Calcs!I17 -> 7313515.8 | J38: =Calcs!J17 -> 13244673
A39: * | B39: TOTAL LIABILITIES & EQUITY | C39: =SUM(C38,C36,C32) -> 5375487 | D39: =SUM(D38,D36,D32) -> 6168078 | E39: =SUM(E38,E36,E32) -> 7175003 | F39: =SUM(F38,F36,F32) -> 10908142 | G39: =SUM(G38,G36,G32) -> 16171006 | H39: =SUM(H38,H36,H32) -> 23071622 | I39: =SUM(I38,I36,I32) -> 30505764 | J39: =SUM(J38,J36,J32) -> 39755778
A41: * | B41: Balance check | C41: =C39-C27 -> 0 | D41: =D39-D27 -> 0 | E41: =E39-E27 -> 0 | F41: =F39-F27 -> 0 | G41: =G39-G27 -> 0 | H41: =H39-H27 -> 0 | I41: =I39-I27 -> 0 | J41: =J39-J27 -> 0

Sheet CashFlow
A1: =CoName -> Roblox Corporation | C1: Hist. | D1: Hist. | E1: Hist. | F1: Proj. | G1: Proj. | H1: Proj. | I1: Proj. | J1: Proj.
A2: Cash flow statement | C2: 2022 | D2: =C2+1 -> 2023 | E2: =D2+1 -> 2024 | F2: =E2+1 -> 2025 | G2: =F2+1 -> 2026 | H2: =G2+1 -> 2027 | I2: =H2+1 -> 2028 | J2: =I2+1 -> 2029
B3: Net Income | F3: =IncState!F36 -> -976179.03 | G3: =IncState!G36 -> -813712.24 | H3: =IncState!H36 -> -288002.85 | I3: =IncState!I36 -> 627006.99 | J3: =IncState!J36 -> 1839560
B4: Depreciation | F4: =IncState!F22 -> 233648.97 | G4: =IncState!G22 -> 241175.22 | H4: =IncState!H22 -> 269227.19 | I4: =IncState!I22 -> 317032.15 | J4: =IncState!J22 -> 375462.88
B5: Amortization | F5: =IncState!F23 -> 0 | G5: =IncState!G23 -> 0 | H5: =IncState!H23 -> 0 | I5: =IncState!I23 -> 0 | J5: =IncState!J23 -> 0
B6: Additional Paid in Compensation | F6: =IncState!F24 -> 1342218.1 | G6: =IncState!G24 -> 1773538.1 | H6: =IncState!H24 -> 2343462.2 | I6: =IncState!I24 -> 3096530.7 | J6: =IncState!J24 -> 4091596.7
B7: (inc) / dec in OWC | F7: =Calcs!F25 -> 851152.17 | G7: =Calcs!G25 -> 615842.42 | H7: =Calcs!H25 -> 677843.3 | I7: =Calcs!I25 -> 495818.91 | J7: =Calcs!J25 -> 425551.05
B8: (inc) / dec in LT assets | F8: =BalSheet!E24-BalSheet!F24 -> -180560.42 | G8: =BalSheet!F24-BalSheet!G24 -> -231477.07 | H8: =BalSheet!G24-BalSheet!H24 -> -261618.17 | I8: =BalSheet!H24-BalSheet!I24 -> -201819.73 | J8: =BalSheet!I24-BalSheet!J24 -> -181637.76
B9: inc / (dec) in LT liabilities | F9: =BalSheet!F35-BalSheet!E35 -> 1417325.2 | G9: =BalSheet!G35-BalSheet!F35 -> 1817000.1 | H9: =BalSheet!H35-BalSheet!G35 -> 2053595.3 | I9: =BalSheet!I35-BalSheet!H35 -> 1584202.1 | J9: =BalSheet!J35-BalSheet!I35 -> 1425781.9
B10: Cash Flow From Operations | F10: =SUM(F3:F9) -> 2687605 | G10: =SUM(G3:G9) -> 3402366.5 | H10: =SUM(H3:H9) -> 4794507 | I10: =SUM(I3:I9) -> 5918771.1 | J10: =SUM(J3:J9) -> 7976314.8
B12: Capex | F12: =-Calcs!F7 -> -276344.86 | G12: =-Calcs!G7 -> -400312.06 | H12: =-Calcs!H7 -> -540421.28 | I12: =-Calcs!I7 -> -648505.54 | J12: =-Calcs!J7 -> -745781.37
B13: Investments | F13: =BalSheet!E23-BalSheet!F23 -> -1000000 | G13: =BalSheet!F23-BalSheet!G23 -> -1000000 | H13: =BalSheet!G23-BalSheet!H23 -> -1000000 | I13: =BalSheet!H23-BalSheet!I23 -> -1000000 | J13: =BalSheet!I23-BalSheet!J23 -> -1000000
B14: Cash Flow From Investing | F14: =SUM(F12:F13) -> -1276344.9 | G14: =SUM(G12:G13) -> -1400312.1 | H14: =SUM(H12:H13) -> -1540421.3 | I14: =SUM(I12:I13) -> -1648505.5 | J14: =SUM(J12:J13) -> -1745781.4
B16: Share issuance | F16: 0 | G16: 0 | H16: 0 | I16: 0 | J16: 0
B17: Debt issuance | F17: 0 | G17: 0 | H17: 0 | I17: 0 | J17: 0
B18: Dividends | F18: 0 | G18: 0 | H18: 0 | I18: 0 | J18: 0
B19: Cash Flow From Financing | F19: =SUM(F16:F18) -> 0 | G19: =SUM(G16:G18) -> 0 | H19: =SUM(H16:H18) -> 0 | I19: =SUM(I16:I18) -> 0 | J19: =SUM(J16:J18) -> 0
B21: Net changes in cash | F21: =SUM(F19,F14,F10) -> 1411260.1 | G21: =SUM(G19,G14,G10) -> 2002054.4 | H21: =SUM(H19,H14,H10) -> 3254085.7 | I21: =SUM(I19,I14,I10) -> 4270265.6 | J21: =SUM(J19,J14,J10) -> 6230533.4
B23: Beginning Cash | F23: =BalSheet!E16 -> 657653.31 | G23: =BalSheet!F16 -> 2068913.4 | H23: =BalSheet!G16 -> 4070967.8 | I23: =BalSheet!H16 -> 7325053.6 | J23: =BalSheet!I16 -> 11595319
B24: =B21 -> Net changes in cash | F24: =F21 -> 1411260.1 | G24: =G21 -> 2002054.4 | H24: =H21 -> 3254085.7 | I24: =I21 -> 4270265.6 | J24: =J21 -> 6230533.4
B25: Ending Cash | F25: =SUM(F23:F24) -> 2068913.4 | G25: =SUM(G23:G24) -> 4070967.8 | H25: =SUM(H23:H24) -> 7325053.6 | I25: =SUM(I23:I24) -> 11595319 | J25: =SUM(J23:J24) -> 17825853

Sheet Free Cash Flow
A1: =CoName -> Roblox Corporation | C1: Hist. | D1: Hist. | E1: Hist. | F1: Proj. | G1: Proj. | H1: Proj. | I1: Proj. | J1: Proj.
A2: Free Cash Flows | C2: 2022 | D2: =C2+1 -> 2023 | E2: =D2+1 -> 2024 | F2: =E2+1 -> 2025 | G2: =F2+1 -> 2026 | H2: =G2+1 -> 2027 | I2: =H2+1 -> 2028 | J2: =I2+1 -> 2029
A3: * | B3: Sales | F3: =IncState!F16 -> 5540832.5 | G3: =IncState!G16 -> 8026427.7 | H3: =IncState!H16 -> 10835677 | I3: =IncState!I16 -> 13002813 | J3: =IncState!J16 -> 14953235
B4: EBIT | F4: =IncState!F20 -> -1109294.3 | G4: =IncState!G20 -> -924673 | H4: =IncState!H20 -> -327275.96 | I4: =IncState!I20 -> 712507.94 | J4: =IncState!J20 -> 2090409.1
B5: Effective Tax Rate | F5: =IncState!F12 -> 0.12 | G5: =IncState!G12 -> 0.12 | H5: =IncState!H12 -> 0.12 | I5: =IncState!I12 -> 0.12 | J5: =IncState!J12 -> 0.12
A7: * | B7: NOPAT | F7: =F4*(1-F5) -> -976179.03 | G7: =G4*(1-G5) -> -813712.24 | H7: =H4*(1-H5) -> -288002.85 | I7: =I4*(1-I5) -> 627006.99 | J7: =J4*(1-J5) -> 1839560
B8: Depreciation | F8: =CashFlow!F4 -> 233648.97 | G8: =CashFlow!G4 -> 241175.22 | H8: =CashFlow!H4 -> 269227.19 | I8: =CashFlow!I4 -> 317032.15 | J8: =CashFlow!J4 -> 375462.88
B9: Amortization | F9: =CashFlow!F5 -> 0 | G9: =CashFlow!G5 -> 0 | H9: =CashFlow!H5 -> 0 | I9: =CashFlow!I5 -> 0 | J9: =CashFlow!J5 -> 0
B10: =CashFlow!B6 -> Additional Paid in Compensation | F10: =CashFlow!F6 -> 1342218.1 | G10: =CashFlow!G6 -> 1773538.1 | H10: =CashFlow!H6 -> 2343462.2 | I10: =CashFlow!I6 -> 3096530.7 | J10: =CashFlow!J6 -> 4091596.7
B11: (inc) / dec in OWC | F11: =CashFlow!F7 -> 851152.17 | G11: =CashFlow!G7 -> 615842.42 | H11: =CashFlow!H7 -> 677843.3 | I11: =CashFlow!I7 -> 495818.91 | J11: =CashFlow!J7 -> 425551.05
B12: (inc) / dec in other long-term assets | F12: =CashFlow!F8 -> -180560.42 | G12: =CashFlow!G8 -> -231477.07 | H12: =CashFlow!H8 -> -261618.17 | I12: =CashFlow!I8 -> -201819.73 | J12: =CashFlow!J8 -> -181637.76
B13: inc / (dec) other long-term liabilities | F13: =CashFlow!F9 -> 1417325.2 | G13: =CashFlow!G9 -> 1817000.1 | H13: =CashFlow!H9 -> 2053595.3 | I13: =CashFlow!I9 -> 1584202.1 | J13: =CashFlow!J9 -> 1425781.9
B14: (Capex) | F14: =CashFlow!F12 -> -276344.86 | G14: =CashFlow!G12 -> -400312.06 | H14: =CashFlow!H12 -> -540421.28 | I14: =CashFlow!I12 -> -648505.54 | J14: =CashFlow!J12 -> -745781.37
A16: * | B16: Free Cash Flow | F16: =SUM(F7:F14) -> 2411260.1 | G16: =SUM(G7:G14) -> 3002054.4 | H16: =SUM(H7:H14) -> 4254085.7 | I16: =SUM(I7:I14) -> 5270265.6 | J16: =SUM(J7:J14) -> 7230533.4

Sheet WACC
A1: =CoName -> Roblox Corporation
A3: * | B3: WACC | G3: Comp | H3: Levered beta | I3: Gross debt | J3: Market cap | K3: Debt/Mcap | L3: MTR | M3: Unlevered beta
B4: Tax Rate | E4: 0.12 | L4: =E4 -> 0.12 | M4: =H4/((1+K4*(1-L4))) -> 0
B5: Risk free rate | E5: 0.04 | L5: =L4 -> 0.12 | M5: =H5/((1+K5*(1-L5))) -> 0
B6: Market risk Premium | E6: 0.05 | L6: =L5 -> 0.12 | M6: =H6/((1+K6*(1-L6))) -> 0
B7: Beta | E7: =1.61*0.66 -> 1.0626 | L7: =L6 -> 0.12 | M7: =H7/((1+K7*(1-L7))) -> 0
B8: Cost of Equity | E8: =E5+E6*E7 -> 0.09313
B9: % Equity | E9: =1-E10 -> 0.98556325 | G9: Industry beta (average) | M9: =AVERAGE(M4:M7) -> 0
B10: % Debt | E10: =MAIN!F8/MAIN!F6 -> 0.014436752
B11: Cost of debt | E11: =Debt!F5 -> 0.04 | G11: Re-levered beta | M11: =M9*(1+E10*(1-E4)) -> 0
B12: Post tax cost of debt | E12: =E11*(1-E4) -> 0.0352
A13: * | B13: WACC | E13: =WACC!E8*WACC!E9+WACC!E12*WACC!E10 -> 0.092293679
B14: Long Term growth rate | E14: 0.025

Sheet DCF Model
A1: =CoName -> Roblox Corporation | D1: Proj. | E1: Proj. | F1: Proj. | G1: Proj. | H1: Proj.
A2: Discount Model Year count | D2: 0.5 | E2: =D2+1 -> 1.5 | F2: =E2+1 -> 2.5 | G2: =F2+1 -> 3.5 | H2: =G2+1 -> 4.5 | I2: WACC | L2: =WACC!E13 -> 0.092293679
B3: Discount factor | D3: =1/(1+$L$2)^D2 -> 0.9568201 | E3: =1/(1+$L$2)^E2 -> 0.8759733 | F3: =1/(1+$L$2)^F2 -> 0.80195768 | G3: =1/(1+$L$2)^G2 -> 0.73419602 | H3: =1/(1+$L$2)^H2 -> 0.67215991 | I3: Long Term growth rate | L3: 0.025
B4: PV FCF | D4: ='Free Cash Flow'!F16*D3 -> 2307142.2 | E4: ='Free Cash Flow'!G16*E3 -> 2629719.5 | F4: ='Free Cash Flow'!H16*F3 -> 3411596.7 | G4: ='Free Cash Flow'!I16*G3 -> 3869408 | H4: ='Free Cash Flow'!J16*H3 -> 4860074.7
H5: =((H4*(1+L3)))/(L2-L3) -> 74027407
A6: Value Calculation | E6: Multiples Calculation
B7: Total PV of FCFs | C7: =SUM(D4:H4) -> 17077941 | E7: Total PV of FCFs | G7: =C7 -> 17077941 | K7: LTGR | P7: Exit Mult.
B8: PV of TV | C8: =H5*H3 -> 49758256 | E8: Multiple TV | G8: =G10*H3*IncState!J25 -> 44076676 | I8: =C18 -> 104.88803 | J8: =K8-E23 -> 0.0225 | K8: 0.025 | L8: =K8+$E$23 -> 0.0275 | N8: =G18 -> 96.212535 | O8: =P8-1 -> 9 | P8: 10 | Q8: =P8+1 -> 11
B9: EV | C9: =SUM(C7:C8) -> 66836197 | E9: EV | G9: =SUM(G7:G8) -> 61154617 | I9: =I10+$E$22 -> 0.10229368 | J9: 87.124382 | K9: 89.177644 | L9: 91.368168 | N9: =I9 -> 0.10229368 | O9: 86.376842 | P9: 92.836705 | Q9: 99.296568
E10: Implied EBITDA multiple | G10: 10 | I10: =I11+$E$22 -> 0.097293679 | J10: 94.017098 | K10: 96.445872 | L10: 99.048643 | N10: =I10 -> 0.097293679 | O10: 87.910825 | P10: 94.504207 | Q10: 101.09759
I11: 0.092293679 | J11: 101.98782 | K11: 104.88803 | L11: 108.01204 | N11: =I11 -> 0.092293679 | O11: 89.482244 | P11: 96.212535 | Q11: 102.94283
B12: Cash & Cash Equiv | C12: =MAIN!F7 -> 2860500 | E12: Cash & Cash Equiv | G12: =C12 -> 2860500 | I12: =I11-$E$22 -> 0.087293679 | J12: 111.29195 | K12: 114.79289 | L12: 118.58657 | N12: =I12 -> 0.087293679 | O12: 91.092203 | P12: 97.962893 | Q12: 104.83358
B13: Debt & Claims | C13: =MAIN!F8 -> 992736 | E13: Debt & Claims | G13: =C13 -> 992736 | I13: =I12-$E$22 -> 0.082293679 | J13: 122.27075 | K13: 126.55044 | L13: 131.22066 | N13: =I13 -> 0.082293679 | O13: 92.741847 | P13: 99.756532 | Q13: 106.77122
B14: NCI | C14: =MAIN!F9 -> 12792 | E14: NCI | G14: =C14 -> 12792
B15: Equity Value | C15: =C9+C12-SUM(C13:C14) -> 68691169 | E15: Equity Value | G15: =G9+G12-SUM(G13:G14) -> 63009589 | K15: Average | P15: Average
K16: =AVERAGE(J9:L13) -> 106.4522 | P16: =AVERAGE(O9:Q13) -> 96.254574
B17: Diluted S/O | C17: =MAIN!F5 -> 654900 | E17: Diluted S/O | G17: =C17 -> 654900
A18: * | B18: Implied Share Price | C18: =C15/C17 -> 104.88803 | E18: Implied Share Price | G18: =G15/G17 -> 96.212535
A20: Sensitivity analysis
C22: Discount rate variance | E22: 0.005 | J22: Discount rate variance | L22: 0.005
C23: Implied growth rate variance | E23: 0.0025 | J23: TV multiple variance | L23: 1
A25: DCF tables
