Workbook
Name Ccy: MAIN!$C$6
Name circ: MAIN!$C$9
Name CoName: MAIN!$C$4
Name g: #REF!
Name IQ_CH: 110000
Name IQ_CQ: 5000
Name IQ_CY: 10000
Name IQ_DAILY: 500000
Name IQ_FH: 100000
Name IQ_FQ: 500
Name IQ_FY: 1000
Name IQ_LTM: 2000
Name IQ_MONTH: 15000
Name IQ_NTM: 6000
Name IQ_WEEK: 50000
Name IQ_YTD: 3000
Name OpCase: [1]DCF!$E$98
Name ScenarioREV: Assumptions!$D$4
Name TTS: #REF!
Name Units: MAIN!$C$7

Sheet MAIN
A1: =CoName -> Warby Parker
A2: Model Details
B4: Company name | C4: Warby Parker | E4: Current Stock Price | F4: 19.22 | H4: Operating Case One | I4: Terminal Mult | J4: Perpetuity | K4: Average
B5: Latest BS date | C5: 247.43 | E5: Diluted s/o | F5: 105727.1 | H5: Implied Price | I5: ='DCF Model'!G18 -> 26.14322 | J5: ='DCF Model'!C18 -> 20.223086 | K5: =AVERAGE(I5:J5) -> 23.183153
B6: Currency | C6: USD | E6: Mkt Cap | F6: =F5*F4 -> 2032074.9 | H6: Difference | I6: =I5/$F$4-1 -> 0.36020915 | J6: =J5/$F$4-1 -> 0.052189691 | K6: =K5/$F$4-1 -> 0.20619942
B7: Units | C7: t | E7: Cash | F7: 280360
B8: Analyst name | C8: Alan Chen | E8: Debt | F8: 203885
B9: Circular switch | C9: 0 | E9: EV | F9: =F6-F7+F8 -> 1955599.9

Sheet Quarterly Projections

Sheet Assumptions
A1: =CoName -> Warby Parker | C1: Hist. | D1: Hist. | E1: Hist. | F1: Proj. | G1: Proj. | H1: Proj. | I1: Proj. | J1: Proj.
A2: * | B2: Income Statement | C2: 2022 | D2: =C2+1 -> 2023 | E2: =D2+1 -> 2024 | F2: =E2+1 -> 2025 | G2: =F2+1 -> 2026 | H2: =G2+1 -> 2027 | I2: =H2+1 -> 2028 | J2: =I2+1 -> 2029
B4: Operating Case | D4: 1
D5: Variance
B6: Street Case | D6: 0 | F6: 0.13 | G6: =F6+0.005 -> 0.135 | H6: =G6+0.005 -> 0.14 | I6: =H6+0.005 -> 0.145 | J6: =I6+0.005 -> 0.15
B7: Optimistic Case | D7: 0.025 | F7: =F6+$D$7 -> 0.155 | G7: =G6+$D$7 -> 0.16 | H7: =H6+$D$7 -> 0.165 | I7: =I6+$D$7 -> 0.17 | J7: =J6+$D$7 -> 0.175
B8: Pessimistic Case | D8: -0.025 | F8: =F6+$D$8 -> 0.105 | G8: =G6+$D$8 -> 0.11 | H8: =H6+$D$8 -> 0.115 | I8: =I6+$D$8 -> 0.12 | J8: =J6+$D$8 -> 0.125
B10: Revenue Growth | D10: =IncState!D15/IncState!C15-1 -> 0.11979863 | E10: =IncState!E15/IncState!D15-1 -> 0.15162034 | F10: =CHOOSE(ScenarioREV,F6,F7,F8) -> 0.13 | G10: =CHOOSE(ScenarioREV,G6,G7,G8) -> 0.135 | H10: =CHOOSE(ScenarioREV,H6,H7,H8) -> 0.14 | I10: =CHOOSE(ScenarioREV,I6,I7,I8) -> 0.145 | J10: =CHOOSE(ScenarioREV,J6,J7,J8) -> 0.15
B11: COGS % of sales | C11: =IncState!C16/IncState!C15 -> 0.42976901 | D11: =IncState!D16/IncState!D15 -> 0.45469829 | E11: =IncState!E16/IncState!E15 -> 0.4466152 | F11: =E11-0.005 -> 0.4416152 | G11: =F11-0.005 -> 0.4366152 | H11: =G11-0.005 -> 0.4316152 | I11: =H11-0.005 -> 0.4266152 | J11: =I11-0.005 -> 0.4216152
B12: SG&A % of sales | C12: =IncState!C17/IncState!C15 -> 0.75615437 | D12: =IncState!D17/IncState!D15 -> 0.65279613 | E12: =IncState!E17/IncState!E15 -> 0.59242463 | F12: =E12-0.05 -> 0.54242463 | G12: =F12-0.05 -> 0.49242463 | H12: =G12-0.05 -> 0.44242463 | I12: =H12-0.05 -> 0.39242463 | J12: =I12-0.05 -> 0.34242463
B13: Amortization $ Amt | C13: =IncState!C21 -> 0 | D13: =IncState!D21 -> 0 | E13: =IncState!E21 -> 0 | F13: =E13 -> 0 | G13: =F13 -> 0 | H13: =G13 -> 0 | I13: =H13 -> 0 | J13: =I13 -> 0
B14: Non recurring income / (expense) | C14: =IncState!C24 -> 0 | D14: =IncState!D24 -> 0 | E14: =IncState!E24 -> 0 | F14: 0 | G14: 0 | H14: 0 | I14: 0 | J14: 0
B15: Other Income / (expense) | C15: =IncState!C25 -> 0 | D15: =IncState!D25 -> 0 | E15: =IncState!E25 -> 0 | F15: 0 | G15: 0 | H15: 0 | I15: 0 | J15: 0
B16: Effective tax rate | C16: =IncState!C32/IncState!C30 -> -0.0045224576 | D16: =IncState!D32/IncState!D30 -> -0.0068988592 | E16: =IncState!E32/IncState!E30 -> -0.044837305 | F16: 0.21 | G16: =F16 -> 0.21 | H16: =G16 -> 0.21 | I16: =H16 -> 0.21 | J16: =I16 -> 0.21
B17: Basic WASO | C17: =IncState!C35 -> 114942 | D17: =IncState!D35 -> 117389 | E17: =IncState!E35 -> 120385 | F17: =E17 -> 120385 | G17: =F17 -> 120385 | H17: =G17 -> 120385 | I17: =H17 -> 120385 | J17: =I17 -> 120385
B18: Diluted WASO | C18: =IncState!C36 -> 114942 | D18: =IncState!D36 -> 117389 | E18: =IncState!E36 -> 120385 | F18: =E18 -> 120385 | G18: =F18 -> 120385 | H18: =G18 -> 120385 | I18: =H18 -> 120385 | J18: =I18 -> 120385
A20: * | B20: Debt | C20: =C2 -> 2022 | D20: =D2 -> 2023 | E20: =E2 -> 2024 | F20: =F2 -> 2025 | G20: =G2 -> 2026 | H20: =H2 -> 2027 | I20: =I2 -> 2028 | J20: =J2 -> 2029
B22: Interest rate on Revolver | E22: 0.05 | F22: =E22 -> 0.05 | G22: =F22 -> 0.05 | H22: =G22 -> 0.05 | I22: =H22 -> 0.05 | J22: =I22 -> 0.05
B23: Interest rate on long-term debt | E23: 0.05 | F23: =E23 -> 0.05 | G23: =F23 -> 0.05 | H23: =G23 -> 0.05 | I23: =H23 -> 0.05 | J23: =I23 -> 0.05
B24: Interest rate on cash | C24: =IncState!C27/SUM(BalSheet!C15:C16) -> 0.0062660306 | D24: =IncState!D27/SUM(BalSheet!D15:D16) -> 0.042564571 | E24: =IncState!E27/SUM(BalSheet!E15:E16) -> 0.041694044 | F24: =E24 -> 0.041694044 | G24: =F24 -> 0.041694044 | H24: =G24 -> 0.041694044 | I24: =H24 -> 0.041694044 | J24: =I24 -> 0.041694044
B26: Issuance of long-term debt | F26: 0 | G26: 0 | H26: 0 | I26: 0 | J26: 0
B27: Repayment of long-term debt | F27: 0 | G27: 0 | H27: 0 | I27: 0 | J27: 0
A29: * | B29: Calcs | C29: =C20 -> 2022 | D29: =D20 -> 2023 | E29: =E20 -> 2024 | F29: =F20 -> 2025 | G29: =G20 -> 2026 | H29: =H20 -> 2027 | I29: =I20 -> 2028 | J29: =J20 -> 2029
B31: CapEx % of Sales | D31: =53671/IncState!D15 -> 0.080134077 | E31: =64032/IncState!E15 -> 0.083016666 | F31: =AVERAGE(D31:E31) -> 0.081575372 | G31: =F31 -> 0.081575372 | H31: =G31 -> 0.081575372 | I31: =H31 -> 0.081575372 | J31: =I31 -> 0.081575372
B32: Depreciation % of beginning PP&E | D32: =IncState!D20/BalSheet!C22 -> 0.14513518 | E32: =IncState!E20/BalSheet!D22 -> 0.16700226 | F32: =E32 -> 0.16700226 | G32: =F32 -> 0.16700226 | H32: =G32 -> 0.16700226 | I32: =H32 -> 0.16700226 | J32: =I32 -> 0.16700226
B33: Share issuance / (repurchases) | F33: 0 | G33: 0 | H33: 0 | I33: 0 | J33: 0
A35: * | B35: Balance Sheet - Assets | C35: =#REF! -> #REF! | D35: =#REF! -> #REF! | E35: =#REF! -> #REF! | F35: =#REF! -> #REF! | G35: =#REF! -> #REF! | H35: =#REF! -> #REF! | I35: =#REF! -> #REF! | J35: =#REF! -> #REF!
B37: Operating Cash % of sales | C37: =BalSheet!C15/IncState!C15 -> 0.05 | D37: =BalSheet!D15/IncState!D15 -> 0.05 | E37: =BalSheet!E15/IncState!E15 -> 0.05 | F37: =E37 -> 0.05 | G37: =F37 -> 0.05 | H37: =G37 -> 0.05 | I37: =H37 -> 0.05 | J37: =I37 -> 0.05
B38: Accounts receivable % of sales | C38: =BalSheet!C17/IncState!C15 -> 0.0023992162 | D38: =BalSheet!D17/IncState!D15 -> 0.0026561555 | E38: =BalSheet!E17/IncState!E15 -> 0.002525557 | F38: =E38 -> 0.002525557 | G38: =F38 -> 0.002525557 | H38: =G38 -> 0.002525557 | I38: =H38 -> 0.002525557 | J38: =I38 -> 0.002525557
B39: Inventories % of COGS | C39: =BalSheet!C18/IncState!C16 -> 0.26783894 | D39: =BalSheet!D18/IncState!D16 -> 0.20435344 | E39: =BalSheet!E18/IncState!E16 -> 0.15195323 | F39: =E39 -> 0.15195323 | G39: =F39 -> 0.15195323 | H39: =G39 -> 0.15195323 | I39: =H39 -> 0.15195323 | J39: =I39 -> 0.15195323
B40: Other current assets % of sales | C40: =BalSheet!C19/IncState!C15 -> 0.026249264 | D40: =BalSheet!D19/IncState!D15 -> 0.026445096 | E40: =BalSheet!E19/IncState!E15 -> 0.022807802 | F40: =E40 -> 0.022807802 | G40: =F40 -> 0.022807802 | H40: =G40 -> 0.022807802 | I40: =H40 -> 0.022807802 | J40: =I40 -> 0.022807802
B41: Other long-term assets % of sales | C41: =BalSheet!C23/IncState!C15 -> 0.014206369 | D41: =BalSheet!D23/IncState!D15 -> 0.010535038 | E41: =BalSheet!E23/IncState!E15 -> 0.011274252 | F41: =E41 -> 0.011274252 | G41: =F41 -> 0.011274252 | H41: =G41 -> 0.011274252 | I41: =H41 -> 0.011274252 | J41: =I41 -> 0.011274252
A43: * | B43: Balance Sheet - Liabilities | C43: =C35 -> #REF! | D43: =D35 -> #REF! | E43: =E35 -> #REF! | F43: =F35 -> #REF! | G43: =G35 -> #REF! | H43: =H35 -> #REF! | I43: =I35 -> #REF! | J43: =J35 -> #REF!
B45: Accounts payable % of COGS | C45: =BalSheet!C29/IncState!C16 -> 0.30738378 | D45: =BalSheet!D29/IncState!D16 -> 0.22583495 | E45: =BalSheet!E29/IncState!E16 -> 0.2180904 | F45: =E45 -> 0.2180904 | G45: =F45 -> 0.2180904 | H45: =G45 -> 0.2180904 | I45: =H45 -> 0.2180904 | J45: =I45 -> 0.2180904
B46: Other current liabilities % of sales | C46: =BalSheet!C30/IncState!C15 -> 0.084505912 | D46: =BalSheet!D30/IncState!D15 -> 0.087066359 | E46: =BalSheet!E30/IncState!E15 -> 0.0715998 | F46: =E46 -> 0.0715998 | G46: =F46 -> 0.0715998 | H46: =G46 -> 0.0715998 | I46: =H46 -> 0.0715998 | J46: =I46 -> 0.0715998
B47: Other long-term liabilities % of sales | C47: =BalSheet!C34/IncState!C15 -> 0.25497566 | D47: =BalSheet!D34/IncState!D15 -> 0.22610169 | E47: =BalSheet!E34/IncState!E15 -> 0.26715804 | F47: =E47 -> 0.26715804 | G47: =F47 -> 0.26715804 | H47: =G47 -> 0.26715804 | I47: =H47 -> 0.26715804 | J47: =I47 -> 0.26715804

Sheet Calcs
A1: =CoName -> Warby Parker | C1: Hist. | D1: Hist. | E1: Hist. | F1: Proj. | G1: Proj. | H1: Proj. | I1: Proj. | J1: Proj.
A2: Net PP&E | C2: 2022 | D2: =C2+1 -> 2023 | E2: =D2+1 -> 2024 | F2: =E2+1 -> 2025 | G2: =F2+1 -> 2026 | H2: =G2+1 -> 2027 | I2: =H2+1 -> 2028 | J2: =I2+1 -> 2029
B3: Capital expenditure % of sales | F3: =Assumptions!F31 -> 0.081575372 | G3: =Assumptions!G31 -> 0.081575372 | H3: =Assumptions!H31 -> 0.081575372 | I3: =Assumptions!I31 -> 0.081575372 | J3: =Assumptions!J31 -> 0.081575372
B4: Depreciation % of PP&E | F4: =Assumptions!F32 -> 0.16700226 | G4: =F4 -> 0.16700226 | H4: =G4 -> 0.16700226 | I4: =H4 -> 0.16700226 | J4: =I4 -> 0.16700226
B6: Beginning PP&E | F6: =E9 -> 341748 | G6: =F9 -> 355775.26 | H6: =G9 -> 377058.43 | I6: =H9 -> 406085.04 | J6: =I9 -> 443603.59
B7: Capex | F7: =F3*IncState!F15 -> 71099.948 | G7: =G3*IncState!G15 -> 80698.441 | H7: =H3*IncState!H15 -> 91996.222 | I7: =I3*IncState!I15 -> 105335.67 | J7: =J3*IncState!J15 -> 121136.03
B8: Depreciation | F8: =F6*F4 -> 57072.689 | G8: =G6*G4 -> 59415.273 | H8: =H6*H4 -> 62969.61 | I8: =I6*I4 -> 67817.12 | J8: =J6*J4 -> 74082.803
B9: Ending PP&E | E9: =BalSheet!E22 -> 341748 | F9: =F6+F7-F8 -> 355775.26 | G9: =G6+G7-G8 -> 377058.43 | H9: =H6+H7-H8 -> 406085.04 | I9: =I6+I7-I8 -> 443603.59 | J9: =J6+J7-J8 -> 490656.82
A10: Equity | C10: =C2 -> 2022 | D10: =D2 -> 2023 | E10: =E2 -> 2024 | F10: =F2 -> 2025 | G10: =G2 -> 2026 | H10: =H2 -> 2027 | I10: =I2 -> 2028 | J10: =J2 -> 2029
B11: Share issuance/(repurchases) | F11: =Assumptions!F33 -> 0 | G11: =Assumptions!G33 -> 0 | H11: =Assumptions!H33 -> 0 | I11: =Assumptions!I33 -> 0 | J11: =Assumptions!J33 -> 0
B13: Beginning balance | F13: =E16 -> 340073 | G13: =F16 -> 351062.43 | H13: =G16 -> 406518.34 | I13: =H16 -> 518738.61 | J13: =I16 -> 703336.41
B14: Net income | F14: =IncState!F33 -> 10989.427 | G14: =IncState!G33 -> 55455.915 | H14: =IncState!H33 -> 112220.27 | I14: =IncState!I33 -> 184597.8 | J14: =IncState!J33 -> 276808.91
B15: Share issuance / (repurchase) | F15: =F11 -> 0 | G15: =G11 -> 0 | H15: =H11 -> 0 | I15: =I11 -> 0 | J15: =J11 -> 0
B16: Ending balance | E16: =BalSheet!E37 -> 340073 | F16: =SUM(F13:F15) -> 351062.43 | G16: =SUM(G13:G15) -> 406518.34 | H16: =SUM(H13:H15) -> 518738.61 | I16: =SUM(I13:I15) -> 703336.41 | J16: =SUM(J13:J15) -> 980145.32
A17: OWC | C17: =C10 -> 2022 | D17: =D10 -> 2023 | E17: =E10 -> 2024 | F17: =F10 -> 2025 | G17: =G10 -> 2026 | H17: =H10 -> 2027 | I17: =I10 -> 2028 | J17: =J10 -> 2029
B18: Operating Cash | E18: =BalSheet!E15 -> 38565.75 | F18: =BalSheet!F15 -> 43579.298 | G18: =BalSheet!G15 -> 49462.503 | H18: =BalSheet!H15 -> 56387.253 | I18: =BalSheet!I15 -> 64563.405 | J18: =BalSheet!J15 -> 74247.915
B19: =BalSheet!B18 -> Inventories | E19: =BalSheet!E17 -> 1948 | F19: =BalSheet!F17 -> 2201.24 | G19: =BalSheet!G17 -> 2498.4074 | H19: =BalSheet!H17 -> 2848.1844 | I19: =BalSheet!I17 -> 3261.1712 | J19: =BalSheet!J17 -> 3750.3469
B20: =BalSheet!B17 -> Accounts receivable | E20: =BalSheet!E18 -> 52345 | F20: =BalSheet!F18 -> 58487.649 | G20: =BalSheet!G18 -> 65631.882 | H20: =BalSheet!H18 -> 73963.523 | I20: =BalSheet!I18 -> 83707.172 | J20: =BalSheet!J18 -> 95135.027
B21: Other current assets | E21: =BalSheet!E19 -> 17592 | F21: =BalSheet!F19 -> 19878.96 | G21: =BalSheet!G19 -> 22562.62 | H21: =BalSheet!H19 -> 25721.386 | I21: =BalSheet!I19 -> 29450.987 | J21: =BalSheet!J19 -> 33868.635
B22: Accounts payables | E22: =BalSheet!E29 -> 75128 | F22: =BalSheet!F29 -> 83944.217 | G22: =BalSheet!G29 -> 94197.957 | H22: =BalSheet!H29 -> 106155.92 | I22: =BalSheet!I29 -> 120140.46 | J22: =BalSheet!J29 -> 136542.25
B23: Other current liabilities | E23: =BalSheet!E30 -> 55226 | F23: =BalSheet!F30 -> 62405.38 | G23: =BalSheet!G30 -> 70830.106 | H23: =BalSheet!H30 -> 80746.321 | I23: =BalSheet!I30 -> 92454.538 | J23: =BalSheet!J30 -> 106322.72
A24: * | B24: OWC | E24: =SUM(E18:E21)-SUM(E22:E23) -> -19903.25 | F24: =SUM(F18:F21)-SUM(F22:F23) -> -22202.451 | G24: =SUM(G18:G21)-SUM(G22:G23) -> -24872.651 | H24: =SUM(H18:H21)-SUM(H22:H23) -> -27981.893 | I24: =SUM(I18:I21)-SUM(I22:I23) -> -31612.263 | J24: =SUM(J18:J21)-SUM(J22:J23) -> -35863.048
B25: Change in OWC | F25: =E24-F24 -> 2299.2013 | G25: =F24-G24 -> 2670.1999 | H25: =G24-H24 -> 3109.2418 | I25: =H24-I24 -> 3630.3704 | J25: =I24-J24 -> 4250.7848

Sheet Debt
A1: =CoName -> Warby Parker | C1: Hist. | D1: Hist. | E1: Hist. | F1: Proj. | G1: Proj. | H1: Proj. | I1: Proj. | J1: Proj.
A2: Assumptions | C2: 2022 | D2: =C2 -> 2022 | E2: =D2 -> 2022 | F2: =E2 -> 2022 | G2: =F2 -> 2022 | H2: =G2 -> 2022 | I2: =H2 -> 2022 | J2: =I2 -> 2022
B4: Interest rate on revolver | F4: =Assumptions!F22 -> 0.05 | G4: =Assumptions!G22 -> 0.05 | H4: =Assumptions!H22 -> 0.05 | I4: =Assumptions!I22 -> 0.05 | J4: =Assumptions!J22 -> 0.05
B5: Interest rate on long-term debt | F5: =Assumptions!F23 -> 0.05 | G5: =Assumptions!G23 -> 0.05 | H5: =Assumptions!H23 -> 0.05 | I5: =Assumptions!I23 -> 0.05 | J5: =Assumptions!J23 -> 0.05
B6: Interest rate on cash | F6: =Assumptions!F24 -> 0.041694044 | G6: =Assumptions!G24 -> 0.041694044 | H6: =Assumptions!H24 -> 0.041694044 | I6: =Assumptions!I24 -> 0.041694044 | J6: =Assumptions!J24 -> 0.041694044
B8: Issuance of long-term debt | F8: =Assumptions!F26 -> 0 | G8: =Assumptions!G26 -> 0 | H8: =Assumptions!H26 -> 0 | I8: =Assumptions!I26 -> 0 | J8: =Assumptions!J26 -> 0
B9: Repayment of long-term debt | F9: =Assumptions!F27 -> 0 | G9: =Assumptions!G27 -> 0 | H9: =Assumptions!H27 -> 0 | I9: =Assumptions!I27 -> 0 | J9: =Assumptions!J27 -> 0
A11: Revolver | C11: =C2 -> 2022 | D11: =D2 -> 2022 | E11: =E2 -> 2022 | F11: =F2 -> 2022 | G11: =G2 -> 2022 | H11: =H2 -> 2022 | I11: =I2 -> 2022 | J11: =J2 -> 2022
B12: Balance
B13: Interest rate
B14: Interest expense
A16: Long term debt | C16: =C11 -> 2022 | D16: =D11 -> 2022 | E16: =E11 -> 2022 | F16: =F11 -> 2022 | G16: =G11 -> 2022 | H16: =H11 -> 2022 | I16: =I11 -> 2022 | J16: =J11 -> 2022
B17: Beginning balance
B18: Issuance
B19: Repayment
B20: Ending balance
B21: Interest rate
B22: Interest expense
A24: Debt summary | C24: =C16 -> 2022 | D24: =D16 -> 2022 | E24: =E16 -> 2022 | F24: =F16 -> 2022 | G24: =G16 -> 2022 | H24: =H16 -> 2022 | I24: =I16 -> 2022 | J24: =J16 -> 2022
B25: Revolver
B26: Total long term debt
B27: Total debt
B28: Total interest expense
A30: Interest income | C30: =C11 -> 2022 | D30: =D11 -> 2022 | E30: =E11 -> 2022 | F30: =F11 -> 2022 | G30: =G11 -> 2022 | H30: =H11 -> 2022 | I30: =I11 -> 2022 | J30: =J11 -> 2022
B31: Excess Cash
B32: Interest rate
B33: Interest income

Sheet IncState
A1: =CoName -> Warby Parker | C1: Hist. | D1: Hist. | E1: Hist. | F1: Proj. | G1: Proj. | H1: Proj. | I1: Proj. | J1: Proj.
A2: Assumptions | C2: 2022 | D2: =C2+1 -> 2023 | E2: =D2+1 -> 2024 | F2: =E2+1 -> 2025 | G2: =F2+1 -> 2026 | H2: =G2+1 -> 2027 | I2: =H2+1 -> 2028 | J2: =I2+1 -> 2029
B4: Revenue growth | F4: =Assumptions!F10 -> 0.13 | G4: =Assumptions!G10 -> 0.135 | H4: =Assumptions!H10 -> 0.14 | I4: =Assumptions!I10 -> 0.145 | J4: =Assumptions!J10 -> 0.15
B5: Cost of goods sold as % of sales | F5: =Assumptions!F11 -> 0.4416152 | G5: =Assumptions!G11 -> 0.4366152 | H5: =Assumptions!H11 -> 0.4316152 | I5: =Assumptions!I11 -> 0.4266152 | J5: =Assumptions!J11 -> 0.4216152
B6: SG&A % of sales | F6: =Assumptions!F12 -> 0.54242463 | G6: =Assumptions!G12 -> 0.49242463 | H6: =Assumptions!H12 -> 0.44242463 | I6: =Assumptions!I12 -> 0.39242463 | J6: =Assumptions!J12 -> 0.34242463
B7: Amortization amount | F7: =Assumptions!F13 -> 0 | G7: =Assumptions!G13 -> 0 | H7: =Assumptions!H13 -> 0 | I7: =Assumptions!I13 -> 0 | J7: =Assumptions!J13 -> 0
B8: Non recurring items, amount | F8: =Assumptions!F14 -> 0 | G8: =Assumptions!G14 -> 0 | H8: =Assumptions!H14 -> 0 | I8: =Assumptions!I14 -> 0 | J8: =Assumptions!J14 -> 0
B9: Other income (expense), amt | F9: =Assumptions!F15 -> 0 | G9: =Assumptions!G15 -> 0 | H9: =Assumptions!H15 -> 0 | I9: =Assumptions!I15 -> 0 | J9: =Assumptions!J15 -> 0
B10: Effective tax rate | F10: =Assumptions!F16 -> 0.21 | G10: =Assumptions!G16 -> 0.21 | H10: =Assumptions!H16 -> 0.21 | I10: =Assumptions!I16 -> 0.21 | J10: =Assumptions!J16 -> 0.21
B11: Basic WASO | F11: =Assumptions!F17 -> 120385 | G11: =Assumptions!G17 -> 120385 | H11: =Assumptions!H17 -> 120385 | I11: =Assumptions!I17 -> 120385 | J11: =Assumptions!J17 -> 120385
B12: Diluted WASO | F12: =Assumptions!F18 -> 120385 | G12: =Assumptions!G18 -> 120385 | H12: =Assumptions!H18 -> 120385 | I12: =Assumptions!I18 -> 120385 | J12: =Assumptions!J18 -> 120385
A14: Income statement | C14: =C34 -> 44926 | D14: =D34 -> 45291 | E14: =E34 -> 45657 | F14: =F34 -> 46022 | G14: =G34 -> 46022 | H14: =H34 -> 46022 | I14: =I34 -> 46022 | J14: =J34 -> 46022
B15: Revenue | C15: 598112 | D15: 669765 | E15: 771315 | F15: =E15*(1+F4) -> 871585.95 | G15: =F15*(1+G4) -> 989250.05 | H15: =G15*(1+H4) -> 1127745.1 | I15: =H15*(1+I4) -> 1291268.1 | J15: =I15*(1+J4) -> 1484958.3
B16: COGS | C16: 257050 | D16: 304541 | E16: 344481 | F16: =F15*F5 -> 384905.6 | G16: =G15*G5 -> 431921.61 | H16: =H15*H5 -> 486751.91 | I16: =I15*I5 -> 550874.59 | J16: =J15*J5 -> 626080.99
B17: SG&A | C17: 452265 | D17: 437220 | E17: 456946 | F17: =F15*F6 -> 472769.68 | G17: =G15*G6 -> 487131.09 | H17: =H15*H6 -> 498942.19 | I17: =I15*I6 -> 506725.4 | J17: =J15*J6 -> 508486.29
A18: * | B18: EBIT | C18: =C15-SUM(C16:C17) -> -111203 | D18: =D15-SUM(D16:D17) -> -71996 | E18: =E15-SUM(E16:E17) -> -30112 | F18: =F15-SUM(F16:F17) -> 13910.667 | G18: =G15-SUM(G16:G17) -> 70197.36 | H18: =H15-SUM(H16:H17) -> 142050.97 | I18: =I15-SUM(I16:I17) -> 233668.1 | J18: =J15-SUM(J16:J17) -> 350391.03
B20: Depreciation | C20: 31864 | D20: 38554 | E20: 45865 | F20: =Calcs!F8 -> 57072.689 | G20: =Calcs!G8 -> 59415.273 | H20: =Calcs!H8 -> 62969.61 | I20: =Calcs!I8 -> 67817.12 | J20: =Calcs!J8 -> 74082.803
B21: Amortization | C21: 0 | D21: 0 | E21: 0 | F21: =F7 -> 0 | G21: =G7 -> 0 | H21: =H7 -> 0 | I21: =I7 -> 0 | J21: =J7 -> 0
A22: * | B22: EBITDA | C22: =SUM(C18,C20:C21) -> -79339 | D22: =SUM(D18,D20:D21) -> -33442 | E22: =SUM(E18,E20:E21) -> 15753 | F22: =SUM(F18,F20:F21) -> 70983.356 | G22: =SUM(G18,G20:G21) -> 129612.63 | H22: =SUM(H18,H20:H21) -> 205020.58 | I22: =SUM(I18,I20:I21) -> 301485.22 | J22: =SUM(J18,J20:J21) -> 424473.83
B24: Non-recurring items
B25: Other income (expense)
B27: Interest income | C27: 1307 | D27: 9232 | E27: 10597
B28: Interest expense
A30: * | B30: Pretax Income | C30: =C18+SUM(C25:C28) -> -109896 | D30: =D18+SUM(D25:D28) -> -62764 | E30: =E18+SUM(E24:E28) -> -19515 | F30: =F18+SUM(F24:F28) -> 13910.667 | G30: =G18+SUM(G24:G28) -> 70197.36 | H30: =H18+SUM(H24:H28) -> 142050.97 | I30: =I18+SUM(I24:I28) -> 233668.1 | J30: =J18+SUM(J24:J28) -> 350391.03
B32: Tax expense | C32: 497 | D32: 433 | E32: 875 | F32: =F30*F10 -> 2921.2401 | G32: =G30*G10 -> 14741.446 | H32: =H30*H10 -> 29830.703 | I32: =I30*I10 -> 49070.302 | J32: =J30*J10 -> 73582.116
A33: * | B33: Net income | C33: =C30-C32 -> -110393 | D33: =D30-D32 -> -63197 | E33: =E30-E32 -> -20390 | F33: =F30-F32 -> 10989.427 | G33: =G30-G32 -> 55455.915 | H33: =H30-H32 -> 112220.27 | I33: =I30-I32 -> 184597.8 | J33: =J30-J32 -> 276808.91
A34: Shareholder information | C34: 44926 | D34: 45291 | E34: 45657 | F34: 46022 | G34: 46022 | H34: 46022 | I34: 46022 | J34: 46022
B35: Basic WASO | C35: 114942 | D35: 117389 | E35: 120385 | F35: =F11 -> 120385 | G35: =G11 -> 120385 | H35: =H11 -> 120385 | I35: =I11 -> 120385 | J35: =J11 -> 120385
B36: Diluted WASO | C36: 114942 | D36: 117389 | E36: 120385 | F36: =F12 -> 120385 | G36: =G12 -> 120385 | H36: =H12 -> 120385 | I36: =I12 -> 120385 | J36: =J12 -> 120385
B37: Basic earnings per share | C37: =C33/C35 -> -0.96042352 | D37: =D33/D35 -> -0.53835538 | E37: =E33/E35 -> -0.16937326 | F37: =F33/F35 -> 0.091285684 | G37: =G33/G35 -> 0.46065469 | H37: =H33/H35 -> 0.93217814 | I37: =I33/I35 -> 1.5333954 | J37: =J33/J35 -> 2.2993638
A38: * | B38: Diluted earnings per share | C38: =C33/C36 -> -0.96042352 | D38: =D33/D36 -> -0.53835538 | E38: =E33/E36 -> -0.16937326 | F38: =F33/F36 -> 0.091285684 | G38: =G33/G36 -> 0.46065469 | H38: =H33/H36 -> 0.93217814 | I38: =I33/I36 -> 1.5333954 | J38: =J33/J36 -> 2.2993638

Sheet BalSheet
A1: =CoName -> Warby Parker | C1: Hist. | D1: Hist. | E1: Hist. | F1: Proj. | G1: Proj. | H1: Proj. | I1: Proj. | J1: Proj.
A2: Assumptions | C2: 2022 | D2: =C2+1 -> 2023 | E2: =D2+1 -> 2024 | F2: =E2+1 -> 2025 | G2: =F2+1 -> 2026 | H2: =G2+1 -> 2027 | I2: =H2+1 -> 2028 | J2: =I2+1 -> 2029
B4: Operating Cash % of sales | F4: =Assumptions!F37 -> 0.05 | G4: =F4 -> 0.05 | H4: =G4 -> 0.05 | I4: =H4 -> 0.05 | J4: =I4 -> 0.05
B5: Accounts receivable % of sales | F5: =Assumptions!F38 -> 0.002525557 | G5: =Assumptions!G38 -> 0.002525557 | H5: =Assumptions!H38 -> 0.002525557 | I5: =Assumptions!I38 -> 0.002525557 | J5: =Assumptions!J38 -> 0.002525557
B6: Inventories % of COGS | F6: =Assumptions!F39 -> 0.15195323 | G6: =Assumptions!G39 -> 0.15195323 | H6: =Assumptions!H39 -> 0.15195323 | I6: =Assumptions!I39 -> 0.15195323 | J6: =Assumptions!J39 -> 0.15195323
B7: Other current assets % of sales | F7: =Assumptions!F40 -> 0.022807802 | G7: =Assumptions!G40 -> 0.022807802 | H7: =Assumptions!H40 -> 0.022807802 | I7: =Assumptions!I40 -> 0.022807802 | J7: =Assumptions!J40 -> 0.022807802
B8: Other long-term assets % of sales | F8: =Assumptions!F41 -> 0.011274252 | G8: =Assumptions!G41 -> 0.011274252 | H8: =Assumptions!H41 -> 0.011274252 | I8: =Assumptions!I41 -> 0.011274252 | J8: =Assumptions!J41 -> 0.011274252
B10: Accounts payable/Accural % of COGS | F10: =Assumptions!F45 -> 0.2180904 | G10: =Assumptions!G45 -> 0.2180904 | H10: =Assumptions!H45 -> 0.2180904 | I10: =Assumptions!I45 -> 0.2180904 | J10: =Assumptions!J45 -> 0.2180904
B11: Other current liabilities % of sales | F11: =Assumptions!F46 -> 0.0715998 | G11: =Assumptions!G46 -> 0.0715998 | H11: =Assumptions!H46 -> 0.0715998 | I11: =Assumptions!I46 -> 0.0715998 | J11: =Assumptions!J46 -> 0.0715998
B12: Other long-term liabilities % of sales | F12: =Assumptions!F47 -> 0.26715804 | G12: =Assumptions!G47 -> 0.26715804 | H12: =Assumptions!H47 -> 0.26715804 | I12: =Assumptions!I47 -> 0.26715804 | J12: =Assumptions!J47 -> 0.26715804
A14: Balance sheet | C14: =C2 -> 2022 | D14: =D2 -> 2023 | E14: =E2 -> 2024 | F14: =F2 -> 2025 | G14: =G2 -> 2026 | H14: =H2 -> 2027 | I14: =I2 -> 2028 | J14: =J2 -> 2029
B15: Operating Cash | C15: =5%*IncState!C15 -> 29905.6 | D15: =5%*IncState!D15 -> 33488.25 | E15: =5%*IncState!E15 -> 38565.75 | F15: =F4*IncState!F15 -> 43579.298 | G15: =G4*IncState!G15 -> 49462.503 | H15: =H4*IncState!H15 -> 56387.253 | I15: =I4*IncState!I15 -> 64563.405 | J15: =J4*IncState!J15 -> 74247.915
B16: Excess cash | C16: =208585-C15 -> 178679.4 | D16: =216894-D15 -> 183405.75 | E16: =254161-E15 -> 215595.25 | F16: =MAX(CashFlow!F22,0) -> 240514.33 | G16: =MAX(CashFlow!G22,0) -> 307465.61 | H16: =MAX(CashFlow!H22,0) -> 429207.13 | I16: =MAX(CashFlow!I22,0) -> 621759.64 | J16: =MAX(CashFlow!J22,0) -> 905328.3
B17: Accounts receivable | C17: 1435 | D17: 1779 | E17: 1948 | F17: =F5*IncState!F15 -> 2201.24 | G17: =G5*IncState!G15 -> 2498.4074 | H17: =H5*IncState!H15 -> 2848.1844 | I17: =I5*IncState!I15 -> 3261.1712 | J17: =J5*IncState!J15 -> 3750.3469
B18: Inventories | C18: 68848 | D18: 62234 | E18: 52345 | F18: =F6*IncState!F16 -> 58487.649 | G18: =G6*IncState!G16 -> 65631.882 | H18: =H6*IncState!H16 -> 73963.523 | I18: =I6*IncState!I16 -> 83707.172 | J18: =J6*IncState!J16 -> 95135.027
B19: Other current assets | C19: 15700 | D19: 17712 | E19: 17592 | F19: =F7*IncState!F15 -> 19878.96 | G19: =G7*IncState!G15 -> 22562.62 | H19: =H7*IncState!H15 -> 25721.386 | I19: =I7*IncState!I15 -> 29450.987 | J19: =J7*IncState!J15 -> 33868.635
B20: Total current assets | C20: =SUM(C15:C19) -> 294568 | D20: =SUM(D15:D19) -> 298619 | E20: =SUM(E15:E19) -> 326046 | F20: =SUM(F15:F19) -> 364661.48 | G20: =SUM(G15:G19) -> 447621.02 | H20: =SUM(H15:H19) -> 588127.48 | I20: =SUM(I15:I19) -> 802742.38 | J20: =SUM(J15:J19) -> 1112330.2
B22: Property, plant & equipment, net | C22: =138628+127014 -> 265642 | D22: =152332+122305 -> 274637 | E22: =170464+171284 -> 341748 | F22: =Calcs!F9 -> 355775.26 | G22: =Calcs!G9 -> 377058.43 | H22: =Calcs!H9 -> 406085.04 | I22: =Calcs!I9 -> 443603.59 | J22: =Calcs!J9 -> 490656.82
B23: Other assets | C23: 8497 | D23: 7056 | E23: 8696 | F23: =F8*IncState!F15 -> 9826.48 | G23: =G8*IncState!G15 -> 11153.055 | H23: =H8*IncState!H15 -> 12714.482 | I23: =I8*IncState!I15 -> 14558.082 | J23: =J8*IncState!J15 -> 16741.795
B24: Total non-current assets | C24: =SUM(C22:C23) -> 274139 | D24: =SUM(D22:D23) -> 281693 | E24: =SUM(E22:E23) -> 350444 | F24: =SUM(F22:F23) -> 365601.74 | G24: =SUM(G22:G23) -> 388211.48 | H24: =SUM(H22:H23) -> 418799.52 | I24: =SUM(I22:I23) -> 458161.68 | J24: =SUM(J22:J23) -> 507398.61
A26: * | B26: TOTAL ASSETS | C26: =SUM(C24,C20) -> 568707 | D26: =SUM(D24,D20) -> 580312 | E26: =SUM(E24,E20) -> 676490 | F26: =SUM(F24,F20) -> 730263.21 | G26: =SUM(G24,G20) -> 835832.51 | H26: =SUM(H24,H20) -> 1006927 | I26: =SUM(I24,I20) -> 1260904.1 | J26: =SUM(J24,J20) -> 1619728.8
B28: Revolver/Short term debt | C28: 0 | D28: 0 | E28: 0 | F28: =MIN(CashFlow!F22,0) -> 0 | G28: =MIN(CashFlow!G22,0) -> 0 | H28: =MIN(CashFlow!H22,0) -> 0 | I28: =MIN(CashFlow!I22,0) -> 0 | J28: =MIN(CashFlow!J22,0) -> 0
B29: Accounts payable/Accurals | C29: =20791+58222 -> 79013 | D29: =22456+46320 -> 68776 | E29: =23519+51609 -> 75128 | F29: =F10*IncState!F16 -> 83944.217 | G29: =G10*IncState!G16 -> 94197.957 | H29: =H10*IncState!H16 -> 106155.92 | I29: =I10*IncState!I16 -> 120140.46 | J29: =J10*IncState!J16 -> 136542.25
B30: Other current liabilities | C30: =25628+22546+2370 -> 50544 | D30: =31617+24286+2411 -> 58314 | E30: =32358+20235+2633 -> 55226 | F30: =F11*IncState!F15 -> 62405.38 | G30: =G11*IncState!G15 -> 70830.106 | H30: =H11*IncState!H15 -> 80746.321 | I30: =I11*IncState!I15 -> 92454.538 | J30: =J11*IncState!J15 -> 106322.72
B31: Total current liabilities | C31: =SUM(C28:C30) -> 129557 | D31: =SUM(D28:D30) -> 127090 | E31: =SUM(E28:E30) -> 130354 | F31: =SUM(F28:F30) -> 146349.6 | G31: =SUM(G28:G30) -> 165028.06 | H31: =SUM(H28:H30) -> 186902.24 | I31: =SUM(I28:I30) -> 212595 | J31: =SUM(J28:J30) -> 242864.97
B33: Long-term debt, including current maturities | C33: 0 | D33: 0 | E33: 0 | F33: 0 | G33: 0 | H33: 0 | I33: 0 | J33: 0
B34: Other long-term liabilities | C34: =150832+1672 -> 152504 | D34: =150171+1264 -> 151435 | E34: =205120+943 -> 206063 | F34: =F12*IncState!F15 -> 232851.19 | G34: =G12*IncState!G15 -> 264286.1 | H34: =H12*IncState!H15 -> 301286.15 | I34: =I12*IncState!I15 -> 344972.65 | J34: =J12*IncState!J15 -> 396718.54
B35: Total non-current liabilities | C35: =SUM(C33:C34) -> 152504 | D35: =SUM(D33:D34) -> 151435 | E35: =SUM(E33:E34) -> 206063 | F35: =SUM(F33:F34) -> 232851.19 | G35: =SUM(G33:G34) -> 264286.1 | H35: =SUM(H33:H34) -> 301286.15 | I35: =SUM(I33:I34) -> 344972.65 | J35: =SUM(J33:J34) -> 396718.54
B37: Equity | C37: 286646 | D37: 301787 | E37: 340073 | F37: =Calcs!F16 -> 351062.43 | G37: =Calcs!G16 -> 406518.34 | H37: =Calcs!H16 -> 518738.61 | I37: =Calcs!I16 -> 703336.41 | J37: =Calcs!J16 -> 980145.32
A38: * | B38: TOTAL LIABILITIES & EQUITY | C38: =SUM(C37,C35,C31) -> 568707 | D38: =SUM(D37,D35,D31) -> 580312 | E38: =SUM(E37,E35,E31) -> 676490 | F38: =SUM(F37,F35,F31) -> 730263.21 | G38: =SUM(G37,G35,G31) -> 835832.51 | H38: =SUM(H37,H35,H31) -> 1006927 | I38: =SUM(I37,I35,I31) -> 1260904.1 | J38: =SUM(J37,J35,J31) -> 1619728.8
A40: * | B40: Balance check | C40: =C38-C26 -> 0 | D40: =D38-D26 -> 0 | E40: =E38-E26 -> 0 | F40: =F38-F26 -> 0 | G40: =G38-G26 -> 0 | H40: =H38-H26 -> 0 | I40: =I38-I26 -> 0 | J40: =J38-J26 -> 0

Sheet CashFlow
A1: =CoName -> Warby Parker | C1: Hist. | D1: Hist. | E1: Hist. | F1: Proj. | G1: Proj. | H1: Proj. | I1: Proj. | J1: Proj.
A2: Cash flow statement | C2: 2022 | D2: =C2+1 -> 2023 | E2: =D2+1 -> 2024 | F2: =E2+1 -> 2025 | G2: =F2+1 -> 2026 | H2: =G2+1 -> 2027 | I2: =H2+1 -> 2028 | J2: =I2+1 -> 2029
B3: Net Income | F3: =IncState!F33 -> 10989.427 | G3: =IncState!G33 -> 55455.915 | H3: =IncState!H33 -> 112220.27 | I3: =IncState!I33 -> 184597.8 | J3: =IncState!J33 -> 276808.91
B4: Depreciation | F4: =IncState!F20 -> 57072.689 | G4: =IncState!G20 -> 59415.273 | H4: =IncState!H20 -> 62969.61 | I4: =IncState!I20 -> 67817.12 | J4: =IncState!J20 -> 74082.803
B5: Amortization | F5: =IncState!F21 -> 0 | G5: =IncState!G21 -> 0 | H5: =IncState!H21 -> 0 | I5: =IncState!I21 -> 0 | J5: =IncState!J21 -> 0
B6: (inc) / dec in OWC | F6: =Calcs!F25 -> 2299.2013 | G6: =Calcs!G25 -> 2670.1999 | H6: =Calcs!H25 -> 3109.2418 | I6: =Calcs!I25 -> 3630.3704 | J6: =Calcs!J25 -> 4250.7848
B7: (inc) / dec in LT assets | F7: =BalSheet!E23-BalSheet!F23 -> -1130.48 | G7: =BalSheet!F23-BalSheet!G23 -> -1326.5748 | H7: =BalSheet!G23-BalSheet!H23 -> -1561.4277 | I7: =BalSheet!H23-BalSheet!I23 -> -1843.6 | J7: =BalSheet!I23-BalSheet!J23 -> -2183.7124
B8: inc / (Dec) in LT liabilities | F8: =BalSheet!F34-BalSheet!E34 -> 26788.19 | G8: =BalSheet!G34-BalSheet!F34 -> 31434.911 | H8: =BalSheet!H34-BalSheet!G34 -> 37000.054 | I8: =BalSheet!I34-BalSheet!H34 -> 43686.492 | J8: =BalSheet!J34-BalSheet!I34 -> 51745.897
B9: CFFO | F9: =SUM(F3:F8) -> 96019.027 | G9: =SUM(G3:G8) -> 147649.72 | H9: =SUM(H3:H8) -> 213737.74 | I9: =SUM(I3:I8) -> 297888.19 | J9: =SUM(J3:J8) -> 404704.68
B11: Capex | F11: =Calcs!F7 -> 71099.948 | G11: =Calcs!G7 -> 80698.441 | H11: =Calcs!H7 -> 91996.222 | I11: =Calcs!I7 -> 105335.67 | J11: =Calcs!J7 -> 121136.03
B12: CFFI | F12: =-F11 -> -71099.948 | G12: =-G11 -> -80698.441 | H12: =-H11 -> -91996.222 | I12: =-I11 -> -105335.67 | J12: =-J11 -> -121136.03
B14: Share issuance | F14: =Calcs!F11 -> 0 | G14: =Calcs!G11 -> 0 | H14: =Calcs!H11 -> 0 | I14: =Calcs!I11 -> 0 | J14: =Calcs!J11 -> 0
B15: Debt issuance | F15: =SUM(Debt!F8:F9) -> 0 | G15: =SUM(Debt!G8:G9) -> 0 | H15: =SUM(Debt!H8:H9) -> 0 | I15: =SUM(Debt!I8:I9) -> 0 | J15: =SUM(Debt!J8:J9) -> 0
B16: CFFF | F16: =SUM(F14:F15) -> 0 | G16: =SUM(G14:G15) -> 0 | H16: =SUM(H14:H15) -> 0 | I16: =SUM(I14:I15) -> 0 | J16: =SUM(J14:J15) -> 0
B18: Net changes in cash | F18: =SUM(F16,F12,F9) -> 24919.079 | G18: =SUM(G16,G12,G9) -> 66951.282 | H18: =SUM(H16,H12,H9) -> 121741.52 | I18: =SUM(I16,I12,I9) -> 192552.51 | J18: =SUM(J16,J12,J9) -> 283568.66
B20: Beginning cash | F20: =BalSheet!E16 -> 215595.25 | G20: =BalSheet!F16 -> 240514.33 | H20: =BalSheet!G16 -> 307465.61 | I20: =BalSheet!H16 -> 429207.13 | J20: =BalSheet!I16 -> 621759.64
B21: =B18 -> Net changes in cash | F21: =F18 -> 24919.079 | G21: =G18 -> 66951.282 | H21: =H18 -> 121741.52 | I21: =I18 -> 192552.51 | J21: =J18 -> 283568.66
B22: Ending cash | F22: =SUM(F20:F21) -> 240514.33 | G22: =SUM(G20:G21) -> 307465.61 | H22: =SUM(H20:H21) -> 429207.13 | I22: =SUM(I20:I21) -> 621759.64 | J22: =SUM(J20:J21) -> 905328.3

Sheet Free Cash Flow
A1: =CoName -> Warby Parker | C1: Hist. | D1: Hist. | E1: Hist. | F1: Proj. | G1: Proj. | H1: Proj. | I1: Proj. | J1: Proj.
A2: Free Cash Flows | C2: 2022 | D2: =C2+1 -> 2023 | E2: =D2+1 -> 2024 | F2: =E2+1 -> 2025 | G2: =F2+1 -> 2026 | H2: =G2+1 -> 2027 | I2: =H2+1 -> 2028 | J2: =I2+1 -> 2029
A3: * | B3: Sales | F3: =IncState!F15 -> 871585.95 | G3: =IncState!G15 -> 989250.05 | H3: =IncState!H15 -> 1127745.1 | I3: =IncState!I15 -> 1291268.1 | J3: =IncState!J15 -> 1484958.3
B4: EBIT | F4: =IncState!F18 -> 13910.667 | G4: =IncState!G18 -> 70197.36 | H4: =IncState!H18 -> 142050.97 | I4: =IncState!I18 -> 233668.1 | J4: =IncState!J18 -> 350391.03
B5: Effective Tax Rate | F5: =Assumptions!F16 -> 0.21 | G5: =Assumptions!G16 -> 0.21 | H5: =Assumptions!H16 -> 0.21 | I5: =Assumptions!I16 -> 0.21 | J5: =Assumptions!J16 -> 0.21
A7: * | B7: NOPAT | F7: =F4*(1-F5) -> 10989.427 | G7: =G4*(1-G5) -> 55455.915 | H7: =H4*(1-H5) -> 112220.27 | I7: =I4*(1-I5) -> 184597.8 | J7: =J4*(1-J5) -> 276808.91
B8: Depreciation | F8: =CashFlow!F4 -> 57072.689 | G8: =CashFlow!G4 -> 59415.273 | H8: =CashFlow!H4 -> 62969.61 | I8: =CashFlow!I4 -> 67817.12 | J8: =CashFlow!J4 -> 74082.803
B9: Amortization | F9: =CashFlow!F5 -> 0 | G9: =CashFlow!G5 -> 0 | H9: =CashFlow!H5 -> 0 | I9: =CashFlow!I5 -> 0 | J9: =CashFlow!J5 -> 0
B10: (inc) / dec in OWC | F10: =CashFlow!F6 -> 2299.2013 | G10: =CashFlow!G6 -> 2670.1999 | H10: =CashFlow!H6 -> 3109.2418 | I10: =CashFlow!I6 -> 3630.3704 | J10: =CashFlow!J6 -> 4250.7848
B11: (inc) / dec in other long-term assets | F11: =CashFlow!F7 -> -1130.48 | G11: =CashFlow!G7 -> -1326.5748 | H11: =CashFlow!H7 -> -1561.4277 | I11: =CashFlow!I7 -> -1843.6 | J11: =CashFlow!J7 -> -2183.7124
B12: inc / (dec) other long-term liabilities | F12: =CashFlow!F8 -> 26788.19 | G12: =CashFlow!G8 -> 31434.911 | H12: =CashFlow!H8 -> 37000.054 | I12: =CashFlow!I8 -> 43686.492 | J12: =CashFlow!J8 -> 51745.897
B13: (Capex) | F13: =CashFlow!F12 -> -71099.948 | G13: =CashFlow!G12 -> -80698.441 | H13: =CashFlow!H12 -> -91996.222 | I13: =CashFlow!I12 -> -105335.67 | J13: =CashFlow!J12 -> -121136.03
A15: * | B15: Free Cash Flow | F15: =SUM(F7:F13) -> 24919.079 | G15: =SUM(G7:G13) -> 66951.282 | H15: =SUM(H7:H13) -> 121741.52 | I15: =SUM(I7:I13) -> 192552.51 | J15: =SUM(J7:J13) -> 283568.66

Sheet WACC
A1: =CoName -> Warby Parker
A3: * | B3: WACC | G3: Comp | H3: Levered beta | I3: Gross debt | J3: Market cap | K3: Debt/Mcap | L3: MTR | M3: Unlevered beta
B4: Tax Rate | E4: =Assumptions!F16 -> 0.21 | L4: =E4 -> 0.21 | M4: =H4/((1+K4*(1-L4))) -> 0
B5: Risk free rate | E5: 0.041 | L5: =L4 -> 0.21 | M5: =H5/((1+K5*(1-L5))) -> 0
B6: Market risk Premium | E6: 0.05 | L6: =L5 -> 0.21 | M6: =H6/((1+K6*(1-L6))) -> 0
B7: Beta | E7: =2.07*0.66 -> 1.3662 | L7: =L6 -> 0.21 | M7: =H7/((1+K7*(1-L7))) -> 0
B8: Cost of Equity | E8: =E5+E6*E7 -> 0.10931
B9: % Equity | E9: =1-E10 -> 0.89966659 | G9: Industry beta (average) | M9: =AVERAGE(M4:M7) -> 0
B10: % Debt | E10: =MAIN!F8/MAIN!F6 -> 0.10033341
B11: Cost of debt | E11: =Assumptions!F23 -> 0.05 | G11: Re-levered beta | M11: =M9*(1+E10*(1-E4)) -> 0
B12: Post tax cost of debt | E12: =E11*(1-E4) -> 0.0395
A13: * | B13: WACC | E13: =WACC!E8*WACC!E9+WACC!E12*WACC!E10 -> 0.10230572
B14: Long Term growth rate | E14: 0.025

Sheet DCF Model
A1: =CoName -> Warby Parker | D1: Proj. | E1: Proj. | F1: Proj. | G1: Proj. | H1: Proj.
A2: Discount Model Year count | D2: 0.5 | E2: =D2+1 -> 1.5 | F2: =E2+1 -> 2.5 | G2: =F2+1 -> 3.5 | H2: =G2+1 -> 4.5
B3: Discount Factor | D3: =1/(1+$K$3)^D2 -> 0.95246487 | E3: =1/(1+$K$3)^E2 -> 0.86406598 | F3: =1/(1+$K$3)^F2 -> 0.78387144 | G3: =1/(1+$K$3)^G2 -> 0.71111981 | H3: =1/(1+$K$3)^H2 -> 0.64512031 | I3: WACC | K3: =WACC!E13 -> 0.10230572
B4: PV FCF | D4: =D3*'Free Cash Flow'!F15 -> 23734.548 | E4: =E3*'Free Cash Flow'!G15 -> 57850.325 | F4: =F3*'Free Cash Flow'!H15 -> 95429.702 | G4: =G3*'Free Cash Flow'!I15 -> 136927.91 | H4: =H3*'Free Cash Flow'!J15 -> 182935.9 | I4: Long Term growth rate | K4: 0.025
H5: =(H4*(1+K4))/(K3-K4) -> 2425555.2
A6: Value Calculation | E6: Multiples Calculation
B7: Total PV of FCFs | C7: =SUM(D4:H4) -> 496878.38 | E7: Total PV of FCFs | G7: =C7 -> 496878.38
B8: PV of TV | C8: =H5*H3 -> 1564774.9 | E8: Multiple TV | G8: =H3*G10*IncState!J22 -> 2190693.5
B9: EV | C9: =SUM(C7:C8) -> 2061653.3 | E9: EV | G9: =SUM(G7:G8) -> 2687571.9
E10: Exit EBITDA mult | G10: 8
B12: Cash & Cash Equiv | C12: =MAIN!F7 -> 280360 | E12: Cash & Cash Equiv | G12: =C12 -> 280360
B13: Debt & Claims | C13: =MAIN!F8 -> 203885 | E13: Debt & Claims | G13: =C13 -> 203885
B14: NCI | C14: 0 | E14: NCI | G14: =C14 -> 0
B15: Equity Value | C15: =C9+C12-C13 -> 2138128.3 | E15: Equity Value | G15: =G9+G12-G13 -> 2764046.9
B17: Diluted S/O | C17: =MAIN!F5 -> 105727.1 | E17: Diluted S/O | G17: =C17 -> 105727.1
A18: * | B18: Implied Share Price | C18: =C15/C17 -> 20.223086 | E18: Implied Share Price | G18: =G15/G17 -> 26.14322
A20: Sensitivity analysis
C22: Discount rate variance | E22: 0.005 | J22: Discount rate variance | L22: 0.005
C23: Implied growth rate variance | E23: 0.0025 | J23: TV multiple variance | L23: 1
